{
  "type": "Feature",
  "properties": {
    "gn:admin1_code":"20.0",
    "gn:asciiname":"Kenderesi Dulo",
    "gn:country_code":"HU",
    "gn:dem":97,
    "gn:feature_class":"P",
    "gn:feature_code":"PPL",
    "gn:name":"Kenderesi D\u0171l\u0151",
    "gn:population":0,
    "gn:timezone":"Europe/Budapest",
    "iso:country":"HU",
    "wof:name":"Kenderesi Dulo",
    "wof:placetype":"locality"
},
  "geometry": {"coordinates":[19.98333,47.63333],"type":"Point"}
}