{
  "type": "Feature",
  "properties": {
    "gn:admin1_code":"22.0",
    "gn:asciiname":"Ferenczmajor",
    "gn:cc2":"HU",
    "gn:country_code":"HU",
    "gn:dem":151,
    "gn:feature_class":"P",
    "gn:feature_code":"PPL",
    "gn:name":"Ferenczmajor",
    "gn:population":0,
    "gn:timezone":"Europe/Budapest",
    "iso:country":"HU",
    "name:und_x_variant":[
        "Ferenc-major",
        "Ferenczmajor"
    ],
    "wof:name":"Ferenczmajor",
    "wof:placetype":"locality"
},
  "geometry": {"coordinates":[17.08333,47.35],"type":"Point"}
}