{
  "type": "Feature",
  "properties": {
    "gn:admin1_code":"24.0",
    "gn:asciiname":"Murahid",
    "gn:country_code":"HU",
    "gn:dem":147,
    "gn:feature_class":"P",
    "gn:feature_code":"PPL",
    "gn:name":"Murahid",
    "gn:population":0,
    "gn:timezone":"Europe/Budapest",
    "iso:country":"HU",
    "wof:name":"Murahid",
    "wof:placetype":"locality"
},
  "geometry": {"coordinates":[16.73333,46.43333],"type":"Point"}
}