{
  "type": "Feature",
  "properties": {
    "gn:admin1_code":"2.0",
    "gn:asciiname":"Kisnyarad",
    "gn:country_code":"HU",
    "gn:dem":141,
    "gn:feature_class":"P",
    "gn:feature_code":"PPL",
    "gn:name":"Kisny\u00e1r\u00e1d",
    "gn:population":0,
    "gn:timezone":"Europe/Budapest",
    "iso:country":"HU",
    "wof:name":"Kisnyarad",
    "wof:placetype":"locality"
},
  "geometry": {"coordinates":[18.56638,46.03571],"type":"Point"}
}