{
  "type": "Feature",
  "properties": {
    "gn:admin1_code":"2.0",
    "gn:asciiname":"Kisnyarad",
    "gn:country_code":"HU",
    "gn:dem":141,
    "gn:feature_class":"P",
    "gn:feature_code":"PPL",
    "gn:name":"Kisny\u00e1r\u00e1d",
    "gn:population":0,
    "gn:timezone":"Europe/Budapest",
    "iso:country":"HU",
    "name:deu_x_preferred":[
        "Kisny\u00e1r\u00e1d"
    ],
    "name:epo_x_preferred":[
        "Kisny\u00e1r\u00e1d"
    ],
    "name:fas_x_preferred":[
        "\u06a9\u06cc\u0634\u0646\u06cc\u0627\u0631\u0627\u062f"
    ],
    "name:fra_x_preferred":[
        "Kisny\u00e1r\u00e1d"
    ],
    "name:hrv_x_preferred":[
        "Narad"
    ],
    "name:hun_x_preferred":[
        "Kisny\u00e1r\u00e1d"
    ],
    "name:ita_x_preferred":[
        "Kisny\u00e1r\u00e1d"
    ],
    "name:msa_x_preferred":[
        "Kisny\u00e1r\u00e1d"
    ],
    "name:nld_x_preferred":[
        "Kisny\u00e1r\u00e1d"
    ],
    "name:pol_x_preferred":[
        "Kisny\u00e1r\u00e1d"
    ],
    "name:ron_x_preferred":[
        "Kisny\u00e1r\u00e1d"
    ],
    "name:slk_x_preferred":[
        "Kisny\u00e1r\u00e1d"
    ],
    "name:slv_x_preferred":[
        "Kisny\u00e1r\u00e1d"
    ],
    "name:srp_x_preferred":[
        "\u041a\u0438\u0448\u045a\u0430\u0440\u0430\u0434"
    ],
    "name:vie_x_preferred":[
        "Kisny\u00e1r\u00e1d"
    ],
    "name:zho_x_preferred":[
        "\u57fa\u4ec0\u5c3c\u4e9a\u62c9\u5fb7"
    ],
    "wof:name":"Kisnyarad",
    "wof:placetype":"locality"
},
  "geometry": {"coordinates":[18.56638,46.03571],"type":"Point"}
}