{
  "type": "Feature",
  "properties": {
    "gn:admin1_code":"6.0",
    "gn:asciiname":"Bokeny",
    "gn:country_code":"HU",
    "gn:dem":84,
    "gn:feature_class":"P",
    "gn:feature_code":"PPL",
    "gn:name":"B\u00f6k\u00e9ny",
    "gn:population":0,
    "gn:timezone":"Europe/Budapest",
    "iso:country":"HU",
    "name:und_x_variant":[
        "B\u00f6k\u00e9ny"
    ],
    "wof:name":"Bokeny",
    "wof:placetype":"locality"
},
  "geometry": {"coordinates":[20.66667,46.16667],"type":"Point"}
}