{
  "type": "Feature",
  "properties": {
    "gn:admin1_code":"22.0",
    "gn:asciiname":"Gyanogeregye",
    "gn:country_code":"HU",
    "gn:dem":184,
    "gn:feature_class":"P",
    "gn:feature_code":"PPL",
    "gn:name":"Gyan\u00f3geregye",
    "gn:population":0,
    "gn:timezone":"Europe/Budapest",
    "iso:country":"HU",
    "name:deu_x_preferred":[
        "Gyan\u00f3geregye"
    ],
    "name:epo_x_preferred":[
        "Gyan\u00f3geregye"
    ],
    "name:fas_x_preferred":[
        "\u06af\u06cc\u0627\u0646\u0648\u06af\u0631\u06af\u06cc\u0647"
    ],
    "name:fra_x_preferred":[
        "Gyan\u00f3geregye"
    ],
    "name:hun_x_preferred":[
        "Gyan\u00f3geregye"
    ],
    "name:ita_x_preferred":[
        "Gyan\u00f3geregye"
    ],
    "name:msa_x_preferred":[
        "Gyan\u00f3geregye"
    ],
    "name:nld_x_preferred":[
        "Gyan\u00f3geregye"
    ],
    "name:ron_x_preferred":[
        "Gyan\u00f3geregye"
    ],
    "name:slk_x_preferred":[
        "Gyan\u00f3geregye"
    ],
    "name:slv_x_preferred":[
        "Gyan\u00f3geregye"
    ],
    "name:und_x_variant":[
        "Gydn\u00f3geregye"
    ],
    "name:vie_x_preferred":[
        "Gyan\u00f3geregye"
    ],
    "name:zho_x_preferred":[
        "\u7126\u8bfa\u76d6\u8d56\u6770"
    ],
    "wof:name":"Gyanogeregye",
    "wof:placetype":"locality"
},
  "geometry": {"coordinates":[16.76481,47.12278],"type":"Point"}
}