{
  "type": "Feature",
  "properties": {
    "gn:admin1_code":"18.0",
    "gn:asciiname":"Kistag",
    "gn:country_code":"HU",
    "gn:dem":117,
    "gn:feature_class":"P",
    "gn:feature_code":"PPL",
    "gn:name":"Kistag",
    "gn:population":0,
    "gn:timezone":"Europe/Budapest",
    "iso:country":"HU",
    "wof:name":"Kistag",
    "wof:placetype":"locality"
},
  "geometry": {"coordinates":[22.7176,47.86489],"type":"Point"}
}