{
  "type": "Feature",
  "properties": {
    "gn:admin1_code":"24.0",
    "gn:asciiname":"Felsoszenterzsebet",
    "gn:country_code":"HU",
    "gn:dem":224,
    "gn:feature_class":"P",
    "gn:feature_code":"PPL",
    "gn:name":"Fels\u0151szenterzs\u00e9bet",
    "gn:population":0,
    "gn:timezone":"Europe/Budapest",
    "iso:country":"HU",
    "name:ces_x_preferred":[
        "Fels\u0151szenterzs\u00e9bet"
    ],
    "name:epo_x_preferred":[
        "Fels\u0151szenterzs\u00e9bet"
    ],
    "name:fra_x_preferred":[
        "Fels\u0151szenterzs\u00e9bet"
    ],
    "name:hun_x_preferred":[
        "Fels\u0151szenterzs\u00e9bet"
    ],
    "name:ita_x_preferred":[
        "Fels\u0151szenterzs\u00e9bet"
    ],
    "name:msa_x_preferred":[
        "Fels\u0151szenterzs\u00e9bet"
    ],
    "name:nld_x_preferred":[
        "Fels\u0151szenterzs\u00e9bet"
    ],
    "name:ron_x_preferred":[
        "Fels\u0151szenterzs\u00e9bet"
    ],
    "name:slk_x_preferred":[
        "Fels\u0151szenterzs\u00e9bet"
    ],
    "name:slv_x_preferred":[
        "Fels\u0151szenterzs\u00e9bet"
    ],
    "name:vie_x_preferred":[
        "Fels\u0151szenterzs\u00e9bet"
    ],
    "name:zho_x_preferred":[
        "\u4e0a\u68ee\u6cf0\u5c14\u70ed\u62dc\u7279"
    ],
    "wof:name":"Felsoszenterzsebet",
    "wof:placetype":"locality"
},
  "geometry": {"coordinates":[16.45499,46.75285],"type":"Point"}
}