{
  "type": "Feature",
  "properties": {
    "gn:admin1_code":"17.0",
    "gn:asciiname":"Rinyabesenyo",
    "gn:cc2":"HU",
    "gn:country_code":"HU",
    "gn:dem":162,
    "gn:feature_class":"P",
    "gn:feature_code":"PPL",
    "gn:name":"Rinyabeseny\u0151",
    "gn:population":0,
    "gn:timezone":"Europe/Budapest",
    "iso:country":"HU",
    "name:epo_x_preferred":[
        "Rinyabeseny\u0151"
    ],
    "name:fas_x_preferred":[
        "\u0631\u06cc\u0646\u06cc\u0627\u0628\u0634\u0646\u06cc\u0648"
    ],
    "name:fra_x_preferred":[
        "Rinyabeseny\u0151"
    ],
    "name:hun_x_preferred":[
        "Rinyabeseny\u0151"
    ],
    "name:ita_x_preferred":[
        "Rinyabeseny\u0151"
    ],
    "name:msa_x_preferred":[
        "Rinyabeseny\u0151"
    ],
    "name:nld_x_preferred":[
        "Rinyabeseny\u0151"
    ],
    "name:ron_x_preferred":[
        "Rinyabeseny\u0151"
    ],
    "name:slk_x_preferred":[
        "Rinyabeseny\u0151"
    ],
    "name:slv_x_preferred":[
        "Rinyabeseny\u0151"
    ],
    "name:und_x_variant":[
        "Rinyabesny\u0151"
    ],
    "name:vie_x_preferred":[
        "Rinyabeseny\u0151"
    ],
    "name:zho_x_preferred":[
        "\u91cc\u5c3c\u5965\u62dc\u8c22\u6d85"
    ],
    "wof:name":"Rinyabesenyo",
    "wof:placetype":"locality"
},
  "geometry": {"coordinates":[17.51667,46.16667],"type":"Point"}
}