{
  "type": "Feature",
  "properties": {
    "gn:admin1_code":"17.0",
    "gn:asciiname":"Batehegy",
    "gn:country_code":"HU",
    "gn:dem":142,
    "gn:feature_class":"P",
    "gn:feature_code":"PPL",
    "gn:name":"Bat\u00e9hegy",
    "gn:population":0,
    "gn:timezone":"Europe/Budapest",
    "iso:country":"HU",
    "wof:name":"Batehegy",
    "wof:placetype":"locality"
},
  "geometry": {"coordinates":[17.96667,46.33333],"type":"Point"}
}