{
  "type": "Feature",
  "properties": {
    "iso:country":"HU",
    "name:hun_x_colloquial":[
        "Borbanya",
        "Borbanya Hazhely"
    ],
    "name:hun_x_preferred":[
        "Borb\u00e1nya"
    ],
    "name:hun_x_variant":[
        "Borb\u00e1nya H\u00e1zhely"
    ],
    "qs:gn_adm0_cc":"HU",
    "qs:gn_local":716935,
    "qs:gn_nam_loc":"Ny\u00edregyh\u00e1za, Ny\u00edregyh\u00e1za, Ny\u00edregyh\u00e1za, HU",
    "qs:gn_namadm1":"18",
    "qs:local_max":164,
    "qs:local_sum":166,
    "qs:localhoods":2,
    "qs:name":"Borb\u00e1nya",
    "qs:name_adm0":"Magyarorsz\u00e1g",
    "qs:name_adm1":"Ny\u00edregyh\u00e1za",
    "qs:name_adm2":"Ny\u00edregyh\u00e1za",
    "qs:name_local":"Ny\u00edregyh\u00e1za",
    "qs:photo_max":1,
    "qs:photo_sum":2,
    "qs:placetype":"Suburb",
    "qs:quad_count":2,
    "qs:woe_adm0":23424844,
    "qs:woe_adm1":56043636,
    "qs:woe_adm2":12593479,
    "qs:woe_lau":0,
    "qs:woe_local":812897,
    "qs:woe_ver":"7.10.0",
    "wof:lang":[
        "hun"
    ],
    "wof:name":"Borb\u00e1nya",
    "wof:placetype":"neighbourhood"
},
  "geometry": {"coordinates":[21.747437,47.931067],"type":"Point"}
}