{
  "type": "Feature",
  "properties": {
    "gn:admin1_code":"17.0",
    "gn:asciiname":"Csabapuszta",
    "gn:country_code":"HU",
    "gn:dem":164,
    "gn:feature_class":"P",
    "gn:feature_code":"PPL",
    "gn:name":"Csabapuszta",
    "gn:population":0,
    "gn:timezone":"Europe/Budapest",
    "iso:country":"HU",
    "wof:name":"Csabapuszta",
    "wof:placetype":"locality"
},
  "geometry": {"coordinates":[17.98763,46.71353],"type":"Point"}
}