{
  "type": "Feature",
  "properties": {
    "gn:admin1_code":"24.0",
    "gn:asciiname":"Homokkomarom",
    "gn:country_code":"HU",
    "gn:dem":181,
    "gn:feature_class":"P",
    "gn:feature_code":"PPL",
    "gn:name":"Homokkom\u00e1rom",
    "gn:population":0,
    "gn:timezone":"Europe/Budapest",
    "iso:country":"HU",
    "name:epo_x_preferred":[
        "Homokkom\u00e1rom"
    ],
    "name:fas_x_preferred":[
        "\u0647\u0648\u0645\u0648\u06a9\u0648\u0645\u0627\u0631\u0648\u0645"
    ],
    "name:fra_x_preferred":[
        "Homokkom\u00e1rom"
    ],
    "name:hun_x_preferred":[
        "Homokkom\u00e1rom"
    ],
    "name:ita_x_preferred":[
        "Homokkom\u00e1rom"
    ],
    "name:msa_x_preferred":[
        "Homokkom\u00e1rom"
    ],
    "name:nld_x_preferred":[
        "Homokkom\u00e1rom"
    ],
    "name:ron_x_preferred":[
        "Homokkom\u00e1rom"
    ],
    "name:slk_x_preferred":[
        "Homokkom\u00e1rom"
    ],
    "name:slv_x_preferred":[
        "Homokkom\u00e1rom"
    ],
    "name:vie_x_preferred":[
        "Homokkom\u00e1rom"
    ],
    "name:zho_x_preferred":[
        "\u970d\u83ab\u514b\u79d1\u9a6c\u7f57\u59c6"
    ],
    "wof:name":"Homokkomarom",
    "wof:placetype":"locality"
},
  "geometry": {"coordinates":[16.91574,46.50484],"type":"Point"}
}