{
  "type": "Feature",
  "properties": {
    "gn:admin1_code":"18.0",
    "gn:asciiname":"Szipazsilip",
    "gn:country_code":"HU",
    "gn:dem":106,
    "gn:feature_class":"P",
    "gn:feature_code":"PPL",
    "gn:name":"Szipazsilip",
    "gn:population":0,
    "gn:timezone":"Europe/Budapest",
    "iso:country":"HU",
    "wof:name":"Szipazsilip",
    "wof:placetype":"locality"
},
  "geometry": {"coordinates":[22.31264,48.16466],"type":"Point"}
}