{
  "type": "Feature",
  "properties": {
    "gn:admin1_code":"3.0",
    "gn:asciiname":"Kerteszsziget",
    "gn:country_code":"HU",
    "gn:dem":81,
    "gn:feature_class":"P",
    "gn:feature_code":"PPL",
    "gn:name":"Kert\u00e9szsziget",
    "gn:population":0,
    "gn:timezone":"Europe/Budapest",
    "iso:country":"HU",
    "name:und_x_variant":[
        "Kert\u00e9szsziget"
    ],
    "wof:name":"Kerteszsziget",
    "wof:placetype":"locality"
},
  "geometry": {"coordinates":[21.06667,47.15],"type":"Point"}
}