{
  "type": "Feature",
  "properties": {
    "gn:admin1_code":"3.0",
    "gn:asciiname":"Kerteszsziget",
    "gn:country_code":"HU",
    "gn:dem":81,
    "gn:feature_class":"P",
    "gn:feature_code":"PPL",
    "gn:name":"Kert\u00e9szsziget",
    "gn:population":0,
    "gn:timezone":"Europe/Budapest",
    "iso:country":"HU",
    "name:deu_x_preferred":[
        "Kert\u00e9szsziget"
    ],
    "name:epo_x_preferred":[
        "Kert\u00e9szsziget"
    ],
    "name:fas_x_preferred":[
        "\u06a9\u0631\u062a\u0633\u0633\u06cc\u06af\u062a"
    ],
    "name:fra_x_preferred":[
        "Kert\u00e9szsziget"
    ],
    "name:hun_x_preferred":[
        "Kert\u00e9szsziget"
    ],
    "name:ita_x_preferred":[
        "Kert\u00e9szsziget"
    ],
    "name:msa_x_preferred":[
        "Kert\u00e9szsziget"
    ],
    "name:nld_x_preferred":[
        "Kert\u00e9szsziget"
    ],
    "name:pol_x_preferred":[
        "Kert\u00e9szsziget"
    ],
    "name:ron_x_preferred":[
        "Kert\u00e9szsziget"
    ],
    "name:slk_x_preferred":[
        "Kert\u00e9szsziget"
    ],
    "name:slv_x_preferred":[
        "Kert\u00e9szsziget"
    ],
    "name:und_x_variant":[
        "Kert\u00e9szsziget"
    ],
    "name:vie_x_preferred":[
        "Kert\u00e9szsziget"
    ],
    "name:zho_x_preferred":[
        "\u51ef\u5c14\u6cf0\u65af\u897f\u76d6\u7279"
    ],
    "wof:name":"Kerteszsziget",
    "wof:placetype":"locality"
},
  "geometry": {"coordinates":[21.06667,47.15],"type":"Point"}
}