{
  "type": "Feature",
  "properties": {
    "gn:admin1_code":"6.0",
    "gn:asciiname":"Farkiret",
    "gn:country_code":"HU",
    "gn:dem":80,
    "gn:feature_class":"P",
    "gn:feature_code":"PPL",
    "gn:name":"Farkir\u00e9t",
    "gn:population":0,
    "gn:timezone":"Europe/Budapest",
    "iso:country":"HU",
    "wof:name":"Farkiret",
    "wof:placetype":"locality"
},
  "geometry": {"coordinates":[20.21667,46.33333],"type":"Point"}
}