{
  "type": "Feature",
  "properties": {
    "gn:admin1_code":"3.0",
    "gn:asciiname":"Berthothitanya",
    "gn:country_code":"HU",
    "gn:dem":83,
    "gn:feature_class":"P",
    "gn:feature_code":"PPL",
    "gn:name":"Berth\u00f3thitanya",
    "gn:population":0,
    "gn:timezone":"Europe/Budapest",
    "iso:country":"HU",
    "wof:name":"Berthothitanya",
    "wof:placetype":"locality"
},
  "geometry": {"coordinates":[20.68333,46.68333],"type":"Point"}
}