{
  "type": "Feature",
  "properties": {
    "gn:admin1_code":"4.0",
    "gn:asciiname":"Tornyosnemeti",
    "gn:cc2":"HU",
    "gn:country_code":"HU",
    "gn:dem":155,
    "gn:feature_class":"P",
    "gn:feature_code":"PPL",
    "gn:name":"Tornyosn\u00e9meti",
    "gn:population":0,
    "gn:timezone":"Europe/Budapest",
    "iso:country":"HU",
    "name:deu_x_preferred":[
        "Tornyosn\u00e9meti"
    ],
    "name:epo_x_preferred":[
        "Tornyosn\u00e9meti"
    ],
    "name:fas_x_preferred":[
        "\u062a\u0648\u0631\u0646\u06cc\u0648\u0634\u0646\u0645\u062a\u06cc"
    ],
    "name:fra_x_preferred":[
        "Tornyosn\u00e9meti"
    ],
    "name:heb_x_preferred":[
        "\u05d8\u05d5\u05e8\u05e0\u05d9\u05d5\u05e9\u05e0\u05de\u05d8\u05d9"
    ],
    "name:hun_x_preferred":[
        "Tornyosn\u00e9meti"
    ],
    "name:ita_x_preferred":[
        "Tornyosn\u00e9meti"
    ],
    "name:msa_x_preferred":[
        "Tornyosn\u00e9meti"
    ],
    "name:nld_x_preferred":[
        "Tornyosn\u00e9meti"
    ],
    "name:pol_x_preferred":[
        "Tornyosn\u00e9meti"
    ],
    "name:ron_x_preferred":[
        "Tornyosn\u00e9meti"
    ],
    "name:slk_x_preferred":[
        "Tornyosn\u00e9meti"
    ],
    "name:slv_x_preferred":[
        "Tornyosn\u00e9meti"
    ],
    "name:swe_x_preferred":[
        "Tornyosn\u00e9meti"
    ],
    "name:und_x_variant":[
        "Tornvosn\u00e9meti",
        "Torryosn\u00e9meti",
        "Toryosn\u00e9meti"
    ],
    "name:vie_x_preferred":[
        "Tornyosn\u00e9meti"
    ],
    "name:zho_x_preferred":[
        "\u6258\u5c14\u7ebd\u4ec0\u5185\u8fc8\u8482"
    ],
    "wof:name":"Tornyosnemeti",
    "wof:placetype":"locality"
},
  "geometry": {"coordinates":[21.26667,48.51667],"type":"Point"}
}