{
  "type": "Feature",
  "properties": {
    "gn:admin1_code":"4.0",
    "gn:asciiname":"Tornyosnemeti",
    "gn:cc2":"HU",
    "gn:country_code":"HU",
    "gn:dem":155,
    "gn:feature_class":"P",
    "gn:feature_code":"PPL",
    "gn:name":"Tornyosn\u00e9meti",
    "gn:population":0,
    "gn:timezone":"Europe/Budapest",
    "iso:country":"HU",
    "name:und_x_variant":[
        "Tornvosn\u00e9meti",
        "Torryosn\u00e9meti",
        "Toryosn\u00e9meti",
        "Tornyosn\u00e9meti"
    ],
    "wof:name":"Tornyosnemeti",
    "wof:placetype":"locality"
},
  "geometry": {"coordinates":[21.26667,48.51667],"type":"Point"}
}