{
  "type": "Feature",
  "properties": {
    "gn:admin1_code":"3.0",
    "gn:asciiname":"Gyulai-tanya",
    "gn:cc2":"HU",
    "gn:country_code":"HU",
    "gn:dem":78,
    "gn:feature_class":"P",
    "gn:feature_code":"PPL",
    "gn:name":"Gyulai-tanya",
    "gn:population":0,
    "gn:timezone":"Europe/Budapest",
    "iso:country":"HU",
    "name:und_x_variant":[
        "Gyulay-tanya",
        "Gyulai-tanya"
    ],
    "wof:name":"Gyulai-tanya",
    "wof:placetype":"locality"
},
  "geometry": {"coordinates":[20.95,46.93333],"type":"Point"}
}