{
  "type": "Feature",
  "properties": {
    "gn:admin1_code":"23.0",
    "gn:asciiname":"Erzsebetpuszta",
    "gn:country_code":"HU",
    "gn:dem":136,
    "gn:feature_class":"P",
    "gn:feature_code":"PPL",
    "gn:name":"Erzs\u00e9betpuszta",
    "gn:population":0,
    "gn:timezone":"Europe/Budapest",
    "iso:country":"HU",
    "name:und_x_variant":[
        "Erzs\u00e9bet-malom",
        "Erzs\u00e9betpuszta"
    ],
    "wof:name":"Erzsebetpuszta",
    "wof:placetype":"locality"
},
  "geometry": {"coordinates":[17.17215,46.98849000000001],"type":"Point"}
}