{
  "type": "Feature",
  "properties": {
    "gn:admin1_code":"10.0",
    "gn:asciiname":"Kisszocskod",
    "gn:country_code":"HU",
    "gn:dem":84,
    "gn:feature_class":"P",
    "gn:feature_code":"PPL",
    "gn:name":"Kissz\u00f6csk\u00f6d",
    "gn:population":0,
    "gn:timezone":"Europe/Budapest",
    "iso:country":"HU",
    "wof:name":"Kisszocskod",
    "wof:placetype":"locality"
},
  "geometry": {"coordinates":[21.36667000000001,46.98333],"type":"Point"}
}