{
  "type": "Feature",
  "properties": {
    "gn:admin1_code":"17.0",
    "gn:asciiname":"Csertelek",
    "gn:country_code":"HU",
    "gn:dem":156,
    "gn:feature_class":"P",
    "gn:feature_code":"PPL",
    "gn:name":"Csertelek",
    "gn:population":0,
    "gn:timezone":"Europe/Budapest",
    "iso:country":"HU",
    "name:und_x_variant":[
        "Csertelek-puszta",
        "Csertelek"
    ],
    "wof:name":"Csertelek",
    "wof:placetype":"locality"
},
  "geometry": {"coordinates":[17.51217999999999,46.09669],"type":"Point"}
}