{
  "type": "Feature",
  "properties": {
    "gn:gn_country":"HU",
    "gn:gn_fcode":"PPL",
    "gn:gn_pop":6886,
    "gn:population":6886,
    "iso:country":"HU",
    "name:rus_x_preferred":[
        "\u042d\u043d\u0447"
    ],
    "name:srp_x_preferred":[
        "\u0415\u043d\u0447"
    ],
    "name:unk_x_variant":[
        "Gib\u00e1rt"
    ],
    "name:zho_x_preferred":[
        "\u6069\u5947"
    ],
    "qs_pg:aaroncc":"HU",
    "qs_pg:gn_country":"HU",
    "qs_pg:gn_fcode":"PPL",
    "qs_pg:gn_pop":6886,
    "qs_pg:name":"Aba\u00fajdevecser",
    "qs_pg:name_adm0":"Magyarorsz\u00e1g",
    "qs_pg:name_adm1":"Borsod-Aba\u00faj-Zempl\u00e9n",
    "qs_pg:photos_9k":1,
    "qs_pg:photos_9r":1,
    "qs_pg:photos_all":1,
    "qs_pg:photos_sr":0,
    "qs_pg:pop_sr":5,
    "qs_pg:qs_pg_placetype":"locality",
    "qs_pg:qs_pg_placetype_gp":"Town",
    "qs_pg:woe_adm0":23424844,
    "woe:adm0_id":23424844,
    "woe:name_adm0":"Magyarorsz\u00e1g",
    "woe:name_adm1":"Borsod-Aba\u00faj-Zempl\u00e9n",
    "woe:placetype":"Town",
    "wof:name":"Aba\u00fajdevecser",
    "wof:placetype":"locality",
    "wof:population":6886
},
  "geometry": {"coordinates":[21.13333,48.33333],"type":"Point"}
}