{
  "type": "Feature",
  "properties": {
    "gn:admin1_code":"18.0",
    "gn:asciiname":"Reichardtag",
    "gn:country_code":"HU",
    "gn:dem":142,
    "gn:feature_class":"P",
    "gn:feature_code":"PPL",
    "gn:name":"Reichardtag",
    "gn:population":0,
    "gn:timezone":"Europe/Budapest",
    "iso:country":"HU",
    "wof:name":"Reichardtag",
    "wof:placetype":"locality"
},
  "geometry": {"coordinates":[22.21667,47.91667],"type":"Point"}
}