{
  "type": "Feature",
  "properties": {
    "gn:admin1_code":"22.0",
    "gn:asciiname":"Kiszsidany",
    "gn:country_code":"HU",
    "gn:dem":220,
    "gn:feature_class":"P",
    "gn:feature_code":"PPL",
    "gn:name":"Kiszsid\u00e1ny",
    "gn:population":0,
    "gn:timezone":"Europe/Budapest",
    "iso:country":"HU",
    "name:deu_x_preferred":[
        "Roggendorf"
    ],
    "name:hrv_x_preferred":[
        "Lukindrof"
    ],
    "name:und_x_variant":[
        "N\u00e9metzsid\u00e1ny",
        "Kiszsid\u00e1ny"
    ],
    "wof:name":"Kiszsidany",
    "wof:placetype":"locality"
},
  "geometry": {"coordinates":[16.63879,47.41061],"type":"Point"}
}