{
  "type": "Feature",
  "properties": {
    "iso:country":"HU",
    "qs_pg:aaroncc":"HU",
    "qs_pg:name":"Fels\u00f4h\u00e1mor",
    "qs_pg:name_adm0":"Magyarorsz\u00e1g",
    "qs_pg:name_adm1":"Miskolc",
    "qs_pg:photos":16,
    "qs_pg:photos_1k":3,
    "qs_pg:photos_9k":1,
    "qs_pg:photos_9r":1,
    "qs_pg:photos_all":16,
    "qs_pg:photos_sr":1,
    "qs_pg:pop_sr":0,
    "qs_pg:qs_pg_placetype":"locality",
    "qs_pg:qs_pg_placetype_gp":"Town",
    "qs_pg:woe_adm0":23424844,
    "woe:adm0_id":23424844,
    "woe:name_adm0":"Magyarorsz\u00e1g",
    "woe:name_adm1":"Miskolc",
    "woe:placetype":"Town",
    "wof:name":"Fels\u00f4h\u00e1mor",
    "wof:placetype":"locality"
},
  "geometry": {"coordinates":[20.633312,48.105242],"type":"Point"}
}