{
  "type": "Feature",
  "properties": {
    "gn:admin1_code":"18.0",
    "gn:asciiname":"Kerekestanya",
    "gn:country_code":"HU",
    "gn:dem":110,
    "gn:feature_class":"P",
    "gn:feature_code":"PPL",
    "gn:name":"Kerekestanya",
    "gn:population":0,
    "gn:timezone":"Europe/Budapest",
    "iso:country":"HU",
    "wof:name":"Kerekestanya",
    "wof:placetype":"locality"
},
  "geometry": {"coordinates":[22.50677,47.88008],"type":"Point"}
}