{
  "type": "Feature",
  "properties": {
    "gn:admin1_code":"18.0",
    "gn:asciiname":"Ludashat",
    "gn:country_code":"HU",
    "gn:dem":88,
    "gn:feature_class":"P",
    "gn:feature_code":"PPL",
    "gn:name":"Ludash\u00e1t",
    "gn:population":0,
    "gn:timezone":"Europe/Budapest",
    "iso:country":"HU",
    "wof:name":"Ludashat",
    "wof:placetype":"locality"
},
  "geometry": {"coordinates":[21.16667,47.96667],"type":"Point"}
}