{
  "type": "Feature",
  "properties": {
    "gn:admin1_code":"2.0",
    "gn:asciiname":"Szaporca",
    "gn:cc2":"HU",
    "gn:country_code":"HU",
    "gn:dem":91,
    "gn:feature_class":"P",
    "gn:feature_code":"PPL",
    "gn:name":"Szaporca",
    "gn:population":0,
    "gn:timezone":"Europe/Budapest",
    "iso:country":"HU",
    "name:epo_x_preferred":[
        "Szaporca"
    ],
    "name:fas_x_preferred":[
        "\u0633\u0627\u067e\u0648\u0631\u062a\u0633\u0627"
    ],
    "name:fra_x_preferred":[
        "Szaporca"
    ],
    "name:hrv_x_preferred":[
        "Sporica"
    ],
    "name:hun_x_preferred":[
        "Szaporca"
    ],
    "name:ita_x_preferred":[
        "Szaporca"
    ],
    "name:msa_x_preferred":[
        "Szaporca"
    ],
    "name:nld_x_preferred":[
        "Szaporca"
    ],
    "name:pol_x_preferred":[
        "Szaporca"
    ],
    "name:ron_x_preferred":[
        "Szaporca"
    ],
    "name:slk_x_preferred":[
        "Szaporca"
    ],
    "name:slv_x_preferred":[
        "Szaporca"
    ],
    "name:und_x_variant":[
        "Szaporea"
    ],
    "name:vie_x_preferred":[
        "Szaporca"
    ],
    "name:zho_x_preferred":[
        "\u7ecd\u6ce2\u5c14\u66f9"
    ],
    "wof:name":"Szaporca",
    "wof:placetype":"locality"
},
  "geometry": {"coordinates":[18.10444,45.81361],"type":"Point"}
}