{
  "type": "Feature",
  "properties": {
    "gn:admin1_code":"2.0",
    "gn:asciiname":"Szaporca",
    "gn:cc2":"HU",
    "gn:country_code":"HU",
    "gn:dem":91,
    "gn:feature_class":"P",
    "gn:feature_code":"PPL",
    "gn:name":"Szaporca",
    "gn:population":0,
    "gn:timezone":"Europe/Budapest",
    "iso:country":"HU",
    "name:und_x_variant":[
        "Szaporea"
    ],
    "wof:name":"Szaporca",
    "wof:placetype":"locality"
},
  "geometry": {"coordinates":[18.10444,45.81361],"type":"Point"}
}