{
  "type": "Feature",
  "properties": {
    "gn:admin1_code":"4.0",
    "gn:asciiname":"Sajopuspoki",
    "gn:country_code":"HU",
    "gn:dem":148,
    "gn:feature_class":"P",
    "gn:feature_code":"PPL",
    "gn:name":"Saj\u00f3p\u00fcsp\u00f6ki",
    "gn:population":0,
    "gn:timezone":"Europe/Budapest",
    "iso:country":"HU",
    "name:und_x_variant":[
        "Saj\u00f3p\u00fcsp\u00f6ki"
    ],
    "wof:name":"Sajopuspoki",
    "wof:placetype":"locality"
},
  "geometry": {"coordinates":[20.35,48.28333],"type":"Point"}
}