{
  "type": "Feature",
  "properties": {
    "gn:gn_country":"HU",
    "gn:gn_fcode":"PPL",
    "gn:gn_pop":0,
    "iso:country":"HU",
    "name:eng_x_preferred":[
        "Szentgy\u00f6rgyv\u00f6lgy"
    ],
    "name:epo_x_preferred":[
        "Szentgy\u00f6rgyv\u00f6lgy"
    ],
    "name:fas_x_preferred":[
        "\u0633\u0646\u062a\u06af\u06cc\u0648\u0631\u06af\u06cc\u0648\u0648\u0644\u06af\u06cc"
    ],
    "name:fra_x_preferred":[
        "Szentgy\u00f6rgyv\u00f6lgy"
    ],
    "name:hun_x_preferred":[
        "Szentgy\u00f6rgyv\u00f6lgy"
    ],
    "name:ita_x_preferred":[
        "Szentgy\u00f6rgyv\u00f6lgy"
    ],
    "name:msa_x_preferred":[
        "Szentgy\u00f6rgyv\u00f6lgy"
    ],
    "name:nan_x_preferred":[
        "Szentgy\u00f6rgyv\u00f6lgy"
    ],
    "name:nld_x_preferred":[
        "Szentgy\u00f6rgyv\u00f6lgy"
    ],
    "name:ron_x_preferred":[
        "Szentgy\u00f6rgyv\u00f6lgy"
    ],
    "name:slk_x_preferred":[
        "Szentgy\u00f6rgyv\u00f6lgy"
    ],
    "name:slv_x_preferred":[
        "Szentgy\u00f6rgyv\u00f6lgy"
    ],
    "name:vie_x_preferred":[
        "Szentgy\u00f6rgyv\u00f6lgy"
    ],
    "name:zho_x_preferred":[
        "\u68ee\u7279\u54f2\u5c14\u5409\u6c83\u5c14\u5409"
    ],
    "qs_pg:aaroncc":"HU",
    "qs_pg:gn_country":"HU",
    "qs_pg:gn_fcode":"PPL",
    "qs_pg:gn_pop":0,
    "qs_pg:name":"Szentgy\u00f6rgyv\u00f6lgy",
    "qs_pg:name_adm0":"Magyarorsz\u00e1g",
    "qs_pg:name_adm1":"Zala",
    "qs_pg:photos":24,
    "qs_pg:photos_1k":5,
    "qs_pg:photos_9k":1,
    "qs_pg:photos_9r":1,
    "qs_pg:photos_all":24,
    "qs_pg:photos_sr":1,
    "qs_pg:pop_sr":0,
    "qs_pg:qs_pg_placetype":"locality",
    "qs_pg:qs_pg_placetype_gp":"Town",
    "qs_pg:woe_adm0":23424844,
    "woe:adm0_id":23424844,
    "woe:name_adm0":"Magyarorsz\u00e1g",
    "woe:name_adm1":"Zala",
    "woe:placetype":"Town",
    "wof:name":"Szentgy\u00f6rgyv\u00f6lgy",
    "wof:placetype":"locality"
},
  "geometry": {"coordinates":[16.41515,46.7235],"type":"Point"}
}