{
  "type": "Feature",
  "properties": {
    "gn:admin1_code":"11.0",
    "gn:asciiname":"Balinttanya",
    "gn:country_code":"HU",
    "gn:dem":118,
    "gn:feature_class":"P",
    "gn:feature_code":"PPL",
    "gn:name":"B\u00e1linttanya",
    "gn:population":0,
    "gn:timezone":"Europe/Budapest",
    "iso:country":"HU",
    "name:und_x_variant":[
        "B\u00e1lind-tanya",
        "B\u00e1linttanya"
    ],
    "wof:name":"Balinttanya",
    "wof:placetype":"locality"
},
  "geometry": {"coordinates":[19.75,47.63333],"type":"Point"}
}