{
  "type": "Feature",
  "properties": {
    "gn:admin1_code":"17.0",
    "gn:asciiname":"Ciperes",
    "gn:country_code":"HU",
    "gn:dem":182,
    "gn:feature_class":"P",
    "gn:feature_code":"PPL",
    "gn:name":"Ciperes",
    "gn:population":0,
    "gn:timezone":"Europe/Budapest",
    "iso:country":"HU",
    "wof:name":"Ciperes",
    "wof:placetype":"locality"
},
  "geometry": {"coordinates":[17.11667000000001,46.36667],"type":"Point"}
}