{
  "type": "Feature",
  "properties": {
    "gn:admin1_code":"9.0",
    "gn:asciiname":"Dunaszentpal",
    "gn:country_code":"HU",
    "gn:dem":113,
    "gn:feature_class":"P",
    "gn:feature_code":"PPL",
    "gn:name":"Dunaszentp\u00e1l",
    "gn:population":0,
    "gn:timezone":"Europe/Budapest",
    "iso:country":"HU",
    "name:epo_x_preferred":[
        "Dunaszentp\u00e1l"
    ],
    "name:fas_x_preferred":[
        "\u062f\u0648\u0646\u0627\u0633\u0646\u062a\u067e\u0627\u0644"
    ],
    "name:fra_x_preferred":[
        "Dunaszentp\u00e1l"
    ],
    "name:hun_x_preferred":[
        "Dunaszentp\u00e1l"
    ],
    "name:ita_x_preferred":[
        "Dunaszentp\u00e1l"
    ],
    "name:msa_x_preferred":[
        "Dunaszentp\u00e1l"
    ],
    "name:nld_x_preferred":[
        "Dunaszentp\u00e1l"
    ],
    "name:pol_x_preferred":[
        "Dunaszentp\u00e1l"
    ],
    "name:ron_x_preferred":[
        "Dunaszentp\u00e1l"
    ],
    "name:slk_x_preferred":[
        "Dunaszentp\u00e1l"
    ],
    "name:slv_x_preferred":[
        "Dunaszentp\u00e1l"
    ],
    "name:spa_x_preferred":[
        "Dunaszentp\u00e1l"
    ],
    "name:vie_x_preferred":[
        "Dunaszentp\u00e1l"
    ],
    "name:zho_x_preferred":[
        "\u675c\u7459\u68ee\u7279\u5e15\u5c14"
    ],
    "wof:name":"Dunaszentpal",
    "wof:placetype":"locality"
},
  "geometry": {"coordinates":[17.50828,47.77858],"type":"Point"}
}