{
  "type": "Feature",
  "properties": {
    "gn:admin1_code":"9.0",
    "gn:asciiname":"Dunaszentpal",
    "gn:country_code":"HU",
    "gn:dem":113,
    "gn:feature_class":"P",
    "gn:feature_code":"PPL",
    "gn:name":"Dunaszentp\u00e1l",
    "gn:population":0,
    "gn:timezone":"Europe/Budapest",
    "iso:country":"HU",
    "name:und_x_variant":[
        "Dunaszentp\u00e1l"
    ],
    "wof:name":"Dunaszentpal",
    "wof:placetype":"locality"
},
  "geometry": {"coordinates":[17.50828,47.77858],"type":"Point"}
}