{
  "type": "Feature",
  "properties": {
    "gn:admin1_code":"16.0",
    "gn:asciiname":"Bedomajor",
    "gn:country_code":"HU",
    "gn:dem":158,
    "gn:feature_class":"P",
    "gn:feature_code":"PPL",
    "gn:name":"Bed\u0151major",
    "gn:population":0,
    "gn:timezone":"Europe/Budapest",
    "iso:country":"HU",
    "wof:name":"Bedomajor",
    "wof:placetype":"locality"
},
  "geometry": {"coordinates":[19.38333,47.73333],"type":"Point"}
}