{
  "type": "Feature",
  "properties": {
    "gn:admin1_code":"8.0",
    "gn:asciiname":"Annatanya",
    "gn:country_code":"HU",
    "gn:dem":150,
    "gn:feature_class":"P",
    "gn:feature_code":"PPL",
    "gn:name":"Annatanya",
    "gn:population":0,
    "gn:timezone":"Europe/Budapest",
    "iso:country":"HU",
    "name:und_x_variant":[
        "Anna-major",
        "Annatanya"
    ],
    "wof:name":"Annatanya",
    "wof:placetype":"locality"
},
  "geometry": {"coordinates":[18.75193,47.24952],"type":"Point"}
}