{
  "type": "Feature",
  "properties": {
    "gn:admin1_code":"23.0",
    "gn:asciiname":"Zalameggyes",
    "gn:country_code":"HU",
    "gn:dem":135,
    "gn:feature_class":"P",
    "gn:feature_code":"PPL",
    "gn:name":"Zalameggyes",
    "gn:population":0,
    "gn:timezone":"Europe/Budapest",
    "iso:country":"HU",
    "name:epo_x_preferred":[
        "Zalameggyes"
    ],
    "name:fas_x_preferred":[
        "\u0632\u0627\u0644\u0627\u0645\u06af\u06cc\u0634"
    ],
    "name:fra_x_preferred":[
        "Zalameggyes"
    ],
    "name:hun_x_preferred":[
        "Zalameggyes"
    ],
    "name:ita_x_preferred":[
        "Zalameggyes"
    ],
    "name:msa_x_preferred":[
        "Zalameggyes"
    ],
    "name:nld_x_preferred":[
        "Zalameggyes"
    ],
    "name:ron_x_preferred":[
        "Zalameggyes"
    ],
    "name:slk_x_preferred":[
        "Zalameggyes"
    ],
    "name:slv_x_preferred":[
        "Zalameggyes"
    ],
    "name:vie_x_preferred":[
        "Zalameggyes"
    ],
    "name:zho_x_preferred":[
        "\u4f50\u6d1b\u8fc8\u683c\u6770\u4ec0"
    ],
    "wof:name":"Zalameggyes",
    "wof:placetype":"locality"
},
  "geometry": {"coordinates":[17.21904,47.08145],"type":"Point"}
}