{
  "type": "Feature",
  "properties": {
    "gn:admin1_code":"4.0",
    "gn:asciiname":"Goncruszka",
    "gn:country_code":"HU",
    "gn:dem":167,
    "gn:feature_class":"P",
    "gn:feature_code":"PPL",
    "gn:name":"G\u00f6ncruszka",
    "gn:population":0,
    "gn:timezone":"Europe/Budapest",
    "iso:country":"HU",
    "name:und_x_variant":[
        "G\u00f6ncruszka"
    ],
    "wof:name":"Goncruszka",
    "wof:placetype":"locality"
},
  "geometry": {"coordinates":[21.25,48.45],"type":"Point"}
}