{
  "type": "Feature",
  "properties": {
    "gn:admin1_code":"4.0",
    "gn:asciiname":"Goncruszka",
    "gn:country_code":"HU",
    "gn:dem":167,
    "gn:feature_class":"P",
    "gn:feature_code":"PPL",
    "gn:name":"G\u00f6ncruszka",
    "gn:population":0,
    "gn:timezone":"Europe/Budapest",
    "iso:country":"HU",
    "name:deu_x_preferred":[
        "G\u00f6ncruszka"
    ],
    "name:epo_x_preferred":[
        "G\u00f6ncruszka"
    ],
    "name:fas_x_preferred":[
        "\u06af\u0648\u0646\u062a\u0633\u0631\u0648\u0633\u06a9\u0627"
    ],
    "name:fra_x_preferred":[
        "G\u00f6ncruszka"
    ],
    "name:heb_x_preferred":[
        "\u05d2\u05e0\u05e6\u05e8\u05d5\u05e1\u05e7\u05d4"
    ],
    "name:hun_x_preferred":[
        "G\u00f6ncruszka"
    ],
    "name:ita_x_preferred":[
        "G\u00f6ncruszka"
    ],
    "name:msa_x_preferred":[
        "G\u00f6ncruszka"
    ],
    "name:nld_x_preferred":[
        "G\u00f6ncruszka"
    ],
    "name:pol_x_preferred":[
        "G\u00f6ncruszka"
    ],
    "name:ron_x_preferred":[
        "G\u00f6ncruszka"
    ],
    "name:slk_x_preferred":[
        "G\u00f6ncruszka"
    ],
    "name:slv_x_preferred":[
        "G\u00f6ncruszka"
    ],
    "name:swe_x_preferred":[
        "G\u00f6ncruszka"
    ],
    "name:und_x_variant":[
        "G\u00f6ncruszka"
    ],
    "name:vie_x_preferred":[
        "G\u00f6ncruszka"
    ],
    "name:zho_x_preferred":[
        "\u6839\u8328\u9c81\u65af\u8003"
    ],
    "wof:name":"Goncruszka",
    "wof:placetype":"locality"
},
  "geometry": {"coordinates":[21.25,48.45],"type":"Point"}
}