{
  "type": "Feature",
  "properties": {
    "gn:gn_country":"HU",
    "gn:gn_fcode":"PPL",
    "gn:gn_pop":0,
    "iso:country":"HU",
    "name:chi_x_preferred":[
        "\u5229\u6ce2\u7279"
    ],
    "name:dut_x_preferred":[
        "Lip\u00f3t"
    ],
    "name:eng_x_preferred":[
        "Lip\u00f3t"
    ],
    "name:epo_x_preferred":[
        "Lip\u00f3t"
    ],
    "name:fre_x_preferred":[
        "Lip\u00f3t"
    ],
    "name:hun_x_preferred":[
        "Lip\u00f3t"
    ],
    "name:ita_x_preferred":[
        "Lip\u00f3t"
    ],
    "name:may_x_preferred":[
        "Lip\u00f3t"
    ],
    "name:nan_x_preferred":[
        "Lip\u00f3t"
    ],
    "name:pol_x_preferred":[
        "Lip\u00f3t"
    ],
    "name:rum_x_preferred":[
        "Lip\u00f3t"
    ],
    "name:slo_x_preferred":[
        "Lip\u00f3t"
    ],
    "name:slv_x_preferred":[
        "Lip\u00f3t"
    ],
    "qs_pg:aaroncc":"HU",
    "qs_pg:gn_country":"HU",
    "qs_pg:gn_fcode":"PPL",
    "qs_pg:gn_pop":0,
    "qs_pg:name":"Lip\u00f3t",
    "qs_pg:name_adm0":"Magyarorsz\u00e1g",
    "qs_pg:name_adm1":"Gy\u0151r-Moson-Sopron",
    "qs_pg:photos":33,
    "qs_pg:photos_1k":7,
    "qs_pg:photos_9k":1,
    "qs_pg:photos_9r":2,
    "qs_pg:photos_all":33,
    "qs_pg:photos_sr":2,
    "qs_pg:pop_sr":0,
    "qs_pg:qs_pg_placetype":"locality",
    "qs_pg:qs_pg_placetype_gp":"Town",
    "qs_pg:woe_adm0":23424844,
    "woe:adm0_id":23424844,
    "woe:name_adm0":"Magyarorsz\u00e1g",
    "woe:name_adm1":"Gy\u0151r-Moson-Sopron",
    "woe:placetype":"Town",
    "wof:name":"Lip\u00f3t",
    "wof:placetype":"locality"
},
  "geometry": {"coordinates":[17.46314,47.86192],"type":"Point"}
}