{
  "type": "Feature",
  "properties": {
    "gn:admin1_code":"24.0",
    "gn:asciiname":"Semjenhaza",
    "gn:country_code":"HU",
    "gn:dem":158,
    "gn:feature_class":"P",
    "gn:feature_code":"PPL",
    "gn:name":"Semj\u00e9nh\u00e1za",
    "gn:population":0,
    "gn:timezone":"Europe/Budapest",
    "iso:country":"HU",
    "name:epo_x_preferred":[
        "Semj\u00e9nh\u00e1za"
    ],
    "name:fas_x_preferred":[
        "\u0634\u0645\u06cc\u0646\u0647\u0627\u0632\u0627"
    ],
    "name:fra_x_preferred":[
        "Semj\u00e9nh\u00e1za"
    ],
    "name:hun_x_preferred":[
        "Semj\u00e9nh\u00e1za"
    ],
    "name:ita_x_preferred":[
        "Semj\u00e9nh\u00e1za"
    ],
    "name:msa_x_preferred":[
        "Semj\u00e9nh\u00e1za"
    ],
    "name:nld_x_preferred":[
        "Semj\u00e9nh\u00e1za"
    ],
    "name:ron_x_preferred":[
        "Semj\u00e9nh\u00e1za"
    ],
    "name:slk_x_preferred":[
        "Semj\u00e9nh\u00e1za"
    ],
    "name:slv_x_preferred":[
        "Semj\u00e9nh\u00e1za"
    ],
    "name:und_x_variant":[
        "Semj\u00e9nh\u00e1za"
    ],
    "name:vie_x_preferred":[
        "Semj\u00e9nh\u00e1za"
    ],
    "name:zho_x_preferred":[
        "\u8c22\u59c6\u5ef6\u54c8\u4f50"
    ],
    "wof:name":"Semjenhaza",
    "wof:placetype":"locality"
},
  "geometry": {"coordinates":[16.84596,46.40024],"type":"Point"}
}