{
  "type": "Feature",
  "properties": {
    "gn:admin1_code":"18.0",
    "gn:asciiname":"Sonkad",
    "gn:country_code":"HU",
    "gn:dem":115,
    "gn:feature_class":"P",
    "gn:feature_code":"PPL",
    "gn:name":"Sonk\u00e1d",
    "gn:population":0,
    "gn:timezone":"Europe/Budapest",
    "iso:country":"HU",
    "name:und_x_variant":[
        "Sonk\u00e1d"
    ],
    "wof:name":"Sonkad",
    "wof:placetype":"locality"
},
  "geometry": {"coordinates":[22.74871,48.05508],"type":"Point"}
}