{
  "type": "Feature",
  "properties": {
    "gn:admin1_code":"18.0",
    "gn:asciiname":"Vadaszszallas",
    "gn:country_code":"HU",
    "gn:dem":103,
    "gn:feature_class":"P",
    "gn:feature_code":"PPL",
    "gn:name":"Vad\u00e1szsz\u00e1ll\u00e1s",
    "gn:population":0,
    "gn:timezone":"Europe/Budapest",
    "iso:country":"HU",
    "wof:name":"Vadaszszallas",
    "wof:placetype":"locality"
},
  "geometry": {"coordinates":[21.55,48.11667],"type":"Point"}
}