{
  "type": "Feature",
  "properties": {
    "gn:admin1_code":"20.0",
    "gn:asciiname":"Ketpo",
    "gn:cc2":"HU",
    "gn:country_code":"HU",
    "gn:dem":82,
    "gn:feature_class":"P",
    "gn:feature_code":"PPL",
    "gn:name":"K\u00e9tp\u00f3",
    "gn:population":0,
    "gn:timezone":"Europe/Budapest",
    "iso:country":"HU",
    "name:und_x_variant":[
        "Pusztap\u00f3",
        "K\u00e9tp\u00f3"
    ],
    "wof:name":"Ketpo",
    "wof:placetype":"locality"
},
  "geometry": {"coordinates":[20.46667,47.08333],"type":"Point"}
}