{
  "type": "Feature",
  "properties": {
    "gn:admin1_code":"2.0",
    "gn:asciiname":"Laposmezo",
    "gn:country_code":"HU",
    "gn:dem":254,
    "gn:feature_class":"P",
    "gn:feature_code":"PPL",
    "gn:name":"Laposmez\u0151",
    "gn:population":0,
    "gn:timezone":"Europe/Budapest",
    "iso:country":"HU",
    "wof:name":"Laposmezo",
    "wof:placetype":"locality"
},
  "geometry": {"coordinates":[18.23333,46.25],"type":"Point"}
}