{
  "type": "Feature",
  "properties": {
    "gn:admin1_code":"12.0",
    "gn:asciiname":"Kisigmand",
    "gn:country_code":"HU",
    "gn:dem":128,
    "gn:feature_class":"P",
    "gn:feature_code":"PPL",
    "gn:name":"Kisigm\u00e1nd",
    "gn:population":0,
    "gn:timezone":"Europe/Budapest",
    "iso:country":"HU",
    "name:und_x_variant":[
        "Kisigm\u00e1nd"
    ],
    "wof:name":"Kisigmand",
    "wof:placetype":"locality"
},
  "geometry": {"coordinates":[18.09893,47.65396],"type":"Point"}
}