{
  "type": "Feature",
  "properties": {
    "gn:admin1_code":"12.0",
    "gn:asciiname":"Kisigmand",
    "gn:country_code":"HU",
    "gn:dem":128,
    "gn:feature_class":"P",
    "gn:feature_code":"PPL",
    "gn:name":"Kisigm\u00e1nd",
    "gn:population":0,
    "gn:timezone":"Europe/Budapest",
    "iso:country":"HU",
    "name:epo_x_preferred":[
        "Kisigm\u00e1nd"
    ],
    "name:fas_x_preferred":[
        "\u06a9\u06cc\u0634\u06cc\u06af\u0645\u0627\u0646\u062f"
    ],
    "name:fra_x_preferred":[
        "Kisigm\u00e1nd"
    ],
    "name:hun_x_preferred":[
        "Kisigm\u00e1nd"
    ],
    "name:ita_x_preferred":[
        "Kisigm\u00e1nd"
    ],
    "name:msa_x_preferred":[
        "Kisigm\u00e1nd"
    ],
    "name:nld_x_preferred":[
        "Kisigm\u00e1nd"
    ],
    "name:ron_x_preferred":[
        "Kisigm\u00e1nd"
    ],
    "name:slk_x_preferred":[
        "Kisigm\u00e1nd"
    ],
    "name:slv_x_preferred":[
        "Kisigm\u00e1nd"
    ],
    "name:und_x_variant":[
        "Kisigm\u00e1nd"
    ],
    "name:vie_x_preferred":[
        "Kisigm\u00e1nd"
    ],
    "name:zho_x_preferred":[
        "\u57fa\u5e0c\u683c\u66fc\u5fb7"
    ],
    "wof:name":"Kisigmand",
    "wof:placetype":"locality"
},
  "geometry": {"coordinates":[18.09893,47.65396],"type":"Point"}
}