{
  "type": "Feature",
  "properties": {
    "gn:admin1_code":"11.0",
    "gn:asciiname":"Csardamajor",
    "gn:country_code":"HU",
    "gn:dem":88,
    "gn:feature_class":"P",
    "gn:feature_code":"PPL",
    "gn:name":"Cs\u00e1rdamajor",
    "gn:population":0,
    "gn:timezone":"Europe/Budapest",
    "iso:country":"HU",
    "wof:name":"Csardamajor",
    "wof:placetype":"locality"
},
  "geometry": {"coordinates":[20.58333,47.61667],"type":"Point"}
}