{
  "type": "Feature",
  "properties": {
    "gn:admin1_code":"2.0",
    "gn:asciiname":"Gerenyes",
    "gn:country_code":"HU",
    "gn:dem":144,
    "gn:feature_class":"P",
    "gn:feature_code":"PPL",
    "gn:name":"Ger\u00e9nyes",
    "gn:population":0,
    "gn:timezone":"Europe/Budapest",
    "iso:country":"HU",
    "name:epo_x_preferred":[
        "Ger\u00e9nyes"
    ],
    "name:fas_x_preferred":[
        "\u06af\u0631\u0646\u06cc\u0634"
    ],
    "name:fra_x_preferred":[
        "Ger\u00e9nyes"
    ],
    "name:hrv_x_preferred":[
        "Grenji\u0161"
    ],
    "name:hun_x_preferred":[
        "Ger\u00e9nyes"
    ],
    "name:ita_x_preferred":[
        "Ger\u00e9nyes"
    ],
    "name:msa_x_preferred":[
        "Ger\u00e9nyes"
    ],
    "name:nld_x_preferred":[
        "Ger\u00e9nyes"
    ],
    "name:pol_x_preferred":[
        "Ger\u00e9nyes"
    ],
    "name:ron_x_preferred":[
        "Ger\u00e9nyes"
    ],
    "name:slk_x_preferred":[
        "Ger\u00e9nyes"
    ],
    "name:slv_x_preferred":[
        "Ger\u00e9nyes"
    ],
    "name:und_x_variant":[
        "Ger\u00e9nyes"
    ],
    "name:vie_x_preferred":[
        "Ger\u00e9nyes"
    ],
    "name:zho_x_preferred":[
        "\u76d6\u96f7\u6d85\u4ec0"
    ],
    "wof:name":"Gerenyes",
    "wof:placetype":"locality"
},
  "geometry": {"coordinates":[18.18208,46.306],"type":"Point"}
}