{
  "type": "Feature",
  "properties": {
    "gn:admin1_code":"20.0",
    "gn:asciiname":"Kuncsorba",
    "gn:cc2":"HU",
    "gn:country_code":"HU",
    "gn:dem":80,
    "gn:feature_class":"P",
    "gn:feature_code":"PPL",
    "gn:name":"Kuncsorba",
    "gn:population":0,
    "gn:timezone":"Europe/Budapest",
    "iso:country":"HU",
    "name:deu_x_preferred":[
        "Kuncsorba"
    ],
    "name:epo_x_preferred":[
        "Kuncsorba"
    ],
    "name:fas_x_preferred":[
        "\u06a9\u0648\u0646\u0686\u0648\u0631\u0628\u0627"
    ],
    "name:fra_x_preferred":[
        "Kuncsorba"
    ],
    "name:hun_x_preferred":[
        "Kuncsorba"
    ],
    "name:ita_x_preferred":[
        "Kuncsorba"
    ],
    "name:msa_x_preferred":[
        "Kuncsorba"
    ],
    "name:nld_x_preferred":[
        "Kuncsorba"
    ],
    "name:ron_x_preferred":[
        "Kuncsorba"
    ],
    "name:slk_x_preferred":[
        "Kuncsorba"
    ],
    "name:slv_x_preferred":[
        "Kuncsorba"
    ],
    "name:und_x_variant":[
        "Csorbai Puszta",
        "Kuncsorba"
    ],
    "name:vie_x_preferred":[
        "Kuncsorba"
    ],
    "name:zho_x_preferred":[
        "\u6606\u4e54\u5c14\u9c8d"
    ],
    "wof:name":"Kuncsorba",
    "wof:placetype":"locality"
},
  "geometry": {"coordinates":[20.56667,47.13333],"type":"Point"}
}