{
  "type": "Feature",
  "properties": {
    "gn:admin1_code":"24.0",
    "gn:asciiname":"Liszo",
    "gn:country_code":"HU",
    "gn:dem":158,
    "gn:feature_class":"P",
    "gn:feature_code":"PPL",
    "gn:name":"Lisz\u00f3",
    "gn:population":0,
    "gn:timezone":"Europe/Budapest",
    "iso:country":"HU",
    "name:und_x_variant":[
        "Lisz\u00f3"
    ],
    "wof:name":"Liszo",
    "wof:placetype":"locality"
},
  "geometry": {"coordinates":[17.00656,46.36635],"type":"Point"}
}