{
  "type": "Feature",
  "properties": {
    "gn:admin1_code":"17.0",
    "gn:asciiname":"Fischerpuszta",
    "gn:country_code":"HU",
    "gn:dem":121,
    "gn:feature_class":"P",
    "gn:feature_code":"PPL",
    "gn:name":"Fischerpuszta",
    "gn:population":0,
    "gn:timezone":"Europe/Budapest",
    "iso:country":"HU",
    "wof:name":"Fischerpuszta",
    "wof:placetype":"locality"
},
  "geometry": {"coordinates":[17.51667,46.58333],"type":"Point"}
}