{
  "type": "Feature",
  "properties": {
    "gn:admin1_code":"1.0",
    "gn:asciiname":"Csavolyi Tanyak",
    "gn:country_code":"HU",
    "gn:dem":124,
    "gn:feature_class":"P",
    "gn:feature_code":"PPL",
    "gn:name":"Cs\u00e1volyi Tany\u00e1k",
    "gn:population":0,
    "gn:timezone":"Europe/Budapest",
    "iso:country":"HU",
    "wof:name":"Csavolyi Tanyak",
    "wof:placetype":"locality"
},
  "geometry": {"coordinates":[19.15,46.18333],"type":"Point"}
}