{
  "type": "Feature",
  "properties": {
    "iso:country":"HU",
    "name:hun_x_preferred":[
        "Soroksar-\u00dajtelep"
    ],
    "wof:name":"Soroksar-Ujtelep",
    "wof:placetype":"neighbourhood"
},
  "geometry": {"coordinates":[19.12879671965553,47.41776969872379],"type":"Point"}
}