{
  "type": "Feature",
  "properties": {
    "gn:admin1_code":"24.0",
    "gn:asciiname":"Teskandi Malom",
    "gn:country_code":"HU",
    "gn:dem":157,
    "gn:feature_class":"P",
    "gn:feature_code":"PPL",
    "gn:name":"Teskandi Malom",
    "gn:population":0,
    "gn:timezone":"Europe/Budapest",
    "iso:country":"HU",
    "name:und_x_variant":[
        "Tesk\u00e1ndi Tany\u00e1k"
    ],
    "wof:name":"Teskandi Malom",
    "wof:placetype":"locality"
},
  "geometry": {"coordinates":[16.77859,46.8628],"type":"Point"}
}