{
  "type": "Feature",
  "properties": {
    "gn:admin1_code":"9.0",
    "gn:asciiname":"Csaszarret",
    "gn:country_code":"HU",
    "gn:dem":115,
    "gn:feature_class":"P",
    "gn:feature_code":"PPL",
    "gn:name":"Cs\u00e1sz\u00e1rr\u00e9t",
    "gn:population":0,
    "gn:timezone":"Europe/Budapest",
    "iso:country":"HU",
    "wof:name":"Csaszarret",
    "wof:placetype":"locality"
},
  "geometry": {"coordinates":[17.18799,47.80658],"type":"Point"}
}