{
  "type": "Feature",
  "properties": {
    "gn:admin1_code":"10.0",
    "gn:asciiname":"Ozes",
    "gn:country_code":"HU",
    "gn:dem":83,
    "gn:feature_class":"P",
    "gn:feature_code":"PPL",
    "gn:name":"\u0150zes",
    "gn:population":0,
    "gn:timezone":"Europe/Budapest",
    "iso:country":"HU",
    "wof:name":"Ozes",
    "wof:placetype":"locality"
},
  "geometry": {"coordinates":[21.03333,47.41667],"type":"Point"}
}