{
  "type": "Feature",
  "properties": {
    "gn:admin1_code":"4.0",
    "gn:asciiname":"Bartosdulo",
    "gn:cc2":"HU",
    "gn:country_code":"HU",
    "gn:dem":92,
    "gn:feature_class":"P",
    "gn:feature_code":"PPL",
    "gn:name":"Bartosd\u0171l\u0151",
    "gn:population":0,
    "gn:timezone":"Europe/Budapest",
    "iso:country":"HU",
    "name:und_x_variant":[
        "B\u00e1rdos-tanya"
    ],
    "wof:name":"Bartosdulo",
    "wof:placetype":"locality"
},
  "geometry": {"coordinates":[21.41667,48.08333],"type":"Point"}
}