{
  "type": "Feature",
  "properties": {
    "gn:admin1_code":"9.0",
    "gn:asciiname":"Cserimajor",
    "gn:country_code":"HU",
    "gn:dem":145,
    "gn:feature_class":"P",
    "gn:feature_code":"PPL",
    "gn:name":"Cs\u00e9rimajor",
    "gn:population":0,
    "gn:timezone":"Europe/Budapest",
    "iso:country":"HU",
    "wof:name":"Cserimajor",
    "wof:placetype":"locality"
},
  "geometry": {"coordinates":[16.93913,47.42456],"type":"Point"}
}