{
  "type": "Feature",
  "properties": {
    "gn:admin1_code":"3.0",
    "gn:asciiname":"Csizmadiafold",
    "gn:country_code":"HU",
    "gn:dem":80,
    "gn:feature_class":"P",
    "gn:feature_code":"PPLL",
    "gn:name":"Csizmadiaf\u00f6ld",
    "gn:population":0,
    "gn:timezone":"Europe/Budapest",
    "iso:country":"HU",
    "wof:name":"Csizmadiafold",
    "wof:placetype":"locality"
},
  "geometry": {"coordinates":[20.66667,46.71667],"type":"Point"}
}