{
  "type": "Feature",
  "properties": {
    "iso:country":"HU",
    "name:chi_x_preferred":[
        "\u8003\u6ce2\u4ec0\u666e\u6d1b"
    ],
    "name:dut_x_preferred":[
        "Kapospula"
    ],
    "name:eng_x_preferred":[
        "Kapospula"
    ],
    "name:epo_x_preferred":[
        "Kapospula"
    ],
    "name:fra_x_preferred":[
        "Kapospula"
    ],
    "name:fre_x_preferred":[
        "Kapospula"
    ],
    "name:ger_x_preferred":[
        "Kapospula"
    ],
    "name:hun_x_preferred":[
        "Kapospula"
    ],
    "name:ita_x_preferred":[
        "Kapospula"
    ],
    "name:may_x_preferred":[
        "Kapospula"
    ],
    "name:msa_x_preferred":[
        "Kapospula"
    ],
    "name:nan_x_preferred":[
        "Kapospula"
    ],
    "name:nld_x_preferred":[
        "Kapospula"
    ],
    "name:ron_x_preferred":[
        "Kapospula"
    ],
    "name:rum_x_preferred":[
        "Kapospula"
    ],
    "name:slk_x_preferred":[
        "Kapospula"
    ],
    "name:slo_x_preferred":[
        "Kapospula"
    ],
    "name:slv_x_preferred":[
        "Kapospula"
    ],
    "name:vie_x_preferred":[
        "Kapospula"
    ],
    "name:zho_min_nan_x_preferred":[
        "Kapospula"
    ],
    "name:zho_x_preferred":[
        "\u8003\u6ce2\u4ec0\u666e\u6d1b"
    ],
    "qs:a0":"Magyarorsz\u00e1g",
    "qs:a1":"*Tolna",
    "qs:a1r":"0D\u00e9l-Dun\u00e1nt\u00fal",
    "qs:adm0":"Magyarorsz\u00e1g",
    "qs:la_lc":"*",
    "qs:level":"locality",
    "qs:loc":"Kapospula",
    "qs:loc_alt":"Kapospula",
    "qs:pop":0,
    "qs:type":"buffered point",
    "wd:wordcount":11,
    "wof:name":"Kapospula",
    "wof:placetype":"locality"
},
  "geometry": {"coordinates":[18.103599,46.371073],"type":"Point"}
}