{
  "type": "Feature",
  "properties": {
    "gn:admin1_code":"14.0",
    "gn:asciiname":"Loszegpuszta",
    "gn:country_code":"HU",
    "gn:dem":250,
    "gn:feature_class":"P",
    "gn:feature_code":"PPL",
    "gn:name":"L\u00f3szegpuszta",
    "gn:population":0,
    "gn:timezone":"Europe/Budapest",
    "iso:country":"HU",
    "wof:name":"Loszegpuszta",
    "wof:placetype":"locality"
},
  "geometry": {"coordinates":[19.98677,48.13476],"type":"Point"}
}