{
  "type": "Feature",
  "properties": {
    "gn:admin1_code":"21.0",
    "gn:asciiname":"Celpuszta",
    "gn:cc2":"HU",
    "gn:country_code":"HU",
    "gn:dem":249,
    "gn:feature_class":"P",
    "gn:feature_code":"PPL",
    "gn:name":"C\u00e9lpuszta",
    "gn:population":0,
    "gn:timezone":"Europe/Budapest",
    "iso:country":"HU",
    "name:und_x_variant":[
        "C\u00e9l",
        "C\u00e9lpuszta"
    ],
    "wof:name":"Celpuszta",
    "wof:placetype":"locality"
},
  "geometry": {"coordinates":[18.38333,46.38333],"type":"Point"}
}