{
  "type": "Feature",
  "properties": {
    "iso:country":"HU",
    "name:hun_x_preferred":[
        "Farkashegy"
    ],
    "name:unk_x_variant":[
        "Farkashegy"
    ],
    "qs:gn_adm0_cc":"HU",
    "qs:gn_local":718739,
    "qs:gn_nam_loc":"Kisv\u00e1rda, Kisv\u00e1rda, Szabolcs-Szatm\u00e1r-Bereg, HU",
    "qs:gn_namadm1":"18",
    "qs:local_max":42,
    "qs:local_sum":42,
    "qs:localhoods":1,
    "qs:name":"Farkashegy",
    "qs:name_adm0":"Magyarorsz\u00e1g",
    "qs:name_adm1":"Szabolcs-Szatm\u00e1r-Bereg",
    "qs:name_adm2":"Kisv\u00e1rda",
    "qs:name_local":"Kisv\u00e1rda",
    "qs:photo_max":25,
    "qs:photo_sum":42,
    "qs:placetype":"Suburb",
    "qs:quad_count":7,
    "qs:woe_adm0":23424844,
    "qs:woe_adm1":12577925,
    "qs:woe_adm2":12594690,
    "qs:woe_lau":0,
    "qs:woe_local":810092,
    "qs:woe_ver":"7.10.0",
    "wof:lang":[
        "hun"
    ],
    "wof:name":"Farkashegy",
    "wof:placetype":"neighbourhood"
},
  "geometry": {"coordinates":[22.072579,48.229117],"type":"Point"}
}