{
  "type": "Feature",
  "properties": {
    "gn:admin1_code":"10.0",
    "gn:asciiname":"Asvany",
    "gn:cc2":"HU",
    "gn:country_code":"HU",
    "gn:dem":88,
    "gn:feature_class":"P",
    "gn:feature_code":"PPL",
    "gn:name":"\u00c1sv\u00e1ny",
    "gn:population":0,
    "gn:timezone":"Europe/Budapest",
    "iso:country":"HU",
    "name:und_x_variant":[
        "\u00c1sv\u00e1ny-k\u00fat",
        "\u00c1sv\u00e1ny"
    ],
    "wof:name":"Asvany",
    "wof:placetype":"locality"
},
  "geometry": {"coordinates":[21.46667,47.15],"type":"Point"}
}