{
  "type": "Feature",
  "properties": {
    "gn:admin1_code":"1.0",
    "gn:asciiname":"Matetelke",
    "gn:country_code":"HU",
    "gn:dem":121,
    "gn:feature_class":"P",
    "gn:feature_code":"PPL",
    "gn:name":"M\u00e1t\u00e9telke",
    "gn:population":0,
    "gn:timezone":"Europe/Budapest",
    "iso:country":"HU",
    "name:und_x_variant":[
        "M\u00e1t\u00e9telke"
    ],
    "wof:name":"Matetelke",
    "wof:placetype":"locality"
},
  "geometry": {"coordinates":[19.28037,46.16167],"type":"Point"}
}