{
  "type": "Feature",
  "properties": {
    "gn:admin1_code":"1.0",
    "gn:asciiname":"Matetelke",
    "gn:country_code":"HU",
    "gn:dem":121,
    "gn:feature_class":"P",
    "gn:feature_code":"PPL",
    "gn:name":"M\u00e1t\u00e9telke",
    "gn:population":0,
    "gn:timezone":"Europe/Budapest",
    "iso:country":"HU",
    "name:ces_x_preferred":[
        "M\u00e1t\u00e9telke"
    ],
    "name:epo_x_preferred":[
        "M\u00e1t\u00e9telke"
    ],
    "name:fas_x_preferred":[
        "\u0645\u0627\u062a\u062a\u0644\u06a9\u0647"
    ],
    "name:fra_x_preferred":[
        "M\u00e1t\u00e9telke"
    ],
    "name:hrv_x_preferred":[
        "Matevi\u0107"
    ],
    "name:hun_x_preferred":[
        "M\u00e1t\u00e9telke"
    ],
    "name:ita_x_preferred":[
        "M\u00e1t\u00e9telke"
    ],
    "name:msa_x_preferred":[
        "M\u00e1t\u00e9telke"
    ],
    "name:nld_x_preferred":[
        "M\u00e1t\u00e9telke"
    ],
    "name:pol_x_preferred":[
        "M\u00e1t\u00e9telke"
    ],
    "name:ron_x_preferred":[
        "M\u00e1t\u00e9telke"
    ],
    "name:slk_x_preferred":[
        "M\u00e1t\u00e9telke"
    ],
    "name:slv_x_preferred":[
        "M\u00e1t\u00e9telke"
    ],
    "name:spa_x_preferred":[
        "M\u00e1t\u00e9telke"
    ],
    "name:srp_x_preferred":[
        "\u041c\u0430\u0442\u0435\u0442\u0435\u043b\u043a\u0435"
    ],
    "name:vie_x_preferred":[
        "M\u00e1t\u00e9telke"
    ],
    "name:zho_x_preferred":[
        "\u9a6c\u6cf0\u6cf0\u5c14\u51ef"
    ],
    "wof:name":"Matetelke",
    "wof:placetype":"locality"
},
  "geometry": {"coordinates":[19.28037,46.16167],"type":"Point"}
}