{
  "type": "Feature",
  "properties": {
    "gn:admin1_code":"14.0",
    "gn:asciiname":"Bezmalapja",
    "gn:country_code":"HU",
    "gn:dem":334,
    "gn:feature_class":"P",
    "gn:feature_code":"PPL",
    "gn:name":"B\u00e9zmalapja",
    "gn:population":0,
    "gn:timezone":"Europe/Budapest",
    "iso:country":"HU",
    "wof:name":"Bezmalapja",
    "wof:placetype":"locality"
},
  "geometry": {"coordinates":[19.58333,47.95],"type":"Point"}
}