{
  "type": "Feature",
  "properties": {
    "gn:admin1_code":"24.0",
    "gn:asciiname":"Buslakpuszta",
    "gn:country_code":"HU",
    "gn:dem":212,
    "gn:feature_class":"P",
    "gn:feature_code":"PPL",
    "gn:name":"B\u00faslakpuszta",
    "gn:population":0,
    "gn:timezone":"Europe/Budapest",
    "iso:country":"HU",
    "name:und_x_variant":[
        "B\u00faslakmajor",
        "B\u00faslakpuszta"
    ],
    "wof:name":"Buslakpuszta",
    "wof:placetype":"locality"
},
  "geometry": {"coordinates":[16.82067,46.79558],"type":"Point"}
}