{
  "type": "Feature",
  "properties": {
    "gn:admin1_code":"21.0",
    "gn:asciiname":"Alsomocsarasdulo",
    "gn:country_code":"HU",
    "gn:dem":164,
    "gn:feature_class":"P",
    "gn:feature_code":"PPL",
    "gn:name":"Als\u00f3mocsarasd\u0171l\u0151",
    "gn:population":0,
    "gn:timezone":"Europe/Budapest",
    "iso:country":"HU",
    "wof:name":"Alsomocsarasdulo",
    "wof:placetype":"locality"
},
  "geometry": {"coordinates":[18.45,46.41667],"type":"Point"}
}