{
  "type": "Feature",
  "properties": {
    "gn:admin1_code":"10.0",
    "gn:asciiname":"Sorefold",
    "gn:country_code":"HU",
    "gn:dem":86,
    "gn:feature_class":"P",
    "gn:feature_code":"PPLL",
    "gn:name":"S\u0151ref\u00f6ld",
    "gn:population":0,
    "gn:timezone":"Europe/Budapest",
    "iso:country":"HU",
    "wof:name":"Sorefold",
    "wof:placetype":"locality"
},
  "geometry": {"coordinates":[21.18333,47.33333],"type":"Point"}
}