{
  "type": "Feature",
  "properties": {
    "iso:country":"HU",
    "oa:elevation_ft":"440",
    "oa:type":"small_airport",
    "woe:hierarchy":{
        "country_id":23424844,
        "county_id":12595155,
        "planet_id":1,
        "state_id":12577918
    },
    "wof:name":"Fertoszentmiklos Repuloter",
    "wof:placetype":"campus"
},
  "geometry": {"coordinates":[16.845277777778,47.582777777778],"type":"Point"}
}