{
  "type": "Feature",
  "properties": {
    "iso:country":"HU",
    "name:ceb_x_preferred":[
        "Fert\u0151szentmikl\u00f3s Airport"
    ],
    "name:deu_x_preferred":[
        "Meidl Airport"
    ],
    "name:eng_x_preferred":[
        "Fert\u0151szentmikl\u00f3s Airport"
    ],
    "name:fas_x_preferred":[
        "\u0641\u0631\u0648\u062f\u06af\u0627\u0647 \u0641\u0631\u062a\u0648\u0633\u0632\u0646\u062a\u0645\u06cc\u06a9\u0644\u0648\u0633"
    ],
    "name:hun_x_preferred":[
        "Meidl Airport Fert\u0151szentmikl\u00f3s"
    ],
    "name:jpn_x_preferred":[
        "\u30d5\u30a7\u30eb\u30c6\u30fc\u30bb\u30f3\u30c8\u30df\u30af\u30ed\u30fc\u30b7\u30e5\u7a7a\u6e2f"
    ],
    "name:msa_x_preferred":[
        "Lapangan Terbang Fertoszentmiklos"
    ],
    "name:pol_x_preferred":[
        "Port lotniczy Fert\u0151szentmikl\u00f3s"
    ],
    "name:ron_x_preferred":[
        "Aeroportul Fert\u0151szentmikl\u00f3s"
    ],
    "name:rus_x_preferred":[
        "\u0424\u0435\u0440\u0442\u0451\u0441\u0435\u043d\u0442\u043c\u0438\u043a\u043b\u043e\u0448"
    ],
    "name:swe_x_preferred":[
        "Fert\u0151szentmikl\u00f3s Airport"
    ],
    "name:tgk_x_preferred":[
        "\u0424\u0443\u0440\u0443\u0434\u0433\u043e\u04b3\u0438 \u0444\u0440\u0442\u0443\u0441\u0437\u043d\u0442\u043c\u0438\u043a\u043b\u0443\u0441"
    ],
    "name:vie_x_preferred":[
        "S\u00e2n bay Fert\u0151szentmikl\u00f3s"
    ],
    "oa:elevation_ft":"440",
    "oa:type":"small_airport",
    "woe:hierarchy":{
        "country_id":23424844,
        "county_id":12595155,
        "planet_id":1,
        "state_id":12577918
    },
    "wof:name":"Fertoszentmiklos Repuloter",
    "wof:placetype":"campus"
},
  "geometry": {"coordinates":[16.845277777778,47.582777777778],"type":"Point"}
}