{
  "type": "Feature",
  "properties": {
    "gn:admin1_code":"16.0",
    "gn:asciiname":"Egerszegpuszta",
    "gn:country_code":"HU",
    "gn:dem":165,
    "gn:feature_class":"P",
    "gn:feature_code":"PPL",
    "gn:name":"Egerszegpuszta",
    "gn:population":0,
    "gn:timezone":"Europe/Budapest",
    "iso:country":"HU",
    "name:und_x_variant":[
        "Egerszeg",
        "Egerszegpuszta"
    ],
    "wof:name":"Egerszegpuszta",
    "wof:placetype":"locality"
},
  "geometry": {"coordinates":[19.40525,47.62867],"type":"Point"}
}