{
  "type": "Feature",
  "properties": {
    "gn:admin1_code":"23.0",
    "gn:asciiname":"Pula",
    "gn:country_code":"HU",
    "gn:dem":210,
    "gn:feature_class":"P",
    "gn:feature_code":"PPL",
    "gn:name":"Pula",
    "gn:population":0,
    "gn:timezone":"Europe/Budapest",
    "iso:country":"HU",
    "name:ces_x_preferred":[
        "Pula"
    ],
    "name:deu_x_preferred":[
        "Pula"
    ],
    "name:epo_x_preferred":[
        "Pula"
    ],
    "name:fas_x_preferred":[
        "\u067e\u0648\u0644\u0627"
    ],
    "name:fra_x_preferred":[
        "Pula"
    ],
    "name:hun_x_preferred":[
        "Pula"
    ],
    "name:ita_x_preferred":[
        "Pula"
    ],
    "name:msa_x_preferred":[
        "Pula"
    ],
    "name:ron_x_preferred":[
        "Pula"
    ],
    "name:slk_x_preferred":[
        "Pula"
    ],
    "name:slv_x_preferred":[
        "Pula"
    ],
    "name:vie_x_preferred":[
        "Pula"
    ],
    "wof:name":"Pula",
    "wof:placetype":"locality"
},
  "geometry": {"coordinates":[17.64957,46.99893],"type":"Point"}
}