{
  "type": "Feature",
  "properties": {
    "gn:admin1_code":"24.0",
    "gn:asciiname":"Ujtelep",
    "gn:country_code":"HU",
    "gn:dem":158,
    "gn:feature_class":"P",
    "gn:feature_code":"PPL",
    "gn:name":"\u00dajtelep",
    "gn:population":0,
    "gn:timezone":"Europe/Budapest",
    "iso:country":"HU",
    "wof:name":"Ujtelep",
    "wof:placetype":"locality"
},
  "geometry": {"coordinates":[16.58333,46.56667],"type":"Point"}
}