{
  "type": "Feature",
  "properties": {
    "gn:admin1_code":"16.0",
    "gn:asciiname":"Nagytanya",
    "gn:country_code":"HU",
    "gn:dem":85,
    "gn:feature_class":"P",
    "gn:feature_code":"PPL",
    "gn:name":"Nagytanya",
    "gn:population":0,
    "gn:timezone":"Europe/Budapest",
    "iso:country":"HU",
    "wof:name":"Nagytanya",
    "wof:placetype":"locality"
},
  "geometry": {"coordinates":[20.01667,47.31667],"type":"Point"}
}