{
  "type": "Feature",
  "properties": {
    "gn:admin1_code":"2.0",
    "gn:asciiname":"Bezedek",
    "gn:country_code":"HU",
    "gn:dem":119,
    "gn:feature_class":"P",
    "gn:feature_code":"PPL",
    "gn:name":"Bezedek",
    "gn:population":0,
    "gn:timezone":"Europe/Budapest",
    "iso:country":"HU",
    "name:deu_x_preferred":[
        "Bezedek"
    ],
    "name:epo_x_preferred":[
        "Bezedek"
    ],
    "name:fas_x_preferred":[
        "\u0628\u0632\u062f\u06a9"
    ],
    "name:fra_x_preferred":[
        "Bezedek"
    ],
    "name:hrv_x_preferred":[
        "Bezedek"
    ],
    "name:hun_x_preferred":[
        "Bezedek"
    ],
    "name:ita_x_preferred":[
        "Bezedek"
    ],
    "name:msa_x_preferred":[
        "Bezedek"
    ],
    "name:nld_x_preferred":[
        "Bezedek"
    ],
    "name:pol_x_preferred":[
        "Bezedek"
    ],
    "name:ron_x_preferred":[
        "Bezedek"
    ],
    "name:slk_x_preferred":[
        "Bezedek"
    ],
    "name:slv_x_preferred":[
        "Bezedek"
    ],
    "name:srp_x_preferred":[
        "\u0411\u0435\u0437\u0435\u0434\u0435\u043a"
    ],
    "name:vie_x_preferred":[
        "Bezedek"
    ],
    "name:zho_x_preferred":[
        "\u62dc\u6cfd\u4ee3\u514b"
    ],
    "wof:name":"Bezedek",
    "wof:placetype":"locality"
},
  "geometry": {"coordinates":[18.58639,45.86472],"type":"Point"}
}