{
  "type": "Feature",
  "properties": {
    "gn:admin1_code":"18.0",
    "gn:asciiname":"Golyatanya",
    "gn:country_code":"HU",
    "gn:dem":111,
    "gn:feature_class":"P",
    "gn:feature_code":"PPL",
    "gn:name":"G\u00f3lyatanya",
    "gn:population":0,
    "gn:timezone":"Europe/Budapest",
    "iso:country":"HU",
    "wof:name":"Golyatanya",
    "wof:placetype":"locality"
},
  "geometry": {"coordinates":[22.31667,48.05],"type":"Point"}
}