{
  "type": "Feature",
  "properties": {
    "gn:admin1_code":"17.0",
    "gn:asciiname":"Osztopan",
    "gn:country_code":"HU",
    "gn:dem":151,
    "gn:feature_class":"P",
    "gn:feature_code":"PPL",
    "gn:name":"Osztop\u00e1n",
    "gn:population":0,
    "gn:timezone":"Europe/Budapest",
    "iso:country":"HU",
    "name:und_x_variant":[
        "Osztop\u00e1n"
    ],
    "wof:name":"Osztopan",
    "wof:placetype":"locality"
},
  "geometry": {"coordinates":[17.66997000000001,46.51921],"type":"Point"}
}