{
  "type": "Feature",
  "properties": {
    "gn:admin1_code":"17.0",
    "gn:asciiname":"Osztopan",
    "gn:country_code":"HU",
    "gn:dem":151,
    "gn:feature_class":"P",
    "gn:feature_code":"PPL",
    "gn:name":"Osztop\u00e1n",
    "gn:population":0,
    "gn:timezone":"Europe/Budapest",
    "iso:country":"HU",
    "name:ces_x_preferred":[
        "Osztop\u00e1n"
    ],
    "name:epo_x_preferred":[
        "Osztop\u00e1n"
    ],
    "name:fas_x_preferred":[
        "\u0627\u0648\u0633\u062a\u0648\u067e\u0627\u0646"
    ],
    "name:fra_x_preferred":[
        "Osztop\u00e1n"
    ],
    "name:hun_x_preferred":[
        "Osztop\u00e1n"
    ],
    "name:ita_x_preferred":[
        "Osztop\u00e1n"
    ],
    "name:msa_x_preferred":[
        "Osztop\u00e1n"
    ],
    "name:nld_x_preferred":[
        "Osztop\u00e1n"
    ],
    "name:ron_x_preferred":[
        "Osztop\u00e1n"
    ],
    "name:slk_x_preferred":[
        "Osztop\u00e1n"
    ],
    "name:slv_x_preferred":[
        "Osztop\u00e1n"
    ],
    "name:vie_x_preferred":[
        "Osztop\u00e1n"
    ],
    "name:zho_x_preferred":[
        "\u6b27\u65af\u6258\u6f58"
    ],
    "wof:name":"Osztopan",
    "wof:placetype":"locality"
},
  "geometry": {"coordinates":[17.66997000000001,46.51921],"type":"Point"}
}