{
  "type": "Feature",
  "properties": {
    "gn:admin1_code":"14.0",
    "gn:asciiname":"Herencseny",
    "gn:country_code":"HU",
    "gn:dem":207,
    "gn:feature_class":"P",
    "gn:feature_code":"PPL",
    "gn:name":"Herencs\u00e9ny",
    "gn:population":0,
    "gn:timezone":"Europe/Budapest",
    "iso:country":"HU",
    "name:epo_x_preferred":[
        "Herencs\u00e9ny"
    ],
    "name:fra_x_preferred":[
        "Herencs\u00e9ny"
    ],
    "name:hun_x_preferred":[
        "Herencs\u00e9ny"
    ],
    "name:ita_x_preferred":[
        "Herencs\u00e9ny"
    ],
    "name:msa_x_preferred":[
        "Herencs\u00e9ny"
    ],
    "name:nld_x_preferred":[
        "Herencs\u00e9ny"
    ],
    "name:pol_x_preferred":[
        "Herencs\u00e9ny"
    ],
    "name:ron_x_preferred":[
        "Herencs\u00e9ny"
    ],
    "name:slk_x_preferred":[
        "Herencs\u00e9ny"
    ],
    "name:slv_x_preferred":[
        "Herencs\u00e9ny"
    ],
    "name:swe_x_preferred":[
        "Herencs\u00e9ny"
    ],
    "name:vie_x_preferred":[
        "Herencs\u00e9ny"
    ],
    "name:zho_x_preferred":[
        "\u6d77\u4f26\u5207\u5c3c"
    ],
    "wof:name":"Herencseny",
    "wof:placetype":"locality"
},
  "geometry": {"coordinates":[19.4761,47.97829],"type":"Point"}
}