{
  "type": "Feature",
  "properties": {
    "gn:country":"HU",
    "gn:fcode":"PPL",
    "gn:population":8399,
    "iso:country":"HU",
    "name:aze_x_preferred":[
        "Lenti"
    ],
    "name:bul_x_preferred":[
        "\u041b\u0435\u043d\u0442\u0438"
    ],
    "name:ceb_x_preferred":[
        "Lenti"
    ],
    "name:ces_x_preferred":[
        "Lenti"
    ],
    "name:deu_x_preferred":[
        "Lenti"
    ],
    "name:eng_x_preferred":[
        "Lenti"
    ],
    "name:epo_x_preferred":[
        "Lenti"
    ],
    "name:fas_x_preferred":[
        "\u0644\u0646\u062a\u06cc"
    ],
    "name:fra_x_preferred":[
        "Lenti"
    ],
    "name:gle_x_preferred":[
        "Lenti"
    ],
    "name:hun_x_preferred":[
        "Lenti"
    ],
    "name:ita_x_preferred":[
        "Lenti"
    ],
    "name:kor_x_preferred":[
        "\ub80c\ud2f0"
    ],
    "name:msa_x_preferred":[
        "Lenti"
    ],
    "name:nan_x_preferred":[
        "Lenti"
    ],
    "name:nld_x_preferred":[
        "Lenti"
    ],
    "name:pol_x_preferred":[
        "Lenti"
    ],
    "name:por_x_preferred":[
        "Lenti"
    ],
    "name:ron_x_preferred":[
        "Lenti"
    ],
    "name:rup_x_preferred":[
        "Lenti"
    ],
    "name:rus_x_preferred":[
        "\u041b\u0435\u043d\u0442\u0438"
    ],
    "name:slk_x_preferred":[
        "Lenti"
    ],
    "name:slv_x_preferred":[
        "Lentiba"
    ],
    "name:spa_x_preferred":[
        "Lenti"
    ],
    "name:srp_x_preferred":[
        "\u041b\u0435\u043d\u0442\u0438"
    ],
    "name:swe_x_preferred":[
        "Lenti"
    ],
    "name:ukr_x_preferred":[
        "\u041b\u0435\u043d\u0442\u0456"
    ],
    "name:und_x_variant":[
        "Mumor"
    ],
    "name:vie_x_preferred":[
        "Lenti"
    ],
    "name:zho_x_preferred":[
        "\u502b\u8482"
    ],
    "qs_pg:aaroncc":"HU",
    "qs_pg:gn_country":"HU",
    "qs_pg:gn_fcode":"PPL",
    "qs_pg:gn_pop":8399,
    "qs_pg:name":"M\u00e1homfa",
    "qs_pg:name_adm0":"Magyarorsz\u00e1g",
    "qs_pg:name_adm1":"Zala",
    "qs_pg:photos_9r":0,
    "qs_pg:photos_sr":0,
    "qs_pg:pop_sr":5,
    "qs_pg:qs_pg_placetype":"locality",
    "qs_pg:qs_pg_placetype_gp":"Town",
    "qs_pg:woe_adm0":23424844,
    "woe:adm0_id":23424844,
    "woe:name_adm0":"Magyarorsz\u00e1g",
    "woe:name_adm1":"Zala",
    "woe:placetype":"Town",
    "wof:name":"M\u00e1homfa",
    "wof:placetype":"locality",
    "wof:population":8399
},
  "geometry": {"coordinates":[16.53863,46.62403],"type":"Point"}
}