{
  "type": "Feature",
  "properties": {
    "gn:admin1_code":"21.0",
    "gn:asciiname":"Hard",
    "gn:country_code":"HU",
    "gn:dem":136,
    "gn:feature_class":"P",
    "gn:feature_code":"PPL",
    "gn:name":"Hard",
    "gn:population":0,
    "gn:timezone":"Europe/Budapest",
    "iso:country":"HU",
    "name:ceb_x_preferred":[
        "Hard"
    ],
    "name:deu_x_preferred":[
        "Hard"
    ],
    "name:fra_x_preferred":[
        "Hard"
    ],
    "name:ita_x_preferred":[
        "Hard"
    ],
    "name:nld_x_preferred":[
        "Hard"
    ],
    "name:nno_x_preferred":[
        "Hardleik"
    ],
    "name:nor_x_preferred":[
        "Hardhet"
    ],
    "name:pol_x_preferred":[
        "Hard"
    ],
    "name:por_x_preferred":[
        "Hard"
    ],
    "name:ron_x_preferred":[
        "Hard"
    ],
    "name:swe_x_preferred":[
        "Hard"
    ],
    "name:ukr_x_preferred":[
        "Hard"
    ],
    "name:und_x_variant":[
        "Als\u00f3hard"
    ],
    "wof:name":"Hard",
    "wof:placetype":"locality"
},
  "geometry": {"coordinates":[18.75,46.73333],"type":"Point"}
}