{
  "type": "Feature",
  "properties": {
    "gn:admin1_code":"16.0",
    "gn:asciiname":"Borzashegymajor",
    "gn:country_code":"HU",
    "gn:dem":94,
    "gn:feature_class":"P",
    "gn:feature_code":"PPL",
    "gn:name":"Borzashegymajor",
    "gn:population":0,
    "gn:timezone":"Europe/Budapest",
    "iso:country":"HU",
    "wof:name":"Borzashegymajor",
    "wof:placetype":"locality"
},
  "geometry": {"coordinates":[19.18333,47.18333],"type":"Point"}
}