{
  "type": "Feature",
  "properties": {
    "gn:admin1_code":"15.0",
    "gn:asciiname":"Cserteto",
    "gn:country_code":"HU",
    "gn:dem":348,
    "gn:feature_class":"P",
    "gn:feature_code":"PPL",
    "gn:name":"Csertet\u0151",
    "gn:population":0,
    "gn:timezone":"Europe/Budapest",
    "iso:country":"HU",
    "wof:name":"Cserteto",
    "wof:placetype":"locality"
},
  "geometry": {"coordinates":[18.28333,46.11667],"type":"Point"}
}