{
  "type": "Feature",
  "properties": {
    "iso:country":"HU",
    "qs_pg:aaroncc":"HU",
    "qs_pg:name":"T\u00e1p\u00e9",
    "qs_pg:name_adm0":"Magyarorsz\u00e1g",
    "qs_pg:name_adm1":"Szeged",
    "qs_pg:photos":45,
    "qs_pg:photos_1k":9,
    "qs_pg:photos_9k":1,
    "qs_pg:photos_9r":2,
    "qs_pg:photos_all":45,
    "qs_pg:photos_sr":2,
    "qs_pg:pop_sr":0,
    "qs_pg:qs_pg_placetype":"locality",
    "qs_pg:qs_pg_placetype_gp":"Town",
    "qs_pg:woe_adm0":23424844,
    "woe:adm0_id":23424844,
    "woe:name_adm0":"Magyarorsz\u00e1g",
    "woe:name_adm1":"Szeged",
    "woe:placetype":"Town",
    "wof:name":"T\u00e1p\u00e9",
    "wof:placetype":"locality"
},
  "geometry": {"coordinates":[20.196025,46.254274],"type":"Point"}
}