{
  "type": "Feature",
  "properties": {
    "gn:admin1_code":"4.0",
    "gn:asciiname":"Taktabaj",
    "gn:cc2":"HU",
    "gn:country_code":"HU",
    "gn:dem":91,
    "gn:feature_class":"P",
    "gn:feature_code":"PPL",
    "gn:name":"Taktab\u00e1j",
    "gn:population":0,
    "gn:timezone":"Europe/Budapest",
    "iso:country":"HU",
    "name:deu_x_preferred":[
        "Taktab\u00e1j"
    ],
    "name:epo_x_preferred":[
        "Taktab\u00e1j"
    ],
    "name:fas_x_preferred":[
        "\u062a\u0627\u06a9\u062a\u0627\u0628\u0627\u06cc"
    ],
    "name:fra_x_preferred":[
        "Taktab\u00e1j"
    ],
    "name:heb_x_preferred":[
        "\u05d8\u05e7\u05d8\u05d1\u05d0\u05d9"
    ],
    "name:hun_x_preferred":[
        "Taktab\u00e1j"
    ],
    "name:ita_x_preferred":[
        "Taktab\u00e1j"
    ],
    "name:msa_x_preferred":[
        "Taktab\u00e1j"
    ],
    "name:nld_x_preferred":[
        "Taktab\u00e1j"
    ],
    "name:pol_x_preferred":[
        "Taktab\u00e1j"
    ],
    "name:ron_x_preferred":[
        "Taktab\u00e1j"
    ],
    "name:slk_x_preferred":[
        "Taktab\u00e1j"
    ],
    "name:slv_x_preferred":[
        "Taktab\u00e1j"
    ],
    "name:und_x_variant":[
        "B\u00e1j",
        "Taktab\u00e1j"
    ],
    "name:vie_x_preferred":[
        "Taktab\u00e1j"
    ],
    "name:zho_x_preferred":[
        "\u9676\u514b\u9676\u5df4\u4f0a"
    ],
    "wof:name":"Taktabaj",
    "wof:placetype":"locality"
},
  "geometry": {"coordinates":[21.31667,48.06667],"type":"Point"}
}