{
  "type": "Feature",
  "properties": {
    "gn:admin1_code":"6.0",
    "gn:asciiname":"Belsoecser",
    "gn:country_code":"HU",
    "gn:dem":80,
    "gn:feature_class":"P",
    "gn:feature_code":"PPL",
    "gn:name":"Bels\u0151ecser",
    "gn:population":0,
    "gn:timezone":"Europe/Budapest",
    "iso:country":"HU",
    "wof:name":"Belsoecser",
    "wof:placetype":"locality"
},
  "geometry": {"coordinates":[20.36667000000001,46.76667],"type":"Point"}
}