{
  "type": "Feature",
  "properties": {
    "gn:admin1_code":"10.0",
    "gn:asciiname":"Legeloszel",
    "gn:country_code":"HU",
    "gn:dem":138,
    "gn:feature_class":"P",
    "gn:feature_code":"PPL",
    "gn:name":"Legel\u0151sz\u00e9l",
    "gn:population":0,
    "gn:timezone":"Europe/Budapest",
    "iso:country":"HU",
    "wof:name":"Legeloszel",
    "wof:placetype":"locality"
},
  "geometry": {"coordinates":[22.03333,47.55],"type":"Point"}
}