{
  "type": "Feature",
  "properties": {
    "gn:admin1_code":"17.0",
    "gn:asciiname":"Somogyfok",
    "gn:country_code":"HU",
    "gn:dem":131,
    "gn:feature_class":"P",
    "gn:feature_code":"PPL",
    "gn:name":"Somogyfok",
    "gn:population":0,
    "gn:timezone":"Europe/Budapest",
    "iso:country":"HU",
    "wof:name":"Somogyfok",
    "wof:placetype":"locality"
},
  "geometry": {"coordinates":[18.01667,46.88333],"type":"Point"}
}