{
  "type": "Feature",
  "properties": {
    "iso:country":"HU",
    "name:deu_x_preferred":[
        "Pesterzs\u00e9bet"
    ],
    "name:eng_x_preferred":[
        "Pesterzs\u00e9bet"
    ],
    "name:epo_x_preferred":[
        "Pesterzs\u00e9bet"
    ],
    "name:fas_x_preferred":[
        "\u067e\u0634\u062a\u0631\u0698\u0628\u062a"
    ],
    "name:fra_x_preferred":[
        "20e arrondissement de Budapest"
    ],
    "name:heb_x_preferred":[
        "\u05e4\u05e9\u05d8\u05d0\u05e8\u05d6'\u05d1\u05d8"
    ],
    "name:hun_x_preferred":[
        "Budapest XX. ker\u00fclete"
    ],
    "name:hun_x_variant":[
        "XX. ker\u00fclet"
    ],
    "name:ita_x_preferred":[
        "Pesterzs\u00e9bet"
    ],
    "name:nld_x_preferred":[
        "Pesterzs\u00e9bet"
    ],
    "name:pol_x_preferred":[
        "Pesterzs\u00e9bet"
    ],
    "name:ron_x_preferred":[
        "Pesterzs\u00e9bet"
    ],
    "name:slk_x_preferred":[
        "XX. obvod"
    ],
    "name:srp_x_preferred":[
        "\u0411\u0443\u0434\u0438\u043c\u043f\u0435\u0448\u0442\u0430 XX \u043e\u043a\u0440\u0443\u0433"
    ],
    "name:und_x_variant":[
        "Leninv\u00e1ros"
    ],
    "name:vie_x_preferred":[
        "Qu\u1eadn XX"
    ],
    "name:zho_x_preferred":[
        "\u5e03\u8fbe\u4f69\u65af\u7b2c\u4e8c\u5341\u533a"
    ],
    "wof:name":"Pesterzs\u00e9bet",
    "wof:placetype":"neighbourhood"
},
  "geometry": {"coordinates":[19.12088598722073,47.43575602672161],"type":"Point"}
}