{
  "type": "Feature",
  "properties": {
    "iso:country":"HU",
    "name:hun_x_preferred":[
        "K\u00fatv\u00f6lgy"
    ],
    "wof:name":"Kutvolgy",
    "wof:placetype":"neighbourhood"
},
  "geometry": {"coordinates":[18.99032313924052,47.50929706053147],"type":"Point"}
}