{
  "type": "Feature",
  "properties": {
    "gn:admin1_code":"2.0",
    "gn:asciiname":"Marocsa",
    "gn:country_code":"HU",
    "gn:dem":98,
    "gn:feature_class":"P",
    "gn:feature_code":"PPL",
    "gn:name":"Mar\u00f3csa",
    "gn:population":0,
    "gn:timezone":"Europe/Budapest",
    "iso:country":"HU",
    "name:deu_x_preferred":[
        "Mar\u00f3csa"
    ],
    "name:epo_x_preferred":[
        "Mar\u00f3csa"
    ],
    "name:fas_x_preferred":[
        "\u0645\u0627\u0631\u0648\u0686\u0627"
    ],
    "name:fra_x_preferred":[
        "Mar\u00f3csa"
    ],
    "name:hrv_x_preferred":[
        "Mara\u010da"
    ],
    "name:hun_x_preferred":[
        "Mar\u00f3csa"
    ],
    "name:ita_x_preferred":[
        "Mar\u00f3csa"
    ],
    "name:msa_x_preferred":[
        "Mar\u00f3csa"
    ],
    "name:nld_x_preferred":[
        "Mar\u00f3csa"
    ],
    "name:pol_x_preferred":[
        "Mar\u00f3csa"
    ],
    "name:ron_x_preferred":[
        "Mar\u00f3csa"
    ],
    "name:slk_x_preferred":[
        "Mar\u00f3csa"
    ],
    "name:slv_x_preferred":[
        "Mar\u00f3csa"
    ],
    "name:vie_x_preferred":[
        "Mar\u00f3csa"
    ],
    "name:zho_x_preferred":[
        "\u6bdb\u7f57\u4e54"
    ],
    "wof:name":"Marocsa",
    "wof:placetype":"locality"
},
  "geometry": {"coordinates":[17.81449,45.91413],"type":"Point"}
}