{
  "type": "Feature",
  "properties": {
    "gn:admin1_code":"23.0",
    "gn:asciiname":"Keszlertanya",
    "gn:country_code":"HU",
    "gn:dem":294,
    "gn:feature_class":"P",
    "gn:feature_code":"PPL",
    "gn:name":"Keszlertanya",
    "gn:population":0,
    "gn:timezone":"Europe/Budapest",
    "iso:country":"HU",
    "wof:name":"Keszlertanya",
    "wof:placetype":"locality"
},
  "geometry": {"coordinates":[17.68332999999999,47.01667],"type":"Point"}
}