{
  "type": "Feature",
  "properties": {
    "gn:gn_country":"HU",
    "gn:gn_fcode":"PPL",
    "gn:gn_pop":0,
    "iso:country":"HU",
    "name:chi_x_preferred":[
        "\u57fa\u7ecd\u7f57\u897f"
    ],
    "name:dut_x_preferred":[
        "Kisoroszi"
    ],
    "name:eng_x_preferred":[
        "Kisoroszi"
    ],
    "name:epo_x_preferred":[
        "Kisoroszi"
    ],
    "name:fre_x_preferred":[
        "Kisoroszi"
    ],
    "name:ger_x_preferred":[
        "Kisoroszi"
    ],
    "name:hun_x_preferred":[
        "Kisoroszi"
    ],
    "name:ita_x_preferred":[
        "Kisoroszi"
    ],
    "name:may_x_preferred":[
        "Kisoroszi"
    ],
    "name:nan_x_preferred":[
        "Kisoroszi"
    ],
    "name:rum_x_preferred":[
        "Kisoroszi"
    ],
    "name:slo_x_preferred":[
        "Kisoroszi"
    ],
    "name:slv_x_preferred":[
        "Kisoroszi"
    ],
    "name:vie_x_preferred":[
        "Kisoroszi"
    ],
    "qs_pg:aaroncc":"HU",
    "qs_pg:gn_country":"HU",
    "qs_pg:gn_fcode":"PPL",
    "qs_pg:gn_pop":0,
    "qs_pg:name":"Kisoroszi",
    "qs_pg:name_adm0":"Magyarorsz\u00e1g",
    "qs_pg:name_adm1":"Pest",
    "qs_pg:photos":231,
    "qs_pg:photos_1k":47,
    "qs_pg:photos_9k":1,
    "qs_pg:photos_9r":4,
    "qs_pg:photos_all":231,
    "qs_pg:photos_sr":4,
    "qs_pg:pop_sr":0,
    "qs_pg:qs_pg_placetype":"locality",
    "qs_pg:qs_pg_placetype_gp":"Town",
    "qs_pg:woe_adm0":23424844,
    "woe:adm0_id":23424844,
    "woe:name_adm0":"Magyarorsz\u00e1g",
    "woe:name_adm1":"Pest",
    "woe:placetype":"Town",
    "wof:name":"Kisoroszi",
    "wof:placetype":"locality"
},
  "geometry": {"coordinates":[19.00974,47.80692],"type":"Point"}
}