{
  "type": "Feature",
  "properties": {
    "gn:admin1_code":"1.0",
    "gn:asciiname":"Konyadulo",
    "gn:country_code":"HU",
    "gn:dem":82,
    "gn:feature_class":"P",
    "gn:feature_code":"PPLL",
    "gn:name":"K\u00f3nyad\u0171l\u0151",
    "gn:population":0,
    "gn:timezone":"Europe/Budapest",
    "iso:country":"HU",
    "wof:name":"Konyadulo",
    "wof:placetype":"locality"
},
  "geometry": {"coordinates":[19.95,46.61667],"type":"Point"}
}