{
  "type": "Feature",
  "properties": {
    "gn:admin1_code":"21.0",
    "gn:asciiname":"Dorogpuszta",
    "gn:country_code":"HU",
    "gn:dem":144,
    "gn:feature_class":"P",
    "gn:feature_code":"PPL",
    "gn:name":"Dorogpuszta",
    "gn:population":0,
    "gn:timezone":"Europe/Budapest",
    "iso:country":"HU",
    "name:und_x_variant":[
        "Pusztadorog",
        "Dorogpuszta"
    ],
    "wof:name":"Dorogpuszta",
    "wof:placetype":"locality"
},
  "geometry": {"coordinates":[18.38727,46.68442],"type":"Point"}
}