{
  "type": "Feature",
  "properties": {
    "gn:admin1_code":"22.0",
    "gn:asciiname":"Kisrakos",
    "gn:country_code":"HU",
    "gn:dem":237,
    "gn:feature_class":"P",
    "gn:feature_code":"PPL",
    "gn:name":"Kisr\u00e1kos",
    "gn:population":0,
    "gn:timezone":"Europe/Budapest",
    "iso:country":"HU",
    "name:epo_x_preferred":[
        "Kisr\u00e1kos"
    ],
    "name:fas_x_preferred":[
        "\u06a9\u06cc\u0634\u0631\u0627\u06a9\u0648\u0634"
    ],
    "name:fra_x_preferred":[
        "Kisr\u00e1kos"
    ],
    "name:hun_x_preferred":[
        "Kisr\u00e1kos"
    ],
    "name:ita_x_preferred":[
        "Kisr\u00e1kos"
    ],
    "name:msa_x_preferred":[
        "Kisr\u00e1kos"
    ],
    "name:nld_x_preferred":[
        "Kisr\u00e1kos"
    ],
    "name:ron_x_preferred":[
        "Kisr\u00e1kos"
    ],
    "name:slk_x_preferred":[
        "Kisr\u00e1kos"
    ],
    "name:slv_x_preferred":[
        "Kisr\u00e1kos"
    ],
    "name:vie_x_preferred":[
        "Kisr\u00e1kos"
    ],
    "name:zho_x_preferred":[
        "\u57fa\u4ec0\u62c9\u79d1\u4ec0"
    ],
    "wof:name":"Kisrakos",
    "wof:placetype":"locality"
},
  "geometry": {"coordinates":[16.50035,46.86031],"type":"Point"}
}