{
  "type": "Feature",
  "properties": {
    "gn:admin1_code":"22.0",
    "gn:asciiname":"Kisrakos",
    "gn:country_code":"HU",
    "gn:dem":237,
    "gn:feature_class":"P",
    "gn:feature_code":"PPL",
    "gn:name":"Kisr\u00e1kos",
    "gn:population":0,
    "gn:timezone":"Europe/Budapest",
    "iso:country":"HU",
    "wof:name":"Kisrakos",
    "wof:placetype":"locality"
},
  "geometry": {"coordinates":[16.50035,46.86031],"type":"Point"}
}