{
  "type": "Feature",
  "properties": {
    "iso:country":"HU",
    "qs_pg:aaroncc":"HU",
    "qs_pg:name":"Klastrompuszta",
    "qs_pg:name_adm0":"Magyarorsz\u00e1g",
    "qs_pg:name_adm1":"Kom\u00e1rom-Esztergom",
    "qs_pg:photos":16,
    "qs_pg:photos_1k":3,
    "qs_pg:photos_9k":1,
    "qs_pg:photos_9r":1,
    "qs_pg:photos_all":16,
    "qs_pg:photos_sr":1,
    "qs_pg:pop_sr":0,
    "qs_pg:qs_pg_placetype":"locality",
    "qs_pg:qs_pg_placetype_gp":"Town",
    "qs_pg:woe_adm0":23424844,
    "woe:adm0_id":23424844,
    "woe:name_adm0":"Magyarorsz\u00e1g",
    "woe:name_adm1":"Kom\u00e1rom-Esztergom",
    "woe:placetype":"Town",
    "wof:name":"Klastrompuszta",
    "wof:placetype":"locality"
},
  "geometry": {"coordinates":[18.8509075,47.6951475],"type":"Point"}
}