{
  "type": "Feature",
  "properties": {
    "gn:admin1_code":"18.0",
    "gn:asciiname":"Homoktag",
    "gn:country_code":"HU",
    "gn:dem":157,
    "gn:feature_class":"P",
    "gn:feature_code":"PPL",
    "gn:name":"Homoktag",
    "gn:population":0,
    "gn:timezone":"Europe/Budapest",
    "iso:country":"HU",
    "name:und_x_variant":[
        "Homoktanya",
        "Homoktagtanya",
        "Homoktag"
    ],
    "wof:name":"Homoktag",
    "wof:placetype":"locality"
},
  "geometry": {"coordinates":[21.99027,47.71489],"type":"Point"}
}