{
  "type": "Feature",
  "properties": {
    "gn:admin1_code":"10.0",
    "gn:asciiname":"Sapi Tanyak",
    "gn:country_code":"HU",
    "gn:dem":88,
    "gn:feature_class":"P",
    "gn:feature_code":"PPL",
    "gn:name":"S\u00e1pi Tany\u00e1k",
    "gn:population":0,
    "gn:timezone":"Europe/Budapest",
    "iso:country":"HU",
    "wof:name":"Sapi Tanyak",
    "wof:placetype":"locality"
},
  "geometry": {"coordinates":[21.36667000000001,47.25],"type":"Point"}
}