{
  "type": "Feature",
  "properties": {
    "gn:admin1_code":"4.0",
    "gn:asciiname":"Karos",
    "gn:country_code":"HU",
    "gn:dem":96,
    "gn:feature_class":"P",
    "gn:feature_code":"PPL",
    "gn:name":"Karos",
    "gn:population":0,
    "gn:timezone":"Europe/Budapest",
    "iso:country":"HU",
    "name:ces_x_preferred":[
        "Karos"
    ],
    "name:deu_x_preferred":[
        "Karos"
    ],
    "name:epo_x_preferred":[
        "Karos"
    ],
    "name:fas_x_preferred":[
        "\u06a9\u0627\u0631\u0648\u0634"
    ],
    "name:fra_x_preferred":[
        "Karos"
    ],
    "name:heb_x_preferred":[
        "\u05e7\u05e8\u05d5\u05e9"
    ],
    "name:hun_x_preferred":[
        "Karos"
    ],
    "name:ita_x_preferred":[
        "Karos"
    ],
    "name:msa_x_preferred":[
        "Karos"
    ],
    "name:nld_x_preferred":[
        "Karos"
    ],
    "name:pol_x_preferred":[
        "Karos"
    ],
    "name:ron_x_preferred":[
        "Karos"
    ],
    "name:slk_x_preferred":[
        "Karos"
    ],
    "name:slv_x_preferred":[
        "Karos"
    ],
    "name:vie_x_preferred":[
        "Karos"
    ],
    "name:zho_x_preferred":[
        "\u8003\u7f57\u4ec0"
    ],
    "wof:name":"Karos",
    "wof:placetype":"locality"
},
  "geometry": {"coordinates":[21.75,48.33333],"type":"Point"}
}