{
  "type": "Feature",
  "properties": {
    "gn:admin1_code":"4.0",
    "gn:asciiname":"Karos",
    "gn:country_code":"HU",
    "gn:dem":96,
    "gn:feature_class":"P",
    "gn:feature_code":"PPL",
    "gn:name":"Karos",
    "gn:population":0,
    "gn:timezone":"Europe/Budapest",
    "iso:country":"HU",
    "wof:name":"Karos",
    "wof:placetype":"locality"
},
  "geometry": {"coordinates":[21.75,48.33333],"type":"Point"}
}