{
  "type": "Feature",
  "properties": {
    "gn:admin1_code":"10.0",
    "gn:asciiname":"Mezosas",
    "gn:country_code":"HU",
    "gn:dem":90,
    "gn:feature_class":"P",
    "gn:feature_code":"PPL",
    "gn:name":"Mez\u0151sas",
    "gn:population":0,
    "gn:timezone":"Europe/Budapest",
    "iso:country":"HU",
    "name:und_x_variant":[
        "Mez\u0151sas"
    ],
    "wof:name":"Mezosas",
    "wof:placetype":"locality"
},
  "geometry": {"coordinates":[21.56667,47.11667],"type":"Point"}
}