{
  "type": "Feature",
  "properties": {
    "gn:admin1_code":"22.0",
    "gn:asciiname":"Doborhegy",
    "gn:country_code":"HU",
    "gn:dem":236,
    "gn:feature_class":"P",
    "gn:feature_code":"PPL",
    "gn:name":"D\u00f6b\u00f6rhegy",
    "gn:population":0,
    "gn:timezone":"Europe/Budapest",
    "iso:country":"HU",
    "name:deu_x_preferred":[
        "D\u00f6b\u00f6rhegy"
    ],
    "name:epo_x_preferred":[
        "D\u00f6b\u00f6rhegy"
    ],
    "name:fas_x_preferred":[
        "\u062f\u0648\u0628\u0648\u0631\u0647\u06af\u06cc"
    ],
    "name:fra_x_preferred":[
        "D\u00f6b\u00f6rhegy"
    ],
    "name:hun_x_preferred":[
        "D\u00f6b\u00f6rhegy"
    ],
    "name:ita_x_preferred":[
        "D\u00f6b\u00f6rhegy"
    ],
    "name:msa_x_preferred":[
        "D\u00f6b\u00f6rhegy"
    ],
    "name:nld_x_preferred":[
        "D\u00f6b\u00f6rhegy"
    ],
    "name:ron_x_preferred":[
        "D\u00f6b\u00f6rhegy"
    ],
    "name:slk_x_preferred":[
        "D\u00f6b\u00f6rhegy"
    ],
    "name:slv_x_preferred":[
        "D\u00f6b\u00f6rhegy"
    ],
    "name:und_x_variant":[
        "D\u00f6b\u00f6rhegy"
    ],
    "name:vie_x_preferred":[
        "D\u00f6b\u00f6rhegy"
    ],
    "name:zho_x_preferred":[
        "\u5fb7\u4f2f\u5c14\u6d77\u5409"
    ],
    "wof:name":"Doborhegy",
    "wof:placetype":"locality"
},
  "geometry": {"coordinates":[16.70382,46.99151],"type":"Point"}
}