{
  "type": "Feature",
  "properties": {
    "gn:admin1_code":"8.0",
    "gn:asciiname":"Farkassimand",
    "gn:country_code":"HU",
    "gn:dem":136,
    "gn:feature_class":"P",
    "gn:feature_code":"PPL",
    "gn:name":"Farkassim\u00e1nd",
    "gn:population":0,
    "gn:timezone":"Europe/Budapest",
    "iso:country":"HU",
    "wof:name":"Farkassimand",
    "wof:placetype":"locality"
},
  "geometry": {"coordinates":[18.78333,46.93333],"type":"Point"}
}