{
  "type": "Feature",
  "properties": {
    "gn:admin1_code":"14.0",
    "gn:asciiname":"Csokapuszta",
    "gn:country_code":"HU",
    "gn:dem":170,
    "gn:feature_class":"P",
    "gn:feature_code":"PPL",
    "gn:name":"Cs\u00f3kapuszta",
    "gn:population":0,
    "gn:timezone":"Europe/Budapest",
    "iso:country":"HU",
    "wof:name":"Csokapuszta",
    "wof:placetype":"locality"
},
  "geometry": {"coordinates":[19.5561,47.80943],"type":"Point"}
}