{
  "type": "Feature",
  "properties": {
    "gn:admin1_code":"18.0",
    "gn:asciiname":"Nagyliget",
    "gn:country_code":"HU",
    "gn:dem":92,
    "gn:feature_class":"P",
    "gn:feature_code":"PPL",
    "gn:name":"Nagyliget",
    "gn:population":0,
    "gn:timezone":"Europe/Budapest",
    "iso:country":"HU",
    "wof:name":"Nagyliget",
    "wof:placetype":"locality"
},
  "geometry": {"coordinates":[21.18333,48.01667],"type":"Point"}
}