{
  "type": "Feature",
  "properties": {
    "gn:country":"HU",
    "gn:fcode":"PPL",
    "gn:population":0,
    "iso:country":"HU",
    "name:ast_x_preferred":[
        "Gy\u0151rs\u00f6v\u00e9nyh\u00e1z"
    ],
    "name:ces_x_preferred":[
        "Gy\u0151rs\u00f6v\u00e9nyh\u00e1z"
    ],
    "name:deu_x_preferred":[
        "Gy\u0151rs\u00f6v\u00e9nyh\u00e1z"
    ],
    "name:eng_x_preferred":[
        "Gy\u0151rs\u00f6v\u00e9nyh\u00e1z"
    ],
    "name:epo_x_preferred":[
        "Gy\u0151rs\u00f6v\u00e9nyh\u00e1z"
    ],
    "name:fas_x_preferred":[
        "\u06af\u06cc\u0648\u0631\u0634\u0648\u0648\u0646\u06cc\u0647\u0627\u0632"
    ],
    "name:fra_x_preferred":[
        "Gy\u0151rs\u00f6v\u00e9nyh\u00e1z"
    ],
    "name:gle_x_preferred":[
        "Gy\u0151rs\u00f6v\u00e9nyh\u00e1z"
    ],
    "name:heb_x_preferred":[
        "\u05d2\u05d9\u05d5\u05e8\u05e9\u05d1\u05e0\u05d4\u05d0\u05d6"
    ],
    "name:hun_x_preferred":[
        "Gy\u0151rs\u00f6v\u00e9nyh\u00e1z"
    ],
    "name:ita_x_preferred":[
        "Gy\u0151rs\u00f6v\u00e9nyh\u00e1z"
    ],
    "name:jpn_x_preferred":[
        "\u30b8\u30a7\u30fc\u30eb\u30b7\u30a7\u30f4\u30a7\u30fc\u30cb\u30cf\u30fc\u30ba"
    ],
    "name:msa_x_preferred":[
        "Gy\u0151rs\u00f6v\u00e9nyh\u00e1z"
    ],
    "name:nan_x_preferred":[
        "Gy\u0151rs\u00f6v\u00e9nyh\u00e1z"
    ],
    "name:nld_x_preferred":[
        "Gy\u0151rs\u00f6v\u00e9nyh\u00e1z"
    ],
    "name:pol_x_preferred":[
        "Gy\u0151rs\u00f6v\u00e9nyh\u00e1z"
    ],
    "name:por_x_preferred":[
        "Gy\u0151rs\u00f6v\u00e9nyh\u00e1z"
    ],
    "name:ron_x_preferred":[
        "Gy\u0151rs\u00f6v\u00e9nyh\u00e1z"
    ],
    "name:slk_x_preferred":[
        "Gy\u0151rs\u00f6v\u00e9nyh\u00e1z"
    ],
    "name:slv_x_preferred":[
        "Gy\u0151rs\u00f6v\u00e9nyh\u00e1z"
    ],
    "name:spa_x_preferred":[
        "Gy\u0151rs\u00f6v\u00e9nyh\u00e1z"
    ],
    "name:vie_x_preferred":[
        "Gy\u0151rs\u00f6v\u00e9nyh\u00e1z"
    ],
    "name:zho_x_preferred":[
        "\u54f2\u5c14\u820d\u97e6\u5c3c\u54c8\u5179"
    ],
    "qs_pg:aaroncc":"HU",
    "qs_pg:gn_country":"HU",
    "qs_pg:gn_fcode":"PPL",
    "qs_pg:gn_pop":0,
    "qs_pg:name":"Gy\u0151rs\u00f6v\u00e9nyh\u00e1z",
    "qs_pg:name_adm0":"Magyarorsz\u00e1g",
    "qs_pg:name_adm1":"Gy\u0151r-Moson-Sopron",
    "qs_pg:photos":6,
    "qs_pg:photos_1k":1,
    "qs_pg:photos_9k":1,
    "qs_pg:photos_9r":1,
    "qs_pg:photos_all":6,
    "qs_pg:photos_sr":1,
    "qs_pg:pop_sr":0,
    "qs_pg:qs_pg_placetype":"locality",
    "qs_pg:qs_pg_placetype_gp":"Town",
    "qs_pg:woe_adm0":23424844,
    "woe:adm0_id":23424844,
    "woe:name_adm0":"Magyarorsz\u00e1g",
    "woe:name_adm1":"Gy\u0151r-Moson-Sopron",
    "woe:placetype":"Town",
    "wof:name":"Gy\u0151rs\u00f6v\u00e9nyh\u00e1z",
    "wof:placetype":"locality"
},
  "geometry": {"coordinates":[17.37361,47.68965],"type":"Point"}
}