{
  "type": "Feature",
  "properties": {
    "gn:admin1_code":"4.0",
    "gn:asciiname":"Basko",
    "gn:country_code":"HU",
    "gn:dem":407,
    "gn:feature_class":"P",
    "gn:feature_code":"PPL",
    "gn:name":"Bask\u00f3",
    "gn:population":0,
    "gn:timezone":"Europe/Budapest",
    "iso:country":"HU",
    "name:und_x_variant":[
        "Bask\u00f3"
    ],
    "wof:name":"Basko",
    "wof:placetype":"locality"
},
  "geometry": {"coordinates":[21.33333,48.33333],"type":"Point"}
}