{
  "type": "Feature",
  "properties": {
    "gn:admin1_code":"22.0",
    "gn:asciiname":"Berbaltavar",
    "gn:country_code":"HU",
    "gn:dem":159,
    "gn:feature_class":"P",
    "gn:feature_code":"PPL",
    "gn:name":"B\u00e9rbaltav\u00e1r",
    "gn:population":0,
    "gn:timezone":"Europe/Budapest",
    "iso:country":"HU",
    "name:ces_x_preferred":[
        "B\u00e9rbaltav\u00e1r"
    ],
    "name:epo_x_preferred":[
        "B\u00e9rbaltav\u00e1r"
    ],
    "name:fas_x_preferred":[
        "\u0628\u0631\u0628\u0627\u0644\u062a\u0627\u0648\u0627\u0631"
    ],
    "name:fra_x_preferred":[
        "B\u00e9rbaltav\u00e1r"
    ],
    "name:hun_x_preferred":[
        "B\u00e9rbaltav\u00e1r"
    ],
    "name:ita_x_preferred":[
        "B\u00e9rbaltav\u00e1r"
    ],
    "name:msa_x_preferred":[
        "B\u00e9rbaltav\u00e1r"
    ],
    "name:nld_x_preferred":[
        "B\u00e9rbaltav\u00e1r"
    ],
    "name:ron_x_preferred":[
        "B\u00e9rbaltav\u00e1r"
    ],
    "name:slk_x_preferred":[
        "B\u00e9rbaltav\u00e1r"
    ],
    "name:slv_x_preferred":[
        "B\u00e9rbaltav\u00e1r"
    ],
    "name:und_x_variant":[
        "B\u00e9rbaltav\u00e1r"
    ],
    "name:vie_x_preferred":[
        "B\u00e9rbaltav\u00e1r"
    ],
    "name:zho_x_preferred":[
        "\u8d1d\u5c14\u9c8d\u5c14\u9676\u74e6\u5c14"
    ],
    "wof:name":"Berbaltavar",
    "wof:placetype":"locality"
},
  "geometry": {"coordinates":[16.96198,47.00729000000001],"type":"Point"}
}