{
  "type": "Feature",
  "properties": {
    "gn:country":"HU",
    "gn:fcode":"PPL",
    "gn:population":0,
    "iso:country":"HU",
    "name:eng_x_preferred":[
        "R\u00e1bacsanak"
    ],
    "name:epo_x_preferred":[
        "R\u00e1bacsanak"
    ],
    "name:fas_x_preferred":[
        "\u0631\u0627\u0628\u0627\u0686\u0627\u0646\u0627\u06a9"
    ],
    "name:fra_x_preferred":[
        "R\u00e1bacsanak"
    ],
    "name:hun_x_preferred":[
        "R\u00e1bacsanak"
    ],
    "name:ita_x_preferred":[
        "R\u00e1bacsanak"
    ],
    "name:msa_x_preferred":[
        "R\u00e1bacsanak"
    ],
    "name:nan_x_preferred":[
        "R\u00e1bacsanak"
    ],
    "name:nld_x_preferred":[
        "R\u00e1bacsanak"
    ],
    "name:pol_x_preferred":[
        "R\u00e1bacsanak"
    ],
    "name:ron_x_preferred":[
        "R\u00e1bacsanak"
    ],
    "name:slk_x_preferred":[
        "R\u00e1bacsanak"
    ],
    "name:slv_x_preferred":[
        "R\u00e1bacsanak"
    ],
    "name:spa_x_preferred":[
        "R\u00e1bacsanak"
    ],
    "name:szl_x_preferred":[
        "R\u00e1bacsanak"
    ],
    "name:vie_x_preferred":[
        "R\u00e1bacsanak"
    ],
    "name:zho_x_preferred":[
        "\u62c9\u9c8d\u4e54\u7459\u514b"
    ],
    "qs_pg:aaroncc":"HU",
    "qs_pg:gn_country":"HU",
    "qs_pg:gn_fcode":"PPL",
    "qs_pg:gn_pop":0,
    "qs_pg:name":"R\u00e1bacsanak",
    "qs_pg:name_adm0":"Magyarorsz\u00e1g",
    "qs_pg:name_adm1":"Gy\u0151r-Moson-Sopron",
    "qs_pg:photos":6,
    "qs_pg:photos_1k":1,
    "qs_pg:photos_9k":1,
    "qs_pg:photos_9r":1,
    "qs_pg:photos_all":6,
    "qs_pg:photos_sr":1,
    "qs_pg:pop_sr":0,
    "qs_pg:qs_pg_placetype":"locality",
    "qs_pg:qs_pg_placetype_gp":"Town",
    "qs_pg:woe_adm0":23424844,
    "woe:adm0_id":23424844,
    "woe:name_adm0":"Magyarorsz\u00e1g",
    "woe:name_adm1":"Gy\u0151r-Moson-Sopron",
    "woe:placetype":"Town",
    "wof:name":"R\u00e1bacsanak",
    "wof:placetype":"locality"
},
  "geometry": {"coordinates":[17.28989,47.52602],"type":"Point"}
}