{
  "type": "Feature",
  "properties": {
    "gn:admin1_code":"16.0",
    "gn:asciiname":"Csikotelep",
    "gn:country_code":"HU",
    "gn:dem":109,
    "gn:feature_class":"P",
    "gn:feature_code":"PPL",
    "gn:name":"Csik\u00f3telep",
    "gn:population":0,
    "gn:timezone":"Europe/Budapest",
    "iso:country":"HU",
    "wof:name":"Csikotelep",
    "wof:placetype":"locality"
},
  "geometry": {"coordinates":[19.14505,47.77129],"type":"Point"}
}