{
  "type": "Feature",
  "properties": {
    "gn:admin1_code":"21.0",
    "gn:asciiname":"Felsonana",
    "gn:country_code":"HU",
    "gn:dem":123,
    "gn:feature_class":"P",
    "gn:feature_code":"PPL",
    "gn:name":"Fels\u0151n\u00e1na",
    "gn:population":0,
    "gn:timezone":"Europe/Budapest",
    "iso:country":"HU",
    "name:und_x_variant":[
        "Fels\u0151n\u00e1na"
    ],
    "wof:name":"Felsonana",
    "wof:placetype":"locality"
},
  "geometry": {"coordinates":[18.52913,46.46681],"type":"Point"}
}