{
  "type": "Feature",
  "properties": {
    "gn:admin1_code":"18.0",
    "gn:asciiname":"Kismaszling",
    "gn:country_code":"HU",
    "gn:dem":118,
    "gn:feature_class":"P",
    "gn:feature_code":"PPL",
    "gn:name":"Kismaszling",
    "gn:population":0,
    "gn:timezone":"Europe/Budapest",
    "iso:country":"HU",
    "wof:name":"Kismaszling",
    "wof:placetype":"locality"
},
  "geometry": {"coordinates":[21.63333,47.81667],"type":"Point"}
}