{
  "type": "Feature",
  "properties": {
    "gn:admin1_code":"23.0",
    "gn:asciiname":"Vigantpetend",
    "gn:country_code":"HU",
    "gn:dem":183,
    "gn:feature_class":"P",
    "gn:feature_code":"PPL",
    "gn:name":"Vig\u00e1ntpetend",
    "gn:population":0,
    "gn:timezone":"Europe/Budapest",
    "iso:country":"HU",
    "name:epo_x_preferred":[
        "Vig\u00e1ntpetend"
    ],
    "name:fas_x_preferred":[
        "\u0648\u06cc\u06af\u0627\u0646\u062a\u067e\u062a\u0646\u062f"
    ],
    "name:fra_x_preferred":[
        "Vig\u00e1ntpetend"
    ],
    "name:hun_x_preferred":[
        "Vig\u00e1ntpetend"
    ],
    "name:ita_x_preferred":[
        "Vig\u00e1ntpetend"
    ],
    "name:msa_x_preferred":[
        "Vig\u00e1ntpetend"
    ],
    "name:nld_x_preferred":[
        "Vig\u00e1ntpetend"
    ],
    "name:ron_x_preferred":[
        "Vig\u00e1ntpetend"
    ],
    "name:slk_x_preferred":[
        "Vig\u00e1ntpetend"
    ],
    "name:slv_x_preferred":[
        "Vig\u00e1ntpetend"
    ],
    "name:und_x_variant":[
        "Vig\u00e1nt",
        "Zalapetend"
    ],
    "name:vie_x_preferred":[
        "Vig\u00e1ntpetend"
    ],
    "name:zho_x_preferred":[
        "\u7ef4\u7518\u7279\u6d3e\u6ed5\u5fb7"
    ],
    "wof:name":"Vigantpetend",
    "wof:placetype":"locality"
},
  "geometry": {"coordinates":[17.62657,46.96477],"type":"Point"}
}