{
  "type": "Feature",
  "properties": {
    "gn:admin1_code":"23.0",
    "gn:asciiname":"Vigantpetend",
    "gn:country_code":"HU",
    "gn:dem":183,
    "gn:feature_class":"P",
    "gn:feature_code":"PPL",
    "gn:name":"Vig\u00e1ntpetend",
    "gn:population":0,
    "gn:timezone":"Europe/Budapest",
    "iso:country":"HU",
    "name:und_x_variant":[
        "Vig\u00e1nt",
        "Zalapetend",
        "Vig\u00e1ntpetend"
    ],
    "wof:name":"Vigantpetend",
    "wof:placetype":"locality"
},
  "geometry": {"coordinates":[17.62657,46.96477],"type":"Point"}
}