{
  "type": "Feature",
  "properties": {
    "gn:admin1_code":"18.0",
    "gn:asciiname":"Darno",
    "gn:country_code":"HU",
    "gn:dem":114,
    "gn:feature_class":"P",
    "gn:feature_code":"PPL",
    "gn:name":"Darn\u00f3",
    "gn:population":0,
    "gn:timezone":"Europe/Budapest",
    "iso:country":"HU",
    "name:epo_x_preferred":[
        "Darn\u00f3"
    ],
    "name:fas_x_preferred":[
        "\u062f\u0627\u0631\u0646\u0648"
    ],
    "name:fra_x_preferred":[
        "Darn\u00f3"
    ],
    "name:hun_x_preferred":[
        "Darn\u00f3"
    ],
    "name:ita_x_preferred":[
        "Darn\u00f3"
    ],
    "name:msa_x_preferred":[
        "Darn\u00f3"
    ],
    "name:nld_x_preferred":[
        "Darn\u00f3"
    ],
    "name:ron_x_preferred":[
        "Darn\u00f3"
    ],
    "name:slk_x_preferred":[
        "Darn\u00f3"
    ],
    "name:slv_x_preferred":[
        "Darn\u00f3"
    ],
    "name:und_x_variant":[
        "Darn\u00f3"
    ],
    "name:vie_x_preferred":[
        "Darn\u00f3"
    ],
    "name:zho_x_preferred":[
        "\u9053\u5c14\u8bfa"
    ],
    "wof:name":"Darno",
    "wof:placetype":"locality"
},
  "geometry": {"coordinates":[22.65926,47.95846],"type":"Point"}
}