{
  "type": "Feature",
  "properties": {
    "gn:admin1_code":"22.0",
    "gn:asciiname":"Nemesmedves",
    "gn:country_code":"HU",
    "gn:dem":232,
    "gn:feature_class":"P",
    "gn:feature_code":"PPL",
    "gn:name":"Nemesmedves",
    "gn:population":0,
    "gn:timezone":"Europe/Budapest",
    "iso:country":"HU",
    "name:deu_x_preferred":[
        "Ginisdorf"
    ],
    "name:deu_x_variant":[
        "Nemesmedves"
    ],
    "name:epo_x_preferred":[
        "Nemesmedves"
    ],
    "name:fas_x_preferred":[
        "\u0646\u0645\u0634\u0645\u062f\u0648\u0634"
    ],
    "name:fra_x_preferred":[
        "Nemesmedves"
    ],
    "name:hun_x_preferred":[
        "Nemesmedves"
    ],
    "name:ita_x_preferred":[
        "Nemesmedves"
    ],
    "name:msa_x_preferred":[
        "Nemesmedves"
    ],
    "name:nld_x_preferred":[
        "Nemesmedves"
    ],
    "name:ron_x_preferred":[
        "Nemesmedves"
    ],
    "name:slk_x_preferred":[
        "Nemesmedves"
    ],
    "name:slv_x_preferred":[
        "Nemesmedves"
    ],
    "name:vie_x_preferred":[
        "Nemesmedves"
    ],
    "name:zho_x_preferred":[
        "\u5948\u8fc8\u4ec0\u8fc8\u5fb7\u97e6\u4ec0"
    ],
    "wof:name":"Nemesmedves",
    "wof:placetype":"locality"
},
  "geometry": {"coordinates":[16.40114,46.9973],"type":"Point"}
}