{
  "type": "Feature",
  "properties": {
    "gn:admin1_code":"22.0",
    "gn:asciiname":"Nemesmedves",
    "gn:country_code":"HU",
    "gn:dem":232,
    "gn:feature_class":"P",
    "gn:feature_code":"PPL",
    "gn:name":"Nemesmedves",
    "gn:population":0,
    "gn:timezone":"Europe/Budapest",
    "iso:country":"HU",
    "name:deu_x_preferred":[
        "Ginisdorf"
    ],
    "wof:name":"Nemesmedves",
    "wof:placetype":"locality"
},
  "geometry": {"coordinates":[16.40114,46.9973],"type":"Point"}
}