{
  "type": "Feature",
  "properties": {
    "gn:admin1_code":"14.0",
    "gn:asciiname":"Nyarjasvolgy",
    "gn:country_code":"HU",
    "gn:dem":241,
    "gn:feature_class":"P",
    "gn:feature_code":"PPL",
    "gn:name":"Ny\u00e1rjasv\u00f6lgy",
    "gn:population":0,
    "gn:timezone":"Europe/Budapest",
    "iso:country":"HU",
    "wof:name":"Nyarjasvolgy",
    "wof:placetype":"locality"
},
  "geometry": {"coordinates":[19.75363,48.04857],"type":"Point"}
}