{
  "type": "Feature",
  "properties": {
    "gn:admin1_code":"2.0",
    "gn:asciiname":"Szentdenes",
    "gn:country_code":"HU",
    "gn:dem":110,
    "gn:feature_class":"P",
    "gn:feature_code":"PPL",
    "gn:name":"Szentd\u00e9nes",
    "gn:population":0,
    "gn:timezone":"Europe/Budapest",
    "iso:country":"HU",
    "name:und_x_variant":[
        "Szentdienes",
        "Szentd\u00e9nes"
    ],
    "wof:name":"Szentdenes",
    "wof:placetype":"locality"
},
  "geometry": {"coordinates":[17.92711,46.00709000000001],"type":"Point"}
}