{
  "type": "Feature",
  "properties": {
    "gn:admin1_code":"2.0",
    "gn:asciiname":"Szentdenes",
    "gn:country_code":"HU",
    "gn:dem":110,
    "gn:feature_class":"P",
    "gn:feature_code":"PPL",
    "gn:name":"Szentd\u00e9nes",
    "gn:population":0,
    "gn:timezone":"Europe/Budapest",
    "iso:country":"HU",
    "name:epo_x_preferred":[
        "Szentd\u00e9nes"
    ],
    "name:fas_x_preferred":[
        "\u0633\u0646\u062a\u062f\u0646\u0634"
    ],
    "name:fra_x_preferred":[
        "Szentd\u00e9nes"
    ],
    "name:hrv_x_preferred":[
        "Sedijana\u0161"
    ],
    "name:hun_x_preferred":[
        "Szentd\u00e9nes"
    ],
    "name:ita_x_preferred":[
        "Szentd\u00e9nes"
    ],
    "name:msa_x_preferred":[
        "Szentd\u00e9nes"
    ],
    "name:nld_x_preferred":[
        "Szentd\u00e9nes"
    ],
    "name:pol_x_preferred":[
        "Szentd\u00e9nes"
    ],
    "name:ron_x_preferred":[
        "Szentd\u00e9nes"
    ],
    "name:slk_x_preferred":[
        "Szentd\u00e9nes"
    ],
    "name:slv_x_preferred":[
        "Szentd\u00e9nes"
    ],
    "name:und_x_variant":[
        "Szentdienes",
        "Szentd\u00e9nes"
    ],
    "name:vie_x_preferred":[
        "Szentd\u00e9nes"
    ],
    "name:zho_x_preferred":[
        "\u68ee\u7279\u4ee3\u5948\u4ec0"
    ],
    "wof:name":"Szentdenes",
    "wof:placetype":"locality"
},
  "geometry": {"coordinates":[17.92711,46.00709000000001],"type":"Point"}
}