{
  "type": "Feature",
  "properties": {
    "gn:admin1_code":"16.0",
    "gn:asciiname":"Dunasziget",
    "gn:country_code":"HU",
    "gn:dem":98,
    "gn:feature_class":"P",
    "gn:feature_code":"PPL",
    "gn:name":"Dunasziget",
    "gn:population":0,
    "gn:timezone":"Europe/Budapest",
    "iso:country":"HU",
    "name:deu_x_preferred":[
        "Dunasziget"
    ],
    "name:epo_x_preferred":[
        "Dunasziget"
    ],
    "name:fas_x_preferred":[
        "\u062f\u0648\u0646\u0627\u0633\u06cc\u06af\u062a"
    ],
    "name:fra_x_preferred":[
        "Dunasziget"
    ],
    "name:hun_x_preferred":[
        "Dunasziget"
    ],
    "name:ita_x_preferred":[
        "Dunasziget"
    ],
    "name:msa_x_preferred":[
        "Dunasziget"
    ],
    "name:nld_x_preferred":[
        "Dunasziget"
    ],
    "name:pol_x_preferred":[
        "Dunasziget"
    ],
    "name:ron_x_preferred":[
        "Dunasziget"
    ],
    "name:slk_x_preferred":[
        "Dunasziget"
    ],
    "name:slv_x_preferred":[
        "Dunasziget"
    ],
    "name:vie_x_preferred":[
        "Dunasziget"
    ],
    "name:zho_x_preferred":[
        "\u675c\u7459\u897f\u76d6\u7279"
    ],
    "wof:name":"Dunasziget",
    "wof:placetype":"locality"
},
  "geometry": {"coordinates":[19.01667,47.23333],"type":"Point"}
}