{
  "type": "Feature",
  "properties": {
    "gn:admin1_code":"4.0",
    "gn:asciiname":"Bogyaytanya",
    "gn:cc2":"HU",
    "gn:country_code":"HU",
    "gn:dem":97,
    "gn:feature_class":"P",
    "gn:feature_code":"PPL",
    "gn:name":"Bogyaytanya",
    "gn:population":0,
    "gn:timezone":"Europe/Budapest",
    "iso:country":"HU",
    "name:und_x_variant":[
        "Bogyai-tanya",
        "Bogyaytanya"
    ],
    "wof:name":"Bogyaytanya",
    "wof:placetype":"locality"
},
  "geometry": {"coordinates":[21.63333,48.28333],"type":"Point"}
}