{
  "type": "Feature",
  "properties": {
    "gn:admin1_code":"10.0",
    "gn:asciiname":"Ligetpuszta",
    "gn:cc2":"HU",
    "gn:country_code":"HU",
    "gn:dem":151,
    "gn:feature_class":"P",
    "gn:feature_code":"PPL",
    "gn:name":"Ligetpuszta",
    "gn:population":0,
    "gn:timezone":"Europe/Budapest",
    "iso:country":"HU",
    "name:und_x_variant":[
        "Liget-tanya",
        "Ligetpuszta"
    ],
    "wof:name":"Ligetpuszta",
    "wof:placetype":"locality"
},
  "geometry": {"coordinates":[21.78333,47.66667],"type":"Point"}
}