{
  "type": "Feature",
  "properties": {
    "gn:admin1_code":"18.0",
    "gn:asciiname":"Nagy I.-tanya",
    "gn:cc2":"HU",
    "gn:country_code":"HU",
    "gn:dem":115,
    "gn:feature_class":"P",
    "gn:feature_code":"PPL",
    "gn:name":"Nagy I.-tanya",
    "gn:population":0,
    "gn:timezone":"Europe/Budapest",
    "iso:country":"HU",
    "name:und_x_variant":[
        "Nagy-tanya",
        "Nagy I.-tanya"
    ],
    "wof:name":"Nagy I.-tanya",
    "wof:placetype":"locality"
},
  "geometry": {"coordinates":[22.76667,48.05],"type":"Point"}
}