{
  "type": "Feature",
  "properties": {
    "gn:admin1_code":"2.0",
    "gn:asciiname":"Mariamajor",
    "gn:country_code":"HU",
    "gn:dem":93,
    "gn:feature_class":"P",
    "gn:feature_code":"PPL",
    "gn:name":"M\u00e1riamajor",
    "gn:population":0,
    "gn:timezone":"Europe/Budapest",
    "iso:country":"HU",
    "wof:name":"Mariamajor",
    "wof:placetype":"locality"
},
  "geometry": {"coordinates":[18.05,45.86667],"type":"Point"}
}