{
  "type": "Feature",
  "properties": {
    "gn:admin1_code":"2.0",
    "gn:asciiname":"Kistapolca",
    "gn:country_code":"HU",
    "gn:dem":100,
    "gn:feature_class":"P",
    "gn:feature_code":"PPL",
    "gn:name":"Kistapolca",
    "gn:population":0,
    "gn:timezone":"Europe/Budapest",
    "iso:country":"HU",
    "name:epo_x_preferred":[
        "Kistapolca"
    ],
    "name:fas_x_preferred":[
        "\u06a9\u06cc\u0634\u062a\u0627\u067e\u0648\u0644\u062a\u0633\u0627"
    ],
    "name:fra_x_preferred":[
        "Kistapolca"
    ],
    "name:hrv_x_preferred":[
        "Tapoca"
    ],
    "name:hun_x_preferred":[
        "Kistapolca"
    ],
    "name:ita_x_preferred":[
        "Kistapolca"
    ],
    "name:msa_x_preferred":[
        "Kistapolca"
    ],
    "name:nld_x_preferred":[
        "Kistapolca"
    ],
    "name:pol_x_preferred":[
        "Kistapolca"
    ],
    "name:ron_x_preferred":[
        "Kistapolca"
    ],
    "name:slk_x_preferred":[
        "Kistapolca"
    ],
    "name:slv_x_preferred":[
        "Kistapolca"
    ],
    "name:vie_x_preferred":[
        "Kistapolca"
    ],
    "name:zho_x_preferred":[
        "\u57fa\u4ec0\u9676\u6ce2\u5c14\u66f9"
    ],
    "wof:name":"Kistapolca",
    "wof:placetype":"locality"
},
  "geometry": {"coordinates":[18.38299,45.82163],"type":"Point"}
}