{
  "type": "Feature",
  "properties": {
    "gn:admin1_code":"12.0",
    "gn:asciiname":"Bakonybank",
    "gn:country_code":"HU",
    "gn:dem":186,
    "gn:feature_class":"P",
    "gn:feature_code":"PPL",
    "gn:name":"Bakonyb\u00e1nk",
    "gn:population":0,
    "gn:timezone":"Europe/Budapest",
    "iso:country":"HU",
    "name:ces_x_preferred":[
        "Bakonyb\u00e1nk"
    ],
    "name:epo_x_preferred":[
        "Bakonyb\u00e1nk"
    ],
    "name:fas_x_preferred":[
        "\u0628\u0627\u06a9\u0648\u0646\u06cc\u0628\u0627\u0646\u06a9"
    ],
    "name:fra_x_preferred":[
        "Bakonyb\u00e1nk"
    ],
    "name:hun_x_preferred":[
        "Bakonyb\u00e1nk"
    ],
    "name:ita_x_preferred":[
        "Bakonyb\u00e1nk"
    ],
    "name:msa_x_preferred":[
        "Bakonyb\u00e1nk"
    ],
    "name:nld_x_preferred":[
        "Bakonyb\u00e1nk"
    ],
    "name:ron_x_preferred":[
        "Bakonyb\u00e1nk"
    ],
    "name:slk_x_preferred":[
        "Bakonyb\u00e1nk"
    ],
    "name:slv_x_preferred":[
        "Bakonyb\u00e1nk"
    ],
    "name:swe_x_preferred":[
        "Bakonyb\u00e1nk"
    ],
    "name:vie_x_preferred":[
        "Bakonyb\u00e1nk"
    ],
    "name:zho_x_preferred":[
        "\u9c8d\u79d1\u5c3c\u73ed\u514b"
    ],
    "wof:name":"Bakonybank",
    "wof:placetype":"locality"
},
  "geometry": {"coordinates":[17.90407,47.4671],"type":"Point"}
}