{
  "type": "Feature",
  "properties": {
    "gn:admin1_code":"14.0",
    "gn:asciiname":"Almaskuttanya",
    "gn:country_code":"HU",
    "gn:dem":283,
    "gn:feature_class":"P",
    "gn:feature_code":"PPL",
    "gn:name":"Alm\u00e1sk\u00fattanya",
    "gn:population":0,
    "gn:timezone":"Europe/Budapest",
    "iso:country":"HU",
    "name:und_x_variant":[
        "Alm\u00e1sikut-puszta",
        "Alm\u00e1sk\u00fattanya"
    ],
    "wof:name":"Almaskuttanya",
    "wof:placetype":"locality"
},
  "geometry": {"coordinates":[19.64115,48.03961],"type":"Point"}
}