{
  "type": "Feature",
  "properties": {
    "gn:admin1_code":"17.0",
    "gn:asciiname":"Csombard",
    "gn:country_code":"HU",
    "gn:dem":152,
    "gn:feature_class":"P",
    "gn:feature_code":"PPL",
    "gn:name":"Csomb\u00e1rd",
    "gn:population":0,
    "gn:timezone":"Europe/Budapest",
    "iso:country":"HU",
    "name:und_x_variant":[
        "Csomb\u00e1rd"
    ],
    "wof:name":"Csombard",
    "wof:placetype":"locality"
},
  "geometry": {"coordinates":[17.67124,46.45217],"type":"Point"}
}