{
  "type": "Feature",
  "properties": {
    "gn:admin1_code":"17.0",
    "gn:asciiname":"Csombard",
    "gn:country_code":"HU",
    "gn:dem":152,
    "gn:feature_class":"P",
    "gn:feature_code":"PPL",
    "gn:name":"Csomb\u00e1rd",
    "gn:population":0,
    "gn:timezone":"Europe/Budapest",
    "iso:country":"HU",
    "name:deu_x_preferred":[
        "Csomb\u00e1rd"
    ],
    "name:epo_x_preferred":[
        "Csomb\u00e1rd"
    ],
    "name:fas_x_preferred":[
        "\u0686\u0648\u0645\u0628\u0627\u0631\u062f"
    ],
    "name:fra_x_preferred":[
        "Csomb\u00e1rd"
    ],
    "name:hun_x_preferred":[
        "Csomb\u00e1rd"
    ],
    "name:ita_x_preferred":[
        "Csomb\u00e1rd"
    ],
    "name:msa_x_preferred":[
        "Csomb\u00e1rd"
    ],
    "name:nld_x_preferred":[
        "Csomb\u00e1rd"
    ],
    "name:ron_x_preferred":[
        "Csomb\u00e1rd"
    ],
    "name:slk_x_preferred":[
        "Csomb\u00e1rd"
    ],
    "name:slv_x_preferred":[
        "Csomb\u00e1rd"
    ],
    "name:vie_x_preferred":[
        "Csomb\u00e1rd"
    ],
    "name:zho_x_preferred":[
        "\u743c\u5df4\u5c14\u5fb7"
    ],
    "wof:name":"Csombard",
    "wof:placetype":"locality"
},
  "geometry": {"coordinates":[17.67124,46.45217],"type":"Point"}
}