{
  "type": "Feature",
  "properties": {
    "gn:admin1_code":"8.0",
    "gn:asciiname":"Borbalapuszta",
    "gn:country_code":"HU",
    "gn:dem":129,
    "gn:feature_class":"P",
    "gn:feature_code":"PPL",
    "gn:name":"Borb\u00e1lapuszta",
    "gn:population":0,
    "gn:timezone":"Europe/Budapest",
    "iso:country":"HU",
    "wof:name":"Borbalapuszta",
    "wof:placetype":"locality"
},
  "geometry": {"coordinates":[18.58333,47.43333],"type":"Point"}
}