{
  "type": "Feature",
  "properties": {
    "gn:admin1_code":"1.0",
    "gn:asciiname":"Kaskantyui Tanyak",
    "gn:country_code":"HU",
    "gn:dem":106,
    "gn:feature_class":"P",
    "gn:feature_code":"PPL",
    "gn:name":"Kaskanty\u00fai Tany\u00e1k",
    "gn:population":0,
    "gn:timezone":"Europe/Budapest",
    "iso:country":"HU",
    "wof:name":"Kaskantyui Tanyak",
    "wof:placetype":"locality"
},
  "geometry": {"coordinates":[19.37438,46.68285],"type":"Point"}
}