{
  "type": "Feature",
  "properties": {
    "gn:gn_country":"HU",
    "gn:gn_fcode":"PPL",
    "gn:gn_pop":0,
    "iso:country":"HU",
    "name:ces_x_preferred":[
        "Nek\u00e9zseny"
    ],
    "name:deu_x_preferred":[
        "Nek\u00e9zseny"
    ],
    "name:eng_x_preferred":[
        "Nek\u00e9zseny"
    ],
    "name:epo_x_preferred":[
        "Nek\u00e9zseny"
    ],
    "name:fas_x_preferred":[
        "\u0646\u06a9\u0698\u0646\u06cc"
    ],
    "name:fra_x_preferred":[
        "Nek\u00e9zseny"
    ],
    "name:heb_x_preferred":[
        "\u05e0\u05e7\u05d6'\u05df"
    ],
    "name:hun_x_preferred":[
        "Nek\u00e9zseny"
    ],
    "name:ita_x_preferred":[
        "Nek\u00e9zseny"
    ],
    "name:msa_x_preferred":[
        "Nek\u00e9zseny"
    ],
    "name:nan_x_preferred":[
        "Nek\u00e9zseny"
    ],
    "name:nld_x_preferred":[
        "Nek\u00e9zseny"
    ],
    "name:pol_x_preferred":[
        "Nek\u00e9zseny"
    ],
    "name:ron_x_preferred":[
        "Nek\u00e9zseny"
    ],
    "name:slk_x_preferred":[
        "Nek\u00e9zseny"
    ],
    "name:slv_x_preferred":[
        "Nek\u00e9zseny"
    ],
    "name:srp_x_preferred":[
        "\u0410\u0442\u0430\u043b\u0430"
    ],
    "name:vie_x_preferred":[
        "Nek\u00e9zseny"
    ],
    "name:zho_x_preferred":[
        "\u5948\u51ef\u70ed\u5c3c"
    ],
    "qs_pg:aaroncc":"HU",
    "qs_pg:gn_country":"HU",
    "qs_pg:gn_fcode":"PPL",
    "qs_pg:gn_pop":0,
    "qs_pg:name":"Nek\u00e9zseny",
    "qs_pg:name_adm0":"Magyarorsz\u00e1g",
    "qs_pg:name_adm1":"Borsod-Aba\u00faj-Zempl\u00e9n",
    "qs_pg:photos":15,
    "qs_pg:photos_1k":3,
    "qs_pg:photos_9k":1,
    "qs_pg:photos_9r":1,
    "qs_pg:photos_all":15,
    "qs_pg:photos_sr":1,
    "qs_pg:pop_sr":0,
    "qs_pg:qs_pg_placetype":"locality",
    "qs_pg:qs_pg_placetype_gp":"Town",
    "qs_pg:woe_adm0":23424844,
    "woe:adm0_id":23424844,
    "woe:name_adm0":"Magyarorsz\u00e1g",
    "woe:name_adm1":"Borsod-Aba\u00faj-Zempl\u00e9n",
    "woe:placetype":"Town",
    "wof:name":"Nek\u00e9zseny",
    "wof:placetype":"locality"
},
  "geometry": {"coordinates":[20.43333,48.16667],"type":"Point"}
}