{
  "type": "Feature",
  "properties": {
    "iso:country":"HU",
    "name:hun_x_colloquial":[
        "Zsoldosdulo"
    ],
    "name:hun_x_preferred":[
        "Zsoldosd\u016fl\u0151"
    ],
    "name:unk_x_variant":[
        "Zsoldosd\u016fl\u0151"
    ],
    "qs:gn_adm0_cc":"HU",
    "qs:gn_local":720276,
    "qs:gn_nam_loc":"Hajd\u00faszoboszl\u00f3, Hajd\u00faszoboszl\u00f3, Hajd\u00fa-Bihar, HU",
    "qs:gn_namadm1":"10",
    "qs:local_max":94,
    "qs:local_sum":105,
    "qs:localhoods":2,
    "qs:name":"Zsoldosd\u016fl\u0151",
    "qs:name_adm0":"Magyarorsz\u00e1g",
    "qs:name_adm1":"Hajd\u00fa-Bihar",
    "qs:name_adm2":"Hajd\u00faszoboszl\u00f3",
    "qs:name_local":"Hajd\u00faszoboszl\u00f3",
    "qs:photo_max":37,
    "qs:photo_sum":94,
    "qs:placetype":"Suburb",
    "qs:quad_count":12,
    "qs:woe_adm0":23424844,
    "qs:woe_adm1":12577919,
    "qs:woe_adm2":12593307,
    "qs:woe_lau":0,
    "qs:woe_local":807525,
    "qs:woe_ver":"7.10.0",
    "wof:lang":[
        "hun"
    ],
    "wof:name":"Zsoldosd\u016fl\u0151",
    "wof:placetype":"neighbourhood"
},
  "geometry": {"coordinates":[21.399242,47.450589],"type":"Point"}
}