{
  "type": "Feature",
  "properties": {
    "gn:admin1_code":"8.0",
    "gn:asciiname":"Nandormajor",
    "gn:country_code":"HU",
    "gn:dem":128,
    "gn:feature_class":"P",
    "gn:feature_code":"PPL",
    "gn:name":"N\u00e1ndormajor",
    "gn:population":0,
    "gn:timezone":"Europe/Budapest",
    "iso:country":"HU",
    "wof:name":"Nandormajor",
    "wof:placetype":"locality"
},
  "geometry": {"coordinates":[18.73314,47.15973],"type":"Point"}
}