{
  "type": "Feature",
  "properties": {
    "gn:admin1_code":"24.0",
    "gn:asciiname":"Varhelypuszta",
    "gn:country_code":"HU",
    "gn:dem":158,
    "gn:feature_class":"P",
    "gn:feature_code":"PPL",
    "gn:name":"V\u00e1rhelypuszta",
    "gn:population":0,
    "gn:timezone":"Europe/Budapest",
    "iso:country":"HU",
    "wof:name":"Varhelypuszta",
    "wof:placetype":"locality"
},
  "geometry": {"coordinates":[16.98981,46.67125],"type":"Point"}
}