{
  "type": "Feature",
  "properties": {
    "gn:admin1_code":"23.0",
    "gn:asciiname":"Bodorfa",
    "gn:country_code":"HU",
    "gn:dem":154,
    "gn:feature_class":"P",
    "gn:feature_code":"PPL",
    "gn:name":"Bodorfa",
    "gn:population":0,
    "gn:timezone":"Europe/Budapest",
    "iso:country":"HU",
    "name:deu_x_preferred":[
        "Bodorfa"
    ],
    "name:epo_x_preferred":[
        "Bodorfa"
    ],
    "name:fas_x_preferred":[
        "\u0628\u0648\u062f\u0648\u0631\u0641\u0627"
    ],
    "name:fra_x_preferred":[
        "Bodorfa"
    ],
    "name:hun_x_preferred":[
        "Bodorfa"
    ],
    "name:ita_x_preferred":[
        "Bodorfa"
    ],
    "name:msa_x_preferred":[
        "Bodorfa"
    ],
    "name:nld_x_preferred":[
        "Bodorfa"
    ],
    "name:ron_x_preferred":[
        "Bodorfa"
    ],
    "name:slk_x_preferred":[
        "Bodorfa"
    ],
    "name:slv_x_preferred":[
        "Bodorfa"
    ],
    "name:vie_x_preferred":[
        "Bodorfa"
    ],
    "name:zho_x_preferred":[
        "\u535a\u591a\u5c14\u798f"
    ],
    "wof:name":"Bodorfa",
    "wof:placetype":"locality"
},
  "geometry": {"coordinates":[17.34206,47.07605],"type":"Point"}
}