{
  "type": "Feature",
  "properties": {
    "gn:admin1_code":"23.0",
    "gn:asciiname":"Bodorfa",
    "gn:country_code":"HU",
    "gn:dem":154,
    "gn:feature_class":"P",
    "gn:feature_code":"PPL",
    "gn:name":"Bodorfa",
    "gn:population":0,
    "gn:timezone":"Europe/Budapest",
    "iso:country":"HU",
    "wof:name":"Bodorfa",
    "wof:placetype":"locality"
},
  "geometry": {"coordinates":[17.34206,47.07605],"type":"Point"}
}