{
  "type": "Feature",
  "properties": {
    "gn:admin1_code":"22.0",
    "gn:asciiname":"Ketvolgy",
    "gn:country_code":"HU",
    "gn:dem":301,
    "gn:feature_class":"P",
    "gn:feature_code":"PPL",
    "gn:name":"K\u00e9tv\u00f6lgy",
    "gn:population":0,
    "gn:timezone":"Europe/Budapest",
    "iso:country":"HU",
    "name:und_x_variant":[
        "Ritkah\u00e1za",
        "Vashegyalja",
        "K\u00e9tv\u00f6lgy"
    ],
    "wof:name":"Ketvolgy",
    "wof:placetype":"locality"
},
  "geometry": {"coordinates":[16.21074,46.88532],"type":"Point"}
}