{
  "type": "Feature",
  "properties": {
    "gn:admin1_code":"22.0",
    "gn:asciiname":"Ketvolgy",
    "gn:country_code":"HU",
    "gn:dem":301,
    "gn:feature_class":"P",
    "gn:feature_code":"PPL",
    "gn:name":"K\u00e9tv\u00f6lgy",
    "gn:population":0,
    "gn:timezone":"Europe/Budapest",
    "iso:country":"HU",
    "name:ces_x_preferred":[
        "K\u00e9tv\u00f6lgy"
    ],
    "name:epo_x_preferred":[
        "K\u00e9tv\u00f6lgy"
    ],
    "name:fas_x_preferred":[
        "\u06a9\u062a\u0648\u0648\u0644\u06af\u06cc"
    ],
    "name:fra_x_preferred":[
        "K\u00e9tv\u00f6lgy"
    ],
    "name:hun_x_preferred":[
        "K\u00e9tv\u00f6lgy"
    ],
    "name:ita_x_preferred":[
        "K\u00e9tv\u00f6lgy"
    ],
    "name:msa_x_preferred":[
        "K\u00e9tv\u00f6lgy"
    ],
    "name:nld_x_preferred":[
        "K\u00e9tv\u00f6lgy"
    ],
    "name:ron_x_preferred":[
        "K\u00e9tv\u00f6lgy"
    ],
    "name:slk_x_preferred":[
        "K\u00e9tv\u00f6lgy"
    ],
    "name:slv_x_preferred":[
        "Verica-Ritkarovci"
    ],
    "name:und_x_variant":[
        "Ritkah\u00e1za",
        "Vashegyalja",
        "K\u00e9tv\u00f6lgy"
    ],
    "name:vie_x_preferred":[
        "K\u00e9tv\u00f6lgy"
    ],
    "name:zho_x_preferred":[
        "\u51ef\u7279\u6c83\u5c14\u5409"
    ],
    "wof:name":"Ketvolgy",
    "wof:placetype":"locality"
},
  "geometry": {"coordinates":[16.21074,46.88532],"type":"Point"}
}