{
  "type": "Feature",
  "properties": {
    "gn:admin1_code":"4.0",
    "gn:asciiname":"Balog-tanya",
    "gn:country_code":"HU",
    "gn:dem":217,
    "gn:feature_class":"P",
    "gn:feature_code":"PPL",
    "gn:name":"Balog-tanya",
    "gn:population":0,
    "gn:timezone":"Europe/Budapest",
    "iso:country":"HU",
    "name:und_x_variant":[
        "Vil\u00e1gos Puszta",
        "Vil\u00e1gostanya"
    ],
    "wof:name":"Balog-tanya",
    "wof:placetype":"locality"
},
  "geometry": {"coordinates":[21.11667000000001,48.26667],"type":"Point"}
}