{
  "type": "Feature",
  "properties": {
    "gn:admin1_code":"2.0",
    "gn:asciiname":"Szilvas",
    "gn:country_code":"HU",
    "gn:dem":159,
    "gn:feature_class":"P",
    "gn:feature_code":"PPL",
    "gn:name":"Szilv\u00e1s",
    "gn:population":0,
    "gn:timezone":"Europe/Budapest",
    "iso:country":"HU",
    "name:epo_x_preferred":[
        "Szilv\u00e1s"
    ],
    "name:fas_x_preferred":[
        "\u0633\u06cc\u0644\u0648\u0627\u0634"
    ],
    "name:fra_x_preferred":[
        "Szilv\u00e1s"
    ],
    "name:hrv_x_preferred":[
        "Silva\u0161"
    ],
    "name:hun_x_preferred":[
        "Szilv\u00e1s"
    ],
    "name:ita_x_preferred":[
        "Szilv\u00e1s"
    ],
    "name:msa_x_preferred":[
        "Szilv\u00e1s"
    ],
    "name:nld_x_preferred":[
        "Szilv\u00e1s"
    ],
    "name:pol_x_preferred":[
        "Szilv\u00e1s"
    ],
    "name:ron_x_preferred":[
        "Szilv\u00e1s"
    ],
    "name:slk_x_preferred":[
        "Szilv\u00e1s"
    ],
    "name:slv_x_preferred":[
        "Szilv\u00e1s"
    ],
    "name:vie_x_preferred":[
        "Szilv\u00e1s"
    ],
    "name:zho_x_preferred":[
        "\u897f\u5c14\u74e6\u4ec0"
    ],
    "wof:name":"Szilvas",
    "wof:placetype":"locality"
},
  "geometry": {"coordinates":[18.19959,45.9628],"type":"Point"}
}