{
  "type": "Feature",
  "properties": {
    "gn:admin1_code":"23.0",
    "gn:asciiname":"Bereg",
    "gn:country_code":"HU",
    "gn:dem":244,
    "gn:feature_class":"P",
    "gn:feature_code":"PPL",
    "gn:name":"Bereg",
    "gn:population":0,
    "gn:timezone":"Europe/Budapest",
    "iso:country":"HU",
    "name:deu_x_preferred":[
        "Bereg"
    ],
    "name:fra_x_preferred":[
        "Bereg"
    ],
    "name:hrv_x_preferred":[
        "Bereg"
    ],
    "name:nld_x_preferred":[
        "Bereg"
    ],
    "wof:name":"Bereg",
    "wof:placetype":"locality"
},
  "geometry": {"coordinates":[17.68332999999999,46.91667],"type":"Point"}
}