{
  "type": "Feature",
  "properties": {
    "gn:admin1_code":"23.0",
    "gn:asciiname":"Kungos",
    "gn:country_code":"HU",
    "gn:dem":159,
    "gn:feature_class":"P",
    "gn:feature_code":"PPL",
    "gn:name":"K\u00fcng\u00f6s",
    "gn:population":0,
    "gn:timezone":"Europe/Budapest",
    "iso:country":"HU",
    "name:und_x_variant":[
        "K\u00fcng\u00f6s"
    ],
    "wof:name":"Kungos",
    "wof:placetype":"locality"
},
  "geometry": {"coordinates":[18.17295,47.06592],"type":"Point"}
}