{
  "type": "Feature",
  "properties": {
    "gn:admin1_code":"2.0",
    "gn:asciiname":"Endroc",
    "gn:country_code":"HU",
    "gn:dem":101,
    "gn:feature_class":"P",
    "gn:feature_code":"PPL",
    "gn:name":"Endr\u0151c",
    "gn:population":0,
    "gn:timezone":"Europe/Budapest",
    "iso:country":"HU",
    "name:und_x_variant":[
        "Endr\u0151c"
    ],
    "wof:name":"Endroc",
    "wof:placetype":"locality"
},
  "geometry": {"coordinates":[17.76054,45.93009],"type":"Point"}
}