{
  "type": "Feature",
  "properties": {
    "gn:country":"HU",
    "gn:fcode":"PPL",
    "gn:population":0,
    "iso:country":"HU",
    "name:eng_x_preferred":[
        "V\u00e1szoly"
    ],
    "name:epo_x_preferred":[
        "V\u00e1szoly"
    ],
    "name:fas_x_preferred":[
        "\u0648\u0627\u0633\u0648\u0644\u06cc"
    ],
    "name:fra_x_preferred":[
        "V\u00e1szoly"
    ],
    "name:hun_x_preferred":[
        "V\u00e1szoly"
    ],
    "name:ita_x_preferred":[
        "V\u00e1szoly"
    ],
    "name:msa_x_preferred":[
        "V\u00e1szoly"
    ],
    "name:nan_x_preferred":[
        "V\u00e1szoly"
    ],
    "name:nld_x_preferred":[
        "V\u00e1szoly"
    ],
    "name:ron_x_preferred":[
        "V\u00e1szoly"
    ],
    "name:slk_x_preferred":[
        "V\u00e1szoly"
    ],
    "name:slv_x_preferred":[
        "V\u00e1szoly"
    ],
    "name:swe_x_preferred":[
        "V\u00e1szoly"
    ],
    "name:vie_x_preferred":[
        "V\u00e1szoly"
    ],
    "name:zho_x_preferred":[
        "\u74e6\u7d22\u4f0a"
    ],
    "qs_pg:aaroncc":"HU",
    "qs_pg:gn_country":"HU",
    "qs_pg:gn_fcode":"PPL",
    "qs_pg:gn_pop":0,
    "qs_pg:name":"V\u00e1szoly",
    "qs_pg:name_adm0":"Magyarorsz\u00e1g",
    "qs_pg:name_adm1":"Veszpr\u00e9m",
    "qs_pg:photos":40,
    "qs_pg:photos_1k":8,
    "qs_pg:photos_9k":1,
    "qs_pg:photos_9r":2,
    "qs_pg:photos_all":40,
    "qs_pg:photos_sr":2,
    "qs_pg:pop_sr":0,
    "qs_pg:qs_pg_placetype":"locality",
    "qs_pg:qs_pg_placetype_gp":"Town",
    "qs_pg:woe_adm0":23424844,
    "woe:adm0_id":23424844,
    "woe:name_adm0":"Magyarorsz\u00e1g",
    "woe:name_adm1":"Veszpr\u00e9m",
    "woe:placetype":"Town",
    "wof:name":"V\u00e1szoly",
    "wof:placetype":"locality"
},
  "geometry": {"coordinates":[17.75858,46.94026],"type":"Point"}
}