{
  "type": "Feature",
  "properties": {
    "gn:admin1_code":"22.0",
    "gn:asciiname":"Nagykolked",
    "gn:country_code":"HU",
    "gn:dem":214,
    "gn:feature_class":"P",
    "gn:feature_code":"PPL",
    "gn:name":"Nagyk\u00f6lked",
    "gn:population":0,
    "gn:timezone":"Europe/Budapest",
    "iso:country":"HU",
    "name:epo_x_preferred":[
        "Nagyk\u00f6lked"
    ],
    "name:fas_x_preferred":[
        "\u0646\u0627\u06af\u06cc\u06a9\u0648\u0644\u06a9\u062f"
    ],
    "name:fra_x_preferred":[
        "Nagyk\u00f6lked"
    ],
    "name:hun_x_preferred":[
        "Nagyk\u00f6lked"
    ],
    "name:ita_x_preferred":[
        "Nagyk\u00f6lked"
    ],
    "name:msa_x_preferred":[
        "Nagyk\u00f6lked"
    ],
    "name:nld_x_preferred":[
        "Nagyk\u00f6lked"
    ],
    "name:ron_x_preferred":[
        "Nagyk\u00f6lked"
    ],
    "name:slk_x_preferred":[
        "Nagyk\u00f6lked"
    ],
    "name:slv_x_preferred":[
        "Nagyk\u00f6lked"
    ],
    "name:und_x_variant":[
        "Nagyk\u00f6lked"
    ],
    "name:vie_x_preferred":[
        "Nagyk\u00f6lked"
    ],
    "name:zho_x_preferred":[
        "\u7459\u5409\u514b\u5c14\u51ef\u5fb7"
    ],
    "wof:name":"Nagykolked",
    "wof:placetype":"locality"
},
  "geometry": {"coordinates":[16.55273,47.06743],"type":"Point"}
}