{
  "type": "Feature",
  "properties": {
    "gn:admin1_code":"22.0",
    "gn:asciiname":"Nagykolked",
    "gn:country_code":"HU",
    "gn:dem":214,
    "gn:feature_class":"P",
    "gn:feature_code":"PPL",
    "gn:name":"Nagyk\u00f6lked",
    "gn:population":0,
    "gn:timezone":"Europe/Budapest",
    "iso:country":"HU",
    "name:und_x_variant":[
        "Nagyk\u00f6lked"
    ],
    "wof:name":"Nagykolked",
    "wof:placetype":"locality"
},
  "geometry": {"coordinates":[16.55273,47.06743],"type":"Point"}
}