{
  "type": "Feature",
  "properties": {
    "gn:admin1_code":"2.0",
    "gn:asciiname":"Totszentgyoergy",
    "gn:country_code":"HU",
    "gn:dem":115,
    "gn:feature_class":"P",
    "gn:feature_code":"PPL",
    "gn:name":"T\u00f3tszentgy\u00f6rgy",
    "gn:population":0,
    "gn:timezone":"Europe/Budapest",
    "iso:country":"HU",
    "name:epo_x_preferred":[
        "T\u00f3tszentgy\u00f6rgy"
    ],
    "name:fas_x_preferred":[
        "\u062a\u0648\u062a\u0632\u0646\u062a \u06af\u06cc\u0648\u0631\u06af\u06cc"
    ],
    "name:fra_x_preferred":[
        "T\u00f3tszentgy\u00f6rgy"
    ],
    "name:hrv_x_preferred":[
        "Se\u0111u\u0111"
    ],
    "name:hun_x_preferred":[
        "T\u00f3tszentgy\u00f6rgy"
    ],
    "name:ita_x_preferred":[
        "T\u00f3tszentgy\u00f6rgy"
    ],
    "name:msa_x_preferred":[
        "T\u00f3tszentgy\u00f6rgy"
    ],
    "name:nld_x_preferred":[
        "T\u00f3tszentgy\u00f6rgy"
    ],
    "name:pol_x_preferred":[
        "T\u00f3tszentgy\u00f6rgy"
    ],
    "name:ron_x_preferred":[
        "T\u00f3tszentgy\u00f6rgy"
    ],
    "name:slk_x_preferred":[
        "T\u00f3tszentgy\u00f6rgy"
    ],
    "name:slv_x_preferred":[
        "T\u00f3tszentgy\u00f6rgy"
    ],
    "name:vie_x_preferred":[
        "T\u00f3tszentgy\u00f6rgy"
    ],
    "name:zho_x_preferred":[
        "\u6258\u7279\u68ee\u7279\u54f2\u5c14\u5409"
    ],
    "wof:name":"Totszentgyoergy",
    "wof:placetype":"locality"
},
  "geometry": {"coordinates":[17.71667,46.05],"type":"Point"}
}