{
  "type": "Feature",
  "properties": {
    "gn:admin1_code":"2.0",
    "gn:asciiname":"Totszentgyoergy",
    "gn:country_code":"HU",
    "gn:dem":115,
    "gn:feature_class":"P",
    "gn:feature_code":"PPL",
    "gn:name":"T\u00f3tszentgy\u00f6rgy",
    "gn:population":0,
    "gn:timezone":"Europe/Budapest",
    "iso:country":"HU",
    "wof:name":"Totszentgyoergy",
    "wof:placetype":"locality"
},
  "geometry": {"coordinates":[17.71667,46.05],"type":"Point"}
}