{
  "type": "Feature",
  "properties": {
    "gn:admin1_code":"1.0",
    "gn:asciiname":"Felsolajos",
    "gn:cc2":"HU",
    "gn:country_code":"HU",
    "gn:dem":131,
    "gn:feature_class":"P",
    "gn:feature_code":"PPL",
    "gn:name":"Fels\u0151lajos",
    "gn:population":0,
    "gn:timezone":"Europe/Budapest",
    "iso:country":"HU",
    "name:und_x_variant":[
        "Fels\u0151lajospuszta"
    ],
    "wof:name":"Felsolajos",
    "wof:placetype":"locality"
},
  "geometry": {"coordinates":[19.49713,47.0672],"type":"Point"}
}