{
  "type": "Feature",
  "properties": {
    "gn:admin1_code":"1.0",
    "gn:asciiname":"Kompoc",
    "gn:country_code":"HU",
    "gn:dem":93,
    "gn:feature_class":"P",
    "gn:feature_code":"PPL",
    "gn:name":"K\u00f6mp\u00f6c",
    "gn:population":0,
    "gn:timezone":"Europe/Budapest",
    "iso:country":"HU",
    "name:deu_x_preferred":[
        "K\u00f6mp\u00f6c"
    ],
    "name:epo_x_preferred":[
        "K\u00f6mp\u00f6c"
    ],
    "name:fas_x_preferred":[
        "\u06a9\u0648\u0645\u067e\u0648\u062a\u0633"
    ],
    "name:fra_x_preferred":[
        "K\u00f6mp\u00f6c"
    ],
    "name:hrv_x_preferred":[
        "Kempac"
    ],
    "name:hun_x_preferred":[
        "K\u00f6mp\u00f6c"
    ],
    "name:ita_x_preferred":[
        "K\u00f6mp\u00f6c"
    ],
    "name:msa_x_preferred":[
        "K\u00f6mp\u00f6c"
    ],
    "name:nld_x_preferred":[
        "K\u00f6mp\u00f6c"
    ],
    "name:pol_x_preferred":[
        "K\u00f6mp\u00f6c"
    ],
    "name:ron_x_preferred":[
        "K\u00f6mp\u00f6c"
    ],
    "name:slk_x_preferred":[
        "K\u00f6mp\u00f6c"
    ],
    "name:slv_x_preferred":[
        "K\u00f6mp\u00f6c"
    ],
    "name:und_x_variant":[
        "K\u00f6mp\u00f6c"
    ],
    "name:vie_x_preferred":[
        "K\u00f6mp\u00f6c"
    ],
    "name:zho_x_preferred":[
        "\u80af\u73c0\u8328"
    ],
    "wof:name":"Kompoc",
    "wof:placetype":"locality"
},
  "geometry": {"coordinates":[19.86667000000001,46.46352],"type":"Point"}
}