{
  "type": "Feature",
  "properties": {
    "gn:admin1_code":"24.0",
    "gn:asciiname":"Zebecke",
    "gn:country_code":"HU",
    "gn:dem":168,
    "gn:feature_class":"P",
    "gn:feature_code":"PPL",
    "gn:name":"Zebecke",
    "gn:population":0,
    "gn:timezone":"Europe/Budapest",
    "iso:country":"HU",
    "name:und_x_variant":[
        "Zebeczke",
        "Zebecke"
    ],
    "wof:name":"Zebecke",
    "wof:placetype":"locality"
},
  "geometry": {"coordinates":[16.68605,46.64344000000001],"type":"Point"}
}