{
  "type": "Feature",
  "properties": {
    "gn:admin1_code":"4.0",
    "gn:asciiname":"Zemplenagard",
    "gn:country_code":"HU",
    "gn:dem":99,
    "gn:feature_class":"P",
    "gn:feature_code":"PPL",
    "gn:name":"Zempl\u00e9nag\u00e1rd",
    "gn:population":0,
    "gn:timezone":"Europe/Budapest",
    "iso:country":"HU",
    "name:und_x_variant":[
        "Zempl\u00e9nag\u00e1rd"
    ],
    "wof:name":"Zemplenagard",
    "wof:placetype":"locality"
},
  "geometry": {"coordinates":[22.08066,48.35739],"type":"Point"}
}