{
  "type": "Feature",
  "properties": {
    "gn:admin1_code":"4.0",
    "gn:asciiname":"Zemplenagard",
    "gn:country_code":"HU",
    "gn:dem":99,
    "gn:feature_class":"P",
    "gn:feature_code":"PPL",
    "gn:name":"Zempl\u00e9nag\u00e1rd",
    "gn:population":0,
    "gn:timezone":"Europe/Budapest",
    "iso:country":"HU",
    "name:ces_x_preferred":[
        "Zempl\u00e9nag\u00e1rd"
    ],
    "name:deu_x_preferred":[
        "Zempl\u00e9nag\u00e1rd"
    ],
    "name:epo_x_preferred":[
        "Zempl\u00e9nag\u00e1rd"
    ],
    "name:fas_x_preferred":[
        "\u0632\u0645\u067e\u0644\u0646\u0627\u06af\u0627\u0631\u062f"
    ],
    "name:fra_x_preferred":[
        "Zempl\u00e9nag\u00e1rd"
    ],
    "name:heb_x_preferred":[
        "\u05d6\u05de\u05e4\u05dc\u05e0\u05d2\u05d0\u05e8\u05d3"
    ],
    "name:hun_x_preferred":[
        "Zempl\u00e9nag\u00e1rd"
    ],
    "name:ita_x_preferred":[
        "Zempl\u00e9nag\u00e1rd"
    ],
    "name:msa_x_preferred":[
        "Zempl\u00e9nag\u00e1rd"
    ],
    "name:nld_x_preferred":[
        "Zempl\u00e9nag\u00e1rd"
    ],
    "name:pol_x_preferred":[
        "Zempl\u00e9nag\u00e1rd"
    ],
    "name:ron_x_preferred":[
        "Zempl\u00e9nag\u00e1rd"
    ],
    "name:slk_x_preferred":[
        "Zempl\u00e9nag\u00e1rd"
    ],
    "name:slv_x_preferred":[
        "Zempl\u00e9nag\u00e1rd"
    ],
    "name:und_x_variant":[
        "Zempl\u00e9nag\u00e1rd"
    ],
    "name:vie_x_preferred":[
        "Zempl\u00e9nag\u00e1rd"
    ],
    "name:zho_x_preferred":[
        "\u66fe\u666e\u83b1\u7459\u52a0\u5c14\u5fb7"
    ],
    "wof:name":"Zemplenagard",
    "wof:placetype":"locality"
},
  "geometry": {"coordinates":[22.08066,48.35739],"type":"Point"}
}