{
  "type": "Feature",
  "properties": {
    "gn:admin1_code":"25.0",
    "gn:asciiname":"Gyor-Szabadhegy",
    "gn:country_code":"HU",
    "gn:dem":113,
    "gn:feature_class":"P",
    "gn:feature_code":"PPL",
    "gn:name":"Gy\u0151r-Szabadhegy",
    "gn:population":0,
    "gn:timezone":"Europe/Budapest",
    "iso:country":"HU",
    "wof:name":"Gyor-Szabadhegy",
    "wof:placetype":"locality"
},
  "geometry": {"coordinates":[17.66343999999999,47.66776],"type":"Point"}
}