{
  "type": "Feature",
  "properties": {
    "gn:admin1_code":"24.0",
    "gn:asciiname":"Zalaber",
    "gn:country_code":"HU",
    "gn:dem":130,
    "gn:feature_class":"P",
    "gn:feature_code":"PPL",
    "gn:name":"Zalab\u00e9r",
    "gn:population":0,
    "gn:timezone":"Europe/Budapest",
    "iso:country":"HU",
    "name:epo_x_preferred":[
        "Zalab\u00e9r"
    ],
    "name:fas_x_preferred":[
        "\u0632\u0627\u0644\u0627\u0628\u0631"
    ],
    "name:fra_x_preferred":[
        "Zalab\u00e9r"
    ],
    "name:hun_x_preferred":[
        "Zalab\u00e9r"
    ],
    "name:ita_x_preferred":[
        "Zalab\u00e9r"
    ],
    "name:msa_x_preferred":[
        "Zalab\u00e9r"
    ],
    "name:nld_x_preferred":[
        "Zalab\u00e9r"
    ],
    "name:ron_x_preferred":[
        "Zalab\u00e9r"
    ],
    "name:slk_x_preferred":[
        "Zalab\u00e9r"
    ],
    "name:slv_x_preferred":[
        "Zalab\u00e9r"
    ],
    "name:und_x_variant":[
        "Zalab\u00e9r"
    ],
    "name:vie_x_preferred":[
        "Zalab\u00e9r"
    ],
    "name:zho_x_preferred":[
        "\u4f50\u6d1b\u8d1d\u5c14"
    ],
    "wof:name":"Zalaber",
    "wof:placetype":"locality"
},
  "geometry": {"coordinates":[17.03045,46.97221],"type":"Point"}
}