{
  "type": "Feature",
  "properties": {
    "gn:gn_country":"HU",
    "gn:gn_fcode":"PPL",
    "gn:gn_pop":0,
    "iso:country":"HU",
    "name:chi_x_preferred":[
        "\u9c8d\u9053\u4e54\u5c3c\u7279\u5c14\u4ee3\u7c73\u8328"
    ],
    "name:dut_x_preferred":[
        "Badacsonyt\u00f6rdemic"
    ],
    "name:eng_x_preferred":[
        "Badacsonyt\u00f6rdemic"
    ],
    "name:epo_x_preferred":[
        "Badacsonyt\u00f6rdemic"
    ],
    "name:fre_x_preferred":[
        "Badacsonyt\u00f6rdemic"
    ],
    "name:hun_x_preferred":[
        "Badacsonyt\u00f6rdemic"
    ],
    "name:ita_x_preferred":[
        "Badacsonyt\u00f6rdemic"
    ],
    "name:may_x_preferred":[
        "Badacsonyt\u00f6rdemic"
    ],
    "name:nan_x_preferred":[
        "Badacsonyt\u00f6rdemic"
    ],
    "name:rum_x_preferred":[
        "Badacsonyt\u00f6rdemic"
    ],
    "name:slo_x_preferred":[
        "Badacsonyt\u00f6rdemic"
    ],
    "name:slv_x_preferred":[
        "Badacsonyt\u00f6rdemic"
    ],
    "name:unk_x_variant":[
        "Nemest\u00f6rdemic"
    ],
    "name:vie_x_preferred":[
        "Badacsonyt\u00f6rdemic"
    ],
    "qs_pg:aaroncc":"HU",
    "qs_pg:gn_country":"HU",
    "qs_pg:gn_fcode":"PPL",
    "qs_pg:gn_pop":0,
    "qs_pg:name":"Badacsonyt\u00f6rdemic",
    "qs_pg:name_adm0":"Magyarorsz\u00e1g",
    "qs_pg:name_adm1":"Veszpr\u00e9m",
    "qs_pg:photos":273,
    "qs_pg:photos_1k":55,
    "qs_pg:photos_9k":1,
    "qs_pg:photos_9r":4,
    "qs_pg:photos_all":273,
    "qs_pg:photos_sr":5,
    "qs_pg:pop_sr":0,
    "qs_pg:qs_pg_placetype":"locality",
    "qs_pg:qs_pg_placetype_gp":"Town",
    "qs_pg:woe_adm0":23424844,
    "woe:adm0_id":23424844,
    "woe:name_adm0":"Magyarorsz\u00e1g",
    "woe:name_adm1":"Veszpr\u00e9m",
    "woe:placetype":"Town",
    "wof:name":"Badacsonyt\u00f6rdemic",
    "wof:placetype":"locality"
},
  "geometry": {"coordinates":[17.47427,46.81068],"type":"Point"}
}