{
  "type": "Feature",
  "properties": {
    "gn:admin1_code":"22.0",
    "gn:asciiname":"Vasegerszeg",
    "gn:country_code":"HU",
    "gn:dem":152,
    "gn:feature_class":"P",
    "gn:feature_code":"PPL",
    "gn:name":"Vasegerszeg",
    "gn:population":0,
    "gn:timezone":"Europe/Budapest",
    "iso:country":"HU",
    "name:deu_x_preferred":[
        "Vasegerszeg"
    ],
    "name:epo_x_preferred":[
        "Vasegerszeg"
    ],
    "name:fas_x_preferred":[
        "\u0648\u0633\u06af\u0631\u0633\u0632\u06af"
    ],
    "name:fra_x_preferred":[
        "Vasegerszeg"
    ],
    "name:hun_x_preferred":[
        "Vasegerszeg"
    ],
    "name:ita_x_preferred":[
        "Vasegerszeg"
    ],
    "name:msa_x_preferred":[
        "Vasegerszeg"
    ],
    "name:nld_x_preferred":[
        "Vasegerszeg"
    ],
    "name:ron_x_preferred":[
        "Vasegerszeg"
    ],
    "name:slk_x_preferred":[
        "Vasegerszeg"
    ],
    "name:slv_x_preferred":[
        "Vasegerszeg"
    ],
    "name:vie_x_preferred":[
        "Vasegerszeg"
    ],
    "name:zho_x_preferred":[
        "\u6c83\u8c22\u76d6\u5c14\u585e\u683c"
    ],
    "wof:name":"Vasegerszeg",
    "wof:placetype":"locality"
},
  "geometry": {"coordinates":[16.92324,47.37422],"type":"Point"}
}