{
  "type": "Feature",
  "properties": {
    "gn:admin1_code":"22.0",
    "gn:asciiname":"Magyarszombatfa",
    "gn:country_code":"HU",
    "gn:dem":217,
    "gn:feature_class":"P",
    "gn:feature_code":"PPL",
    "gn:name":"Magyarszombatfa",
    "gn:population":0,
    "gn:timezone":"Europe/Budapest",
    "iso:country":"HU",
    "name:deu_x_preferred":[
        "Magyarszombatfa"
    ],
    "name:epo_x_preferred":[
        "Magyarszombatfa"
    ],
    "name:fas_x_preferred":[
        "\u0645\u0627\u06af\u06cc\u0627\u0631\u0633\u0648\u0645\u0628\u0627\u062a\u0641\u0627"
    ],
    "name:fra_x_preferred":[
        "Magyarszombatfa"
    ],
    "name:hun_x_preferred":[
        "Magyarszombatfa"
    ],
    "name:ita_x_preferred":[
        "Magyarszombatfa"
    ],
    "name:msa_x_preferred":[
        "Magyarszombatfa"
    ],
    "name:nld_x_preferred":[
        "Magyarszombatfa"
    ],
    "name:ron_x_preferred":[
        "Magyarszombatfa"
    ],
    "name:slk_x_preferred":[
        "Magyarszombatfa"
    ],
    "name:slv_x_preferred":[
        "Sobo\u0161ka ves"
    ],
    "name:und_x_variant":[
        "G\u00f6d\u00f6rh\u00e1za"
    ],
    "name:vie_x_preferred":[
        "Magyarszombatfa"
    ],
    "name:zho_x_preferred":[
        "\u6bdb\u7126\u5c14\u6d2a\u9c8d\u7279\u798f"
    ],
    "wof:name":"Magyarszombatfa",
    "wof:placetype":"locality"
},
  "geometry": {"coordinates":[16.34249,46.7603],"type":"Point"}
}