{
  "type": "Feature",
  "properties": {
    "gn:admin1_code":"22.0",
    "gn:asciiname":"Magyarszombatfa",
    "gn:country_code":"HU",
    "gn:dem":217,
    "gn:feature_class":"P",
    "gn:feature_code":"PPL",
    "gn:name":"Magyarszombatfa",
    "gn:population":0,
    "gn:timezone":"Europe/Budapest",
    "iso:country":"HU",
    "name:und_x_variant":[
        "G\u00f6d\u00f6rh\u00e1za",
        "Magyarszombatfa"
    ],
    "wof:name":"Magyarszombatfa",
    "wof:placetype":"locality"
},
  "geometry": {"coordinates":[16.34249,46.7603],"type":"Point"}
}