{
  "type": "Feature",
  "properties": {
    "gn:admin1_code":"24.0",
    "gn:asciiname":"Fenyvesmajor",
    "gn:country_code":"HU",
    "gn:dem":112,
    "gn:feature_class":"P",
    "gn:feature_code":"PPL",
    "gn:name":"Fenyvesmajor",
    "gn:population":0,
    "gn:timezone":"Europe/Budapest",
    "iso:country":"HU",
    "wof:name":"Fenyvesmajor",
    "wof:placetype":"locality"
},
  "geometry": {"coordinates":[17.18754,46.61675],"type":"Point"}
}