{
  "type": "Feature",
  "properties": {
    "gn:admin1_code":"17.0",
    "gn:asciiname":"Devenyitanya",
    "gn:country_code":"HU",
    "gn:dem":140,
    "gn:feature_class":"P",
    "gn:feature_code":"PPL",
    "gn:name":"D\u00e9v\u00e9nyitanya",
    "gn:population":0,
    "gn:timezone":"Europe/Budapest",
    "iso:country":"HU",
    "wof:name":"Devenyitanya",
    "wof:placetype":"locality"
},
  "geometry": {"coordinates":[17.45,46.15],"type":"Point"}
}