{
  "type": "Feature",
  "properties": {
    "gn:admin1_code":"18.0",
    "gn:asciiname":"Fulposdaroc",
    "gn:country_code":"HU",
    "gn:dem":115,
    "gn:feature_class":"P",
    "gn:feature_code":"PPL",
    "gn:name":"F\u00fclp\u00f6sdar\u00f3c",
    "gn:population":0,
    "gn:timezone":"Europe/Budapest",
    "iso:country":"HU",
    "name:deu_x_preferred":[
        "F\u00fclp\u00f6sdar\u00f3c"
    ],
    "name:epo_x_preferred":[
        "F\u00fclp\u00f6sdar\u00f3c"
    ],
    "name:fra_x_preferred":[
        "F\u00fclp\u00f6sdar\u00f3c"
    ],
    "name:hun_x_preferred":[
        "F\u00fclp\u00f6sdar\u00f3c"
    ],
    "name:ita_x_preferred":[
        "F\u00fclp\u00f6sdar\u00f3c"
    ],
    "name:msa_x_preferred":[
        "F\u00fclp\u00f6sdar\u00f3c"
    ],
    "name:nld_x_preferred":[
        "F\u00fclp\u00f6sdar\u00f3c"
    ],
    "name:ron_x_preferred":[
        "F\u00fclp\u00f6sdar\u00f3c"
    ],
    "name:slk_x_preferred":[
        "F\u00fclp\u00f6sdar\u00f3c"
    ],
    "name:slv_x_preferred":[
        "F\u00fclp\u00f6sdar\u00f3c"
    ],
    "name:und_x_variant":[
        "F\u00fclp\u00f6sdar\u00f3c"
    ],
    "name:vie_x_preferred":[
        "F\u00fclp\u00f6sdar\u00f3c"
    ],
    "name:zho_x_preferred":[
        "\u83f2\u5c14\u73c0\u4ec0\u9053\u7f57\u8328"
    ],
    "wof:name":"Fulposdaroc",
    "wof:placetype":"locality"
},
  "geometry": {"coordinates":[22.4799,47.9361],"type":"Point"}
}