{
  "type": "Feature",
  "properties": {
    "gn:gn_country":"HU",
    "gn:gn_fcode":"PPL",
    "gn:gn_pop":15874,
    "gn:population":15874,
    "iso:country":"HU",
    "name:ceb_x_preferred":[
        "G\u00f6d"
    ],
    "name:ces_x_preferred":[
        "G\u00f6d"
    ],
    "name:cym_x_preferred":[
        "G\u00f6d"
    ],
    "name:deu_x_preferred":[
        "G\u00f6d"
    ],
    "name:eng_x_preferred":[
        "G\u00f6d"
    ],
    "name:epo_x_preferred":[
        "G\u00f6d"
    ],
    "name:est_x_preferred":[
        "G\u00f6d"
    ],
    "name:fra_x_preferred":[
        "G\u00f6d"
    ],
    "name:hun_x_preferred":[
        "G\u00f6d"
    ],
    "name:ita_x_preferred":[
        "G\u00f6d"
    ],
    "name:msa_x_preferred":[
        "G\u00f6d"
    ],
    "name:nan_x_preferred":[
        "G\u00f6d"
    ],
    "name:nld_x_preferred":[
        "G\u00f6d"
    ],
    "name:pol_x_preferred":[
        "G\u00f6d"
    ],
    "name:ron_x_preferred":[
        "G\u00f6d"
    ],
    "name:rup_x_preferred":[
        "G\u00f6d"
    ],
    "name:rus_x_preferred":[
        "\u0413\u0451\u0434"
    ],
    "name:sco_x_preferred":[
        "G\u00f6d"
    ],
    "name:slk_x_preferred":[
        "G\u00f6d"
    ],
    "name:slv_x_preferred":[
        "G\u00f6d"
    ],
    "name:spa_x_preferred":[
        "G\u00f6d"
    ],
    "name:srp_x_preferred":[
        "\u0413\u0435\u0434"
    ],
    "name:swe_x_preferred":[
        "G\u00f6d"
    ],
    "name:unk_x_variant":[
        "Als\u00f3g\u00f6d"
    ],
    "name:vie_x_preferred":[
        "G\u00f6d"
    ],
    "name:zho_x_preferred":[
        "\u683c\u5fb7"
    ],
    "qs_pg:aaroncc":"HU",
    "qs_pg:gn_country":"HU",
    "qs_pg:gn_fcode":"PPL",
    "qs_pg:gn_pop":15874,
    "qs_pg:name":"Fels\u0151g\u00f6d",
    "qs_pg:name_adm0":"Magyarorsz\u00e1g",
    "qs_pg:name_adm1":"Pest",
    "qs_pg:photos":335,
    "qs_pg:photos_1k":68,
    "qs_pg:photos_9k":1,
    "qs_pg:photos_9r":5,
    "qs_pg:photos_all":335,
    "qs_pg:photos_sr":5,
    "qs_pg:pop_sr":6,
    "qs_pg:qs_pg_placetype":"locality",
    "qs_pg:qs_pg_placetype_gp":"Town",
    "qs_pg:woe_adm0":23424844,
    "woe:adm0_id":23424844,
    "woe:name_adm0":"Magyarorsz\u00e1g",
    "woe:name_adm1":"Pest",
    "woe:placetype":"Town",
    "wof:name":"Fels\u0151g\u00f6d",
    "wof:placetype":"locality",
    "wof:population":15874
},
  "geometry": {"coordinates":[19.13417,47.68324],"type":"Point"}
}