{
  "type": "Feature",
  "properties": {
    "gn:admin1_code":"17.0",
    "gn:asciiname":"Csakany",
    "gn:country_code":"HU",
    "gn:dem":126,
    "gn:feature_class":"P",
    "gn:feature_code":"PPL",
    "gn:name":"Cs\u00e1k\u00e1ny",
    "gn:population":0,
    "gn:timezone":"Europe/Budapest",
    "iso:country":"HU",
    "name:und_x_variant":[
        "Cs\u00e1k\u00e1ny"
    ],
    "wof:name":"Csakany",
    "wof:placetype":"locality"
},
  "geometry": {"coordinates":[17.27234,46.53872],"type":"Point"}
}