{
  "type": "Feature",
  "properties": {
    "gn:admin1_code":"17.0",
    "gn:asciiname":"Nemesded",
    "gn:country_code":"HU",
    "gn:dem":152,
    "gn:feature_class":"P",
    "gn:feature_code":"PPL",
    "gn:name":"Nemesd\u00e9d",
    "gn:population":0,
    "gn:timezone":"Europe/Budapest",
    "iso:country":"HU",
    "name:und_x_variant":[
        "Nemesd\u00e9d"
    ],
    "wof:name":"Nemesded",
    "wof:placetype":"locality"
},
  "geometry": {"coordinates":[17.24745,46.4331],"type":"Point"}
}