{
  "type": "Feature",
  "properties": {
    "gn:admin1_code":"17.0",
    "gn:asciiname":"Nemesded",
    "gn:country_code":"HU",
    "gn:dem":152,
    "gn:feature_class":"P",
    "gn:feature_code":"PPL",
    "gn:name":"Nemesd\u00e9d",
    "gn:population":0,
    "gn:timezone":"Europe/Budapest",
    "iso:country":"HU",
    "name:epo_x_preferred":[
        "Nemesd\u00e9d"
    ],
    "name:fas_x_preferred":[
        "\u0646\u0645\u0634\u062f\u062f"
    ],
    "name:fra_x_preferred":[
        "Nemesd\u00e9d"
    ],
    "name:hun_x_preferred":[
        "Nemesd\u00e9d"
    ],
    "name:ita_x_preferred":[
        "Nemesd\u00e9d"
    ],
    "name:msa_x_preferred":[
        "Nemesd\u00e9d"
    ],
    "name:nld_x_preferred":[
        "Nemesd\u00e9d"
    ],
    "name:ron_x_preferred":[
        "Nemesd\u00e9d"
    ],
    "name:slk_x_preferred":[
        "Nemesd\u00e9d"
    ],
    "name:slv_x_preferred":[
        "Nemesd\u00e9d"
    ],
    "name:und_x_variant":[
        "Nemesd\u00e9d"
    ],
    "name:vie_x_preferred":[
        "Nemesd\u00e9d"
    ],
    "name:zho_x_preferred":[
        "\u5948\u8fc8\u4ec0\u4ee3\u5fb7"
    ],
    "wof:name":"Nemesded",
    "wof:placetype":"locality"
},
  "geometry": {"coordinates":[17.24745,46.4331],"type":"Point"}
}