{
  "type": "Feature",
  "properties": {
    "gn:admin1_code":"8.0",
    "gn:asciiname":"Kajtori Tanyak",
    "gn:country_code":"HU",
    "gn:dem":107,
    "gn:feature_class":"P",
    "gn:feature_code":"PPL",
    "gn:name":"Kajtori Tany\u00e1k",
    "gn:population":0,
    "gn:timezone":"Europe/Budapest",
    "iso:country":"HU",
    "wof:name":"Kajtori Tanyak",
    "wof:placetype":"locality"
},
  "geometry": {"coordinates":[18.51667,47.03333],"type":"Point"}
}