{
  "type": "Feature",
  "properties": {
    "gn:admin1_code":"24.0",
    "gn:asciiname":"Varfolde",
    "gn:country_code":"HU",
    "gn:dem":194,
    "gn:feature_class":"P",
    "gn:feature_code":"PPL",
    "gn:name":"V\u00e1rf\u00f6lde",
    "gn:population":0,
    "gn:timezone":"Europe/Budapest",
    "iso:country":"HU",
    "name:und_x_variant":[
        "V\u00e1rf\u00f6lde"
    ],
    "wof:name":"Varfolde",
    "wof:placetype":"locality"
},
  "geometry": {"coordinates":[16.76106,46.55839],"type":"Point"}
}