{
  "type": "Feature",
  "properties": {
    "gn:admin1_code":"24.0",
    "gn:asciiname":"Varfolde",
    "gn:country_code":"HU",
    "gn:dem":194,
    "gn:feature_class":"P",
    "gn:feature_code":"PPL",
    "gn:name":"V\u00e1rf\u00f6lde",
    "gn:population":0,
    "gn:timezone":"Europe/Budapest",
    "iso:country":"HU",
    "name:epo_x_preferred":[
        "V\u00e1rf\u00f6lde"
    ],
    "name:fas_x_preferred":[
        "\u0648\u0627\u0631\u0641\u0648\u0644\u062f\u0647"
    ],
    "name:fra_x_preferred":[
        "V\u00e1rf\u00f6lde"
    ],
    "name:hun_x_preferred":[
        "V\u00e1rf\u00f6lde"
    ],
    "name:ita_x_preferred":[
        "V\u00e1rf\u00f6lde"
    ],
    "name:msa_x_preferred":[
        "V\u00e1rf\u00f6lde"
    ],
    "name:nld_x_preferred":[
        "V\u00e1rf\u00f6lde"
    ],
    "name:ron_x_preferred":[
        "V\u00e1rf\u00f6lde"
    ],
    "name:slk_x_preferred":[
        "V\u00e1rf\u00f6lde"
    ],
    "name:slv_x_preferred":[
        "V\u00e1rf\u00f6lde"
    ],
    "name:vie_x_preferred":[
        "V\u00e1rf\u00f6lde"
    ],
    "name:zho_x_preferred":[
        "\u74e6\u5c14\u5f17\u5c14\u4ee3"
    ],
    "wof:name":"Varfolde",
    "wof:placetype":"locality"
},
  "geometry": {"coordinates":[16.76106,46.55839],"type":"Point"}
}