{
  "type": "Feature",
  "properties": {
    "gn:admin1_code":"18.0",
    "gn:asciiname":"Csipkesszegtanya",
    "gn:country_code":"HU",
    "gn:dem":109,
    "gn:feature_class":"P",
    "gn:feature_code":"PPL",
    "gn:name":"Csipk\u00e9sszegtanya",
    "gn:population":0,
    "gn:timezone":"Europe/Budapest",
    "iso:country":"HU",
    "wof:name":"Csipkesszegtanya",
    "wof:placetype":"locality"
},
  "geometry": {"coordinates":[22.46667,48.16667],"type":"Point"}
}