{
  "type": "Feature",
  "properties": {
    "gn:admin1_code":"23.0",
    "gn:asciiname":"Gic",
    "gn:country_code":"HU",
    "gn:dem":162,
    "gn:feature_class":"P",
    "gn:feature_code":"PPL",
    "gn:name":"Gic",
    "gn:population":0,
    "gn:timezone":"Europe/Budapest",
    "iso:country":"HU",
    "name:ces_x_preferred":[
        "Gic"
    ],
    "name:epo_x_preferred":[
        "Gic"
    ],
    "name:fas_x_preferred":[
        "\u06af\u06cc\u062a\u0633"
    ],
    "name:fra_x_preferred":[
        "Gic"
    ],
    "name:hun_x_preferred":[
        "Gic"
    ],
    "name:ita_x_preferred":[
        "Gic"
    ],
    "name:msa_x_preferred":[
        "Gic"
    ],
    "name:nld_x_preferred":[
        "Gic"
    ],
    "name:ron_x_preferred":[
        "Gic"
    ],
    "name:slk_x_preferred":[
        "Gic"
    ],
    "name:slv_x_preferred":[
        "Gic"
    ],
    "name:vie_x_preferred":[
        "Gic"
    ],
    "wof:name":"Gic",
    "wof:placetype":"locality"
},
  "geometry": {"coordinates":[17.75245,47.43341],"type":"Point"}
}