{
  "type": "Feature",
  "properties": {
    "gn:admin1_code":"9.0",
    "gn:asciiname":"Mosonszentmiklosi Tanyak",
    "gn:country_code":"HU",
    "gn:dem":115,
    "gn:feature_class":"P",
    "gn:feature_code":"PPL",
    "gn:name":"Mosonszentmikl\u00f3si Tany\u00e1k",
    "gn:population":0,
    "gn:timezone":"Europe/Budapest",
    "iso:country":"HU",
    "wof:name":"Mosonszentmiklosi Tanyak",
    "wof:placetype":"locality"
},
  "geometry": {"coordinates":[17.4258,47.7282],"type":"Point"}
}