{
  "type": "Feature",
  "properties": {
    "gn:admin1_code":"23.0",
    "gn:asciiname":"Retimalom",
    "gn:country_code":"HU",
    "gn:dem":110,
    "gn:feature_class":"P",
    "gn:feature_code":"PPL",
    "gn:name":"R\u00e9timalom",
    "gn:population":0,
    "gn:timezone":"Europe/Budapest",
    "iso:country":"HU",
    "wof:name":"Retimalom",
    "wof:placetype":"locality"
},
  "geometry": {"coordinates":[17.96667,46.98333],"type":"Point"}
}