{
  "type": "Feature",
  "properties": {
    "gn:admin1_code":"16.0",
    "gn:asciiname":"Buboshalomdulo",
    "gn:country_code":"HU",
    "gn:dem":90,
    "gn:feature_class":"P",
    "gn:feature_code":"PPL",
    "gn:name":"B\u00faboshalomd\u0171l\u0151",
    "gn:population":0,
    "gn:timezone":"Europe/Budapest",
    "iso:country":"HU",
    "wof:name":"Buboshalomdulo",
    "wof:placetype":"locality"
},
  "geometry": {"coordinates":[19.95,47.13333],"type":"Point"}
}