{
  "type": "Feature",
  "properties": {
    "gn:admin1_code":"18.0",
    "gn:asciiname":"Besenyod",
    "gn:country_code":"HU",
    "gn:dem":126,
    "gn:feature_class":"P",
    "gn:feature_code":"PPL",
    "gn:name":"Beseny\u0151d",
    "gn:population":0,
    "gn:timezone":"Europe/Budapest",
    "iso:country":"HU",
    "name:epo_x_preferred":[
        "Beseny\u0151d"
    ],
    "name:fas_x_preferred":[
        "\u0628\u0634\u0646\u06cc\u0648\u062f"
    ],
    "name:fra_x_preferred":[
        "Beseny\u0151d"
    ],
    "name:hun_x_preferred":[
        "Beseny\u0151d"
    ],
    "name:ita_x_preferred":[
        "Beseny\u0151d"
    ],
    "name:msa_x_preferred":[
        "Beseny\u0151d"
    ],
    "name:nld_x_preferred":[
        "Beseny\u0151d"
    ],
    "name:ron_x_preferred":[
        "Beseny\u0151d"
    ],
    "name:slk_x_preferred":[
        "Beseny\u0151d"
    ],
    "name:slv_x_preferred":[
        "Beseny\u0151d"
    ],
    "name:swe_x_preferred":[
        "Beseny\u0151d"
    ],
    "name:und_x_variant":[
        "Beseny\u0151d"
    ],
    "name:vie_x_preferred":[
        "Beseny\u0151d"
    ],
    "name:zho_x_preferred":[
        "\u62dc\u8c22\u6d85\u5fb7"
    ],
    "wof:name":"Besenyod",
    "wof:placetype":"locality"
},
  "geometry": {"coordinates":[22.01649,47.9688],"type":"Point"}
}