{
  "type": "Feature",
  "properties": {
    "gn:gn_country":"HU",
    "gn:gn_fcode":"PPLX",
    "gn:gn_pop":0,
    "iso:country":"HU",
    "name:unk_x_variant":[
        "Ny\u00e1m\u00e1nd"
    ],
    "qs_pg:aaroncc":"HU",
    "qs_pg:gn_country":"HU",
    "qs_pg:gn_fcode":"PPLX",
    "qs_pg:gn_pop":0,
    "qs_pg:name":"Ny\u00e1m\u00e1ndpuszta",
    "qs_pg:name_adm0":"Magyarorsz\u00e1g",
    "qs_pg:name_adm1":"Szeksz\u00e1rd",
    "qs_pg:photos":9,
    "qs_pg:photos_1k":2,
    "qs_pg:photos_9k":1,
    "qs_pg:photos_9r":1,
    "qs_pg:photos_all":9,
    "qs_pg:photos_sr":1,
    "qs_pg:pop_sr":0,
    "qs_pg:qs_pg_placetype":"neighbourhood",
    "qs_pg:qs_pg_placetype_gp":"Suburb",
    "qs_pg:woe_adm0":23424844,
    "woe:adm0_id":23424844,
    "woe:name_adm0":"Magyarorsz\u00e1g",
    "woe:name_adm1":"Szeksz\u00e1rd",
    "woe:placetype":"Suburb",
    "wof:name":"Ny\u00e1m\u00e1ndpuszta",
    "wof:placetype":"neighbourhood"
},
  "geometry": {"coordinates":[18.74285,46.35095],"type":"Point"}
}