{
  "type": "Feature",
  "properties": {
    "gn:admin1_code":"9.0",
    "gn:asciiname":"Zsebehaza",
    "gn:country_code":"HU",
    "gn:dem":124,
    "gn:feature_class":"P",
    "gn:feature_code":"PPL",
    "gn:name":"Zsebeh\u00e1za",
    "gn:population":0,
    "gn:timezone":"Europe/Budapest",
    "iso:country":"HU",
    "name:epo_x_preferred":[
        "Zsebeh\u00e1za"
    ],
    "name:fas_x_preferred":[
        "\u0698\u0628\u0647\u0627\u0632\u0627"
    ],
    "name:fra_x_preferred":[
        "Zsebeh\u00e1za"
    ],
    "name:hun_x_preferred":[
        "Zsebeh\u00e1za"
    ],
    "name:ita_x_preferred":[
        "Zsebeh\u00e1za"
    ],
    "name:msa_x_preferred":[
        "Zsebeh\u00e1za"
    ],
    "name:nld_x_preferred":[
        "Zsebeh\u00e1za"
    ],
    "name:pol_x_preferred":[
        "Zsebeh\u00e1za"
    ],
    "name:ron_x_preferred":[
        "Zsebeh\u00e1za"
    ],
    "name:slk_x_preferred":[
        "Zsebeh\u00e1za"
    ],
    "name:slv_x_preferred":[
        "Zsebeh\u00e1za"
    ],
    "name:spa_x_preferred":[
        "Zsebeh\u00e1za"
    ],
    "name:vie_x_preferred":[
        "Zsebeh\u00e1za"
    ],
    "name:zho_x_preferred":[
        "\u70ed\u62dc\u54c8\u4f50"
    ],
    "wof:name":"Zsebehaza",
    "wof:placetype":"locality"
},
  "geometry": {"coordinates":[17.19111,47.51046],"type":"Point"}
}