{
  "type": "Feature",
  "properties": {
    "iso:country":"HU",
    "name:hun_x_preferred":[
        "\u00dajlak"
    ],
    "wof:name":"Ujlak",
    "wof:placetype":"neighbourhood"
},
  "geometry": {"coordinates":[19.03717241360619,47.52790892937952],"type":"Point"}
}