{
  "type": "Feature",
  "properties": {
    "gn:admin1_code":"18.0",
    "gn:asciiname":"Kistanya",
    "gn:country_code":"HU",
    "gn:dem":94,
    "gn:feature_class":"P",
    "gn:feature_code":"PPL",
    "gn:name":"Kistanya",
    "gn:population":0,
    "gn:timezone":"Europe/Budapest",
    "iso:country":"HU",
    "wof:name":"Kistanya",
    "wof:placetype":"locality"
},
  "geometry": {"coordinates":[21.85,48.11667],"type":"Point"}
}