{
  "type": "Feature",
  "properties": {
    "iso:country":"HU",
    "name:eng_x_preferred":[
        "Kecsk\u00e9d Airport"
    ],
    "name:eng_x_variant":[
        "LHKD"
    ],
    "name:hun_x_preferred":[
        "Kecsk\u00e9di rep\u00fcl\u0151t\u00e9r"
    ],
    "name:jpn_x_preferred":[
        "\u30b1\u30c1\u30b1\u30fc\u30c9\u7a7a\u6e2f"
    ],
    "name:ron_x_preferred":[
        "Aeroportul Kecsk\u00e9d"
    ],
    "oa:elevation_ft":"570",
    "oa:type":"small_airport",
    "woe:hierarchy":{
        "country_id":23424844,
        "county_id":12595625,
        "planet_id":1,
        "state_id":12577921
    },
    "wof:name":"Kecsked Repuloter",
    "wof:placetype":"campus"
},
  "geometry": {"coordinates":[18.323333,47.5175],"type":"Point"}
}