{
  "type": "Feature",
  "properties": {
    "gn:admin1_code":"2.0",
    "gn:asciiname":"Kacsota",
    "gn:country_code":"HU",
    "gn:dem":116,
    "gn:feature_class":"P",
    "gn:feature_code":"PPL",
    "gn:name":"Kacs\u00f3ta",
    "gn:population":0,
    "gn:timezone":"Europe/Budapest",
    "iso:country":"HU",
    "name:epo_x_preferred":[
        "Kacs\u00f3ta"
    ],
    "name:fas_x_preferred":[
        "\u06a9\u0627\u0686\u0648\u062a\u0627"
    ],
    "name:fra_x_preferred":[
        "Kacs\u00f3ta"
    ],
    "name:hrv_x_preferred":[
        "Kacs\u00f3ta"
    ],
    "name:hun_x_preferred":[
        "Kacs\u00f3ta"
    ],
    "name:ita_x_preferred":[
        "Kacs\u00f3ta"
    ],
    "name:msa_x_preferred":[
        "Kacs\u00f3ta"
    ],
    "name:nld_x_preferred":[
        "Kacs\u00f3ta"
    ],
    "name:pol_x_preferred":[
        "Kacs\u00f3ta"
    ],
    "name:ron_x_preferred":[
        "Kacs\u00f3ta"
    ],
    "name:slk_x_preferred":[
        "Kacs\u00f3ta"
    ],
    "name:slv_x_preferred":[
        "Kacs\u00f3ta"
    ],
    "name:vie_x_preferred":[
        "Kacs\u00f3ta"
    ],
    "name:zho_x_preferred":[
        "\u8003\u4e54\u9676"
    ],
    "wof:name":"Kacsota",
    "wof:placetype":"locality"
},
  "geometry": {"coordinates":[17.95655,46.03881],"type":"Point"}
}