{
  "type": "Feature",
  "properties": {
    "gn:admin1_code":"18.0",
    "gn:asciiname":"Matyus",
    "gn:country_code":"HU",
    "gn:dem":105,
    "gn:feature_class":"P",
    "gn:feature_code":"PPL",
    "gn:name":"M\u00e1tyus",
    "gn:population":0,
    "gn:timezone":"Europe/Budapest",
    "iso:country":"HU",
    "name:deu_x_preferred":[
        "M\u00e1tyus"
    ],
    "name:epo_x_preferred":[
        "M\u00e1tyus"
    ],
    "name:fas_x_preferred":[
        "\u0645\u0627\u06a9\u0648\u0634"
    ],
    "name:fra_x_preferred":[
        "M\u00e1tyus"
    ],
    "name:hun_x_preferred":[
        "M\u00e1tyus"
    ],
    "name:ita_x_preferred":[
        "M\u00e1tyus"
    ],
    "name:msa_x_preferred":[
        "M\u00e1tyus"
    ],
    "name:nld_x_preferred":[
        "M\u00e1tyus"
    ],
    "name:ron_x_preferred":[
        "M\u00e1tyus"
    ],
    "name:slk_x_preferred":[
        "M\u00e1tyus"
    ],
    "name:slv_x_preferred":[
        "M\u00e1tyus"
    ],
    "name:vie_x_preferred":[
        "M\u00e1tyus"
    ],
    "name:zho_x_preferred":[
        "\u9a6c\u4e45\u4ec0"
    ],
    "wof:name":"Matyus",
    "wof:placetype":"locality"
},
  "geometry": {"coordinates":[22.2783,48.28303],"type":"Point"}
}