{
  "type": "Feature",
  "properties": {
    "gn:admin1_code":"23.0",
    "gn:asciiname":"Cirfuszmajor",
    "gn:cc2":"HU",
    "gn:country_code":"HU",
    "gn:dem":159,
    "gn:feature_class":"P",
    "gn:feature_code":"PPL",
    "gn:name":"Cirfuszmajor",
    "gn:population":0,
    "gn:timezone":"Europe/Budapest",
    "iso:country":"HU",
    "name:und_x_variant":[
        "Czirfuszmajor",
        "Cirfuszmajor"
    ],
    "wof:name":"Cirfuszmajor",
    "wof:placetype":"locality"
},
  "geometry": {"coordinates":[17.56667,47.35],"type":"Point"}
}