{
  "type": "Feature",
  "properties": {
    "gn:admin1_code":"10.0",
    "gn:asciiname":"Szlavitanya",
    "gn:country_code":"HU",
    "gn:dem":116,
    "gn:feature_class":"P",
    "gn:feature_code":"PPL",
    "gn:name":"Szl\u00e1vitanya",
    "gn:population":0,
    "gn:timezone":"Europe/Budapest",
    "iso:country":"HU",
    "wof:name":"Szlavitanya",
    "wof:placetype":"locality"
},
  "geometry": {"coordinates":[21.98333,47.41667],"type":"Point"}
}