{
  "type": "Feature",
  "properties": {
    "gn:admin1_code":"24.0",
    "gn:asciiname":"Zalaigrice",
    "gn:country_code":"HU",
    "gn:dem":166,
    "gn:feature_class":"P",
    "gn:feature_code":"PPL",
    "gn:name":"Zalaigrice",
    "gn:population":0,
    "gn:timezone":"Europe/Budapest",
    "iso:country":"HU",
    "wof:name":"Zalaigrice",
    "wof:placetype":"locality"
},
  "geometry": {"coordinates":[17.00992,46.74724000000001],"type":"Point"}
}