{
  "type": "Feature",
  "properties": {
    "gn:admin1_code":"24.0",
    "gn:asciiname":"Zalaigrice",
    "gn:country_code":"HU",
    "gn:dem":166,
    "gn:feature_class":"P",
    "gn:feature_code":"PPL",
    "gn:name":"Zalaigrice",
    "gn:population":0,
    "gn:timezone":"Europe/Budapest",
    "iso:country":"HU",
    "name:epo_x_preferred":[
        "Zalaigrice"
    ],
    "name:fas_x_preferred":[
        "\u0632\u0627\u0644\u0627\u06cc\u06af\u0631\u06cc\u062a\u0633\u0647"
    ],
    "name:fra_x_preferred":[
        "Zalaigrice"
    ],
    "name:hun_x_preferred":[
        "Zalaigrice"
    ],
    "name:ita_x_preferred":[
        "Zalaigrice"
    ],
    "name:msa_x_preferred":[
        "Zalaigrice"
    ],
    "name:nld_x_preferred":[
        "Zalaigrice"
    ],
    "name:ron_x_preferred":[
        "Zalaigrice"
    ],
    "name:slk_x_preferred":[
        "Zalaigrice"
    ],
    "name:slv_x_preferred":[
        "Zalaigrice"
    ],
    "name:vie_x_preferred":[
        "Zalaigrice"
    ],
    "name:zho_x_preferred":[
        "\u4f50\u6d1b\u4f0a\u683c\u91cc\u91c7"
    ],
    "wof:name":"Zalaigrice",
    "wof:placetype":"locality"
},
  "geometry": {"coordinates":[17.00992,46.74724000000001],"type":"Point"}
}