{
  "type": "Feature",
  "properties": {
    "gn:admin1_code":"18.0",
    "gn:asciiname":"Tisztaberek",
    "gn:country_code":"HU",
    "gn:dem":116,
    "gn:feature_class":"P",
    "gn:feature_code":"PPL",
    "gn:name":"Tisztaberek",
    "gn:population":0,
    "gn:timezone":"Europe/Budapest",
    "iso:country":"HU",
    "wof:name":"Tisztaberek",
    "wof:placetype":"locality"
},
  "geometry": {"coordinates":[22.79109,47.95501],"type":"Point"}
}