{
  "type": "Feature",
  "properties": {
    "gn:admin1_code":"18.0",
    "gn:asciiname":"Tisztaberek",
    "gn:country_code":"HU",
    "gn:dem":116,
    "gn:feature_class":"P",
    "gn:feature_code":"PPL",
    "gn:name":"Tisztaberek",
    "gn:population":0,
    "gn:timezone":"Europe/Budapest",
    "iso:country":"HU",
    "name:epo_x_preferred":[
        "Tisztaberek"
    ],
    "name:fas_x_preferred":[
        "\u062a\u06cc\u0633\u062a\u0627\u0628\u0631\u06a9"
    ],
    "name:fra_x_preferred":[
        "Tisztaberek"
    ],
    "name:hun_x_preferred":[
        "Tisztaberek"
    ],
    "name:ita_x_preferred":[
        "Tisztaberek"
    ],
    "name:msa_x_preferred":[
        "Tisztaberek"
    ],
    "name:nld_x_preferred":[
        "Tisztaberek"
    ],
    "name:ron_x_preferred":[
        "Tisztaberek"
    ],
    "name:slk_x_preferred":[
        "Tisztaberek"
    ],
    "name:slv_x_preferred":[
        "Tisztaberek"
    ],
    "name:vie_x_preferred":[
        "Tisztaberek"
    ],
    "name:zho_x_preferred":[
        "\u8482\u65af\u9676\u62dc\u8d56\u514b"
    ],
    "wof:name":"Tisztaberek",
    "wof:placetype":"locality"
},
  "geometry": {"coordinates":[22.79109,47.95501],"type":"Point"}
}