{
  "type": "Feature",
  "properties": {
    "gn:admin1_code":"23.0",
    "gn:asciiname":"Hetyefo",
    "gn:country_code":"HU",
    "gn:dem":135,
    "gn:feature_class":"P",
    "gn:feature_code":"PPL",
    "gn:name":"Hetyef\u0151",
    "gn:population":0,
    "gn:timezone":"Europe/Budapest",
    "iso:country":"HU",
    "name:epo_x_preferred":[
        "Hetyef\u0151"
    ],
    "name:fas_x_preferred":[
        "\u0647\u06a9\u0641\u0648"
    ],
    "name:fra_x_preferred":[
        "Hetyef\u0151"
    ],
    "name:hun_x_preferred":[
        "Hetyef\u0151"
    ],
    "name:ita_x_preferred":[
        "Hetyef\u0151"
    ],
    "name:msa_x_preferred":[
        "Hetyef\u0151"
    ],
    "name:nld_x_preferred":[
        "Hetyef\u0151"
    ],
    "name:ron_x_preferred":[
        "Hetyef\u0151"
    ],
    "name:slk_x_preferred":[
        "Hetyef\u0151"
    ],
    "name:slv_x_preferred":[
        "Hetyef\u0151"
    ],
    "name:und_x_variant":[
        "Hetyef\u0151"
    ],
    "name:vie_x_preferred":[
        "Hetyef\u0151"
    ],
    "name:zho_x_preferred":[
        "\u6d77\u6770\u5f17"
    ],
    "wof:name":"Hetyefo",
    "wof:placetype":"locality"
},
  "geometry": {"coordinates":[17.16056,47.0464],"type":"Point"}
}