{
  "type": "Feature",
  "properties": {
    "gn:admin1_code":"2.0",
    "gn:asciiname":"Szava",
    "gn:country_code":"HU",
    "gn:dem":127,
    "gn:feature_class":"P",
    "gn:feature_code":"PPL",
    "gn:name":"Szava",
    "gn:population":0,
    "gn:timezone":"Europe/Budapest",
    "iso:country":"HU",
    "wof:name":"Szava",
    "wof:placetype":"locality"
},
  "geometry": {"coordinates":[18.17769,45.90237],"type":"Point"}
}