{
  "type": "Feature",
  "properties": {
    "gn:admin1_code":"2.0",
    "gn:asciiname":"Szava",
    "gn:country_code":"HU",
    "gn:dem":127,
    "gn:feature_class":"P",
    "gn:feature_code":"PPL",
    "gn:name":"Szava",
    "gn:population":0,
    "gn:timezone":"Europe/Budapest",
    "iso:country":"HU",
    "name:deu_x_preferred":[
        "Szava"
    ],
    "name:epo_x_preferred":[
        "Szava"
    ],
    "name:fas_x_preferred":[
        "\u0633\u0627\u0648\u0627"
    ],
    "name:fra_x_preferred":[
        "Szava"
    ],
    "name:hrv_x_preferred":[
        "Szava"
    ],
    "name:hun_x_preferred":[
        "Szava"
    ],
    "name:ita_x_preferred":[
        "Szava"
    ],
    "name:msa_x_preferred":[
        "Szava"
    ],
    "name:nld_x_preferred":[
        "Szava"
    ],
    "name:pol_x_preferred":[
        "Szava"
    ],
    "name:ron_x_preferred":[
        "Szava"
    ],
    "name:slk_x_preferred":[
        "Szava"
    ],
    "name:slv_x_preferred":[
        "Szava"
    ],
    "name:vie_x_preferred":[
        "Szava"
    ],
    "wof:name":"Szava",
    "wof:placetype":"locality"
},
  "geometry": {"coordinates":[18.17769,45.90237],"type":"Point"}
}