{
  "type": "Feature",
  "properties": {
    "gn:admin1_code":"23.0",
    "gn:asciiname":"Bakonyoszlop",
    "gn:country_code":"HU",
    "gn:dem":253,
    "gn:feature_class":"P",
    "gn:feature_code":"PPL",
    "gn:name":"Bakonyoszlop",
    "gn:population":0,
    "gn:timezone":"Europe/Budapest",
    "iso:country":"HU",
    "name:ces_x_preferred":[
        "Bakonyoszlop"
    ],
    "name:epo_x_preferred":[
        "Bakonyoszlop"
    ],
    "name:fas_x_preferred":[
        "\u0628\u0627\u06a9\u0648\u0646\u06cc\u0648\u0633\u0644\u0648\u067e"
    ],
    "name:fra_x_preferred":[
        "Bakonyoszlop"
    ],
    "name:hun_x_preferred":[
        "Bakonyoszlop"
    ],
    "name:ita_x_preferred":[
        "Bakonyoszlop"
    ],
    "name:msa_x_preferred":[
        "Bakonyoszlop"
    ],
    "name:nld_x_preferred":[
        "Bakonyoszlop"
    ],
    "name:ron_x_preferred":[
        "Bakonyoszlop"
    ],
    "name:slk_x_preferred":[
        "Bakonyoszlop"
    ],
    "name:slv_x_preferred":[
        "Bakonyoszlop"
    ],
    "name:vie_x_preferred":[
        "Bakonyoszlop"
    ],
    "name:zho_x_preferred":[
        "\u9c8d\u79d1\u7ebd\u65af\u6d1b\u666e"
    ],
    "wof:name":"Bakonyoszlop",
    "wof:placetype":"locality"
},
  "geometry": {"coordinates":[17.92728,47.34324],"type":"Point"}
}