{
  "type": "Feature",
  "properties": {
    "gn:admin1_code":"23.0",
    "gn:asciiname":"Csatarimalom",
    "gn:country_code":"HU",
    "gn:dem":153,
    "gn:feature_class":"P",
    "gn:feature_code":"PPL",
    "gn:name":"Csat\u00e1rimalom",
    "gn:population":0,
    "gn:timezone":"Europe/Budapest",
    "iso:country":"HU",
    "wof:name":"Csatarimalom",
    "wof:placetype":"locality"
},
  "geometry": {"coordinates":[18.03823,47.11731],"type":"Point"}
}