{
  "type": "Feature",
  "properties": {
    "gn:admin1_code":"18.0",
    "gn:asciiname":"Okorkut",
    "gn:cc2":"HU",
    "gn:country_code":"HU",
    "gn:dem":121,
    "gn:feature_class":"P",
    "gn:feature_code":"PPL",
    "gn:name":"\u00d6k\u00f6rk\u00fat",
    "gn:population":0,
    "gn:timezone":"Europe/Budapest",
    "iso:country":"HU",
    "name:und_x_variant":[
        "\u00d6k\u00f6rf\u00f6ldi Puszta",
        "\u00d6k\u00f6rk\u00fat"
    ],
    "wof:name":"Okorkut",
    "wof:placetype":"locality"
},
  "geometry": {"coordinates":[21.65,47.83333],"type":"Point"}
}