{
  "type": "Feature",
  "properties": {
    "gn:admin1_code":"24.0",
    "gn:asciiname":"Karmacs",
    "gn:country_code":"HU",
    "gn:dem":147,
    "gn:feature_class":"P",
    "gn:feature_code":"PPL",
    "gn:name":"Karmacs",
    "gn:population":0,
    "gn:timezone":"Europe/Budapest",
    "iso:country":"HU",
    "name:epo_x_preferred":[
        "Karmacs"
    ],
    "name:fas_x_preferred":[
        "\u06a9\u0627\u0631\u0645\u0627\u0686"
    ],
    "name:fra_x_preferred":[
        "Karmacs"
    ],
    "name:hun_x_preferred":[
        "Karmacs"
    ],
    "name:ita_x_preferred":[
        "Karmacs"
    ],
    "name:msa_x_preferred":[
        "Karmacs"
    ],
    "name:nld_x_preferred":[
        "Karmacs"
    ],
    "name:ron_x_preferred":[
        "Karmacs"
    ],
    "name:slk_x_preferred":[
        "Karmacs"
    ],
    "name:slv_x_preferred":[
        "Karmacs"
    ],
    "name:und_x_variant":[
        "Hertelendy-major"
    ],
    "name:vie_x_preferred":[
        "Karmacs"
    ],
    "name:zho_x_preferred":[
        "\u8003\u5c14\u6bdb\u5947"
    ],
    "wof:name":"Karmacs",
    "wof:placetype":"locality"
},
  "geometry": {"coordinates":[17.17369,46.83702],"type":"Point"}
}