{
  "type": "Feature",
  "properties": {
    "gn:admin1_code":"18.0",
    "gn:asciiname":"Lehotanya",
    "gn:country_code":"HU",
    "gn:dem":111,
    "gn:feature_class":"P",
    "gn:feature_code":"PPL",
    "gn:name":"Leh\u00f3tanya",
    "gn:population":0,
    "gn:timezone":"Europe/Budapest",
    "iso:country":"HU",
    "wof:name":"Lehotanya",
    "wof:placetype":"locality"
},
  "geometry": {"coordinates":[21.93333,48.01667],"type":"Point"}
}