{
  "type": "Feature",
  "properties": {
    "gn:admin1_code":"18.0",
    "gn:asciiname":"Gemzse",
    "gn:country_code":"HU",
    "gn:dem":116,
    "gn:feature_class":"P",
    "gn:feature_code":"PPL",
    "gn:name":"Gemzse",
    "gn:population":0,
    "gn:timezone":"Europe/Budapest",
    "iso:country":"HU",
    "name:epo_x_preferred":[
        "Gemzse"
    ],
    "name:fas_x_preferred":[
        "\u06af\u0645\u0698\u0647"
    ],
    "name:fra_x_preferred":[
        "Gemzse"
    ],
    "name:hun_x_preferred":[
        "Gemzse"
    ],
    "name:ita_x_preferred":[
        "Gemzse"
    ],
    "name:msa_x_preferred":[
        "Gemzse"
    ],
    "name:nld_x_preferred":[
        "Gemzse"
    ],
    "name:ron_x_preferred":[
        "Gemzse"
    ],
    "name:slk_x_preferred":[
        "Gemzse"
    ],
    "name:slv_x_preferred":[
        "Gemzse"
    ],
    "name:vie_x_preferred":[
        "Gemzse"
    ],
    "name:zho_x_preferred":[
        "\u76d6\u59c6\u70ed"
    ],
    "wof:name":"Gemzse",
    "wof:placetype":"locality"
},
  "geometry": {"coordinates":[22.1947,48.14128],"type":"Point"}
}