{
  "type": "Feature",
  "properties": {
    "gn:admin1_code":"18.0",
    "gn:asciiname":"Gemzse",
    "gn:country_code":"HU",
    "gn:dem":116,
    "gn:feature_class":"P",
    "gn:feature_code":"PPL",
    "gn:name":"Gemzse",
    "gn:population":0,
    "gn:timezone":"Europe/Budapest",
    "iso:country":"HU",
    "wof:name":"Gemzse",
    "wof:placetype":"locality"
},
  "geometry": {"coordinates":[22.1947,48.14128],"type":"Point"}
}