{
  "type": "Feature",
  "properties": {
    "gn:admin1_code":"14.0",
    "gn:asciiname":"Lokostelep",
    "gn:country_code":"HU",
    "gn:dem":170,
    "gn:feature_class":"P",
    "gn:feature_code":"PPL",
    "gn:name":"L\u00f3kostelep",
    "gn:population":0,
    "gn:timezone":"Europe/Budapest",
    "iso:country":"HU",
    "wof:name":"Lokostelep",
    "wof:placetype":"locality"
},
  "geometry": {"coordinates":[19.16667,48.03333],"type":"Point"}
}