{
  "type": "Feature",
  "properties": {
    "gn:admin1_code":"24.0",
    "gn:asciiname":"Potrete",
    "gn:country_code":"HU",
    "gn:dem":148,
    "gn:feature_class":"P",
    "gn:feature_code":"PPL",
    "gn:name":"P\u00f6tr\u00e9te",
    "gn:population":0,
    "gn:timezone":"Europe/Budapest",
    "iso:country":"HU",
    "name:und_x_variant":[
        "P\u00f6tr\u00e9te"
    ],
    "wof:name":"Potrete",
    "wof:placetype":"locality"
},
  "geometry": {"coordinates":[16.95022,46.68004000000001],"type":"Point"}
}