{
  "type": "Feature",
  "properties": {
    "gn:admin1_code":"24.0",
    "gn:asciiname":"Potrete",
    "gn:country_code":"HU",
    "gn:dem":148,
    "gn:feature_class":"P",
    "gn:feature_code":"PPL",
    "gn:name":"P\u00f6tr\u00e9te",
    "gn:population":0,
    "gn:timezone":"Europe/Budapest",
    "iso:country":"HU",
    "name:epo_x_preferred":[
        "P\u00f6tr\u00e9te"
    ],
    "name:fas_x_preferred":[
        "\u067e\u0648\u062a\u0631\u062a\u0647"
    ],
    "name:fra_x_preferred":[
        "P\u00f6tr\u00e9te"
    ],
    "name:hun_x_preferred":[
        "P\u00f6tr\u00e9te"
    ],
    "name:ita_x_preferred":[
        "P\u00f6tr\u00e9te"
    ],
    "name:msa_x_preferred":[
        "P\u00f6tr\u00e9te"
    ],
    "name:nld_x_preferred":[
        "P\u00f6tr\u00e9te"
    ],
    "name:ron_x_preferred":[
        "P\u00f6tr\u00e9te"
    ],
    "name:slk_x_preferred":[
        "P\u00f6tr\u00e9te"
    ],
    "name:slv_x_preferred":[
        "P\u00f6tr\u00e9te"
    ],
    "name:vie_x_preferred":[
        "P\u00f6tr\u00e9te"
    ],
    "name:zho_x_preferred":[
        "\u73c0\u7279\u96f7\u6cf0"
    ],
    "wof:name":"Potrete",
    "wof:placetype":"locality"
},
  "geometry": {"coordinates":[16.95022,46.68004000000001],"type":"Point"}
}