{
  "type": "Feature",
  "properties": {
    "gn:admin1_code":"2.0",
    "gn:asciiname":"Samod",
    "gn:country_code":"HU",
    "gn:dem":96,
    "gn:feature_class":"P",
    "gn:feature_code":"PPL",
    "gn:name":"S\u00e1mod",
    "gn:population":0,
    "gn:timezone":"Europe/Budapest",
    "iso:country":"HU",
    "name:deu_x_preferred":[
        "S\u00e1mod"
    ],
    "name:epo_x_preferred":[
        "S\u00e1mod"
    ],
    "name:fas_x_preferred":[
        "\u0634\u0627\u0645\u0648\u062f"
    ],
    "name:fra_x_preferred":[
        "S\u00e1mod"
    ],
    "name:hrv_x_preferred":[
        "S\u00e1mod"
    ],
    "name:hun_x_preferred":[
        "S\u00e1mod"
    ],
    "name:ita_x_preferred":[
        "S\u00e1mod"
    ],
    "name:msa_x_preferred":[
        "S\u00e1mod"
    ],
    "name:nld_x_preferred":[
        "S\u00e1mod"
    ],
    "name:pol_x_preferred":[
        "S\u00e1mod"
    ],
    "name:ron_x_preferred":[
        "S\u00e1mod"
    ],
    "name:slk_x_preferred":[
        "S\u00e1mod"
    ],
    "name:slv_x_preferred":[
        "S\u00e1mod"
    ],
    "name:vie_x_preferred":[
        "S\u00e1mod"
    ],
    "name:zho_x_preferred":[
        "\u6c99\u83ab\u5fb7"
    ],
    "wof:name":"Samod",
    "wof:placetype":"locality"
},
  "geometry": {"coordinates":[18.0375,45.85444],"type":"Point"}
}