{
  "type": "Feature",
  "properties": {
    "gn:admin1_code":"24.0",
    "gn:asciiname":"Asszonyvar",
    "gn:cc2":"HU",
    "gn:country_code":"HU",
    "gn:dem":174,
    "gn:feature_class":"P",
    "gn:feature_code":"PPL",
    "gn:name":"Asszonyv\u00e1r",
    "gn:population":0,
    "gn:timezone":"Europe/Budapest",
    "iso:country":"HU",
    "name:und_x_variant":[
        "Asszonyv\u00e1risz\u0151ll\u0151",
        "Asszonyv\u00e1risz\u0151l\u0151",
        "Asszonyv\u00e1r"
    ],
    "wof:name":"Asszonyvar",
    "wof:placetype":"locality"
},
  "geometry": {"coordinates":[16.95,46.33333],"type":"Point"}
}