{
  "type": "Feature",
  "properties": {
    "gn:admin1_code":"4.0",
    "gn:asciiname":"Felsogilip",
    "gn:country_code":"HU",
    "gn:dem":102,
    "gn:feature_class":"P",
    "gn:feature_code":"PPL",
    "gn:name":"Fels\u0151gilip",
    "gn:population":0,
    "gn:timezone":"Europe/Budapest",
    "iso:country":"HU",
    "wof:name":"Felsogilip",
    "wof:placetype":"locality"
},
  "geometry": {"coordinates":[21.15,48.15],"type":"Point"}
}