{
  "type": "Feature",
  "properties": {
    "gn:admin1_code":"20.0",
    "gn:asciiname":"Bekas",
    "gn:country_code":"HU",
    "gn:dem":82,
    "gn:feature_class":"P",
    "gn:feature_code":"PPL",
    "gn:name":"B\u00e9k\u00e1s",
    "gn:population":0,
    "gn:timezone":"Europe/Budapest",
    "iso:country":"HU",
    "name:ckb_x_preferred":[
        "\u0628\u06ce\u06a9\u06d5\u0633"
    ],
    "name:deu_x_preferred":[
        "Bekas"
    ],
    "name:rus_x_preferred":[
        "\u0411\u0435\u043a\u0430\u0441"
    ],
    "wof:name":"Bekas",
    "wof:placetype":"locality"
},
  "geometry": {"coordinates":[20.76667,47.25],"type":"Point"}
}