{
  "type": "Feature",
  "properties": {
    "gn:country":"HU",
    "gn:fcode":"PPL",
    "gn:population":0,
    "iso:country":"HU",
    "name:ast_x_preferred":[
        "Somogyfajsz"
    ],
    "name:deu_x_preferred":[
        "Somogyfajsz"
    ],
    "name:eng_x_preferred":[
        "Somogyfajsz"
    ],
    "name:epo_x_preferred":[
        "Somogyfajsz"
    ],
    "name:fra_x_preferred":[
        "Somogyfajsz"
    ],
    "name:gle_x_preferred":[
        "Somogyfajsz"
    ],
    "name:hun_x_preferred":[
        "Somogyfajsz"
    ],
    "name:ita_x_preferred":[
        "Somogyfajsz"
    ],
    "name:lmo_x_preferred":[
        "Somogyfajsz"
    ],
    "name:msa_x_preferred":[
        "Somogyfajsz"
    ],
    "name:nan_x_preferred":[
        "Somogyfajsz"
    ],
    "name:nld_x_preferred":[
        "Somogyfajsz"
    ],
    "name:por_x_preferred":[
        "Somogyfajsz"
    ],
    "name:ron_x_preferred":[
        "Somogyfajsz"
    ],
    "name:slk_x_preferred":[
        "Somogyfajsz"
    ],
    "name:slv_x_preferred":[
        "Somogyfajsz"
    ],
    "name:spa_x_preferred":[
        "Somogyfajsz"
    ],
    "name:vie_x_preferred":[
        "Somogyfajsz"
    ],
    "name:zho_x_preferred":[
        "\u7ecd\u83ab\u5409\u798f\u4f0a\u65af"
    ],
    "qs_pg:aaroncc":"HU",
    "qs_pg:gn_country":"HU",
    "qs_pg:gn_fcode":"PPL",
    "qs_pg:gn_pop":0,
    "qs_pg:name":"Somogyfajsz",
    "qs_pg:name_adm0":"Magyarorsz\u00e1g",
    "qs_pg:name_adm1":"Somogy",
    "qs_pg:photos":17,
    "qs_pg:photos_1k":3,
    "qs_pg:photos_9k":1,
    "qs_pg:photos_9r":1,
    "qs_pg:photos_all":17,
    "qs_pg:photos_sr":1,
    "qs_pg:pop_sr":0,
    "qs_pg:qs_pg_placetype":"locality",
    "qs_pg:qs_pg_placetype_gp":"Town",
    "qs_pg:woe_adm0":23424844,
    "woe:adm0_id":23424844,
    "woe:name_adm0":"Magyarorsz\u00e1g",
    "woe:name_adm1":"Somogy",
    "woe:placetype":"Town",
    "wof:name":"Somogyfajsz",
    "wof:placetype":"locality"
},
  "geometry": {"coordinates":[17.56644,46.50854],"type":"Point"}
}