{
  "type": "Feature",
  "properties": {
    "gn:admin1_code":"14.0",
    "gn:asciiname":"Apacapuszta",
    "gn:country_code":"HU",
    "gn:dem":216,
    "gn:feature_class":"P",
    "gn:feature_code":"PPL",
    "gn:name":"Ap\u00e1capuszta",
    "gn:population":0,
    "gn:timezone":"Europe/Budapest",
    "iso:country":"HU",
    "wof:name":"Apacapuszta",
    "wof:placetype":"locality"
},
  "geometry": {"coordinates":[19.58457000000001,48.05009],"type":"Point"}
}