{
  "type": "Feature",
  "properties": {
    "gn:admin1_code":"18.0",
    "gn:asciiname":"Matetanya",
    "gn:country_code":"HU",
    "gn:dem":112,
    "gn:feature_class":"P",
    "gn:feature_code":"PPL",
    "gn:name":"M\u00e1t\u00e9tanya",
    "gn:population":0,
    "gn:timezone":"Europe/Budapest",
    "iso:country":"HU",
    "wof:name":"Matetanya",
    "wof:placetype":"locality"
},
  "geometry": {"coordinates":[22.71667,48.01667],"type":"Point"}
}