{
  "type": "Feature",
  "properties": {
    "gn:admin1_code":"2.0",
    "gn:asciiname":"Ilonamajor",
    "gn:country_code":"HU",
    "gn:dem":168,
    "gn:feature_class":"P",
    "gn:feature_code":"PPL",
    "gn:name":"Ilonamajor",
    "gn:population":0,
    "gn:timezone":"Europe/Budapest",
    "iso:country":"HU",
    "wof:name":"Ilonamajor",
    "wof:placetype":"locality"
},
  "geometry": {"coordinates":[16.71795,47.62306],"type":"Point"}
}