{
  "type": "Feature",
  "properties": {
    "gn:admin1_code":"1.0",
    "gn:asciiname":"Alsogalambos",
    "gn:country_code":"HU",
    "gn:dem":101,
    "gn:feature_class":"P",
    "gn:feature_code":"PPL",
    "gn:name":"Als\u00f3galambos",
    "gn:population":0,
    "gn:timezone":"Europe/Budapest",
    "iso:country":"HU",
    "wof:name":"Alsogalambos",
    "wof:placetype":"locality"
},
  "geometry": {"coordinates":[19.79315,46.69452],"type":"Point"}
}