{
  "type": "Feature",
  "properties": {
    "gn:admin1_code":"24.0",
    "gn:asciiname":"Ramocsa",
    "gn:country_code":"HU",
    "gn:dem":202,
    "gn:feature_class":"P",
    "gn:feature_code":"PPL",
    "gn:name":"Ramocsa",
    "gn:population":0,
    "gn:timezone":"Europe/Budapest",
    "iso:country":"HU",
    "wof:name":"Ramocsa",
    "wof:placetype":"locality"
},
  "geometry": {"coordinates":[16.44569,46.77634000000001],"type":"Point"}
}