{
  "type": "Feature",
  "properties": {
    "gn:admin1_code":"24.0",
    "gn:asciiname":"Ramocsa",
    "gn:country_code":"HU",
    "gn:dem":202,
    "gn:feature_class":"P",
    "gn:feature_code":"PPL",
    "gn:name":"Ramocsa",
    "gn:population":0,
    "gn:timezone":"Europe/Budapest",
    "iso:country":"HU",
    "name:epo_x_preferred":[
        "Ramocsa"
    ],
    "name:fas_x_preferred":[
        "\u0631\u0627\u0645\u0648\u0686\u0627"
    ],
    "name:fra_x_preferred":[
        "Ramocsa"
    ],
    "name:hun_x_preferred":[
        "Ramocsa"
    ],
    "name:ita_x_preferred":[
        "Ramocsa"
    ],
    "name:msa_x_preferred":[
        "Ramocsa"
    ],
    "name:nld_x_preferred":[
        "Ramocsa"
    ],
    "name:ron_x_preferred":[
        "Ramocsa"
    ],
    "name:slk_x_preferred":[
        "Ramocsa"
    ],
    "name:slv_x_preferred":[
        "Ramocsa"
    ],
    "name:vie_x_preferred":[
        "Ramocsa"
    ],
    "name:zho_x_preferred":[
        "\u52b3\u83ab\u4e54"
    ],
    "wof:name":"Ramocsa",
    "wof:placetype":"locality"
},
  "geometry": {"coordinates":[16.44569,46.77634000000001],"type":"Point"}
}