{
  "type": "Feature",
  "properties": {
    "gn:admin1_code":"4.0",
    "gn:asciiname":"Ujcsanalos",
    "gn:country_code":"HU",
    "gn:dem":183,
    "gn:feature_class":"P",
    "gn:feature_code":"PPL",
    "gn:name":"\u00dajcsan\u00e1los",
    "gn:population":0,
    "gn:timezone":"Europe/Budapest",
    "iso:country":"HU",
    "name:und_x_variant":[
        "\u00dajcsan\u00e1los"
    ],
    "wof:name":"Ujcsanalos",
    "wof:placetype":"locality"
},
  "geometry": {"coordinates":[21.01667,48.13333],"type":"Point"}
}