{
  "type": "Feature",
  "properties": {
    "gn:admin1_code":"4.0",
    "gn:asciiname":"Ujcsanalos",
    "gn:country_code":"HU",
    "gn:dem":183,
    "gn:feature_class":"P",
    "gn:feature_code":"PPL",
    "gn:name":"\u00dajcsan\u00e1los",
    "gn:population":0,
    "gn:timezone":"Europe/Budapest",
    "iso:country":"HU",
    "name:deu_x_preferred":[
        "\u00dajcsan\u00e1los"
    ],
    "name:epo_x_preferred":[
        "\u00dajcsan\u00e1los"
    ],
    "name:fas_x_preferred":[
        "\u0648\u06cc\u0686\u0627\u0646\u0627\u0644\u0648\u0634"
    ],
    "name:fra_x_preferred":[
        "\u00dajcsan\u00e1los"
    ],
    "name:heb_x_preferred":[
        "\u05d0\u05d5\u05d9\u05e6'\u05e0\u05d0\u05dc\u05d5\u05e9"
    ],
    "name:hun_x_preferred":[
        "\u00dajcsan\u00e1los"
    ],
    "name:ita_x_preferred":[
        "\u00dajcsan\u00e1los"
    ],
    "name:msa_x_preferred":[
        "\u00dajcsan\u00e1los"
    ],
    "name:nld_x_preferred":[
        "\u00dajcsan\u00e1los"
    ],
    "name:pol_x_preferred":[
        "\u00dajcsan\u00e1los"
    ],
    "name:ron_x_preferred":[
        "\u00dajcsan\u00e1los"
    ],
    "name:slk_x_preferred":[
        "\u00dajcsan\u00e1los"
    ],
    "name:slv_x_preferred":[
        "\u00dajcsan\u00e1los"
    ],
    "name:vie_x_preferred":[
        "\u00dajcsan\u00e1los"
    ],
    "name:zho_x_preferred":[
        "\u65b0\u4e54\u7eb3\u6d1b\u4ec0"
    ],
    "wof:name":"Ujcsanalos",
    "wof:placetype":"locality"
},
  "geometry": {"coordinates":[21.01667,48.13333],"type":"Point"}
}