{
  "type": "Feature",
  "properties": {
    "gn:admin1_code":"24.0",
    "gn:asciiname":"Nagyhegy",
    "gn:country_code":"HU",
    "gn:dem":270,
    "gn:feature_class":"P",
    "gn:feature_code":"PPL",
    "gn:name":"Nagyhegy",
    "gn:population":0,
    "gn:timezone":"Europe/Budapest",
    "iso:country":"HU",
    "wof:name":"Nagyhegy",
    "wof:placetype":"locality"
},
  "geometry": {"coordinates":[16.60873,46.57252],"type":"Point"}
}