{
  "type": "Feature",
  "properties": {
    "gn:admin1_code":"22.0",
    "gn:asciiname":"Buda",
    "gn:cc2":"HU",
    "gn:country_code":"HU",
    "gn:dem":137,
    "gn:feature_class":"P",
    "gn:feature_code":"PPL",
    "gn:name":"Buda",
    "gn:population":0,
    "gn:timezone":"Europe/Budapest",
    "iso:country":"HU",
    "name:afr_x_preferred":[
        "Boeda"
    ],
    "name:ara_x_preferred":[
        "\u0628\u0648\u062f\u0627"
    ],
    "name:arg_x_preferred":[
        "Buda"
    ],
    "name:aze_x_preferred":[
        "Buda"
    ],
    "name:bel_x_preferred":[
        "\u0411\u0443\u0434\u0430"
    ],
    "name:bul_x_preferred":[
        "\u0411\u0443\u0434\u0430"
    ],
    "name:cat_x_preferred":[
        "Buda"
    ],
    "name:ces_x_preferred":[
        "Bud\u00edn"
    ],
    "name:che_x_preferred":[
        "\u0411\u0443\u0434\u0430"
    ],
    "name:dan_x_preferred":[
        "Buda"
    ],
    "name:deu_x_preferred":[
        "Buda"
    ],
    "name:epo_x_preferred":[
        "Buda"
    ],
    "name:est_x_preferred":[
        "Buda"
    ],
    "name:fas_x_preferred":[
        "\u0628\u0648\u062f\u0627"
    ],
    "name:fin_x_preferred":[
        "Buda"
    ],
    "name:fra_x_preferred":[
        "Buda"
    ],
    "name:glg_x_preferred":[
        "Buda"
    ],
    "name:hrv_x_preferred":[
        "Budim"
    ],
    "name:hun_x_preferred":[
        "Buda"
    ],
    "name:hye_x_preferred":[
        "\u0532\u0578\u0582\u0564\u0561"
    ],
    "name:ind_x_preferred":[
        "Buda"
    ],
    "name:ita_x_preferred":[
        "Buda"
    ],
    "name:kaz_x_preferred":[
        "\u0411\u0443\u0434\u0430"
    ],
    "name:kur_x_preferred":[
        "Buda"
    ],
    "name:lat_x_preferred":[
        "Buda"
    ],
    "name:mkd_x_preferred":[
        "\u0411\u0443\u0434\u0438\u043c"
    ],
    "name:msa_x_preferred":[
        "Buda"
    ],
    "name:nld_x_preferred":[
        "Boeda"
    ],
    "name:nno_x_preferred":[
        "Buda"
    ],
    "name:pol_x_preferred":[
        "Buda"
    ],
    "name:por_x_preferred":[
        "Buda"
    ],
    "name:ron_x_preferred":[
        "Buda"
    ],
    "name:rue_x_preferred":[
        "\u0411\u0443\u0434\u0438\u043d"
    ],
    "name:rus_x_preferred":[
        "\u0411\u0443\u0434\u0430"
    ],
    "name:sco_x_preferred":[
        "Buda"
    ],
    "name:slk_x_preferred":[
        "Bud\u00edn"
    ],
    "name:slv_x_preferred":[
        "Budim"
    ],
    "name:spa_x_preferred":[
        "Buda"
    ],
    "name:srp_x_preferred":[
        "\u0411\u0443\u0434\u0438\u043c"
    ],
    "name:swe_x_preferred":[
        "Buda"
    ],
    "name:tha_x_preferred":[
        "\u0e1a\u0e39\u0e14\u0e2d"
    ],
    "name:tur_x_preferred":[
        "Budin"
    ],
    "name:ukr_x_preferred":[
        "\u0411\u0443\u0434\u0430"
    ],
    "name:und_x_variant":[
        "Budahegy",
        "Buda"
    ],
    "name:vie_x_preferred":[
        "Buda"
    ],
    "wof:name":"Buda",
    "wof:placetype":"locality"
},
  "geometry": {"coordinates":[17.03333,47.23333],"type":"Point"}
}