{
  "type": "Feature",
  "properties": {
    "gn:admin1_code":"22.0",
    "gn:asciiname":"Buda",
    "gn:cc2":"HU",
    "gn:country_code":"HU",
    "gn:dem":137,
    "gn:feature_class":"P",
    "gn:feature_code":"PPL",
    "gn:name":"Buda",
    "gn:population":0,
    "gn:timezone":"Europe/Budapest",
    "iso:country":"HU",
    "name:und_x_variant":[
        "Budahegy",
        "Buda"
    ],
    "wof:name":"Buda",
    "wof:placetype":"locality"
},
  "geometry": {"coordinates":[17.03333,47.23333],"type":"Point"}
}