{
  "type": "Feature",
  "properties": {
    "gn:admin1_code":"11.0",
    "gn:asciiname":"Lajoshaza",
    "gn:country_code":"HU",
    "gn:dem":371,
    "gn:feature_class":"P",
    "gn:feature_code":"PPL",
    "gn:name":"Lajosh\u00e1za",
    "gn:population":0,
    "gn:timezone":"Europe/Budapest",
    "iso:country":"HU",
    "wof:name":"Lajoshaza",
    "wof:placetype":"locality"
},
  "geometry": {"coordinates":[19.93615,47.86051],"type":"Point"}
}