{
  "type": "Feature",
  "properties": {
    "iso:country":"HU",
    "name:hun_x_preferred":[
        "Spanyolr\u00e9t"
    ],
    "wof:name":"Spanyolret",
    "wof:placetype":"neighbourhood"
},
  "geometry": {"coordinates":[18.98185450704985,47.46579694832007],"type":"Point"}
}