{
  "type": "Feature",
  "properties": {
    "iso:country":"HU",
    "name:hun_x_colloquial":[
        "Alsobadurbokor"
    ],
    "name:hun_x_preferred":[
        "Als\u00f3badurbokor"
    ],
    "qs:gn_adm0_cc":"HU",
    "qs:gn_fcode":"PPLX",
    "qs:gn_local":716935,
    "qs:gn_nam_loc":"Ny\u00edregyh\u00e1za, Ny\u00edregyh\u00e1za, Ny\u00edregyh\u00e1za, HU",
    "qs:gn_namadm1":"18",
    "qs:gn_name":"Als\u00f3badurbokor",
    "qs:local_max":164,
    "qs:local_sum":166,
    "qs:localhoods":2,
    "qs:name":"Als\u00f3badurbokor",
    "qs:name_adm0":"Magyarorsz\u00e1g",
    "qs:name_adm1":"Ny\u00edregyh\u00e1za",
    "qs:name_adm2":"Ny\u00edregyh\u00e1za",
    "qs:name_local":"Ny\u00edregyh\u00e1za",
    "qs:photo_max":99,
    "qs:photo_sum":164,
    "qs:placetype":"Suburb",
    "qs:quad_count":16,
    "qs:woe_adm0":23424844,
    "qs:woe_adm1":56043636,
    "qs:woe_adm2":12593479,
    "qs:woe_lau":0,
    "qs:woe_local":812897,
    "qs:woe_ver":"7.10.0",
    "wof:lang":[
        "hun"
    ],
    "wof:name":"Als\u00f3badurbokor",
    "wof:placetype":"neighbourhood"
},
  "geometry": {"coordinates":[21.721544,47.954735],"type":"Point"}
}