{
  "type": "Feature",
  "properties": {
    "gn:admin1_code":"10.0",
    "gn:asciiname":"Pallagdulo",
    "gn:country_code":"HU",
    "gn:dem":86,
    "gn:feature_class":"P",
    "gn:feature_code":"PPL",
    "gn:name":"Pallagd\u0171l\u0151",
    "gn:population":0,
    "gn:timezone":"Europe/Budapest",
    "iso:country":"HU",
    "wof:name":"Pallagdulo",
    "wof:placetype":"locality"
},
  "geometry": {"coordinates":[21.28333,47.35],"type":"Point"}
}