{
  "type": "Feature",
  "properties": {
    "gn:admin1_code":"20.0",
    "gn:asciiname":"Lukacsfenek",
    "gn:country_code":"HU",
    "gn:dem":84,
    "gn:feature_class":"P",
    "gn:feature_code":"PPLL",
    "gn:name":"Luk\u00e1csfen\u00e9k",
    "gn:population":0,
    "gn:timezone":"Europe/Budapest",
    "iso:country":"HU",
    "wof:name":"Lukacsfenek",
    "wof:placetype":"locality"
},
  "geometry": {"coordinates":[20.86667000000001,47.21667],"type":"Point"}
}