{
  "type": "Feature",
  "properties": {
    "gn:admin1_code":"6.0",
    "gn:asciiname":"Nagytoke",
    "gn:country_code":"HU",
    "gn:dem":81,
    "gn:feature_class":"P",
    "gn:feature_code":"PPL",
    "gn:name":"Nagyt\u0151ke",
    "gn:population":0,
    "gn:timezone":"Europe/Budapest",
    "iso:country":"HU",
    "name:epo_x_preferred":[
        "Nagyt\u0151ke"
    ],
    "name:fas_x_preferred":[
        "\u0646\u0627\u06af\u06cc\u062a\u0648\u06a9\u0647"
    ],
    "name:fra_x_preferred":[
        "Nagyt\u0151ke"
    ],
    "name:hun_x_preferred":[
        "Nagyt\u0151ke"
    ],
    "name:ita_x_preferred":[
        "Nagyt\u0151ke"
    ],
    "name:msa_x_preferred":[
        "Nagyt\u0151ke"
    ],
    "name:nld_x_preferred":[
        "Nagyt\u0151ke"
    ],
    "name:pol_x_preferred":[
        "Nagyt\u0151ke"
    ],
    "name:ron_x_preferred":[
        "Nagyt\u0151ke"
    ],
    "name:slk_x_preferred":[
        "Nagyt\u0151ke"
    ],
    "name:slv_x_preferred":[
        "Nagyt\u0151ke"
    ],
    "name:vie_x_preferred":[
        "Nagyt\u0151ke"
    ],
    "name:zho_x_preferred":[
        "\u5927\u7279\u51ef"
    ],
    "wof:name":"Nagytoke",
    "wof:placetype":"locality"
},
  "geometry": {"coordinates":[20.28763,46.75721],"type":"Point"}
}