{
  "type": "Feature",
  "properties": {
    "gn:admin1_code":"14.0",
    "gn:asciiname":"Hont",
    "gn:country_code":"HU",
    "gn:dem":128,
    "gn:feature_class":"P",
    "gn:feature_code":"PPL",
    "gn:name":"Hont",
    "gn:population":0,
    "gn:timezone":"Europe/Budapest",
    "iso:country":"HU",
    "name:epo_x_preferred":[
        "Hont"
    ],
    "name:fra_x_preferred":[
        "Hont"
    ],
    "name:hun_x_preferred":[
        "Hont"
    ],
    "name:ita_x_preferred":[
        "Hont"
    ],
    "name:msa_x_preferred":[
        "Hont"
    ],
    "name:pol_x_preferred":[
        "Hont"
    ],
    "name:ron_x_preferred":[
        "Hont"
    ],
    "name:slk_x_preferred":[
        "Hont"
    ],
    "name:slv_x_preferred":[
        "Hont"
    ],
    "name:swe_x_preferred":[
        "Hont"
    ],
    "name:vie_x_preferred":[
        "Hont"
    ],
    "wof:name":"Hont",
    "wof:placetype":"locality"
},
  "geometry": {"coordinates":[18.99193,48.05112],"type":"Point"}
}