{
  "type": "Feature",
  "properties": {
    "gn:admin1_code":"2.0",
    "gn:asciiname":"Almaskeresztur",
    "gn:country_code":"HU",
    "gn:dem":139,
    "gn:feature_class":"P",
    "gn:feature_code":"PPL",
    "gn:name":"Alm\u00e1skereszt\u00far",
    "gn:population":0,
    "gn:timezone":"Europe/Budapest",
    "iso:country":"HU",
    "name:und_x_variant":[
        "Alm\u00e1skereszt\u00far"
    ],
    "wof:name":"Almaskeresztur",
    "wof:placetype":"locality"
},
  "geometry": {"coordinates":[17.89562,46.11994],"type":"Point"}
}