{
  "type": "Feature",
  "properties": {
    "gn:admin1_code":"2.0",
    "gn:asciiname":"Almaskeresztur",
    "gn:country_code":"HU",
    "gn:dem":139,
    "gn:feature_class":"P",
    "gn:feature_code":"PPL",
    "gn:name":"Alm\u00e1skereszt\u00far",
    "gn:population":0,
    "gn:timezone":"Europe/Budapest",
    "iso:country":"HU",
    "name:ces_x_preferred":[
        "Alm\u00e1skereszt\u00far"
    ],
    "name:deu_x_preferred":[
        "Alm\u00e1skereszt\u00far"
    ],
    "name:epo_x_preferred":[
        "Alm\u00e1skereszt\u00far"
    ],
    "name:fas_x_preferred":[
        "\u0627\u0644\u0645\u0633\u06a9\u0631\u0632\u062a\u0648\u0631"
    ],
    "name:fra_x_preferred":[
        "Alm\u00e1skereszt\u00far"
    ],
    "name:hrv_x_preferred":[
        "Alm\u00e1skereszt\u00far"
    ],
    "name:hun_x_preferred":[
        "Alm\u00e1skereszt\u00far"
    ],
    "name:ita_x_preferred":[
        "Alm\u00e1skereszt\u00far"
    ],
    "name:msa_x_preferred":[
        "Alm\u00e1skereszt\u00far"
    ],
    "name:nld_x_preferred":[
        "Alm\u00e1skereszt\u00far"
    ],
    "name:pol_x_preferred":[
        "Alm\u00e1skereszt\u00far"
    ],
    "name:ron_x_preferred":[
        "Alm\u00e1skereszt\u00far"
    ],
    "name:slk_x_preferred":[
        "Alm\u00e1skereszt\u00far"
    ],
    "name:slv_x_preferred":[
        "Alm\u00e1skereszt\u00far"
    ],
    "name:vie_x_preferred":[
        "Alm\u00e1skereszt\u00far"
    ],
    "name:zho_x_preferred":[
        "\u5965\u5c14\u9a6c\u4ec0\u51ef\u8d56\u65af\u56fe\u5c14"
    ],
    "wof:name":"Almaskeresztur",
    "wof:placetype":"locality"
},
  "geometry": {"coordinates":[17.89562,46.11994],"type":"Point"}
}