{
  "type": "Feature",
  "properties": {
    "gn:admin1_code":"21.0",
    "gn:asciiname":"Ujhegy",
    "gn:country_code":"HU",
    "gn:dem":137,
    "gn:feature_class":"P",
    "gn:feature_code":"PPL",
    "gn:name":"\u00dajhegy",
    "gn:population":0,
    "gn:timezone":"Europe/Budapest",
    "iso:country":"HU",
    "wof:name":"Ujhegy",
    "wof:placetype":"locality"
},
  "geometry": {"coordinates":[18.48333,46.55],"type":"Point"}
}