{
  "type": "Feature",
  "properties": {
    "gn:admin1_code":"14.0",
    "gn:asciiname":"Pusztaberki",
    "gn:country_code":"HU",
    "gn:dem":169,
    "gn:feature_class":"P",
    "gn:feature_code":"PPL",
    "gn:name":"Pusztaberki",
    "gn:population":0,
    "gn:timezone":"Europe/Budapest",
    "iso:country":"HU",
    "name:epo_x_preferred":[
        "Pusztaberki"
    ],
    "name:fas_x_preferred":[
        "\u067e\u0648\u0633\u062a\u0627\u0628\u0631\u06a9\u06cc"
    ],
    "name:fra_x_preferred":[
        "Pusztaberki"
    ],
    "name:hun_x_preferred":[
        "Pusztaberki"
    ],
    "name:ita_x_preferred":[
        "Pusztaberki"
    ],
    "name:msa_x_preferred":[
        "Pusztaberki"
    ],
    "name:nld_x_preferred":[
        "Pusztaberki"
    ],
    "name:pol_x_preferred":[
        "Pusztaberki"
    ],
    "name:ron_x_preferred":[
        "Pusztaberki"
    ],
    "name:slk_x_preferred":[
        "Pusztaberki"
    ],
    "name:slv_x_preferred":[
        "Pusztaberki"
    ],
    "name:vie_x_preferred":[
        "Pusztaberki"
    ],
    "name:zho_x_preferred":[
        "\u666e\u65af\u9676\u62dc\u5c14\u57fa"
    ],
    "wof:name":"Pusztaberki",
    "wof:placetype":"locality"
},
  "geometry": {"coordinates":[19.16228,47.9751],"type":"Point"}
}