{
  "type": "Feature",
  "properties": {
    "gn:admin1_code":"14.0",
    "gn:asciiname":"Pusztaberki",
    "gn:country_code":"HU",
    "gn:dem":169,
    "gn:feature_class":"P",
    "gn:feature_code":"PPL",
    "gn:name":"Pusztaberki",
    "gn:population":0,
    "gn:timezone":"Europe/Budapest",
    "iso:country":"HU",
    "wof:name":"Pusztaberki",
    "wof:placetype":"locality"
},
  "geometry": {"coordinates":[19.16228,47.9751],"type":"Point"}
}