{
  "type": "Feature",
  "properties": {
    "gn:admin1_code":"2.0",
    "gn:asciiname":"Alsoszallas",
    "gn:country_code":"HU",
    "gn:dem":90,
    "gn:feature_class":"P",
    "gn:feature_code":"PPL",
    "gn:name":"Als\u00f3sz\u00e1ll\u00e1s",
    "gn:population":0,
    "gn:timezone":"Europe/Budapest",
    "iso:country":"HU",
    "wof:name":"Alsoszallas",
    "wof:placetype":"locality"
},
  "geometry": {"coordinates":[18.76667,46.06667],"type":"Point"}
}