{
  "type": "Feature",
  "properties": {
    "gn:admin1_code":"10.0",
    "gn:asciiname":"Cenzusdulo",
    "gn:cc2":"HU",
    "gn:country_code":"HU",
    "gn:dem":91,
    "gn:feature_class":"P",
    "gn:feature_code":"PPLL",
    "gn:name":"Cenzusd\u0171l\u0151",
    "gn:population":0,
    "gn:timezone":"Europe/Budapest",
    "iso:country":"HU",
    "name:und_x_variant":[
        "Cenzusf\u00f6ld"
    ],
    "wof:name":"Cenzusdulo",
    "wof:placetype":"locality"
},
  "geometry": {"coordinates":[21.51667,47.36667],"type":"Point"}
}