{
  "type": "Feature",
  "properties": {
    "gn:admin1_code":"2.0",
    "gn:asciiname":"Csanadikert",
    "gn:cc2":"HU",
    "gn:country_code":"HU",
    "gn:dem":81,
    "gn:feature_class":"P",
    "gn:feature_code":"PPL",
    "gn:name":"Csan\u00e1dikert",
    "gn:population":0,
    "gn:timezone":"Europe/Budapest",
    "iso:country":"HU",
    "name:und_x_variant":[
        "Csan\u00e1dikert Major",
        "Csan\u00e1dikert"
    ],
    "wof:name":"Csanadikert",
    "wof:placetype":"locality"
},
  "geometry": {"coordinates":[18.83333,46.05],"type":"Point"}
}