{
  "type": "Feature",
  "properties": {
    "gn:admin1_code":"9.0",
    "gn:asciiname":"Toth Ferenc-tag",
    "gn:country_code":"HU",
    "gn:dem":126,
    "gn:feature_class":"P",
    "gn:feature_code":"PPL",
    "gn:name":"T\u00f3th Ferenc-tag",
    "gn:population":0,
    "gn:timezone":"Europe/Budapest",
    "iso:country":"HU",
    "wof:name":"Toth Ferenc-tag",
    "wof:placetype":"locality"
},
  "geometry": {"coordinates":[17.85,47.63333],"type":"Point"}
}