{
  "type": "Feature",
  "properties": {
    "gn:admin1_code":"10.0",
    "gn:asciiname":"Kigyospuszta",
    "gn:country_code":"HU",
    "gn:dem":86,
    "gn:feature_class":"P",
    "gn:feature_code":"PPL",
    "gn:name":"K\u00edgy\u00f3spuszta",
    "gn:population":0,
    "gn:timezone":"Europe/Budapest",
    "iso:country":"HU",
    "wof:name":"Kigyospuszta",
    "wof:placetype":"locality"
},
  "geometry": {"coordinates":[21.38333,47.08333],"type":"Point"}
}