{
  "type": "Feature",
  "properties": {
    "gn:admin1_code":"4.0",
    "gn:asciiname":"Gomorszolos",
    "gn:cc2":"HU",
    "gn:country_code":"HU",
    "gn:dem":272,
    "gn:feature_class":"P",
    "gn:feature_code":"PPL",
    "gn:name":"G\u00f6m\u00f6rsz\u0151l\u0151s",
    "gn:population":0,
    "gn:timezone":"Europe/Budapest",
    "iso:country":"HU",
    "name:und_x_variant":[
        "G\u00f6m\u00f6rsz\u0151ll\u0151s",
        "G\u00f6m\u00f6rsz\u0151l\u0151s"
    ],
    "wof:name":"Gomorszolos",
    "wof:placetype":"locality"
},
  "geometry": {"coordinates":[20.43333,48.38333],"type":"Point"}
}