{
  "type": "Feature",
  "properties": {
    "gn:admin1_code":"4.0",
    "gn:asciiname":"Gomorszolos",
    "gn:cc2":"HU",
    "gn:country_code":"HU",
    "gn:dem":272,
    "gn:feature_class":"P",
    "gn:feature_code":"PPL",
    "gn:name":"G\u00f6m\u00f6rsz\u0151l\u0151s",
    "gn:population":0,
    "gn:timezone":"Europe/Budapest",
    "iso:country":"HU",
    "name:ces_x_preferred":[
        "G\u00f6m\u00f6rsz\u0151l\u0151s"
    ],
    "name:deu_x_preferred":[
        "G\u00f6m\u00f6rsz\u0151l\u0151s"
    ],
    "name:epo_x_preferred":[
        "G\u00f6m\u00f6rsz\u0151l\u0151s"
    ],
    "name:est_x_preferred":[
        "G\u00f6m\u00f6rsz\u0151l\u0151s"
    ],
    "name:fas_x_preferred":[
        "\u06af\u0648\u0645\u0648\u0631\u0633\u0648\u0644\u0648\u0634"
    ],
    "name:fra_x_preferred":[
        "G\u00f6m\u00f6rsz\u0151l\u0151s"
    ],
    "name:heb_x_preferred":[
        "\u05d2\u05de\u05e8\u05e1\u05dc\u05e9"
    ],
    "name:hun_x_preferred":[
        "G\u00f6m\u00f6rsz\u0151l\u0151s"
    ],
    "name:ita_x_preferred":[
        "G\u00f6m\u00f6rsz\u0151l\u0151s"
    ],
    "name:msa_x_preferred":[
        "G\u00f6m\u00f6rsz\u0151l\u0151s"
    ],
    "name:nld_x_preferred":[
        "G\u00f6m\u00f6rsz\u0151l\u0151s"
    ],
    "name:pol_x_preferred":[
        "G\u00f6m\u00f6rsz\u0151l\u0151s"
    ],
    "name:ron_x_preferred":[
        "G\u00f6m\u00f6rsz\u0151l\u0151s"
    ],
    "name:slk_x_preferred":[
        "G\u00f6m\u00f6rsz\u0151l\u0151s"
    ],
    "name:slv_x_preferred":[
        "G\u00f6m\u00f6rsz\u0151l\u0151s"
    ],
    "name:und_x_variant":[
        "G\u00f6m\u00f6rsz\u0151ll\u0151s"
    ],
    "name:vie_x_preferred":[
        "G\u00f6m\u00f6rsz\u0151l\u0151s"
    ],
    "name:zho_x_preferred":[
        "\u683c\u9ed8\u5c14\u745f\u52d2\u4ec0"
    ],
    "wof:name":"Gomorszolos",
    "wof:placetype":"locality"
},
  "geometry": {"coordinates":[20.43333,48.38333],"type":"Point"}
}