{
  "type": "Feature",
  "properties": {
    "gn:admin1_code":"9.0",
    "gn:asciiname":"Szentkutpuszta",
    "gn:country_code":"HU",
    "gn:dem":117,
    "gn:feature_class":"P",
    "gn:feature_code":"PPL",
    "gn:name":"Szentk\u00fatpuszta",
    "gn:population":0,
    "gn:timezone":"Europe/Budapest",
    "iso:country":"HU",
    "wof:name":"Szentkutpuszta",
    "wof:placetype":"locality"
},
  "geometry": {"coordinates":[17.41667,47.51667],"type":"Point"}
}