{
  "type": "Feature",
  "properties": {
    "gn:admin1_code":"18.0",
    "gn:asciiname":"Tiszacsecse",
    "gn:country_code":"HU",
    "gn:dem":116,
    "gn:feature_class":"P",
    "gn:feature_code":"PPL",
    "gn:name":"Tiszacs\u00e9cse",
    "gn:population":0,
    "gn:timezone":"Europe/Budapest",
    "iso:country":"HU",
    "name:ces_x_preferred":[
        "Tiszacs\u00e9cse"
    ],
    "name:deu_x_preferred":[
        "Tiszacs\u00e9cse"
    ],
    "name:epo_x_preferred":[
        "Tiszacs\u00e9cse"
    ],
    "name:fas_x_preferred":[
        "\u062a\u06cc\u0633\u0627\u0686\u0686\u0647"
    ],
    "name:fra_x_preferred":[
        "Tiszacs\u00e9cse"
    ],
    "name:hun_x_preferred":[
        "Tiszacs\u00e9cse"
    ],
    "name:ita_x_preferred":[
        "Tiszacs\u00e9cse"
    ],
    "name:msa_x_preferred":[
        "Tiszacs\u00e9cse"
    ],
    "name:nld_x_preferred":[
        "Tiszacs\u00e9cse"
    ],
    "name:ron_x_preferred":[
        "Tiszacs\u00e9cse"
    ],
    "name:slk_x_preferred":[
        "Tiszacs\u00e9cse"
    ],
    "name:slv_x_preferred":[
        "Tiszacs\u00e9cse"
    ],
    "name:vie_x_preferred":[
        "Tiszacs\u00e9cse"
    ],
    "name:zho_x_preferred":[
        "\u8482\u7ecd\u5207\u5207"
    ],
    "wof:name":"Tiszacsecse",
    "wof:placetype":"locality"
},
  "geometry": {"coordinates":[22.74647,48.11031],"type":"Point"}
}