{
  "type": "Feature",
  "properties": {
    "gn:admin1_code":"18.0",
    "gn:asciiname":"Weinbergertanya",
    "gn:country_code":"HU",
    "gn:dem":104,
    "gn:feature_class":"P",
    "gn:feature_code":"PPL",
    "gn:name":"Weinbergertanya",
    "gn:population":0,
    "gn:timezone":"Europe/Budapest",
    "iso:country":"HU",
    "wof:name":"Weinbergertanya",
    "wof:placetype":"locality"
},
  "geometry": {"coordinates":[22.28333,48.16667],"type":"Point"}
}