{
  "type": "Feature",
  "properties": {
    "gn:admin1_code":"22.0",
    "gn:asciiname":"Pecol",
    "gn:country_code":"HU",
    "gn:dem":173,
    "gn:feature_class":"P",
    "gn:feature_code":"PPL",
    "gn:name":"Pec\u00f6l",
    "gn:population":0,
    "gn:timezone":"Europe/Budapest",
    "iso:country":"HU",
    "name:epo_x_preferred":[
        "Pec\u00f6l"
    ],
    "name:fas_x_preferred":[
        "\u067e\u062a\u0633\u0648\u0644"
    ],
    "name:fra_x_preferred":[
        "Pec\u00f6l"
    ],
    "name:hun_x_preferred":[
        "Pec\u00f6l"
    ],
    "name:ita_x_preferred":[
        "Pec\u00f6l"
    ],
    "name:msa_x_preferred":[
        "Pec\u00f6l"
    ],
    "name:nld_x_preferred":[
        "Pec\u00f6l"
    ],
    "name:ron_x_preferred":[
        "Pec\u00f6l"
    ],
    "name:slk_x_preferred":[
        "Pec\u00f6l"
    ],
    "name:slv_x_preferred":[
        "Pec\u00f6l"
    ],
    "name:vie_x_preferred":[
        "Pec\u00f6l"
    ],
    "name:zho_x_preferred":[
        "\u6d3e\u7b56\u5c14"
    ],
    "wof:name":"Pecol",
    "wof:placetype":"locality"
},
  "geometry": {"coordinates":[16.8211,47.20517],"type":"Point"}
}