{
  "type": "Feature",
  "properties": {
    "gn:admin1_code":"22.0",
    "gn:asciiname":"Pecol",
    "gn:country_code":"HU",
    "gn:dem":173,
    "gn:feature_class":"P",
    "gn:feature_code":"PPL",
    "gn:name":"Pec\u00f6l",
    "gn:population":0,
    "gn:timezone":"Europe/Budapest",
    "iso:country":"HU",
    "wof:name":"Pecol",
    "wof:placetype":"locality"
},
  "geometry": {"coordinates":[16.8211,47.20517],"type":"Point"}
}