{
  "type": "Feature",
  "properties": {
    "gn:admin1_code":"22.0",
    "gn:asciiname":"Csehimindszent",
    "gn:country_code":"HU",
    "gn:dem":175,
    "gn:feature_class":"P",
    "gn:feature_code":"PPL",
    "gn:name":"Csehimindszent",
    "gn:population":0,
    "gn:timezone":"Europe/Budapest",
    "iso:country":"HU",
    "name:epo_x_preferred":[
        "Csehimindszent"
    ],
    "name:fas_x_preferred":[
        "\u0686\u0647\u06cc\u200c\u0645\u06cc\u0646\u062f\u0633\u0646\u062a"
    ],
    "name:fra_x_preferred":[
        "Csehimindszent"
    ],
    "name:hun_x_preferred":[
        "Csehimindszent"
    ],
    "name:ita_x_preferred":[
        "Csehimindszent"
    ],
    "name:msa_x_preferred":[
        "Csehimindszent"
    ],
    "name:nld_x_preferred":[
        "Csehimindszent"
    ],
    "name:ron_x_preferred":[
        "Csehimindszent"
    ],
    "name:slk_x_preferred":[
        "Csehimindszent"
    ],
    "name:slv_x_preferred":[
        "Csehimindszent"
    ],
    "name:swe_x_preferred":[
        "Csehimindszent"
    ],
    "name:ukr_x_preferred":[
        "\u0427\u0435\u0445\u0456\u043c\u0456\u043d\u0434\u0441\u0435\u043d\u0442"
    ],
    "name:vie_x_preferred":[
        "Csehimindszent"
    ],
    "name:zho_x_preferred":[
        "\u5207\u5e0c\u660e\u5fb7\u68ee\u7279"
    ],
    "wof:name":"Csehimindszent",
    "wof:placetype":"locality"
},
  "geometry": {"coordinates":[16.95491,47.04793],"type":"Point"}
}