{
  "type": "Feature",
  "properties": {
    "gn:admin1_code":"22.0",
    "gn:asciiname":"Csehimindszent",
    "gn:country_code":"HU",
    "gn:dem":175,
    "gn:feature_class":"P",
    "gn:feature_code":"PPL",
    "gn:name":"Csehimindszent",
    "gn:population":0,
    "gn:timezone":"Europe/Budapest",
    "iso:country":"HU",
    "wof:name":"Csehimindszent",
    "wof:placetype":"locality"
},
  "geometry": {"coordinates":[16.95491,47.04793],"type":"Point"}
}