{
  "type": "Feature",
  "properties": {
    "gn:admin1_code":"24.0",
    "gn:asciiname":"Fiatalospuszta",
    "gn:country_code":"HU",
    "gn:dem":139,
    "gn:feature_class":"P",
    "gn:feature_code":"PPL",
    "gn:name":"Fiatalospuszta",
    "gn:population":0,
    "gn:timezone":"Europe/Budapest",
    "iso:country":"HU",
    "name:und_x_variant":[
        "Fiatalosmajor",
        "Fiatalospuszta"
    ],
    "wof:name":"Fiatalospuszta",
    "wof:placetype":"locality"
},
  "geometry": {"coordinates":[17.20333,47.00115],"type":"Point"}
}