{
  "type": "Feature",
  "properties": {
    "gn:admin1_code":"22.0",
    "gn:asciiname":"Uraiujfalu",
    "gn:country_code":"HU",
    "gn:dem":147,
    "gn:feature_class":"P",
    "gn:feature_code":"PPL",
    "gn:name":"Urai\u00fajfalu",
    "gn:population":0,
    "gn:timezone":"Europe/Budapest",
    "iso:country":"HU",
    "name:epo_x_preferred":[
        "Urai\u00fajfalu"
    ],
    "name:fas_x_preferred":[
        "\u0627\u0648\u0631\u0627\u06cc\u0648\u06cc\u0641\u0627\u0644\u0648"
    ],
    "name:fra_x_preferred":[
        "Urai\u00fajfalu"
    ],
    "name:hun_x_preferred":[
        "Urai\u00fajfalu"
    ],
    "name:ita_x_preferred":[
        "Urai\u00fajfalu"
    ],
    "name:msa_x_preferred":[
        "Urai\u00fajfalu"
    ],
    "name:nld_x_preferred":[
        "Urai\u00fajfalu"
    ],
    "name:ron_x_preferred":[
        "Urai\u00fajfalu"
    ],
    "name:slk_x_preferred":[
        "Urai\u00fajfalu"
    ],
    "name:slv_x_preferred":[
        "Urai\u00fajfalu"
    ],
    "name:vie_x_preferred":[
        "Urai\u00fajfalu"
    ],
    "name:zho_x_preferred":[
        "\u4e4c\u52b3\u4f0a\u4e4c\u4f0a\u798f\u5362"
    ],
    "wof:name":"Uraiujfalu",
    "wof:placetype":"locality"
},
  "geometry": {"coordinates":[16.98504,47.37203],"type":"Point"}
}