{
  "type": "Feature",
  "properties": {
    "gn:admin1_code":"22.0",
    "gn:asciiname":"Uraiujfalu",
    "gn:country_code":"HU",
    "gn:dem":147,
    "gn:feature_class":"P",
    "gn:feature_code":"PPL",
    "gn:name":"Urai\u00fajfalu",
    "gn:population":0,
    "gn:timezone":"Europe/Budapest",
    "iso:country":"HU",
    "name:und_x_variant":[
        "Urai\u00fajfalu"
    ],
    "wof:name":"Uraiujfalu",
    "wof:placetype":"locality"
},
  "geometry": {"coordinates":[16.98504,47.37203],"type":"Point"}
}