{
  "type": "Feature",
  "properties": {
    "gn:admin1_code":"11.0",
    "gn:asciiname":"Szelestanya",
    "gn:country_code":"HU",
    "gn:dem":357,
    "gn:feature_class":"P",
    "gn:feature_code":"PPL",
    "gn:name":"Sz\u00e9lestanya",
    "gn:population":0,
    "gn:timezone":"Europe/Budapest",
    "iso:country":"HU",
    "wof:name":"Szelestanya",
    "wof:placetype":"locality"
},
  "geometry": {"coordinates":[20.31667,48.11667],"type":"Point"}
}