{
  "type": "Feature",
  "properties": {
    "iso:country":"HU",
    "qs_pg:aaroncc":"HU",
    "qs_pg:name":"Budai \u00dat",
    "qs_pg:name_adm0":"Magyarorsz\u00e1g",
    "qs_pg:name_adm1":"Pest",
    "qs_pg:photos":56,
    "qs_pg:photos_1k":11,
    "qs_pg:photos_9k":1,
    "qs_pg:photos_9r":2,
    "qs_pg:photos_all":56,
    "qs_pg:photos_sr":2,
    "qs_pg:pop_sr":0,
    "qs_pg:qs_pg_placetype":"locality",
    "qs_pg:qs_pg_placetype_gp":"Town",
    "qs_pg:woe_adm0":23424844,
    "woe:adm0_id":23424844,
    "woe:name_adm0":"Magyarorsz\u00e1g",
    "woe:name_adm1":"Pest",
    "woe:placetype":"Town",
    "wof:name":"Budai \u00dat",
    "wof:placetype":"locality"
},
  "geometry": {"coordinates":[19.7329415,47.201088],"type":"Point"}
}