{
  "type": "Feature",
  "properties": {
    "gn:admin1_code":"24.0",
    "gn:asciiname":"Toti Allami Gazdasag",
    "gn:country_code":"HU",
    "gn:dem":159,
    "gn:feature_class":"P",
    "gn:feature_code":"PPL",
    "gn:name":"T\u00f3ti \u00c1llami Gazdas\u00e1g",
    "gn:population":0,
    "gn:timezone":"Europe/Budapest",
    "iso:country":"HU",
    "name:und_x_variant":[
        "T\u00f3timajor",
        "T\u00f3ti \u00c1llami Gazdas\u00e1g"
    ],
    "wof:name":"Toti Allami Gazdasag",
    "wof:placetype":"locality"
},
  "geometry": {"coordinates":[17.01244,47.02631],"type":"Point"}
}