{
  "type": "Feature",
  "properties": {
    "gn:admin1_code":"17.0",
    "gn:asciiname":"Csoma",
    "gn:country_code":"HU",
    "gn:dem":136,
    "gn:feature_class":"P",
    "gn:feature_code":"PPL",
    "gn:name":"Csoma",
    "gn:population":0,
    "gn:timezone":"Europe/Budapest",
    "iso:country":"HU",
    "wof:name":"Csoma",
    "wof:placetype":"locality"
},
  "geometry": {"coordinates":[18.05182000000001,46.37294],"type":"Point"}
}