{
  "type": "Feature",
  "properties": {
    "gn:admin1_code":"17.0",
    "gn:asciiname":"Csoma",
    "gn:country_code":"HU",
    "gn:dem":136,
    "gn:feature_class":"P",
    "gn:feature_code":"PPL",
    "gn:name":"Csoma",
    "gn:population":0,
    "gn:timezone":"Europe/Budapest",
    "iso:country":"HU",
    "name:deu_x_preferred":[
        "Csoma"
    ],
    "name:epo_x_preferred":[
        "Csoma"
    ],
    "name:fas_x_preferred":[
        "\u0686\u0648\u0645\u0627"
    ],
    "name:fra_x_preferred":[
        "Csoma"
    ],
    "name:hun_x_preferred":[
        "Csoma"
    ],
    "name:ita_x_preferred":[
        "Csoma"
    ],
    "name:msa_x_preferred":[
        "Csoma"
    ],
    "name:nld_x_preferred":[
        "Csoma"
    ],
    "name:ron_x_preferred":[
        "Csoma"
    ],
    "name:slk_x_preferred":[
        "Csoma"
    ],
    "name:slv_x_preferred":[
        "Csoma"
    ],
    "name:vie_x_preferred":[
        "Csoma"
    ],
    "wof:name":"Csoma",
    "wof:placetype":"locality"
},
  "geometry": {"coordinates":[18.05182000000001,46.37294],"type":"Point"}
}