{
  "type": "Feature",
  "properties": {
    "gn:admin1_code":"1.0",
    "gn:asciiname":"Baracs",
    "gn:country_code":"HU",
    "gn:dem":109,
    "gn:feature_class":"P",
    "gn:feature_code":"PPL",
    "gn:name":"Baracs",
    "gn:population":0,
    "gn:timezone":"Europe/Budapest",
    "iso:country":"HU",
    "wof:name":"Baracs",
    "wof:placetype":"locality"
},
  "geometry": {"coordinates":[19.41667,46.98333],"type":"Point"}
}