{
  "type": "Feature",
  "properties": {
    "gn:admin1_code":"1.0",
    "gn:asciiname":"Baracs",
    "gn:country_code":"HU",
    "gn:dem":109,
    "gn:feature_class":"P",
    "gn:feature_code":"PPL",
    "gn:name":"Baracs",
    "gn:population":0,
    "gn:timezone":"Europe/Budapest",
    "iso:country":"HU",
    "name:ceb_x_preferred":[
        "Baracs"
    ],
    "name:deu_x_preferred":[
        "Baracs"
    ],
    "name:epo_x_preferred":[
        "Baracs"
    ],
    "name:fas_x_preferred":[
        "\u0628\u0627\u0631\u0627\u0686"
    ],
    "name:fra_x_preferred":[
        "Baracs"
    ],
    "name:hun_x_preferred":[
        "Baracs"
    ],
    "name:ita_x_preferred":[
        "Baracs"
    ],
    "name:msa_x_preferred":[
        "Baracs"
    ],
    "name:nld_x_preferred":[
        "Baracs"
    ],
    "name:ron_x_preferred":[
        "Baracs"
    ],
    "name:slk_x_preferred":[
        "Baracs"
    ],
    "name:slv_x_preferred":[
        "Baracs"
    ],
    "name:swe_x_preferred":[
        "Baracs"
    ],
    "name:vie_x_preferred":[
        "Baracs"
    ],
    "name:zho_x_preferred":[
        "\u5305\u52de\u5947"
    ],
    "wof:name":"Baracs",
    "wof:placetype":"locality"
},
  "geometry": {"coordinates":[19.41667,46.98333],"type":"Point"}
}