{
  "type": "Feature",
  "properties": {
    "gn:admin1_code":"17.0",
    "gn:asciiname":"Andormajor",
    "gn:country_code":"HU",
    "gn:dem":128,
    "gn:feature_class":"P",
    "gn:feature_code":"PPL",
    "gn:name":"Andormajor",
    "gn:population":0,
    "gn:timezone":"Europe/Budapest",
    "iso:country":"HU",
    "wof:name":"Andormajor",
    "wof:placetype":"locality"
},
  "geometry": {"coordinates":[17.2571,46.51535],"type":"Point"}
}