{
  "type": "Feature",
  "properties": {
    "gn:admin1_code":"24.0",
    "gn:asciiname":"Szilvagy",
    "gn:country_code":"HU",
    "gn:dem":196,
    "gn:feature_class":"P",
    "gn:feature_code":"PPL",
    "gn:name":"Szilv\u00e1gy",
    "gn:population":0,
    "gn:timezone":"Europe/Budapest",
    "iso:country":"HU",
    "name:und_x_variant":[
        "Szilv\u00e1gy"
    ],
    "wof:name":"Szilvagy",
    "wof:placetype":"locality"
},
  "geometry": {"coordinates":[16.6274,46.73428],"type":"Point"}
}