{
  "type": "Feature",
  "properties": {
    "gn:admin1_code":"24.0",
    "gn:asciiname":"Szilvagy",
    "gn:country_code":"HU",
    "gn:dem":196,
    "gn:feature_class":"P",
    "gn:feature_code":"PPL",
    "gn:name":"Szilv\u00e1gy",
    "gn:population":0,
    "gn:timezone":"Europe/Budapest",
    "iso:country":"HU",
    "name:epo_x_preferred":[
        "Szilv\u00e1gy"
    ],
    "name:fas_x_preferred":[
        "\u0633\u06cc\u0644\u0648\u0627\u06af\u06cc"
    ],
    "name:fra_x_preferred":[
        "Szilv\u00e1gy"
    ],
    "name:hun_x_preferred":[
        "Szilv\u00e1gy"
    ],
    "name:ita_x_preferred":[
        "Szilv\u00e1gy"
    ],
    "name:msa_x_preferred":[
        "Szilv\u00e1gy"
    ],
    "name:nld_x_preferred":[
        "Szilv\u00e1gy"
    ],
    "name:ron_x_preferred":[
        "Szilv\u00e1gy"
    ],
    "name:slk_x_preferred":[
        "Szilv\u00e1gy"
    ],
    "name:slv_x_preferred":[
        "Szilv\u00e1gy"
    ],
    "name:vie_x_preferred":[
        "Szilv\u00e1gy"
    ],
    "name:zho_x_preferred":[
        "\u897f\u5c14\u74e6\u5409"
    ],
    "wof:name":"Szilvagy",
    "wof:placetype":"locality"
},
  "geometry": {"coordinates":[16.6274,46.73428],"type":"Point"}
}