{
  "type": "Feature",
  "properties": {
    "gn:admin1_code":"2.0",
    "gn:asciiname":"Bogdasa",
    "gn:country_code":"HU",
    "gn:dem":102,
    "gn:feature_class":"P",
    "gn:feature_code":"PPL",
    "gn:name":"Bogd\u00e1sa",
    "gn:population":0,
    "gn:timezone":"Europe/Budapest",
    "iso:country":"HU",
    "name:und_x_variant":[
        "Bogd\u00e1sa"
    ],
    "wof:name":"Bogdasa",
    "wof:placetype":"locality"
},
  "geometry": {"coordinates":[17.79027,45.8756],"type":"Point"}
}