{
  "type": "Feature",
  "properties": {
    "gn:admin1_code":"2.0",
    "gn:asciiname":"Bogdasa",
    "gn:country_code":"HU",
    "gn:dem":102,
    "gn:feature_class":"P",
    "gn:feature_code":"PPL",
    "gn:name":"Bogd\u00e1sa",
    "gn:population":0,
    "gn:timezone":"Europe/Budapest",
    "iso:country":"HU",
    "name:deu_x_preferred":[
        "Bogd\u00e1sa"
    ],
    "name:epo_x_preferred":[
        "Bogd\u00e1sa"
    ],
    "name:fas_x_preferred":[
        "\u0628\u0648\u06af\u062f\u0627\u0634\u0627"
    ],
    "name:fra_x_preferred":[
        "Bogd\u00e1sa"
    ],
    "name:hrv_x_preferred":[
        "Bogda\u0161in"
    ],
    "name:hun_x_preferred":[
        "Bogd\u00e1sa"
    ],
    "name:ita_x_preferred":[
        "Bogd\u00e1sa"
    ],
    "name:msa_x_preferred":[
        "Bogd\u00e1sa"
    ],
    "name:nld_x_preferred":[
        "Bogd\u00e1sa"
    ],
    "name:pol_x_preferred":[
        "Bogd\u00e1sa"
    ],
    "name:ron_x_preferred":[
        "Bogd\u00e1sa"
    ],
    "name:slk_x_preferred":[
        "Bogd\u00e1sa"
    ],
    "name:slv_x_preferred":[
        "Bogd\u00e1sa"
    ],
    "name:vie_x_preferred":[
        "Bogd\u00e1sa"
    ],
    "name:zho_x_preferred":[
        "\u535a\u683c\u8fbe\u7ecd"
    ],
    "wof:name":"Bogdasa",
    "wof:placetype":"locality"
},
  "geometry": {"coordinates":[17.79027,45.8756],"type":"Point"}
}