{
  "type": "Feature",
  "properties": {
    "gn:admin1_code":"18.0",
    "gn:asciiname":"Emmamajor",
    "gn:country_code":"HU",
    "gn:dem":150,
    "gn:feature_class":"P",
    "gn:feature_code":"PPL",
    "gn:name":"Emmamajor",
    "gn:population":0,
    "gn:timezone":"Europe/Budapest",
    "iso:country":"HU",
    "name:und_x_variant":[
        "Palacsinta Tanya",
        "Emmamajor"
    ],
    "wof:name":"Emmamajor",
    "wof:placetype":"locality"
},
  "geometry": {"coordinates":[22.14499,47.76185],"type":"Point"}
}