{
  "type": "Feature",
  "properties": {
    "gn:admin1_code":"24.0",
    "gn:asciiname":"Csilladulo",
    "gn:country_code":"HU",
    "gn:dem":147,
    "gn:feature_class":"P",
    "gn:feature_code":"PPL",
    "gn:name":"Csillad\u0171l\u0151",
    "gn:population":0,
    "gn:timezone":"Europe/Budapest",
    "iso:country":"HU",
    "wof:name":"Csilladulo",
    "wof:placetype":"locality"
},
  "geometry": {"coordinates":[16.85,46.85],"type":"Point"}
}