{
  "type": "Feature",
  "properties": {
    "gn:admin1_code":"8.0",
    "gn:asciiname":"Matyasdomb",
    "gn:country_code":"HU",
    "gn:dem":132,
    "gn:feature_class":"P",
    "gn:feature_code":"PPL",
    "gn:name":"M\u00e1ty\u00e1sdomb",
    "gn:population":0,
    "gn:timezone":"Europe/Budapest",
    "iso:country":"HU",
    "name:ces_x_preferred":[
        "M\u00e1ty\u00e1sdomb"
    ],
    "name:epo_x_preferred":[
        "M\u00e1ty\u00e1sdomb"
    ],
    "name:fas_x_preferred":[
        "\u0645\u0627\u06a9\u0627\u0634\u062f\u0648\u0645\u0628"
    ],
    "name:fra_x_preferred":[
        "M\u00e1ty\u00e1sdomb"
    ],
    "name:hun_x_preferred":[
        "M\u00e1ty\u00e1sdomb"
    ],
    "name:ita_x_preferred":[
        "M\u00e1ty\u00e1sdomb"
    ],
    "name:msa_x_preferred":[
        "M\u00e1ty\u00e1sdomb"
    ],
    "name:nld_x_preferred":[
        "M\u00e1ty\u00e1sdomb"
    ],
    "name:ron_x_preferred":[
        "M\u00e1ty\u00e1sdomb"
    ],
    "name:slk_x_preferred":[
        "M\u00e1ty\u00e1sdomb"
    ],
    "name:vie_x_preferred":[
        "M\u00e1ty\u00e1sdomb"
    ],
    "name:zho_x_preferred":[
        "\u9a6c\u8d3e\u4ec0\u4e1c\u5e03"
    ],
    "wof:name":"Matyasdomb",
    "wof:placetype":"locality"
},
  "geometry": {"coordinates":[18.34781,46.92219],"type":"Point"}
}