{
  "type": "Feature",
  "properties": {
    "gn:admin1_code":"4.0",
    "gn:asciiname":"Hernadkercs",
    "gn:country_code":"HU",
    "gn:dem":120,
    "gn:feature_class":"P",
    "gn:feature_code":"PPL",
    "gn:name":"Hern\u00e1dk\u00e9rcs",
    "gn:population":0,
    "gn:timezone":"Europe/Budapest",
    "iso:country":"HU",
    "name:und_x_variant":[
        "Hern\u00e1dk\u00e9rcs"
    ],
    "wof:name":"Hernadkercs",
    "wof:placetype":"locality"
},
  "geometry": {"coordinates":[21.05,48.25],"type":"Point"}
}