{
  "type": "Feature",
  "properties": {
    "gn:admin1_code":"4.0",
    "gn:asciiname":"Hernadkercs",
    "gn:country_code":"HU",
    "gn:dem":120,
    "gn:feature_class":"P",
    "gn:feature_code":"PPL",
    "gn:name":"Hern\u00e1dk\u00e9rcs",
    "gn:population":0,
    "gn:timezone":"Europe/Budapest",
    "iso:country":"HU",
    "name:deu_x_preferred":[
        "Hern\u00e1dk\u00e9rcs"
    ],
    "name:epo_x_preferred":[
        "Hern\u00e1dk\u00e9rcs"
    ],
    "name:fas_x_preferred":[
        "\u0647\u0631\u0646\u0627\u062f\u06a9\u0631\u0686"
    ],
    "name:fra_x_preferred":[
        "Hern\u00e1dk\u00e9rcs"
    ],
    "name:heb_x_preferred":[
        "\u05d4\u05e8\u05e0\u05d0\u05d3\u05e7\u05e8\u05e5'"
    ],
    "name:hun_x_preferred":[
        "Hern\u00e1dk\u00e9rcs"
    ],
    "name:ita_x_preferred":[
        "Hern\u00e1dk\u00e9rcs"
    ],
    "name:msa_x_preferred":[
        "Hern\u00e1dk\u00e9rcs"
    ],
    "name:nld_x_preferred":[
        "Hern\u00e1dk\u00e9rcs"
    ],
    "name:pol_x_preferred":[
        "Hern\u00e1dk\u00e9rcs"
    ],
    "name:ron_x_preferred":[
        "Hern\u00e1dk\u00e9rcs"
    ],
    "name:slk_x_preferred":[
        "Hern\u00e1dk\u00e9rcs"
    ],
    "name:slv_x_preferred":[
        "Hern\u00e1dk\u00e9rcs"
    ],
    "name:und_x_variant":[
        "Hern\u00e1dk\u00e9rcs"
    ],
    "name:vie_x_preferred":[
        "Hern\u00e1dk\u00e9rcs"
    ],
    "name:zho_x_preferred":[
        "\u6d77\u5c14\u7eb3\u5fb7\u51ef\u5c14\u5947"
    ],
    "wof:name":"Hernadkercs",
    "wof:placetype":"locality"
},
  "geometry": {"coordinates":[21.05,48.25],"type":"Point"}
}