{
  "type": "Feature",
  "properties": {
    "gn:admin1_code":"4.0",
    "gn:asciiname":"Lacaitanya",
    "gn:country_code":"HU",
    "gn:dem":235,
    "gn:feature_class":"P",
    "gn:feature_code":"PPL",
    "gn:name":"L\u00e1caitanya",
    "gn:population":0,
    "gn:timezone":"Europe/Budapest",
    "iso:country":"HU",
    "wof:name":"Lacaitanya",
    "wof:placetype":"locality"
},
  "geometry": {"coordinates":[20.96667,48.35],"type":"Point"}
}