{
  "type": "Feature",
  "properties": {
    "gn:admin1_code":"17.0",
    "gn:asciiname":"Balatonmariafurdo",
    "gn:country_code":"HU",
    "gn:dem":108,
    "gn:feature_class":"P",
    "gn:feature_code":"PPL",
    "gn:name":"Balatonm\u00e1riaf\u00fcrd\u0151",
    "gn:population":0,
    "gn:timezone":"Europe/Budapest",
    "iso:country":"HU",
    "name:aze_x_preferred":[
        "Balatonmariyaf\u00fcrd\u00f6"
    ],
    "name:ces_x_preferred":[
        "Balatonm\u00e1riaf\u00fcrd\u0151"
    ],
    "name:deu_x_preferred":[
        "Balatonm\u00e1riaf\u00fcrd\u0151"
    ],
    "name:epo_x_preferred":[
        "Balatonm\u00e1riaf\u00fcrd\u0151"
    ],
    "name:fas_x_preferred":[
        "\u0628\u0627\u0644\u0627\u062a\u0648\u0646\u0645\u0627\u0631\u06cc\u0627\u0641\u0648\u0631\u062f\u0648"
    ],
    "name:fra_x_preferred":[
        "Balatonm\u00e1riaf\u00fcrd\u0151"
    ],
    "name:hun_x_preferred":[
        "Balatonm\u00e1riaf\u00fcrd\u0151"
    ],
    "name:ita_x_preferred":[
        "Balatonm\u00e1riaf\u00fcrd\u0151"
    ],
    "name:msa_x_preferred":[
        "Balatonm\u00e1riaf\u00fcrd\u0151"
    ],
    "name:nld_x_preferred":[
        "Balatonm\u00e1riaf\u00fcrd\u0151"
    ],
    "name:ron_x_preferred":[
        "Balatonm\u00e1riaf\u00fcrd\u0151"
    ],
    "name:slk_x_preferred":[
        "Balatonm\u00e1riaf\u00fcrd\u0151"
    ],
    "name:slv_x_preferred":[
        "Balatonm\u00e1riaf\u00fcrd\u0151"
    ],
    "name:vie_x_preferred":[
        "Balatonm\u00e1riaf\u00fcrd\u0151"
    ],
    "name:zho_x_preferred":[
        "\u9c8d\u6d1b\u901a\u9a6c\u91cc\u5965\u83f2\u5c14\u5fb7"
    ],
    "wof:name":"Balatonmariafurdo",
    "wof:placetype":"locality"
},
  "geometry": {"coordinates":[17.37072,46.70559],"type":"Point"}
}