{
  "type": "Feature",
  "properties": {
    "gn:admin1_code":"2.0",
    "gn:asciiname":"Alsokanda",
    "gn:country_code":"HU",
    "gn:dem":85,
    "gn:feature_class":"P",
    "gn:feature_code":"PPL",
    "gn:name":"Als\u00f3kanda",
    "gn:population":0,
    "gn:timezone":"Europe/Budapest",
    "iso:country":"HU",
    "wof:name":"Alsokanda",
    "wof:placetype":"locality"
},
  "geometry": {"coordinates":[18.68333,45.98333],"type":"Point"}
}