{
  "type": "Feature",
  "properties": {
    "gn:admin1_code":"17.0",
    "gn:asciiname":"Inkelepled",
    "gn:country_code":"HU",
    "gn:dem":161,
    "gn:feature_class":"P",
    "gn:feature_code":"PPL",
    "gn:name":"Inkelepled",
    "gn:population":0,
    "gn:timezone":"Europe/Budapest",
    "iso:country":"HU",
    "wof:name":"Inkelepled",
    "wof:placetype":"locality"
},
  "geometry": {"coordinates":[17.2769,46.35817],"type":"Point"}
}