{
  "type": "Feature",
  "properties": {
    "gn:admin1_code":"2.0",
    "gn:asciiname":"Szaszvari Tanyak",
    "gn:country_code":"HU",
    "gn:dem":213,
    "gn:feature_class":"P",
    "gn:feature_code":"PPL",
    "gn:name":"Sz\u00e1szv\u00e1ri Tany\u00e1k",
    "gn:population":0,
    "gn:timezone":"Europe/Budapest",
    "iso:country":"HU",
    "wof:name":"Szaszvari Tanyak",
    "wof:placetype":"locality"
},
  "geometry": {"coordinates":[18.38333,46.26667],"type":"Point"}
}