{
  "type": "Feature",
  "properties": {
    "gn:country":"HU",
    "gn:fcode":"PPL",
    "gn:population":0,
    "iso:country":"HU",
    "name:ceb_x_preferred":[
        "Martf\u0171"
    ],
    "name:ces_x_preferred":[
        "Martf\u0171"
    ],
    "name:deu_x_preferred":[
        "Martf\u0171"
    ],
    "name:eng_x_preferred":[
        "Martf\u0171"
    ],
    "name:epo_x_preferred":[
        "Martf\u0171"
    ],
    "name:est_x_preferred":[
        "Martf\u0171"
    ],
    "name:fas_x_preferred":[
        "\u0645\u0627\u0631\u062a\u0641\u0648"
    ],
    "name:fra_x_preferred":[
        "Martf\u0171"
    ],
    "name:gle_x_preferred":[
        "Martf\u0171"
    ],
    "name:hun_x_preferred":[
        "Martf\u0171"
    ],
    "name:ita_x_preferred":[
        "Martf\u0171"
    ],
    "name:msa_x_preferred":[
        "Martf\u0171"
    ],
    "name:nan_x_preferred":[
        "Martf\u0171"
    ],
    "name:nld_x_preferred":[
        "Martf\u0171"
    ],
    "name:pol_x_preferred":[
        "Martf\u0171"
    ],
    "name:por_x_preferred":[
        "Martf\u0171"
    ],
    "name:ron_x_preferred":[
        "Martf\u0171"
    ],
    "name:rup_x_preferred":[
        "Martf\u0171"
    ],
    "name:slk_x_preferred":[
        "Martf\u0171"
    ],
    "name:slv_x_preferred":[
        "Martf\u0171"
    ],
    "name:srp_x_preferred":[
        "\u041c\u0430\u0440\u0442\u0444\u0438"
    ],
    "name:swe_x_preferred":[
        "Martf\u0171"
    ],
    "name:vie_x_preferred":[
        "Martf\u0171"
    ],
    "name:zho_x_preferred":[
        "\u6bdb\u723e\u7279\u83f2"
    ],
    "qs_pg:aaroncc":"HU",
    "qs_pg:gn_country":"HU",
    "qs_pg:gn_fcode":"PPL",
    "qs_pg:gn_pop":0,
    "qs_pg:name":"Martf\u016f",
    "qs_pg:name_adm0":"Magyarorsz\u00e1g",
    "qs_pg:name_adm1":"J\u00e1sz-Nagykun-Szolnok",
    "qs_pg:photos":32,
    "qs_pg:photos_1k":6,
    "qs_pg:photos_9k":1,
    "qs_pg:photos_9r":2,
    "qs_pg:photos_all":32,
    "qs_pg:photos_sr":2,
    "qs_pg:pop_sr":0,
    "qs_pg:qs_pg_placetype":"locality",
    "qs_pg:qs_pg_placetype_gp":"Town",
    "qs_pg:woe_adm0":23424844,
    "woe:adm0_id":23424844,
    "woe:name_adm0":"Magyarorsz\u00e1g",
    "woe:name_adm1":"J\u00e1sz-Nagykun-Szolnok",
    "woe:placetype":"Town",
    "wof:name":"Martf\u016f",
    "wof:placetype":"locality"
},
  "geometry": {"coordinates":[20.28333,47.01667],"type":"Point"}
}