{
  "type": "Feature",
  "properties": {
    "gn:admin1_code":"17.0",
    "gn:asciiname":"Gadacs",
    "gn:country_code":"HU",
    "gn:dem":177,
    "gn:feature_class":"P",
    "gn:feature_code":"PPL",
    "gn:name":"Gad\u00e1cs",
    "gn:population":0,
    "gn:timezone":"Europe/Budapest",
    "iso:country":"HU",
    "name:deu_x_preferred":[
        "Gad\u00e1cs"
    ],
    "name:epo_x_preferred":[
        "Gad\u00e1cs"
    ],
    "name:fas_x_preferred":[
        "\u06af\u0627\u062f\u0627\u0686"
    ],
    "name:fra_x_preferred":[
        "Gad\u00e1cs"
    ],
    "name:hun_x_preferred":[
        "Gad\u00e1cs"
    ],
    "name:ita_x_preferred":[
        "Gad\u00e1cs"
    ],
    "name:msa_x_preferred":[
        "Gad\u00e1cs"
    ],
    "name:nld_x_preferred":[
        "Gad\u00e1cs"
    ],
    "name:ron_x_preferred":[
        "Gad\u00e1cs"
    ],
    "name:slk_x_preferred":[
        "Gad\u00e1cs"
    ],
    "name:slv_x_preferred":[
        "Gad\u00e1cs"
    ],
    "name:und_x_variant":[
        "Gad\u00e1cs"
    ],
    "name:vie_x_preferred":[
        "Gad\u00e1cs"
    ],
    "name:zho_x_preferred":[
        "\u9ad8\u8fbe\u5947"
    ],
    "wof:name":"Gadacs",
    "wof:placetype":"locality"
},
  "geometry": {"coordinates":[18.00505,46.53971],"type":"Point"}
}