{
  "type": "Feature",
  "properties": {
    "iso:country":"HU",
    "name:hun_x_preferred":[
        "B\u00e9k\u00e1smegyer"
    ],
    "wof:name":"Bekasmegyer",
    "wof:placetype":"neighbourhood"
},
  "geometry": {"coordinates":[19.05084811018434,47.60207819595562],"type":"Point"}
}