{
  "type": "Feature",
  "properties": {
    "gn:admin1_code":"22.0",
    "gn:asciiname":"Tomord",
    "gn:country_code":"HU",
    "gn:dem":221,
    "gn:feature_class":"P",
    "gn:feature_code":"PPL",
    "gn:name":"T\u00f6m\u00f6rd",
    "gn:population":0,
    "gn:timezone":"Europe/Budapest",
    "iso:country":"HU",
    "name:epo_x_preferred":[
        "T\u00f6m\u00f6rd"
    ],
    "name:fas_x_preferred":[
        "\u062a\u0648\u0645\u0648\u0631\u062f"
    ],
    "name:fra_x_preferred":[
        "T\u00f6m\u00f6rd"
    ],
    "name:hrv_x_preferred":[
        "Temerje"
    ],
    "name:hun_x_preferred":[
        "Tomord"
    ],
    "name:hun_x_variant":[
        "T\u00f6m\u00f6rd"
    ],
    "name:ita_x_preferred":[
        "T\u00f6m\u00f6rd"
    ],
    "name:msa_x_preferred":[
        "T\u00f6m\u00f6rd"
    ],
    "name:nld_x_preferred":[
        "T\u00f6m\u00f6rd"
    ],
    "name:pol_x_preferred":[
        "T\u00f6m\u00f6rd"
    ],
    "name:ron_x_preferred":[
        "T\u00f6m\u00f6rd"
    ],
    "name:slk_x_preferred":[
        "T\u00f6m\u00f6rd"
    ],
    "name:slv_x_preferred":[
        "T\u00f6m\u00f6rd"
    ],
    "name:und_x_variant":[
        "T\u00f6m\u00f6rd"
    ],
    "name:vie_x_preferred":[
        "T\u00f6m\u00f6rd"
    ],
    "name:zho_x_preferred":[
        "\u7279\u9ed8\u5c14\u5fb7"
    ],
    "wof:name":"Tomord",
    "wof:placetype":"locality"
},
  "geometry": {"coordinates":[16.67572,47.36372],"type":"Point"}
}