{
  "type": "Feature",
  "properties": {
    "gn:admin1_code":"22.0",
    "gn:asciiname":"Tomord",
    "gn:country_code":"HU",
    "gn:dem":221,
    "gn:feature_class":"P",
    "gn:feature_code":"PPL",
    "gn:name":"T\u00f6m\u00f6rd",
    "gn:population":0,
    "gn:timezone":"Europe/Budapest",
    "iso:country":"HU",
    "name:hrv_x_preferred":[
        "Temerje"
    ],
    "name:hun_x_preferred":[
        "Tomord"
    ],
    "name:und_x_variant":[
        "T\u00f6m\u00f6rd"
    ],
    "wof:name":"Tomord",
    "wof:placetype":"locality"
},
  "geometry": {"coordinates":[16.67572,47.36372],"type":"Point"}
}