{
  "type": "Feature",
  "properties": {
    "gn:admin1_code":"17.0",
    "gn:asciiname":"Kisasszond",
    "gn:country_code":"HU",
    "gn:dem":173,
    "gn:feature_class":"P",
    "gn:feature_code":"PPL",
    "gn:name":"Kisasszond",
    "gn:population":0,
    "gn:timezone":"Europe/Budapest",
    "iso:country":"HU",
    "wof:name":"Kisasszond",
    "wof:placetype":"locality"
},
  "geometry": {"coordinates":[17.63459,46.33225],"type":"Point"}
}