{
  "type": "Feature",
  "properties": {
    "gn:admin1_code":"17.0",
    "gn:asciiname":"Kisasszond",
    "gn:country_code":"HU",
    "gn:dem":173,
    "gn:feature_class":"P",
    "gn:feature_code":"PPL",
    "gn:name":"Kisasszond",
    "gn:population":0,
    "gn:timezone":"Europe/Budapest",
    "iso:country":"HU",
    "name:epo_x_preferred":[
        "Kisasszond"
    ],
    "name:fas_x_preferred":[
        "\u06a9\u06cc\u0634\u0627\u0634\u0633\u0648\u0646\u062f"
    ],
    "name:fra_x_preferred":[
        "Kisasszond"
    ],
    "name:hun_x_preferred":[
        "Kisasszond"
    ],
    "name:ita_x_preferred":[
        "Kisasszond"
    ],
    "name:msa_x_preferred":[
        "Kisasszond"
    ],
    "name:nld_x_preferred":[
        "Kisasszond"
    ],
    "name:ron_x_preferred":[
        "Kisasszond"
    ],
    "name:slk_x_preferred":[
        "Kisasszond"
    ],
    "name:slv_x_preferred":[
        "Kisasszond"
    ],
    "name:vie_x_preferred":[
        "Kisasszond"
    ],
    "name:zho_x_preferred":[
        "\u57fa\u7ecd\u4ec0\u6d2a\u5fb7"
    ],
    "wof:name":"Kisasszond",
    "wof:placetype":"locality"
},
  "geometry": {"coordinates":[17.63459,46.33225],"type":"Point"}
}