{
  "type": "Feature",
  "properties": {
    "gn:admin1_code":"12.0",
    "gn:asciiname":"Thalypuszta",
    "gn:country_code":"HU",
    "gn:dem":114,
    "gn:feature_class":"P",
    "gn:feature_code":"PPL",
    "gn:name":"Thalypuszta",
    "gn:population":0,
    "gn:timezone":"Europe/Budapest",
    "iso:country":"HU",
    "wof:name":"Thalypuszta",
    "wof:placetype":"locality"
},
  "geometry": {"coordinates":[18.094,47.72776],"type":"Point"}
}