{
  "type": "Feature",
  "properties": {
    "gn:admin1_code":"23.0",
    "gn:asciiname":"Laszlomajor",
    "gn:country_code":"HU",
    "gn:dem":327,
    "gn:feature_class":"P",
    "gn:feature_code":"PPL",
    "gn:name":"L\u00e1szl\u00f3major",
    "gn:population":0,
    "gn:timezone":"Europe/Budapest",
    "iso:country":"HU",
    "wof:name":"Laszlomajor",
    "wof:placetype":"locality"
},
  "geometry": {"coordinates":[17.91667,47.05],"type":"Point"}
}