{
  "type": "Feature",
  "properties": {
    "gn:admin1_code":"20.0",
    "gn:asciiname":"Nagyrev",
    "gn:country_code":"HU",
    "gn:dem":85,
    "gn:feature_class":"P",
    "gn:feature_code":"PPL",
    "gn:name":"Nagyr\u00e9v",
    "gn:population":0,
    "gn:timezone":"Europe/Budapest",
    "iso:country":"HU",
    "name:deu_x_preferred":[
        "Nagyr\u00e9v"
    ],
    "name:epo_x_preferred":[
        "Nagyr\u00e9v"
    ],
    "name:fas_x_preferred":[
        "\u0646\u0627\u06af\u06cc\u0631\u0648"
    ],
    "name:fra_x_preferred":[
        "Nagyr\u00e9v"
    ],
    "name:hun_x_preferred":[
        "Nagyr\u00e9v"
    ],
    "name:ita_x_preferred":[
        "Nagyr\u00e9v"
    ],
    "name:msa_x_preferred":[
        "Nagyr\u00e9v"
    ],
    "name:nld_x_preferred":[
        "Nagyr\u00e9v"
    ],
    "name:ron_x_preferred":[
        "Nagyr\u00e9v"
    ],
    "name:slk_x_preferred":[
        "Nagyr\u00e9v"
    ],
    "name:slv_x_preferred":[
        "Nagyr\u00e9v"
    ],
    "name:und_x_variant":[
        "Nagyr\u00e9v"
    ],
    "name:vie_x_preferred":[
        "Nagyr\u00e9v"
    ],
    "name:zho_x_preferred":[
        "\u5927\u96f7\u592b"
    ],
    "wof:name":"Nagyrev",
    "wof:placetype":"locality"
},
  "geometry": {"coordinates":[20.14322,46.94581],"type":"Point"}
}