{
  "type": "Feature",
  "properties": {
    "gn:admin1_code":"20.0",
    "gn:asciiname":"Nagyrev",
    "gn:country_code":"HU",
    "gn:dem":85,
    "gn:feature_class":"P",
    "gn:feature_code":"PPL",
    "gn:name":"Nagyr\u00e9v",
    "gn:population":0,
    "gn:timezone":"Europe/Budapest",
    "iso:country":"HU",
    "name:und_x_variant":[
        "Nagyr\u00e9v"
    ],
    "wof:name":"Nagyrev",
    "wof:placetype":"locality"
},
  "geometry": {"coordinates":[20.14322,46.94581],"type":"Point"}
}