{
  "type": "Feature",
  "properties": {
    "gn:admin1_code":"22.0",
    "gn:asciiname":"Sopte",
    "gn:country_code":"HU",
    "gn:dem":221,
    "gn:feature_class":"P",
    "gn:feature_code":"PPL",
    "gn:name":"S\u00f6pte",
    "gn:population":0,
    "gn:timezone":"Europe/Budapest",
    "iso:country":"HU",
    "name:und_x_variant":[
        "S\u00f6pte"
    ],
    "wof:name":"Sopte",
    "wof:placetype":"locality"
},
  "geometry": {"coordinates":[16.65153,47.28628],"type":"Point"}
}