{
  "type": "Feature",
  "properties": {
    "gn:admin1_code":"17.0",
    "gn:asciiname":"Visnye",
    "gn:country_code":"HU",
    "gn:dem":148,
    "gn:feature_class":"P",
    "gn:feature_code":"PPL",
    "gn:name":"Visnye",
    "gn:population":0,
    "gn:timezone":"Europe/Budapest",
    "iso:country":"HU",
    "name:epo_x_preferred":[
        "Visnye"
    ],
    "name:fas_x_preferred":[
        "\u0648\u06cc\u0634\u0646\u06cc\u0647"
    ],
    "name:fra_x_preferred":[
        "Visnye"
    ],
    "name:hun_x_preferred":[
        "Visnye"
    ],
    "name:ita_x_preferred":[
        "Visnye"
    ],
    "name:msa_x_preferred":[
        "Visnye"
    ],
    "name:nld_x_preferred":[
        "Visnye"
    ],
    "name:ron_x_preferred":[
        "Visnye"
    ],
    "name:slk_x_preferred":[
        "Visnye"
    ],
    "name:slv_x_preferred":[
        "Visnye"
    ],
    "name:vie_x_preferred":[
        "Visnye"
    ],
    "name:zho_x_preferred":[
        "\u7ef4\u4ec0\u6d85"
    ],
    "wof:name":"Visnye",
    "wof:placetype":"locality"
},
  "geometry": {"coordinates":[17.67628999999999,46.19106],"type":"Point"}
}