{
  "type": "Feature",
  "properties": {
    "gn:admin1_code":"17.0",
    "gn:asciiname":"Visnye",
    "gn:country_code":"HU",
    "gn:dem":148,
    "gn:feature_class":"P",
    "gn:feature_code":"PPL",
    "gn:name":"Visnye",
    "gn:population":0,
    "gn:timezone":"Europe/Budapest",
    "iso:country":"HU",
    "wof:name":"Visnye",
    "wof:placetype":"locality"
},
  "geometry": {"coordinates":[17.67628999999999,46.19106],"type":"Point"}
}