{
  "type": "Feature",
  "properties": {
    "gn:admin1_code":"1.0",
    "gn:asciiname":"Borsoshatpuszta",
    "gn:country_code":"HU",
    "gn:dem":89,
    "gn:feature_class":"P",
    "gn:feature_code":"PPL",
    "gn:name":"Borsosh\u00e1tpuszta",
    "gn:population":0,
    "gn:timezone":"Europe/Budapest",
    "iso:country":"HU",
    "name:und_x_variant":[
        "Borsosh\u00e1t",
        "Borsosh\u00e1tpuszta"
    ],
    "wof:name":"Borsoshatpuszta",
    "wof:placetype":"locality"
},
  "geometry": {"coordinates":[18.96296,46.36581],"type":"Point"}
}