{
  "type": "Feature",
  "properties": {
    "iso:country":"HU",
    "name:epo_x_preferred":[
        "\u021ae\u021bchea"
    ],
    "name:fra_x_preferred":[
        "\u021ae\u021bchea"
    ],
    "name:hbs_x_preferred":[
        "Op\u0161tina \u0162e\u0163chea"
    ],
    "name:hun_x_colloquial":[
        "Koalja",
        "Koaljai Dulo"
    ],
    "name:hun_x_preferred":[
        "K\u0151alja"
    ],
    "name:hun_x_variant":[
        "K\u0151aljai D\u016fl\u0151"
    ],
    "name:ita_x_preferred":[
        "\u021ae\u021bchea"
    ],
    "name:msa_x_preferred":[
        "\u0162e\u0163chea"
    ],
    "name:nld_x_preferred":[
        "\u021ae\u021bchea"
    ],
    "name:por_x_preferred":[
        "\u0162e\u0163chea"
    ],
    "name:ron_x_preferred":[
        "Comuna \u021ae\u021bchea"
    ],
    "name:sqi_x_preferred":[
        "\u0162e\u0163chea"
    ],
    "name:ukr_x_preferred":[
        "\u0426\u0435\u0446\u043a\u044f"
    ],
    "qs:gn_adm0_cc":"HU",
    "qs:gn_fcode":"PPLX",
    "qs:gn_local":3053163,
    "qs:gn_nam_loc":"Esztergom, Esztergom, Kom\u00e1rom-Esztergom, HU",
    "qs:gn_namadm1":"12",
    "qs:gn_name":"K\u0151alja",
    "qs:local_max":2348,
    "qs:local_sum":2390,
    "qs:localhoods":3,
    "qs:name":"K\u0151alja",
    "qs:name_adm0":"Magyarorsz\u00e1g",
    "qs:name_adm1":"Kom\u00e1rom-Esztergom",
    "qs:name_adm2":"Esztergom",
    "qs:name_local":"Esztergom",
    "qs:photo_max":383,
    "qs:photo_sum":2348,
    "qs:placetype":"Suburb",
    "qs:quad_count":94,
    "qs:woe_adm0":23424844,
    "qs:woe_adm1":12577921,
    "qs:woe_adm2":12593798,
    "qs:woe_lau":0,
    "qs:woe_local":806023,
    "qs:woe_ver":"7.10.0",
    "wof:lang":[
        "hun"
    ],
    "wof:name":"K\u0151alja",
    "wof:placetype":"neighbourhood"
},
  "geometry": {"coordinates":[18.739289,47.796731],"type":"Point"}
}