{
  "type": "Feature",
  "properties": {
    "gn:admin1_code":"11.0",
    "gn:asciiname":"Zamorszenegeto",
    "gn:country_code":"HU",
    "gn:dem":236,
    "gn:feature_class":"P",
    "gn:feature_code":"PPL",
    "gn:name":"Z\u00e1morsz\u00e9n\u00e9get\u0151",
    "gn:population":0,
    "gn:timezone":"Europe/Budapest",
    "iso:country":"HU",
    "wof:name":"Zamorszenegeto",
    "wof:placetype":"locality"
},
  "geometry": {"coordinates":[20.02125,48.05485],"type":"Point"}
}