{
  "type": "Feature",
  "properties": {
    "iso:country":"HU",
    "wof:name":"Csarnok negyed",
    "wof:placetype":"neighbourhood"
},
  "geometry": {"coordinates":[19.07492363041558,47.4925392836796],"type":"Point"}
}