{
  "type": "Feature",
  "properties": {
    "gn:admin1_code":"17.0",
    "gn:asciiname":"Kozepkolked",
    "gn:country_code":"HU",
    "gn:dem":145,
    "gn:feature_class":"P",
    "gn:feature_code":"PPL",
    "gn:name":"K\u00f6z\u00e9pk\u00f6lked",
    "gn:population":0,
    "gn:timezone":"Europe/Budapest",
    "iso:country":"HU",
    "wof:name":"Kozepkolked",
    "wof:placetype":"locality"
},
  "geometry": {"coordinates":[17.56667,46.53333],"type":"Point"}
}