{
  "type": "Feature",
  "properties": {
    "iso:country":"HU",
    "qs_pg:aaroncc":"HU",
    "qs_pg:name":"K\u00e1rolyh\u00e1zapuszta",
    "qs_pg:name_adm0":"Magyarorsz\u00e1g",
    "qs_pg:name_adm1":"Gy\u0151r-Moson-Sopron",
    "qs_pg:photos":53,
    "qs_pg:photos_1k":11,
    "qs_pg:photos_9k":1,
    "qs_pg:photos_9r":2,
    "qs_pg:photos_all":53,
    "qs_pg:photos_sr":2,
    "qs_pg:pop_sr":0,
    "qs_pg:qs_pg_placetype":"locality",
    "qs_pg:qs_pg_placetype_gp":"Town",
    "qs_pg:woe_adm0":23424844,
    "woe:adm0_id":23424844,
    "woe:name_adm0":"Magyarorsz\u00e1g",
    "woe:name_adm1":"Gy\u0151r-Moson-Sopron",
    "woe:placetype":"Town",
    "wof:name":"K\u00e1rolyh\u00e1zapuszta",
    "wof:placetype":"locality"
},
  "geometry": {"coordinates":[17.334022,47.804392],"type":"Point"}
}