{
  "type": "Feature",
  "properties": {
    "gn:admin1_code":"14.0",
    "gn:asciiname":"Nadastelep",
    "gn:country_code":"HU",
    "gn:dem":195,
    "gn:feature_class":"P",
    "gn:feature_code":"PPL",
    "gn:name":"N\u00e1dastelep",
    "gn:population":0,
    "gn:timezone":"Europe/Budapest",
    "iso:country":"HU",
    "wof:name":"Nadastelep",
    "wof:placetype":"locality"
},
  "geometry": {"coordinates":[19.56667,47.85],"type":"Point"}
}