{
  "type": "Feature",
  "properties": {
    "gn:admin1_code":"2.0",
    "gn:asciiname":"Szentimre Felsopuszta",
    "gn:country_code":"HU",
    "gn:dem":84,
    "gn:feature_class":"P",
    "gn:feature_code":"PPL",
    "gn:name":"Szentimre Fels\u0151puszta",
    "gn:population":0,
    "gn:timezone":"Europe/Budapest",
    "iso:country":"HU",
    "wof:name":"Szentimre Felsopuszta",
    "wof:placetype":"locality"
},
  "geometry": {"coordinates":[18.76667,46.08333],"type":"Point"}
}