{
  "type": "Feature",
  "properties": {
    "gn:admin1_code":"4.0",
    "gn:asciiname":"Haromhuta",
    "gn:country_code":"HU",
    "gn:dem":364,
    "gn:feature_class":"P",
    "gn:feature_code":"PPL",
    "gn:name":"H\u00e1romhuta",
    "gn:population":0,
    "gn:timezone":"Europe/Budapest",
    "iso:country":"HU",
    "name:und_x_variant":[
        "H\u00e1romhuta"
    ],
    "wof:name":"Haromhuta",
    "wof:placetype":"locality"
},
  "geometry": {"coordinates":[21.43333,48.38333],"type":"Point"}
}