{
  "type": "Feature",
  "properties": {
    "gn:admin1_code":"4.0",
    "gn:asciiname":"Haromhuta",
    "gn:country_code":"HU",
    "gn:dem":364,
    "gn:feature_class":"P",
    "gn:feature_code":"PPL",
    "gn:name":"H\u00e1romhuta",
    "gn:population":0,
    "gn:timezone":"Europe/Budapest",
    "iso:country":"HU",
    "name:deu_x_preferred":[
        "H\u00e1romhuta"
    ],
    "name:epo_x_preferred":[
        "H\u00e1romhuta"
    ],
    "name:fas_x_preferred":[
        "\u0647\u0627\u0631\u0648\u0645\u0647\u0648\u062a\u0627"
    ],
    "name:fra_x_preferred":[
        "H\u00e1romhuta"
    ],
    "name:heb_x_preferred":[
        "\u05d4\u05d0\u05e8\u05d5\u05de\u05d4\u05d5\u05d8\u05d4"
    ],
    "name:hun_x_preferred":[
        "H\u00e1romhuta"
    ],
    "name:ita_x_preferred":[
        "H\u00e1romhuta"
    ],
    "name:msa_x_preferred":[
        "H\u00e1romhuta"
    ],
    "name:nld_x_preferred":[
        "H\u00e1romhuta"
    ],
    "name:pol_x_preferred":[
        "H\u00e1romhuta"
    ],
    "name:ron_x_preferred":[
        "H\u00e1romhuta"
    ],
    "name:slk_x_preferred":[
        "H\u00e1romhuta"
    ],
    "name:slv_x_preferred":[
        "H\u00e1romhuta"
    ],
    "name:und_x_variant":[
        "H\u00e1romhuta"
    ],
    "name:vie_x_preferred":[
        "H\u00e1romhuta"
    ],
    "name:zho_x_preferred":[
        "\u54c8\u7f57\u59c6\u80e1\u9676"
    ],
    "wof:name":"Haromhuta",
    "wof:placetype":"locality"
},
  "geometry": {"coordinates":[21.43333,48.38333],"type":"Point"}
}