{
  "type": "Feature",
  "properties": {
    "gn:country":"HU",
    "gn:fcode":"PPL",
    "gn:population":0,
    "iso:country":"HU",
    "name:ast_x_preferred":[
        "B\u00e1nk"
    ],
    "name:cat_x_preferred":[
        "B\u00e1nk"
    ],
    "name:ces_x_preferred":[
        "B\u00e1nk"
    ],
    "name:deu_x_preferred":[
        "B\u00e1nk"
    ],
    "name:eng_x_preferred":[
        "B\u00e1nk"
    ],
    "name:epo_x_preferred":[
        "B\u00e1nk"
    ],
    "name:fra_x_preferred":[
        "B\u00e1nk"
    ],
    "name:gle_x_preferred":[
        "B\u00e1nk"
    ],
    "name:glg_x_preferred":[
        "B\u00e1nk"
    ],
    "name:heb_x_preferred":[
        "\u05d1\u05d0\u05e0\u05e7"
    ],
    "name:hun_x_preferred":[
        "B\u00e1nk"
    ],
    "name:ita_x_preferred":[
        "B\u00e1nk"
    ],
    "name:msa_x_preferred":[
        "B\u00e1nk"
    ],
    "name:nan_x_preferred":[
        "B\u00e1nk"
    ],
    "name:nld_x_preferred":[
        "B\u00e1nk"
    ],
    "name:pol_x_preferred":[
        "B\u00e1nk"
    ],
    "name:por_x_preferred":[
        "B\u00e1nk"
    ],
    "name:ron_x_preferred":[
        "B\u00e1nk"
    ],
    "name:slk_x_preferred":[
        "Banka"
    ],
    "name:slv_x_preferred":[
        "B\u00e1nk"
    ],
    "name:spa_x_preferred":[
        "B\u00e1nk"
    ],
    "name:vie_x_preferred":[
        "B\u00e1nk"
    ],
    "name:zho_x_preferred":[
        "\u73ed\u514b"
    ],
    "qs_pg:aaroncc":"HU",
    "qs_pg:gn_country":"HU",
    "qs_pg:gn_fcode":"PPL",
    "qs_pg:gn_pop":0,
    "qs_pg:name":"B\u00e1nk",
    "qs_pg:name_adm0":"Magyarorsz\u00e1g",
    "qs_pg:name_adm1":"N\u00f3gr\u00e1d",
    "qs_pg:photos":78,
    "qs_pg:photos_1k":16,
    "qs_pg:photos_9k":1,
    "qs_pg:photos_9r":3,
    "qs_pg:photos_all":78,
    "qs_pg:photos_sr":3,
    "qs_pg:pop_sr":0,
    "qs_pg:qs_pg_placetype":"locality",
    "qs_pg:qs_pg_placetype_gp":"Town",
    "qs_pg:woe_adm0":23424844,
    "woe:adm0_id":23424844,
    "woe:name_adm0":"Magyarorsz\u00e1g",
    "woe:name_adm1":"N\u00f3gr\u00e1d",
    "woe:placetype":"Town",
    "wof:name":"B\u00e1nk",
    "wof:placetype":"locality"
},
  "geometry": {"coordinates":[19.17356,47.92503],"type":"Point"}
}