{
  "type": "Feature",
  "properties": {
    "gn:admin1_code":"1.0",
    "gn:asciiname":"Bauertanya",
    "gn:country_code":"HU",
    "gn:dem":95,
    "gn:feature_class":"P",
    "gn:feature_code":"PPL",
    "gn:name":"Bauertanya",
    "gn:population":0,
    "gn:timezone":"Europe/Budapest",
    "iso:country":"HU",
    "wof:name":"Bauertanya",
    "wof:placetype":"locality"
},
  "geometry": {"coordinates":[18.98333,46.91667],"type":"Point"}
}