{
  "type": "Feature",
  "properties": {
    "gn:admin1_code":"2.0",
    "gn:asciiname":"Oregszollodulo",
    "gn:country_code":"HU",
    "gn:dem":248,
    "gn:feature_class":"P",
    "gn:feature_code":"PPL",
    "gn:name":"\u00d6regsz\u0151ll\u0151d\u0171l\u0151",
    "gn:population":0,
    "gn:timezone":"Europe/Budapest",
    "iso:country":"HU",
    "wof:name":"Oregszollodulo",
    "wof:placetype":"locality"
},
  "geometry": {"coordinates":[18.41667,46.16667],"type":"Point"}
}