{
  "type": "Feature",
  "properties": {
    "gn:gn_country":"HU",
    "gn:gn_fcode":"PPL",
    "gn:gn_pop":0,
    "iso:country":"HU",
    "name:deu_x_preferred":[
        "Ordacsehi"
    ],
    "name:eng_x_preferred":[
        "Ordacsehi"
    ],
    "name:epo_x_preferred":[
        "Ordacsehi"
    ],
    "name:fas_x_preferred":[
        "\u0627\u0648\u0631\u062f\u0627\u0686\u0647\u06cc"
    ],
    "name:fra_x_preferred":[
        "Ordacsehi"
    ],
    "name:hrv_x_preferred":[
        "\u010ceja"
    ],
    "name:hun_x_preferred":[
        "Ordacsehi"
    ],
    "name:ita_x_preferred":[
        "Ordacsehi"
    ],
    "name:msa_x_preferred":[
        "Ordacsehi"
    ],
    "name:nan_x_preferred":[
        "Ordacsehi"
    ],
    "name:nld_x_preferred":[
        "Ordacsehi"
    ],
    "name:ron_x_preferred":[
        "Ordacsehi"
    ],
    "name:slk_x_preferred":[
        "Ordacsehi"
    ],
    "name:slv_x_preferred":[
        "Ordacsehi"
    ],
    "name:vie_x_preferred":[
        "Ordacsehi"
    ],
    "name:zho_x_preferred":[
        "\u6b27\u5c14\u9053\u5207\u5e0c"
    ],
    "qs_pg:aaroncc":"HU",
    "qs_pg:gn_country":"HU",
    "qs_pg:gn_fcode":"PPL",
    "qs_pg:gn_pop":0,
    "qs_pg:name":"Ordacsehi",
    "qs_pg:name_adm0":"Magyarorsz\u00e1g",
    "qs_pg:name_adm1":"Somogy",
    "qs_pg:photos":39,
    "qs_pg:photos_1k":8,
    "qs_pg:photos_9k":1,
    "qs_pg:photos_9r":2,
    "qs_pg:photos_all":39,
    "qs_pg:photos_sr":2,
    "qs_pg:pop_sr":0,
    "qs_pg:qs_pg_placetype":"locality",
    "qs_pg:qs_pg_placetype_gp":"Town",
    "qs_pg:woe_adm0":23424844,
    "woe:adm0_id":23424844,
    "woe:name_adm0":"Magyarorsz\u00e1g",
    "woe:name_adm1":"Somogy",
    "woe:placetype":"Town",
    "wof:name":"Ordacsehi",
    "wof:placetype":"locality"
},
  "geometry": {"coordinates":[17.62355,46.74088],"type":"Point"}
}