{
  "type": "Feature",
  "properties": {
    "gn:country":"HU",
    "gn:fcode":"PPLX",
    "gn:population":0,
    "iso:country":"HU",
    "qs_pg:aaroncc":"HU",
    "qs_pg:gn_country":"HU",
    "qs_pg:gn_fcode":"PPLX",
    "qs_pg:gn_pop":0,
    "qs_pg:name":"Szolnokihegy",
    "qs_pg:name_adm0":"Magyarorsz\u00e1g",
    "qs_pg:name_adm1":"Kecskem\u00e9t",
    "qs_pg:photos":5,
    "qs_pg:photos_1k":1,
    "qs_pg:photos_9k":1,
    "qs_pg:photos_9r":1,
    "qs_pg:photos_all":5,
    "qs_pg:photos_sr":1,
    "qs_pg:pop_sr":0,
    "qs_pg:qs_pg_placetype":"neighbourhood",
    "qs_pg:qs_pg_placetype_gp":"Suburb",
    "qs_pg:woe_adm0":23424844,
    "woe:adm0_id":23424844,
    "woe:name_adm0":"Magyarorsz\u00e1g",
    "woe:name_adm1":"Kecskem\u00e9t",
    "woe:placetype":"Suburb",
    "wof:name":"Szolnokihegy",
    "wof:placetype":"neighbourhood"
},
  "geometry": {"coordinates":[19.72751,46.89808],"type":"Point"}
}