{
  "type": "Feature",
  "properties": {
    "gn:admin1_code":"1.0",
    "gn:asciiname":"Berke",
    "gn:country_code":"HU",
    "gn:dem":87,
    "gn:feature_class":"P",
    "gn:feature_code":"PPL",
    "gn:name":"Berke",
    "gn:population":0,
    "gn:timezone":"Europe/Budapest",
    "iso:country":"HU",
    "name:afr_x_preferred":[
        "Berke Khan"
    ],
    "name:ara_x_preferred":[
        "\u0628\u0631\u0643\u0629 \u062e\u0627\u0646"
    ],
    "name:azb_x_preferred":[
        "\u0628\u0631\u06a9\u0647\u200c\u062e\u0627\u0646"
    ],
    "name:aze_x_preferred":[
        "B\u0259rk\u0259 xan"
    ],
    "name:cat_x_preferred":[
        "B\u00f6rke"
    ],
    "name:deu_x_preferred":[
        "Berke Khan"
    ],
    "name:epo_x_preferred":[
        "Berke"
    ],
    "name:fin_x_preferred":[
        "Berke-kaani"
    ],
    "name:fra_x_preferred":[
        "Berk\u00e9"
    ],
    "name:glg_x_preferred":[
        "Berke"
    ],
    "name:hun_x_preferred":[
        "Berke k\u00e1n"
    ],
    "name:ind_x_preferred":[
        "Berke Khan"
    ],
    "name:ita_x_preferred":[
        "Berke"
    ],
    "name:jpn_x_preferred":[
        "\u30d9\u30eb\u30b1"
    ],
    "name:kat_x_preferred":[
        "\u10d1\u10d4\u10e0\u10e5\u10d0"
    ],
    "name:kaz_x_preferred":[
        "\u0411\u0435\u0440\u043a\u0435 \u0445\u0430\u043d"
    ],
    "name:kor_x_preferred":[
        "\ubca0\ub974\ucf00 \uce78"
    ],
    "name:mon_x_preferred":[
        "\u0411\u044d\u0440\u0445"
    ],
    "name:nld_x_preferred":[
        "Berke"
    ],
    "name:nor_x_preferred":[
        "Berke khan"
    ],
    "name:pol_x_preferred":[
        "Berke-chan"
    ],
    "name:por_x_preferred":[
        "Berke"
    ],
    "name:rus_x_preferred":[
        "\u0411\u0435\u0440\u043a\u0435"
    ],
    "name:slv_x_preferred":[
        "Berke"
    ],
    "name:srp_x_preferred":[
        "\u0411\u0435\u0440\u043a\u0435-\u043a\u0430\u043d"
    ],
    "name:tat_x_preferred":[
        "\u0411\u04d9\u0440\u043a\u04d9"
    ],
    "name:tur_x_preferred":[
        "Berke"
    ],
    "name:ukr_x_preferred":[
        "\u0411\u0435\u0440\u043a\u0435"
    ],
    "name:uzb_x_preferred":[
        "Berkaxon"
    ],
    "name:zho_x_preferred":[
        "\u522b\u513f\u54e5"
    ],
    "wof:name":"Berke",
    "wof:placetype":"locality"
},
  "geometry": {"coordinates":[19.03333,46.53333],"type":"Point"}
}