{
  "type": "Feature",
  "properties": {
    "gn:admin1_code":"9.0",
    "gn:asciiname":"Fertoboz",
    "gn:country_code":"HU",
    "gn:dem":120,
    "gn:feature_class":"P",
    "gn:feature_code":"PPL",
    "gn:name":"Fert\u0151boz",
    "gn:population":0,
    "gn:timezone":"Europe/Budapest",
    "iso:country":"HU",
    "name:deu_x_preferred":[
        "Holling"
    ],
    "name:hrv_x_preferred":[
        "Buza"
    ],
    "name:und_x_variant":[
        "Fert\u0151boz"
    ],
    "wof:name":"Fertoboz",
    "wof:placetype":"locality"
},
  "geometry": {"coordinates":[16.70085,47.63638],"type":"Point"}
}