{
  "type": "Feature",
  "properties": {
    "gn:admin1_code":"11.0",
    "gn:asciiname":"Tolgyestanya",
    "gn:country_code":"HU",
    "gn:dem":198,
    "gn:feature_class":"P",
    "gn:feature_code":"PPL",
    "gn:name":"T\u00f6lgyestanya",
    "gn:population":0,
    "gn:timezone":"Europe/Budapest",
    "iso:country":"HU",
    "wof:name":"Tolgyestanya",
    "wof:placetype":"locality"
},
  "geometry": {"coordinates":[20.18333,47.85],"type":"Point"}
}