{
  "type": "Feature",
  "properties": {
    "gn:admin1_code":"8.0",
    "gn:asciiname":"Csiribpuszta",
    "gn:country_code":"HU",
    "gn:dem":150,
    "gn:feature_class":"P",
    "gn:feature_code":"PPL",
    "gn:name":"Csiribpuszta",
    "gn:population":0,
    "gn:timezone":"Europe/Budapest",
    "iso:country":"HU",
    "name:und_x_variant":[
        "Csiribmajor",
        "Csiribpuszta"
    ],
    "wof:name":"Csiribpuszta",
    "wof:placetype":"locality"
},
  "geometry": {"coordinates":[18.63846,47.15823],"type":"Point"}
}