{
  "type": "Feature",
  "properties": {
    "gn:admin1_code":"24.0",
    "gn:asciiname":"Zalaujlak",
    "gn:country_code":"HU",
    "gn:dem":188,
    "gn:feature_class":"P",
    "gn:feature_code":"PPL",
    "gn:name":"Zala\u00fajlak",
    "gn:population":0,
    "gn:timezone":"Europe/Budapest",
    "iso:country":"HU",
    "name:und_x_variant":[
        "Zala\u00fajlak"
    ],
    "wof:name":"Zalaujlak",
    "wof:placetype":"locality"
},
  "geometry": {"coordinates":[17.07829,46.55998],"type":"Point"}
}