{
  "type": "Feature",
  "properties": {
    "gn:admin1_code":"24.0",
    "gn:asciiname":"Zalaujlak",
    "gn:country_code":"HU",
    "gn:dem":188,
    "gn:feature_class":"P",
    "gn:feature_code":"PPL",
    "gn:name":"Zala\u00fajlak",
    "gn:population":0,
    "gn:timezone":"Europe/Budapest",
    "iso:country":"HU",
    "name:deu_x_preferred":[
        "Zala\u00fajlak"
    ],
    "name:epo_x_preferred":[
        "Zala\u00fajlak"
    ],
    "name:fas_x_preferred":[
        "\u0632\u0627\u0644\u0627\u0648\u06cc\u0644\u0627\u06a9"
    ],
    "name:fra_x_preferred":[
        "Zala\u00fajlak"
    ],
    "name:hun_x_preferred":[
        "Zala\u00fajlak"
    ],
    "name:ita_x_preferred":[
        "Zala\u00fajlak"
    ],
    "name:msa_x_preferred":[
        "Zala\u00fajlak"
    ],
    "name:nld_x_preferred":[
        "Zala\u00fajlak"
    ],
    "name:ron_x_preferred":[
        "Zala\u00fajlak"
    ],
    "name:slk_x_preferred":[
        "Zala\u00fajlak"
    ],
    "name:slv_x_preferred":[
        "Zala\u00fajlak"
    ],
    "name:und_x_variant":[
        "Zala\u00fajlak"
    ],
    "name:vie_x_preferred":[
        "Zala\u00fajlak"
    ],
    "name:zho_x_preferred":[
        "\u4f50\u6d1b\u4e4c\u4f0a\u6d1b\u514b"
    ],
    "wof:name":"Zalaujlak",
    "wof:placetype":"locality"
},
  "geometry": {"coordinates":[17.07829,46.55998],"type":"Point"}
}