{
  "type": "Feature",
  "properties": {
    "gn:admin1_code":"8.0",
    "gn:asciiname":"Antoniamajor",
    "gn:country_code":"HU",
    "gn:dem":188,
    "gn:feature_class":"P",
    "gn:feature_code":"PPL",
    "gn:name":"Ant\u00f3niamajor",
    "gn:population":0,
    "gn:timezone":"Europe/Budapest",
    "iso:country":"HU",
    "wof:name":"Antoniamajor",
    "wof:placetype":"locality"
},
  "geometry": {"coordinates":[18.28248,47.11581],"type":"Point"}
}