{
  "type": "Feature",
  "properties": {
    "gn:admin1_code":"4.0",
    "gn:asciiname":"Bodrogolaszi",
    "gn:country_code":"HU",
    "gn:dem":98,
    "gn:feature_class":"P",
    "gn:feature_code":"PPL",
    "gn:name":"Bodrogolaszi",
    "gn:population":0,
    "gn:timezone":"Europe/Budapest",
    "iso:country":"HU",
    "name:deu_x_preferred":[
        "Bodrogolaszi"
    ],
    "name:epo_x_preferred":[
        "Bodrogolaszi"
    ],
    "name:fas_x_preferred":[
        "\u0628\u0648\u062f\u0631\u0648\u06af\u0648\u0644\u0627\u0633\u06cc"
    ],
    "name:fra_x_preferred":[
        "Bodrogolaszi"
    ],
    "name:heb_x_preferred":[
        "\u05d1\u05d5\u05d3\u05e8\u05d5\u05d2\u05d5\u05dc\u05e1\u05d9"
    ],
    "name:hun_x_preferred":[
        "Bodrogolaszi"
    ],
    "name:ita_x_preferred":[
        "Bodrogolaszi"
    ],
    "name:msa_x_preferred":[
        "Bodrogolaszi"
    ],
    "name:nld_x_preferred":[
        "Bodrogolaszi"
    ],
    "name:pol_x_preferred":[
        "Bodrogolaszi"
    ],
    "name:ron_x_preferred":[
        "Bodrogolaszi"
    ],
    "name:slk_x_preferred":[
        "Bodrogolaszi"
    ],
    "name:slv_x_preferred":[
        "Bodrogolaszi"
    ],
    "name:vie_x_preferred":[
        "Bodrogolaszi"
    ],
    "name:zho_x_preferred":[
        "\u535a\u5fb7\u7f57\u6208\u6d1b\u897f"
    ],
    "wof:name":"Bodrogolaszi",
    "wof:placetype":"locality"
},
  "geometry": {"coordinates":[21.51667,48.28333],"type":"Point"}
}