{
  "type": "Feature",
  "properties": {
    "gn:admin1_code":"20.0",
    "gn:asciiname":"Nyariastanya",
    "gn:country_code":"HU",
    "gn:dem":78,
    "gn:feature_class":"P",
    "gn:feature_code":"PPL",
    "gn:name":"Ny\u00e1riastanya",
    "gn:population":0,
    "gn:timezone":"Europe/Budapest",
    "iso:country":"HU",
    "wof:name":"Nyariastanya",
    "wof:placetype":"locality"
},
  "geometry": {"coordinates":[20.08333,46.81667],"type":"Point"}
}