{
  "type": "Feature",
  "properties": {
    "gn:admin1_code":"22.0",
    "gn:asciiname":"Peresznye",
    "gn:country_code":"HU",
    "gn:dem":214,
    "gn:feature_class":"P",
    "gn:feature_code":"PPL",
    "gn:name":"Peresznye",
    "gn:population":0,
    "gn:timezone":"Europe/Budapest",
    "iso:country":"HU",
    "name:deu_x_preferred":[
        "Pr\u00f6ssing"
    ],
    "name:hrv_x_preferred":[
        "Prisika"
    ],
    "name:hun_x_preferred":[
        "Peresznye"
    ],
    "wof:name":"Peresznye",
    "wof:placetype":"locality"
},
  "geometry": {"coordinates":[16.65114,47.42384000000001],"type":"Point"}
}