{
  "type": "Feature",
  "properties": {
    "gn:admin1_code":"10.0",
    "gn:asciiname":"Ujszolloskert",
    "gn:country_code":"HU",
    "gn:dem":100,
    "gn:feature_class":"P",
    "gn:feature_code":"PPL",
    "gn:name":"\u00dajsz\u0151ll\u0151skert",
    "gn:population":0,
    "gn:timezone":"Europe/Budapest",
    "iso:country":"HU",
    "wof:name":"Ujszolloskert",
    "wof:placetype":"locality"
},
  "geometry": {"coordinates":[21.83333,47.25],"type":"Point"}
}