{
  "type": "Feature",
  "properties": {
    "gn:gn_country":"HU",
    "gn:gn_fcode":"PPL",
    "gn:gn_pop":0,
    "iso:country":"HU",
    "name:deu_x_preferred":[
        "Bik\u00e1cs"
    ],
    "name:eng_x_preferred":[
        "Bik\u00e1cs"
    ],
    "name:epo_x_preferred":[
        "Bik\u00e1cs"
    ],
    "name:fas_x_preferred":[
        "\u0628\u06cc\u06a9\u0627\u0686"
    ],
    "name:fra_x_preferred":[
        "Bik\u00e1cs"
    ],
    "name:hun_x_preferred":[
        "Bik\u00e1cs"
    ],
    "name:ita_x_preferred":[
        "Bik\u00e1cs"
    ],
    "name:msa_x_preferred":[
        "Bik\u00e1cs"
    ],
    "name:nan_x_preferred":[
        "Bik\u00e1cs"
    ],
    "name:nld_x_preferred":[
        "Bik\u00e1cs"
    ],
    "name:ron_x_preferred":[
        "Bik\u00e1cs"
    ],
    "name:rus_x_preferred":[
        "\u0411\u0438\u043a\u0430\u0447"
    ],
    "name:slk_x_preferred":[
        "Bik\u00e1cs"
    ],
    "name:slv_x_preferred":[
        "Bik\u00e1cs"
    ],
    "name:vie_x_preferred":[
        "Bik\u00e1cs"
    ],
    "name:zho_x_preferred":[
        "\u6bd4\u5361\u5947"
    ],
    "qs_pg:aaroncc":"HU",
    "qs_pg:gn_country":"HU",
    "qs_pg:gn_fcode":"PPL",
    "qs_pg:gn_pop":0,
    "qs_pg:name":"Bik\u00e1cs",
    "qs_pg:name_adm0":"Magyarorsz\u00e1g",
    "qs_pg:name_adm1":"Tolna",
    "qs_pg:photos":3,
    "qs_pg:photos_1k":1,
    "qs_pg:photos_9k":1,
    "qs_pg:photos_9r":1,
    "qs_pg:photos_all":3,
    "qs_pg:photos_sr":1,
    "qs_pg:pop_sr":0,
    "qs_pg:qs_pg_placetype":"locality",
    "qs_pg:qs_pg_placetype_gp":"Town",
    "qs_pg:woe_adm0":23424844,
    "woe:adm0_id":23424844,
    "woe:name_adm0":"Magyarorsz\u00e1g",
    "woe:name_adm1":"Tolna",
    "woe:placetype":"Town",
    "wof:name":"Bik\u00e1cs",
    "wof:placetype":"locality"
},
  "geometry": {"coordinates":[18.66723,46.67745],"type":"Point"}
}