{
  "type": "Feature",
  "properties": {
    "gn:admin1_code":"2.0",
    "gn:asciiname":"Egyhazasharaszti",
    "gn:country_code":"HU",
    "gn:dem":91,
    "gn:feature_class":"P",
    "gn:feature_code":"PPL",
    "gn:name":"Egyh\u00e1zasharaszti",
    "gn:population":0,
    "gn:timezone":"Europe/Budapest",
    "iso:country":"HU",
    "name:deu_x_preferred":[
        "Egyh\u00e1zasharaszti"
    ],
    "name:epo_x_preferred":[
        "Egyh\u00e1zasharaszti"
    ],
    "name:fas_x_preferred":[
        "\u0627\u06af\u06cc\u0647\u0627\u0632\u0627\u0634\u0647\u0627\u0631\u0627\u0633\u062a\u06cc"
    ],
    "name:fra_x_preferred":[
        "Egyh\u00e1zasharaszti"
    ],
    "name:hrv_x_preferred":[
        "Rastince"
    ],
    "name:hun_x_preferred":[
        "Egyh\u00e1zasharaszti"
    ],
    "name:ita_x_preferred":[
        "Egyh\u00e1zasharaszti"
    ],
    "name:msa_x_preferred":[
        "Egyh\u00e1zasharaszti"
    ],
    "name:nld_x_preferred":[
        "Egyh\u00e1zasharaszti"
    ],
    "name:pol_x_preferred":[
        "Egyh\u00e1zasharaszti"
    ],
    "name:ron_x_preferred":[
        "Egyh\u00e1zasharaszti"
    ],
    "name:slk_x_preferred":[
        "Egyh\u00e1zasharaszti"
    ],
    "name:slv_x_preferred":[
        "Egyh\u00e1zasharaszti"
    ],
    "name:vie_x_preferred":[
        "Egyh\u00e1zasharaszti"
    ],
    "name:zho_x_preferred":[
        "\u827e\u5409\u54c8\u4f50\u4ec0\u8c6a\u52b3\u65af\u8482"
    ],
    "wof:name":"Egyhazasharaszti",
    "wof:placetype":"locality"
},
  "geometry": {"coordinates":[18.33418,45.8104],"type":"Point"}
}