{
  "type": "Feature",
  "properties": {
    "gn:admin1_code":"10.0",
    "gn:asciiname":"Tiszagyulahaza",
    "gn:country_code":"HU",
    "gn:dem":88,
    "gn:feature_class":"P",
    "gn:feature_code":"PPL",
    "gn:name":"Tiszagyulah\u00e1za",
    "gn:population":0,
    "gn:timezone":"Europe/Budapest",
    "iso:country":"HU",
    "name:und_x_variant":[
        "Tiszagyulah\u00e1za"
    ],
    "wof:name":"Tiszagyulahaza",
    "wof:placetype":"locality"
},
  "geometry": {"coordinates":[21.15,47.95],"type":"Point"}
}