{
  "type": "Feature",
  "properties": {
    "gn:admin1_code":"10.0",
    "gn:asciiname":"Tiszagyulahaza",
    "gn:country_code":"HU",
    "gn:dem":88,
    "gn:feature_class":"P",
    "gn:feature_code":"PPL",
    "gn:name":"Tiszagyulah\u00e1za",
    "gn:population":0,
    "gn:timezone":"Europe/Budapest",
    "iso:country":"HU",
    "name:deu_x_preferred":[
        "Tiszagyulah\u00e1za"
    ],
    "name:epo_x_preferred":[
        "Tiszagyulah\u00e1za"
    ],
    "name:fas_x_preferred":[
        "\u062a\u06cc\u0633\u0627\u06af\u06cc\u0648\u0644\u0627\u0647\u0627\u0632\u0627"
    ],
    "name:fra_x_preferred":[
        "Tiszagyulah\u00e1za"
    ],
    "name:hun_x_preferred":[
        "Tiszagyulah\u00e1za"
    ],
    "name:ita_x_preferred":[
        "Tiszagyulah\u00e1za"
    ],
    "name:msa_x_preferred":[
        "Tiszagyulah\u00e1za"
    ],
    "name:nld_x_preferred":[
        "Tiszagyulah\u00e1za"
    ],
    "name:ron_x_preferred":[
        "Tiszagyulah\u00e1za"
    ],
    "name:slk_x_preferred":[
        "Tiszagyulah\u00e1za"
    ],
    "name:slv_x_preferred":[
        "Tiszagyulah\u00e1za"
    ],
    "name:vie_x_preferred":[
        "Tiszagyulah\u00e1za"
    ],
    "name:zho_x_preferred":[
        "\u8482\u7ecd\u4e45\u6d1b\u54c8\u4f50"
    ],
    "wof:name":"Tiszagyulahaza",
    "wof:placetype":"locality"
},
  "geometry": {"coordinates":[21.15,47.95],"type":"Point"}
}