{
  "type": "Feature",
  "properties": {
    "gn:admin1_code":"16.0",
    "gn:asciiname":"Gater",
    "gn:country_code":"HU",
    "gn:dem":113,
    "gn:feature_class":"P",
    "gn:feature_code":"PPL",
    "gn:name":"G\u00e1t\u00e9r",
    "gn:population":0,
    "gn:timezone":"Europe/Budapest",
    "iso:country":"HU",
    "wof:name":"Gater",
    "wof:placetype":"locality"
},
  "geometry": {"coordinates":[19.78333,47.03333],"type":"Point"}
}