{
  "type": "Feature",
  "properties": {
    "gn:admin1_code":"10.0",
    "gn:asciiname":"Hort",
    "gn:country_code":"HU",
    "gn:dem":85,
    "gn:feature_class":"P",
    "gn:feature_code":"PPL",
    "gn:name":"Hort",
    "gn:population":0,
    "gn:timezone":"Europe/Budapest",
    "iso:country":"HU",
    "name:ces_x_preferred":[
        "Hort"
    ],
    "name:deu_x_preferred":[
        "Hort"
    ],
    "name:fra_x_preferred":[
        "Hort"
    ],
    "name:nld_x_preferred":[
        "Hort"
    ],
    "name:rus_x_preferred":[
        "\u0425\u043e\u0440\u0442"
    ],
    "name:slk_x_preferred":[
        "Hort"
    ],
    "wof:name":"Hort",
    "wof:placetype":"locality"
},
  "geometry": {"coordinates":[21.28333,47.63333],"type":"Point"}
}