{
  "type": "Feature",
  "properties": {
    "gn:admin1_code":"1.0",
    "gn:asciiname":"Csanadfeheregyhaza",
    "gn:country_code":"HU",
    "gn:dem":94,
    "gn:feature_class":"P",
    "gn:feature_code":"PPL",
    "gn:name":"Csan\u00e1dfeh\u00e9regyh\u00e1za",
    "gn:population":0,
    "gn:timezone":"Europe/Budapest",
    "iso:country":"HU",
    "name:und_x_variant":[
        "Feh\u00e9regyh\u00e1za-puszta",
        "Csan\u00e1dfeh\u00e9regyh\u00e1za"
    ],
    "wof:name":"Csanadfeheregyhaza",
    "wof:placetype":"locality"
},
  "geometry": {"coordinates":[19.08836,46.91067],"type":"Point"}
}