{
  "type": "Feature",
  "properties": {
    "gn:admin1_code":"11.0",
    "gn:asciiname":"Detaly",
    "gn:country_code":"HU",
    "gn:dem":211,
    "gn:feature_class":"P",
    "gn:feature_code":"PPL",
    "gn:name":"Det\u00e1ly",
    "gn:population":0,
    "gn:timezone":"Europe/Budapest",
    "iso:country":"HU",
    "wof:name":"Detaly",
    "wof:placetype":"locality"
},
  "geometry": {"coordinates":[20.38333,47.93333],"type":"Point"}
}