{
  "type": "Feature",
  "properties": {
    "gn:admin1_code":"9.0",
    "gn:asciiname":"Sulysziget",
    "gn:country_code":"HU",
    "gn:dem":123,
    "gn:feature_class":"P",
    "gn:feature_code":"PPL",
    "gn:name":"S\u00fclysziget",
    "gn:population":0,
    "gn:timezone":"Europe/Budapest",
    "iso:country":"HU",
    "wof:name":"Sulysziget",
    "wof:placetype":"locality"
},
  "geometry": {"coordinates":[17.41667,47.91667],"type":"Point"}
}