{
  "type": "Feature",
  "properties": {
    "gn:admin1_code":"9.0",
    "gn:asciiname":"Kishazasidulo",
    "gn:country_code":"HU",
    "gn:dem":118,
    "gn:feature_class":"P",
    "gn:feature_code":"PPL",
    "gn:name":"Kish\u00e1zasid\u0171l\u0151",
    "gn:population":0,
    "gn:timezone":"Europe/Budapest",
    "iso:country":"HU",
    "wof:name":"Kishazasidulo",
    "wof:placetype":"locality"
},
  "geometry": {"coordinates":[17.25,47.61667],"type":"Point"}
}