{
  "type": "Feature",
  "properties": {
    "gn:admin1_code":"23.0",
    "gn:asciiname":"Hidegkut",
    "gn:country_code":"HU",
    "gn:dem":337,
    "gn:feature_class":"P",
    "gn:feature_code":"PPL",
    "gn:name":"Hidegk\u00fat",
    "gn:population":0,
    "gn:timezone":"Europe/Budapest",
    "iso:country":"HU",
    "name:und_x_variant":[
        "Hidegk\u00fat"
    ],
    "wof:name":"Hidegkut",
    "wof:placetype":"locality"
},
  "geometry": {"coordinates":[17.82959,47.00268],"type":"Point"}
}