{
  "type": "Feature",
  "properties": {
    "gn:admin1_code":"23.0",
    "gn:asciiname":"Hidegkut",
    "gn:country_code":"HU",
    "gn:dem":337,
    "gn:feature_class":"P",
    "gn:feature_code":"PPL",
    "gn:name":"Hidegk\u00fat",
    "gn:population":0,
    "gn:timezone":"Europe/Budapest",
    "iso:country":"HU",
    "name:epo_x_preferred":[
        "Hidegk\u00fat"
    ],
    "name:fas_x_preferred":[
        "\u0647\u06cc\u062f\u06af\u06a9\u0648\u062a"
    ],
    "name:fra_x_preferred":[
        "Hidegk\u00fat"
    ],
    "name:hun_x_preferred":[
        "Hidegk\u00fat"
    ],
    "name:ita_x_preferred":[
        "Hidegk\u00fat"
    ],
    "name:msa_x_preferred":[
        "Hidegk\u00fat"
    ],
    "name:nld_x_preferred":[
        "Hidegk\u00fat"
    ],
    "name:ron_x_preferred":[
        "Hidegk\u00fat"
    ],
    "name:slk_x_preferred":[
        "Hidegk\u00fat"
    ],
    "name:slv_x_preferred":[
        "Hidegk\u00fat"
    ],
    "name:und_x_variant":[
        "Hidegk\u00fat"
    ],
    "name:vie_x_preferred":[
        "Hidegk\u00fat"
    ],
    "name:zho_x_preferred":[
        "\u5e0c\u4ee3\u683c\u5e93\u7279"
    ],
    "wof:name":"Hidegkut",
    "wof:placetype":"locality"
},
  "geometry": {"coordinates":[17.82959,47.00268],"type":"Point"}
}