{
  "type": "Feature",
  "properties": {
    "gn:admin1_code":"18.0",
    "gn:asciiname":"Kisszekeres",
    "gn:country_code":"HU",
    "gn:dem":112,
    "gn:feature_class":"P",
    "gn:feature_code":"PPL",
    "gn:name":"Kisszekeres",
    "gn:population":0,
    "gn:timezone":"Europe/Budapest",
    "iso:country":"HU",
    "name:epo_x_preferred":[
        "Kisszekeres"
    ],
    "name:fas_x_preferred":[
        "\u06a9\u06cc\u0634\u0633\u06a9\u0631\u0634"
    ],
    "name:fra_x_preferred":[
        "Kisszekeres"
    ],
    "name:hun_x_preferred":[
        "Kisszekeres"
    ],
    "name:ita_x_preferred":[
        "Kisszekeres"
    ],
    "name:msa_x_preferred":[
        "Kisszekeres"
    ],
    "name:nld_x_preferred":[
        "Kisszekeres"
    ],
    "name:ron_x_preferred":[
        "Kisszekeres"
    ],
    "name:slk_x_preferred":[
        "Kisszekeres"
    ],
    "name:slv_x_preferred":[
        "Kisszekeres"
    ],
    "name:vie_x_preferred":[
        "Kisszekeres"
    ],
    "name:zho_x_preferred":[
        "\u57fa\u4ec0\u585e\u51ef\u8d56\u4ec0"
    ],
    "wof:name":"Kisszekeres",
    "wof:placetype":"locality"
},
  "geometry": {"coordinates":[22.63313,47.97337],"type":"Point"}
}