{
  "type": "Feature",
  "properties": {
    "gn:admin1_code":"18.0",
    "gn:asciiname":"Kisszekeres",
    "gn:country_code":"HU",
    "gn:dem":112,
    "gn:feature_class":"P",
    "gn:feature_code":"PPL",
    "gn:name":"Kisszekeres",
    "gn:population":0,
    "gn:timezone":"Europe/Budapest",
    "iso:country":"HU",
    "wof:name":"Kisszekeres",
    "wof:placetype":"locality"
},
  "geometry": {"coordinates":[22.63313,47.97337],"type":"Point"}
}