{
  "type": "Feature",
  "properties": {
    "gn:admin1_code":"22.0",
    "gn:asciiname":"Estemajor",
    "gn:country_code":"HU",
    "gn:dem":159,
    "gn:feature_class":"P",
    "gn:feature_code":"PPL",
    "gn:name":"Estemajor",
    "gn:population":0,
    "gn:timezone":"Europe/Budapest",
    "iso:country":"HU",
    "wof:name":"Estemajor",
    "wof:placetype":"locality"
},
  "geometry": {"coordinates":[16.88278,47.27548],"type":"Point"}
}