{
  "type": "Feature",
  "properties": {
    "gn:admin1_code":"24.0",
    "gn:asciiname":"Hervadtfa",
    "gn:country_code":"HU",
    "gn:dem":144,
    "gn:feature_class":"P",
    "gn:feature_code":"PPL",
    "gn:name":"Hervadtfa",
    "gn:population":0,
    "gn:timezone":"Europe/Budapest",
    "iso:country":"HU",
    "name:und_x_variant":[
        "Herbatfa",
        "Hervadtfa"
    ],
    "wof:name":"Hervadtfa",
    "wof:placetype":"locality"
},
  "geometry": {"coordinates":[16.96459,46.9747],"type":"Point"}
}