{
  "type": "Feature",
  "properties": {
    "gn:admin1_code":"18.0",
    "gn:asciiname":"Kiralytanya",
    "gn:country_code":"HU",
    "gn:dem":107,
    "gn:feature_class":"P",
    "gn:feature_code":"PPL",
    "gn:name":"Kir\u00e1lytanya",
    "gn:population":0,
    "gn:timezone":"Europe/Budapest",
    "iso:country":"HU",
    "wof:name":"Kiralytanya",
    "wof:placetype":"locality"
},
  "geometry": {"coordinates":[22.03333,48.11667],"type":"Point"}
}