{
  "type": "Feature",
  "properties": {
    "gn:admin1_code":"2.0",
    "gn:asciiname":"Dencshaza",
    "gn:country_code":"HU",
    "gn:dem":105,
    "gn:feature_class":"P",
    "gn:feature_code":"PPL",
    "gn:name":"Dencsh\u00e1za",
    "gn:population":0,
    "gn:timezone":"Europe/Budapest",
    "iso:country":"HU",
    "name:deu_x_preferred":[
        "Dencsh\u00e1za"
    ],
    "name:epo_x_preferred":[
        "Dencsh\u00e1za"
    ],
    "name:fas_x_preferred":[
        "\u062f\u0646\u0686\u0647\u0627\u0632\u0627"
    ],
    "name:fra_x_preferred":[
        "Dencsh\u00e1za"
    ],
    "name:hrv_x_preferred":[
        "Den\u010daz"
    ],
    "name:hun_x_preferred":[
        "Dencsh\u00e1za"
    ],
    "name:ita_x_preferred":[
        "Dencsh\u00e1za"
    ],
    "name:msa_x_preferred":[
        "Dencsh\u00e1za"
    ],
    "name:nld_x_preferred":[
        "Dencsh\u00e1za"
    ],
    "name:pol_x_preferred":[
        "Dencsh\u00e1za"
    ],
    "name:ron_x_preferred":[
        "Dencsh\u00e1za"
    ],
    "name:slk_x_preferred":[
        "Dencsh\u00e1za"
    ],
    "name:slv_x_preferred":[
        "Dencsh\u00e1za"
    ],
    "name:und_x_variant":[
        "Dencsh\u00e1za"
    ],
    "name:vie_x_preferred":[
        "Dencsh\u00e1za"
    ],
    "name:zho_x_preferred":[
        "\u767b\u5947\u54c8\u4f50"
    ],
    "wof:name":"Dencshaza",
    "wof:placetype":"locality"
},
  "geometry": {"coordinates":[17.83591000000001,45.993],"type":"Point"}
}