{
  "type": "Feature",
  "properties": {
    "gn:admin1_code":"2.0",
    "gn:asciiname":"Dencshaza",
    "gn:country_code":"HU",
    "gn:dem":105,
    "gn:feature_class":"P",
    "gn:feature_code":"PPL",
    "gn:name":"Dencsh\u00e1za",
    "gn:population":0,
    "gn:timezone":"Europe/Budapest",
    "iso:country":"HU",
    "name:und_x_variant":[
        "Dencsh\u00e1za"
    ],
    "wof:name":"Dencshaza",
    "wof:placetype":"locality"
},
  "geometry": {"coordinates":[17.83591000000001,45.993],"type":"Point"}
}