{
  "type": "Feature",
  "properties": {
    "gn:admin1_code":"12.0",
    "gn:asciiname":"Dag",
    "gn:country_code":"HU",
    "gn:dem":161,
    "gn:feature_class":"P",
    "gn:feature_code":"PPL",
    "gn:name":"D\u00e1g",
    "gn:population":0,
    "gn:timezone":"Europe/Budapest",
    "iso:country":"HU",
    "name:epo_x_preferred":[
        "D\u00e1g"
    ],
    "name:fas_x_preferred":[
        "\u062f\u0627\u06af"
    ],
    "name:fra_x_preferred":[
        "D\u00e1g"
    ],
    "name:hun_x_preferred":[
        "D\u00e1g"
    ],
    "name:ita_x_preferred":[
        "D\u00e1g"
    ],
    "name:msa_x_preferred":[
        "D\u00e1g"
    ],
    "name:nld_x_preferred":[
        "D\u00e1g"
    ],
    "name:ron_x_preferred":[
        "D\u00e1g"
    ],
    "name:slk_x_preferred":[
        "D\u00e1g"
    ],
    "name:slv_x_preferred":[
        "D\u00e1g"
    ],
    "name:und_x_variant":[
        "D\u00e1g"
    ],
    "name:vie_x_preferred":[
        "D\u00e1g"
    ],
    "wof:name":"Dag",
    "wof:placetype":"locality"
},
  "geometry": {"coordinates":[18.72049,47.66257],"type":"Point"}
}