{
  "type": "Feature",
  "properties": {
    "gn:admin1_code":"24.0",
    "gn:asciiname":"Pordefolde",
    "gn:country_code":"HU",
    "gn:dem":193,
    "gn:feature_class":"P",
    "gn:feature_code":"PPL",
    "gn:name":"P\u00f6rdef\u00f6lde",
    "gn:population":0,
    "gn:timezone":"Europe/Budapest",
    "iso:country":"HU",
    "name:und_x_variant":[
        "P\u00f6rdef\u00f6lde"
    ],
    "wof:name":"Pordefolde",
    "wof:placetype":"locality"
},
  "geometry": {"coordinates":[16.71052,46.58839],"type":"Point"}
}