{
  "type": "Feature",
  "properties": {
    "iso:country":"HU",
    "name:hun_x_preferred":[
        "Szent Imre-kertv\u00e1ros"
    ],
    "wof:name":"Szent Imre-kertvaros",
    "wof:placetype":"neighbourhood"
},
  "geometry": {"coordinates":[19.20604437815154,47.42762253524733],"type":"Point"}
}