{
  "type": "Feature",
  "properties": {
    "gn:admin1_code":"22.0",
    "gn:asciiname":"Olbo",
    "gn:country_code":"HU",
    "gn:dem":162,
    "gn:feature_class":"P",
    "gn:feature_code":"PPL",
    "gn:name":"\u00d6lb\u0151",
    "gn:population":0,
    "gn:timezone":"Europe/Budapest",
    "iso:country":"HU",
    "name:epo_x_preferred":[
        "\u00d6lb\u0151"
    ],
    "name:fas_x_preferred":[
        "\u0627\u0648\u0644\u0628\u0648"
    ],
    "name:fra_x_preferred":[
        "\u00d6lb\u0151"
    ],
    "name:hun_x_preferred":[
        "\u00d6lb\u0151"
    ],
    "name:ita_x_preferred":[
        "\u00d6lb\u0151"
    ],
    "name:msa_x_preferred":[
        "\u00d6lb\u0151"
    ],
    "name:nld_x_preferred":[
        "\u00d6lb\u0151"
    ],
    "name:ron_x_preferred":[
        "\u00d6lb\u0151"
    ],
    "name:slk_x_preferred":[
        "\u00d6lb\u0151"
    ],
    "name:slv_x_preferred":[
        "\u00d6lb\u0151"
    ],
    "name:vie_x_preferred":[
        "\u00d6lb\u0151"
    ],
    "name:zho_x_preferred":[
        "\u5384\u5c14\u4f2f"
    ],
    "wof:name":"Olbo",
    "wof:placetype":"locality"
},
  "geometry": {"coordinates":[16.86121,47.30109],"type":"Point"}
}