{
  "type": "Feature",
  "properties": {
    "gn:admin1_code":"22.0",
    "gn:asciiname":"Olbo",
    "gn:country_code":"HU",
    "gn:dem":162,
    "gn:feature_class":"P",
    "gn:feature_code":"PPL",
    "gn:name":"\u00d6lb\u0151",
    "gn:population":0,
    "gn:timezone":"Europe/Budapest",
    "iso:country":"HU",
    "name:und_x_variant":[
        "\u00d6lb\u0151"
    ],
    "wof:name":"Olbo",
    "wof:placetype":"locality"
},
  "geometry": {"coordinates":[16.86121,47.30109],"type":"Point"}
}