{
  "type": "Feature",
  "properties": {
    "iso:country":"HU",
    "name:hun_x_colloquial":[
        "Homokgyor"
    ],
    "name:hun_x_preferred":[
        "Homokgy\u0151r"
    ],
    "name:unk_x_variant":[
        "Homokgy\u0151r"
    ],
    "qs:gn_adm0_cc":"HU",
    "qs:gn_fcode":"PPLX",
    "qs:gn_local":3050719,
    "qs:gn_nam_loc":"Kalocsa, Kalocsa, B\u00e1cs-Kiskun, HU",
    "qs:gn_namadm1":"01",
    "qs:gn_name":"Homokgy\u0151r",
    "qs:local_max":54,
    "qs:local_sum":54,
    "qs:localhoods":1,
    "qs:name":"Homokgy\u0151r",
    "qs:name_adm0":"Magyarorsz\u00e1g",
    "qs:name_adm1":"B\u00e1cs-Kiskun",
    "qs:name_adm2":"Kalocsa",
    "qs:name_local":"Kalocsa",
    "qs:photo_max":26,
    "qs:photo_sum":54,
    "qs:placetype":"Suburb",
    "qs:quad_count":8,
    "qs:woe_adm0":23424844,
    "qs:woe_adm1":12577911,
    "qs:woe_adm2":12594310,
    "qs:woe_lau":0,
    "qs:woe_local":808850,
    "qs:woe_ver":"7.10.0",
    "wof:lang":[
        "hun"
    ],
    "wof:name":"Homokgy\u0151r",
    "wof:placetype":"neighbourhood"
},
  "geometry": {"coordinates":[18.975729,46.527654],"type":"Point"}
}