{
  "type": "Feature",
  "properties": {
    "gn:admin1_code":"3.0",
    "gn:asciiname":"Kunagotai Tanyak",
    "gn:country_code":"HU",
    "gn:dem":94,
    "gn:feature_class":"P",
    "gn:feature_code":"PPL",
    "gn:name":"Kun\u00e1gotai Tany\u00e1k",
    "gn:population":0,
    "gn:timezone":"Europe/Budapest",
    "iso:country":"HU",
    "wof:name":"Kunagotai Tanyak",
    "wof:placetype":"locality"
},
  "geometry": {"coordinates":[21.05,46.43333],"type":"Point"}
}