{
  "type": "Feature",
  "properties": {
    "gn:admin1_code":"6.0",
    "gn:asciiname":"Belsodulo",
    "gn:country_code":"HU",
    "gn:dem":79,
    "gn:feature_class":"P",
    "gn:feature_code":"PPL",
    "gn:name":"Bels\u0151d\u0171l\u0151",
    "gn:population":0,
    "gn:timezone":"Europe/Budapest",
    "iso:country":"HU",
    "wof:name":"Belsodulo",
    "wof:placetype":"locality"
},
  "geometry": {"coordinates":[20.46667,46.68333],"type":"Point"}
}