{
  "type": "Feature",
  "properties": {
    "gn:admin1_code":"23.0",
    "gn:asciiname":"Papakovacsi",
    "gn:country_code":"HU",
    "gn:dem":171,
    "gn:feature_class":"P",
    "gn:feature_code":"PPL",
    "gn:name":"P\u00e1pakov\u00e1csi",
    "gn:population":0,
    "gn:timezone":"Europe/Budapest",
    "iso:country":"HU",
    "name:ces_x_preferred":[
        "P\u00e1pakov\u00e1csi"
    ],
    "name:epo_x_preferred":[
        "P\u00e1pakov\u00e1csi"
    ],
    "name:fas_x_preferred":[
        "\u067e\u0627\u067e\u0627\u06a9\u0648\u0648\u0627\u0686\u06cc"
    ],
    "name:fra_x_preferred":[
        "P\u00e1pakov\u00e1csi"
    ],
    "name:hun_x_preferred":[
        "P\u00e1pakov\u00e1csi"
    ],
    "name:ita_x_preferred":[
        "P\u00e1pakov\u00e1csi"
    ],
    "name:msa_x_preferred":[
        "P\u00e1pakov\u00e1csi"
    ],
    "name:nld_x_preferred":[
        "P\u00e1pakov\u00e1csi"
    ],
    "name:ron_x_preferred":[
        "P\u00e1pakov\u00e1csi"
    ],
    "name:slk_x_preferred":[
        "P\u00e1pakov\u00e1csi"
    ],
    "name:slv_x_preferred":[
        "P\u00e1pakov\u00e1csi"
    ],
    "name:vie_x_preferred":[
        "P\u00e1pakov\u00e1csi"
    ],
    "name:zho_x_preferred":[
        "\u5e15\u4fdd\u79d1\u74e6\u5947"
    ],
    "wof:name":"Papakovacsi",
    "wof:placetype":"locality"
},
  "geometry": {"coordinates":[17.48772,47.26438],"type":"Point"}
}