{
  "type": "Feature",
  "properties": {
    "gn:admin1_code":"3.0",
    "gn:asciiname":"Szebegyinszkidulo",
    "gn:country_code":"HU",
    "gn:dem":81,
    "gn:feature_class":"P",
    "gn:feature_code":"PPL",
    "gn:name":"Szebegyinszkid\u0171l\u0151",
    "gn:population":0,
    "gn:timezone":"Europe/Budapest",
    "iso:country":"HU",
    "wof:name":"Szebegyinszkidulo",
    "wof:placetype":"locality"
},
  "geometry": {"coordinates":[20.78333,46.85],"type":"Point"}
}