{
  "type": "Feature",
  "properties": {
    "gn:admin1_code":"23.0",
    "gn:asciiname":"Dabrokaicsarda",
    "gn:country_code":"HU",
    "gn:dem":131,
    "gn:feature_class":"P",
    "gn:feature_code":"PPL",
    "gn:name":"Dabr\u00f3kaics\u00e1rda",
    "gn:population":0,
    "gn:timezone":"Europe/Budapest",
    "iso:country":"HU",
    "name:und_x_variant":[
        "Dabr\u00f3ka",
        "Dabr\u00f3kaics\u00e1rda"
    ],
    "wof:name":"Dabrokaicsarda",
    "wof:placetype":"locality"
},
  "geometry": {"coordinates":[17.21383,47.11983],"type":"Point"}
}