{
  "type": "Feature",
  "properties": {
    "iso:country":"HU",
    "name:deu_x_preferred":[
        "Paszab"
    ],
    "name:eng_x_preferred":[
        "Paszab"
    ],
    "name:epo_x_preferred":[
        "Paszab"
    ],
    "name:fra_x_preferred":[
        "Paszab"
    ],
    "name:hun_x_preferred":[
        "Paszab"
    ],
    "name:ita_x_preferred":[
        "Paszab"
    ],
    "name:msa_x_preferred":[
        "Paszab"
    ],
    "name:nan_x_preferred":[
        "Paszab"
    ],
    "name:nld_x_preferred":[
        "Paszab"
    ],
    "name:nno_x_preferred":[
        "Paszab"
    ],
    "name:ron_x_preferred":[
        "Paszab"
    ],
    "name:slk_x_preferred":[
        "Paszab"
    ],
    "name:slv_x_preferred":[
        "Paszab"
    ],
    "name:vie_x_preferred":[
        "Paszab"
    ],
    "name:zho_min_nan_x_preferred":[
        "Paszab"
    ],
    "name:zho_x_preferred":[
        "\u4fdd\u7ecd\u5e03"
    ],
    "qs:a0":"Magyarorsz\u00e1g",
    "qs:a1":"*Szabolcs-Szatm\u00e1r-Bereg",
    "qs:a1r":"0\u00c9szak-Alf\u00f6ld",
    "qs:adm0":"Magyarorsz\u00e1g",
    "qs:la_lc":"*",
    "qs:level":"locality",
    "qs:loc":"Paszab",
    "qs:loc_alt":"Paszab",
    "qs:pop":0,
    "qs:type":"buffered point",
    "wd:wordcount":72,
    "wof:lang":[
        "hun"
    ],
    "wof:name":"Paszab",
    "wof:placetype":"locality"
},
  "geometry": {"coordinates":[21.672437,48.14521],"type":"Point"}
}