{
  "type": "Feature",
  "properties": {
    "gn:admin1_code":"23.0",
    "gn:asciiname":"Csabberekpuszta",
    "gn:cc2":"HU",
    "gn:country_code":"HU",
    "gn:dem":278,
    "gn:feature_class":"P",
    "gn:feature_code":"PPL",
    "gn:name":"Csabberekpuszta",
    "gn:population":0,
    "gn:timezone":"Europe/Budapest",
    "iso:country":"HU",
    "name:und_x_variant":[
        "Csabberek",
        "Csabberekpuszta"
    ],
    "wof:name":"Csabberekpuszta",
    "wof:placetype":"locality"
},
  "geometry": {"coordinates":[17.81667000000001,47.11667],"type":"Point"}
}