{
  "type": "Feature",
  "properties": {
    "gn:admin1_code":"17.0",
    "gn:asciiname":"Nyim",
    "gn:country_code":"HU",
    "gn:dem":138,
    "gn:feature_class":"P",
    "gn:feature_code":"PPL",
    "gn:name":"Nyim",
    "gn:population":0,
    "gn:timezone":"Europe/Budapest",
    "iso:country":"HU",
    "name:epo_x_preferred":[
        "Nyim"
    ],
    "name:fas_x_preferred":[
        "\u0646\u06cc\u06cc\u0645"
    ],
    "name:fra_x_preferred":[
        "Nyim"
    ],
    "name:hun_x_preferred":[
        "Nyim"
    ],
    "name:ita_x_preferred":[
        "Nyim"
    ],
    "name:msa_x_preferred":[
        "Nyim"
    ],
    "name:nld_x_preferred":[
        "Nyim"
    ],
    "name:ron_x_preferred":[
        "Nyim"
    ],
    "name:slk_x_preferred":[
        "Nyim"
    ],
    "name:slv_x_preferred":[
        "Nyim"
    ],
    "name:swe_x_preferred":[
        "Nyim"
    ],
    "name:vie_x_preferred":[
        "Nyim"
    ],
    "name:zho_x_preferred":[
        "\u5c3c\u59c6"
    ],
    "wof:name":"Nyim",
    "wof:placetype":"locality"
},
  "geometry": {"coordinates":[18.10904,46.80405],"type":"Point"}
}