{
  "type": "Feature",
  "properties": {
    "gn:admin1_code":"10.0",
    "gn:asciiname":"Csereerdo",
    "gn:country_code":"HU",
    "gn:dem":151,
    "gn:feature_class":"P",
    "gn:feature_code":"PPL",
    "gn:name":"Csereerd\u0151",
    "gn:population":0,
    "gn:timezone":"Europe/Budapest",
    "iso:country":"HU",
    "wof:name":"Csereerdo",
    "wof:placetype":"locality"
},
  "geometry": {"coordinates":[21.65,47.65],"type":"Point"}
}