{
  "type": "Feature",
  "properties": {
    "gn:admin1_code":"18.0",
    "gn:asciiname":"Szallasfold",
    "gn:country_code":"HU",
    "gn:dem":143,
    "gn:feature_class":"P",
    "gn:feature_code":"PPL",
    "gn:name":"Sz\u00e1ll\u00e1sf\u00f6ld",
    "gn:population":0,
    "gn:timezone":"Europe/Budapest",
    "iso:country":"HU",
    "wof:name":"Szallasfold",
    "wof:placetype":"locality"
},
  "geometry": {"coordinates":[21.78572,47.7078],"type":"Point"}
}