{
  "type": "Feature",
  "properties": {
    "gn:admin1_code":"4.0",
    "gn:asciiname":"Dobostanya",
    "gn:country_code":"HU",
    "gn:dem":179,
    "gn:feature_class":"P",
    "gn:feature_code":"PPL",
    "gn:name":"Dobostanya",
    "gn:population":0,
    "gn:timezone":"Europe/Budapest",
    "iso:country":"HU",
    "wof:name":"Dobostanya",
    "wof:placetype":"locality"
},
  "geometry": {"coordinates":[20.23333,48.23333],"type":"Point"}
}