{
  "type": "Feature",
  "properties": {
    "gn:admin1_code":"17.0",
    "gn:asciiname":"Belahazapuszta",
    "gn:country_code":"HU",
    "gn:dem":133,
    "gn:feature_class":"P",
    "gn:feature_code":"PPL",
    "gn:name":"B\u00e9lah\u00e1zapuszta",
    "gn:population":0,
    "gn:timezone":"Europe/Budapest",
    "iso:country":"HU",
    "wof:name":"Belahazapuszta",
    "wof:placetype":"locality"
},
  "geometry": {"coordinates":[17.41667,46.28333],"type":"Point"}
}