{
  "type": "Feature",
  "properties": {
    "iso:country":"HU",
    "name:hun_x_preferred":[
        "Krepuska G\u00e9za-telep"
    ],
    "wof:name":"Krepuska Geza-telep",
    "wof:placetype":"neighbourhood"
},
  "geometry": {"coordinates":[19.20501440937159,47.41291035192496],"type":"Point"}
}