{
  "type": "Feature",
  "properties": {
    "iso:country":"HU",
    "name:hun_x_preferred":[
        "Erzs\u00e9betfalva"
    ],
    "wof:name":"Erzsebetfalva",
    "wof:placetype":"neighbourhood"
},
  "geometry": {"coordinates":[19.10894121039767,47.44256280723641],"type":"Point"}
}