{
  "type": "Feature",
  "properties": {
    "gn:admin1_code":"18.0",
    "gn:asciiname":"Mand",
    "gn:country_code":"HU",
    "gn:dem":111,
    "gn:feature_class":"P",
    "gn:feature_code":"PPL",
    "gn:name":"M\u00e1nd",
    "gn:population":0,
    "gn:timezone":"Europe/Budapest",
    "iso:country":"HU",
    "name:epo_x_preferred":[
        "M\u00e1nd"
    ],
    "name:fas_x_preferred":[
        "\u0645\u0627\u0646\u062f"
    ],
    "name:fra_x_preferred":[
        "M\u00e1nd"
    ],
    "name:hun_x_preferred":[
        "M\u00e1nd"
    ],
    "name:ita_x_preferred":[
        "M\u00e1nd"
    ],
    "name:msa_x_preferred":[
        "M\u00e1nd"
    ],
    "name:nld_x_preferred":[
        "M\u00e1nd"
    ],
    "name:ron_x_preferred":[
        "M\u00e1nd"
    ],
    "name:slk_x_preferred":[
        "M\u00e1nd"
    ],
    "name:slv_x_preferred":[
        "M\u00e1nd"
    ],
    "name:vie_x_preferred":[
        "M\u00e1nd"
    ],
    "wof:name":"Mand",
    "wof:placetype":"locality"
},
  "geometry": {"coordinates":[22.60852,47.99796],"type":"Point"}
}