{
  "type": "Feature",
  "properties": {
    "gn:admin1_code":"10.0",
    "gn:asciiname":"Ferdiktanya",
    "gn:country_code":"HU",
    "gn:dem":138,
    "gn:feature_class":"P",
    "gn:feature_code":"PPL",
    "gn:name":"Ferdiktanya",
    "gn:population":0,
    "gn:timezone":"Europe/Budapest",
    "iso:country":"HU",
    "name:und_x_variant":[
        "Terdik-tanya",
        "Ferdiktanya"
    ],
    "wof:name":"Ferdiktanya",
    "wof:placetype":"locality"
},
  "geometry": {"coordinates":[22.08635,47.59084],"type":"Point"}
}