{
  "type": "Feature",
  "properties": {
    "gn:admin1_code":"9.0",
    "gn:asciiname":"Ujhidmajor",
    "gn:country_code":"HU",
    "gn:dem":138,
    "gn:feature_class":"P",
    "gn:feature_code":"PPL",
    "gn:name":"\u00dajh\u00eddmajor",
    "gn:population":0,
    "gn:timezone":"Europe/Budapest",
    "iso:country":"HU",
    "name:und_x_variant":[
        "\u00dajh\u00eddi-major",
        "\u00dajh\u00eddmajor"
    ],
    "wof:name":"Ujhidmajor",
    "wof:placetype":"locality"
},
  "geometry": {"coordinates":[17.06073,47.42876],"type":"Point"}
}