{
  "type": "Feature",
  "properties": {
    "gn:admin1_code":"24.0",
    "gn:asciiname":"Bezsento",
    "gn:country_code":"HU",
    "gn:dem":152,
    "gn:feature_class":"P",
    "gn:feature_code":"PPL",
    "gn:name":"Bezsent\u00f3",
    "gn:population":0,
    "gn:timezone":"Europe/Budapest",
    "iso:country":"HU",
    "name:und_x_variant":[
        "Bezsent\u00f3i Malom",
        "Bezsent\u00f3"
    ],
    "wof:name":"Bezsento",
    "wof:placetype":"locality"
},
  "geometry": {"coordinates":[16.9125,46.35549],"type":"Point"}
}