{
  "type": "Feature",
  "properties": {
    "gn:admin1_code":"16.0",
    "gn:asciiname":"Cegledi Uti Tanyak",
    "gn:country_code":"HU",
    "gn:dem":96,
    "gn:feature_class":"P",
    "gn:feature_code":"PPL",
    "gn:name":"Cegl\u00e9di \u00dati Tany\u00e1k",
    "gn:population":0,
    "gn:timezone":"Europe/Budapest",
    "iso:country":"HU",
    "name:und_x_variant":[
        "Cegl\u00e9di Tany\u00e1k",
        "Cegl\u00e9di \u00dati Tany\u00e1k"
    ],
    "wof:name":"Cegledi Uti Tanyak",
    "wof:placetype":"locality"
},
  "geometry": {"coordinates":[19.86091,47.28278],"type":"Point"}
}