{
  "type": "Feature",
  "properties": {
    "gn:admin1_code":"2.0",
    "gn:asciiname":"Csokoladepuszta",
    "gn:country_code":"HU",
    "gn:dem":208,
    "gn:feature_class":"P",
    "gn:feature_code":"PPL",
    "gn:name":"Csokol\u00e1d\u00e9puszta",
    "gn:population":0,
    "gn:timezone":"Europe/Budapest",
    "iso:country":"HU",
    "name:und_x_variant":[
        "Csokol\u00e1d\u00e9",
        "Csokol\u00e1d\u00e9puszta"
    ],
    "wof:name":"Csokoladepuszta",
    "wof:placetype":"locality"
},
  "geometry": {"coordinates":[18.37276,46.13209000000001],"type":"Point"}
}