{
  "type": "Feature",
  "properties": {
    "gn:admin1_code":"20.0",
    "gn:asciiname":"Almasytanya",
    "gn:cc2":"HU",
    "gn:country_code":"HU",
    "gn:dem":89,
    "gn:feature_class":"P",
    "gn:feature_code":"PPL",
    "gn:name":"Alm\u00e1sytanya",
    "gn:population":0,
    "gn:timezone":"Europe/Budapest",
    "iso:country":"HU",
    "name:und_x_variant":[
        "Alm\u00e1sitanya",
        "Alm\u00e1sytanya"
    ],
    "wof:name":"Almasytanya",
    "wof:placetype":"locality"
},
  "geometry": {"coordinates":[20.85,47.53333],"type":"Point"}
}