{
  "type": "Feature",
  "properties": {
    "gn:admin1_code":"1.0",
    "gn:asciiname":"Baromjaras",
    "gn:country_code":"HU",
    "gn:dem":113,
    "gn:feature_class":"P",
    "gn:feature_code":"PPL",
    "gn:name":"Baromj\u00e1r\u00e1s",
    "gn:population":0,
    "gn:timezone":"Europe/Budapest",
    "iso:country":"HU",
    "wof:name":"Baromjaras",
    "wof:placetype":"locality"
},
  "geometry": {"coordinates":[19.61667000000001,46.76667],"type":"Point"}
}