{
  "type": "Feature",
  "properties": {
    "gn:country":"HU",
    "gn:fcode":"PPL",
    "gn:population":0,
    "iso:country":"HU",
    "name:aze_x_preferred":[
        "Aqard"
    ],
    "name:bel_x_preferred":[
        "\u0410\u0433\u0430\u0440\u0434"
    ],
    "name:ces_x_preferred":[
        "Ag\u00e1rd"
    ],
    "name:eng_x_preferred":[
        "Ag\u00e1rd"
    ],
    "name:hun_x_preferred":[
        "Ag\u00e1rd"
    ],
    "name:hye_x_preferred":[
        "\u0531\u0563\u0561\u0580\u0564"
    ],
    "name:nld_x_preferred":[
        "Ag\u00e1rd"
    ],
    "name:und_x_variant":[
        "Ag\u00e1rdpuszta"
    ],
    "qs_pg:aaroncc":"HU",
    "qs_pg:gn_country":"HU",
    "qs_pg:gn_fcode":"PPL",
    "qs_pg:gn_pop":0,
    "qs_pg:name":"Ag\u00e1rd",
    "qs_pg:name_adm0":"Magyarorsz\u00e1g",
    "qs_pg:name_adm1":"Fej\u00e9r",
    "qs_pg:photos":769,
    "qs_pg:photos_1k":156,
    "qs_pg:photos_9k":3,
    "qs_pg:photos_9r":6,
    "qs_pg:photos_all":769,
    "qs_pg:photos_sr":9,
    "qs_pg:pop_sr":0,
    "qs_pg:qs_pg_placetype":"locality",
    "qs_pg:qs_pg_placetype_gp":"Town",
    "qs_pg:woe_adm0":23424844,
    "woe:adm0_id":23424844,
    "woe:name_adm0":"Magyarorsz\u00e1g",
    "woe:name_adm1":"Fej\u00e9r",
    "woe:placetype":"Town",
    "wof:name":"Ag\u00e1rd",
    "wof:placetype":"locality"
},
  "geometry": {"coordinates":[18.59359,47.19076],"type":"Point"}
}