{
  "type": "Feature",
  "properties": {
    "gn:admin1_code":"24.0",
    "gn:asciiname":"Kallosd",
    "gn:country_code":"HU",
    "gn:dem":143,
    "gn:feature_class":"P",
    "gn:feature_code":"PPL",
    "gn:name":"Kall\u00f3sd",
    "gn:population":0,
    "gn:timezone":"Europe/Budapest",
    "iso:country":"HU",
    "name:und_x_variant":[
        "Kall\u00f3sd"
    ],
    "wof:name":"Kallosd",
    "wof:placetype":"locality"
},
  "geometry": {"coordinates":[17.06401,46.87139000000001],"type":"Point"}
}