{
  "type": "Feature",
  "properties": {
    "gn:admin1_code":"24.0",
    "gn:asciiname":"Kallosd",
    "gn:country_code":"HU",
    "gn:dem":143,
    "gn:feature_class":"P",
    "gn:feature_code":"PPL",
    "gn:name":"Kall\u00f3sd",
    "gn:population":0,
    "gn:timezone":"Europe/Budapest",
    "iso:country":"HU",
    "name:epo_x_preferred":[
        "Kall\u00f3sd"
    ],
    "name:fas_x_preferred":[
        "\u06a9\u0627\u0644\u0648\u0634\u062f"
    ],
    "name:fra_x_preferred":[
        "Kall\u00f3sd"
    ],
    "name:hun_x_preferred":[
        "Kall\u00f3sd"
    ],
    "name:ita_x_preferred":[
        "Kall\u00f3sd"
    ],
    "name:msa_x_preferred":[
        "Kall\u00f3sd"
    ],
    "name:nld_x_preferred":[
        "Kall\u00f3sd"
    ],
    "name:ron_x_preferred":[
        "Kall\u00f3sd"
    ],
    "name:slk_x_preferred":[
        "Kall\u00f3sd"
    ],
    "name:slv_x_preferred":[
        "Kall\u00f3sd"
    ],
    "name:und_x_variant":[
        "Kall\u00f3sd"
    ],
    "name:vie_x_preferred":[
        "Kall\u00f3sd"
    ],
    "name:zho_x_preferred":[
        "\u8003\u5c14\u6d1b\u4ec0\u5fb7"
    ],
    "wof:name":"Kallosd",
    "wof:placetype":"locality"
},
  "geometry": {"coordinates":[17.06401,46.87139000000001],"type":"Point"}
}