{
  "type": "Feature",
  "properties": {
    "gn:country":"HU",
    "gn:fcode":"PPL",
    "gn:population":0,
    "iso:country":"HU",
    "name:eng_x_preferred":[
        "Mogyor\u00f3sb\u00e1nya"
    ],
    "name:epo_x_preferred":[
        "Mogyor\u00f3sb\u00e1nya"
    ],
    "name:fas_x_preferred":[
        "\u0645\u0648\u06af\u06cc\u0648\u0631\u0648\u0634\u0628\u0627\u0646\u06cc\u0627"
    ],
    "name:fra_x_preferred":[
        "Mogyor\u00f3sb\u00e1nya"
    ],
    "name:hun_x_preferred":[
        "Mogyor\u00f3sb\u00e1nya"
    ],
    "name:ita_x_preferred":[
        "Mogyor\u00f3sb\u00e1nya"
    ],
    "name:msa_x_preferred":[
        "Mogyor\u00f3sb\u00e1nya"
    ],
    "name:nan_x_preferred":[
        "Mogyor\u00f3sb\u00e1nya"
    ],
    "name:nld_x_preferred":[
        "Mogyor\u00f3sb\u00e1nya"
    ],
    "name:ron_x_preferred":[
        "Mogyor\u00f3sb\u00e1nya"
    ],
    "name:slk_x_preferred":[
        "Mo\u010foro\u0161"
    ],
    "name:slv_x_preferred":[
        "Mogyor\u00f3sb\u00e1nya"
    ],
    "name:vie_x_preferred":[
        "Mogyor\u00f3sb\u00e1nya"
    ],
    "name:zho_x_preferred":[
        "\u83ab\u7126\u7f57\u4ec0\u5df4\u5c3c\u5965"
    ],
    "qs_pg:aaroncc":"HU",
    "qs_pg:gn_country":"HU",
    "qs_pg:gn_fcode":"PPL",
    "qs_pg:gn_pop":0,
    "qs_pg:name":"Mogyor\u00f3sb\u00e1nya",
    "qs_pg:name_adm0":"Magyarorsz\u00e1g",
    "qs_pg:name_adm1":"Kom\u00e1rom-Esztergom",
    "qs_pg:photos":49,
    "qs_pg:photos_1k":10,
    "qs_pg:photos_9k":1,
    "qs_pg:photos_9r":2,
    "qs_pg:photos_all":49,
    "qs_pg:photos_sr":2,
    "qs_pg:pop_sr":0,
    "qs_pg:qs_pg_placetype":"locality",
    "qs_pg:qs_pg_placetype_gp":"Town",
    "qs_pg:woe_adm0":23424844,
    "woe:adm0_id":23424844,
    "woe:name_adm0":"Magyarorsz\u00e1g",
    "woe:name_adm1":"Kom\u00e1rom-Esztergom",
    "woe:placetype":"Town",
    "wof:name":"Mogyor\u00f3sb\u00e1nya",
    "wof:placetype":"locality"
},
  "geometry": {"coordinates":[18.59739,47.72839],"type":"Point"}
}