{
  "type": "Feature",
  "properties": {
    "gn:admin1_code":"17.0",
    "gn:asciiname":"Nagocs",
    "gn:country_code":"HU",
    "gn:dem":217,
    "gn:feature_class":"P",
    "gn:feature_code":"PPL",
    "gn:name":"N\u00e1gocs",
    "gn:population":0,
    "gn:timezone":"Europe/Budapest",
    "iso:country":"HU",
    "name:epo_x_preferred":[
        "N\u00e1gocs"
    ],
    "name:fas_x_preferred":[
        "\u0646\u0627\u06af\u0648\u0686"
    ],
    "name:fra_x_preferred":[
        "N\u00e1gocs"
    ],
    "name:hun_x_preferred":[
        "N\u00e1gocs"
    ],
    "name:ita_x_preferred":[
        "N\u00e1gocs"
    ],
    "name:msa_x_preferred":[
        "N\u00e1gocs"
    ],
    "name:nld_x_preferred":[
        "N\u00e1gocs"
    ],
    "name:ron_x_preferred":[
        "N\u00e1gocs"
    ],
    "name:slk_x_preferred":[
        "N\u00e1gocs"
    ],
    "name:slv_x_preferred":[
        "N\u00e1gocs"
    ],
    "name:und_x_variant":[
        "N\u00e1gocs"
    ],
    "name:vie_x_preferred":[
        "N\u00e1gocs"
    ],
    "name:zho_x_preferred":[
        "\u7eb3\u6208\u5947"
    ],
    "wof:name":"Nagocs",
    "wof:placetype":"locality"
},
  "geometry": {"coordinates":[17.96667,46.66254],"type":"Point"}
}