{
  "type": "Feature",
  "properties": {
    "gn:admin1_code":"17.0",
    "gn:asciiname":"Balatonszabadi Furdotelep",
    "gn:country_code":"HU",
    "gn:dem":111,
    "gn:feature_class":"P",
    "gn:feature_code":"PPL",
    "gn:name":"Balatonszabadi F\u00fcrd\u0151telep",
    "gn:population":0,
    "gn:timezone":"Europe/Budapest",
    "iso:country":"HU",
    "wof:name":"Balatonszabadi Furdotelep",
    "wof:placetype":"locality"
},
  "geometry": {"coordinates":[18.10272,46.92401],"type":"Point"}
}