{
  "type": "Feature",
  "properties": {
    "gn:admin1_code":"2.0",
    "gn:asciiname":"Bezedekpuszta",
    "gn:country_code":"HU",
    "gn:dem":119,
    "gn:feature_class":"P",
    "gn:feature_code":"PPL",
    "gn:name":"Bezedekpuszta",
    "gn:population":0,
    "gn:timezone":"Europe/Budapest",
    "iso:country":"HU",
    "wof:name":"Bezedekpuszta",
    "wof:placetype":"locality"
},
  "geometry": {"coordinates":[18.58638,45.86467],"type":"Point"}
}