{
  "type": "Feature",
  "properties": {
    "gn:admin1_code":"10.0",
    "gn:asciiname":"Told",
    "gn:country_code":"HU",
    "gn:dem":92,
    "gn:feature_class":"P",
    "gn:feature_code":"PPL",
    "gn:name":"Told",
    "gn:population":0,
    "gn:timezone":"Europe/Budapest",
    "iso:country":"HU",
    "wof:name":"Told",
    "wof:placetype":"locality"
},
  "geometry": {"coordinates":[21.65,47.11667],"type":"Point"}
}