{
  "type": "Feature",
  "properties": {
    "gn:admin1_code":"10.0",
    "gn:asciiname":"Told",
    "gn:country_code":"HU",
    "gn:dem":92,
    "gn:feature_class":"P",
    "gn:feature_code":"PPL",
    "gn:name":"Told",
    "gn:population":0,
    "gn:timezone":"Europe/Budapest",
    "iso:country":"HU",
    "name:deu_x_preferred":[
        "Told"
    ],
    "name:epo_x_preferred":[
        "Told"
    ],
    "name:fas_x_preferred":[
        "\u062a\u0648\u0644\u062f"
    ],
    "name:fra_x_preferred":[
        "Told"
    ],
    "name:hun_x_preferred":[
        "Told"
    ],
    "name:ita_x_preferred":[
        "Told"
    ],
    "name:msa_x_preferred":[
        "Told"
    ],
    "name:nld_x_preferred":[
        "Told"
    ],
    "name:ron_x_preferred":[
        "Told"
    ],
    "name:slk_x_preferred":[
        "Told"
    ],
    "name:slv_x_preferred":[
        "Told"
    ],
    "name:vie_x_preferred":[
        "Told"
    ],
    "name:zho_x_preferred":[
        "\u6258\u5c14\u5fb7"
    ],
    "wof:name":"Told",
    "wof:placetype":"locality"
},
  "geometry": {"coordinates":[21.65,47.11667],"type":"Point"}
}