{
  "type": "Feature",
  "properties": {
    "gn:gn_country":"HU",
    "gn:gn_fcode":"PPL",
    "gn:gn_pop":0,
    "iso:country":"HU",
    "name:chi_x_preferred":[
        "\u7c73\u514b\u6d1b\u5e0c"
    ],
    "name:dut_x_preferred":[
        "Mikl\u00f3si"
    ],
    "name:eng_x_preferred":[
        "Mikl\u00f3si"
    ],
    "name:epo_x_preferred":[
        "Mikl\u00f3si"
    ],
    "name:fre_x_preferred":[
        "Mikl\u00f3si"
    ],
    "name:ger_x_preferred":[
        "Mikl\u00f3si"
    ],
    "name:hun_x_preferred":[
        "Mikl\u00f3si"
    ],
    "name:ita_x_preferred":[
        "Mikl\u00f3si"
    ],
    "name:may_x_preferred":[
        "Mikl\u00f3si"
    ],
    "name:nan_x_preferred":[
        "Mikl\u00f3si"
    ],
    "name:pol_x_preferred":[
        "Mikl\u00f3si"
    ],
    "name:rum_x_preferred":[
        "Mikl\u00f3si"
    ],
    "name:slo_x_preferred":[
        "Mikl\u00f3si"
    ],
    "name:slv_x_preferred":[
        "Mikl\u00f3si"
    ],
    "name:vie_x_preferred":[
        "Mikl\u00f3si"
    ],
    "qs_pg:aaroncc":"HU",
    "qs_pg:gn_country":"HU",
    "qs_pg:gn_fcode":"PPL",
    "qs_pg:gn_pop":0,
    "qs_pg:name":"Mikl\u00f3si",
    "qs_pg:name_adm0":"Magyarorsz\u00e1g",
    "qs_pg:name_adm1":"Somogy",
    "qs_pg:photos":61,
    "qs_pg:photos_1k":12,
    "qs_pg:photos_9k":1,
    "qs_pg:photos_9r":2,
    "qs_pg:photos_all":61,
    "qs_pg:photos_sr":2,
    "qs_pg:pop_sr":0,
    "qs_pg:qs_pg_placetype":"locality",
    "qs_pg:qs_pg_placetype_gp":"Town",
    "qs_pg:woe_adm0":23424844,
    "woe:adm0_id":23424844,
    "woe:name_adm0":"Magyarorsz\u00e1g",
    "woe:name_adm1":"Somogy",
    "woe:placetype":"Town",
    "wof:name":"Mikl\u00f3si",
    "wof:placetype":"locality"
},
  "geometry": {"coordinates":[17.99297,46.64662],"type":"Point"}
}