{
  "type": "Feature",
  "properties": {
    "gn:admin1_code":"23.0",
    "gn:asciiname":"Dobresimalom",
    "gn:country_code":"HU",
    "gn:dem":192,
    "gn:feature_class":"P",
    "gn:feature_code":"PPL",
    "gn:name":"D\u00f6br\u00e9simalom",
    "gn:population":0,
    "gn:timezone":"Europe/Budapest",
    "iso:country":"HU",
    "wof:name":"Dobresimalom",
    "wof:placetype":"locality"
},
  "geometry": {"coordinates":[17.53333,47.28333],"type":"Point"}
}