{
  "type": "Feature",
  "properties": {
    "gn:admin1_code":"23.0",
    "gn:asciiname":"Alsoszalmavar",
    "gn:country_code":"HU",
    "gn:dem":165,
    "gn:feature_class":"P",
    "gn:feature_code":"PPL",
    "gn:name":"Als\u00f3szalmav\u00e1r",
    "gn:population":0,
    "gn:timezone":"Europe/Budapest",
    "iso:country":"HU",
    "name:und_x_variant":[
        "Als\u00f3szalmav\u00e1r-major",
        "Als\u00f3szalmav\u00e1r"
    ],
    "wof:name":"Alsoszalmavar",
    "wof:placetype":"locality"
},
  "geometry": {"coordinates":[17.60107,47.39643],"type":"Point"}
}