{
  "type": "Feature",
  "properties": {
    "gn:admin1_code":"3.0",
    "gn:asciiname":"Begecspuszta",
    "gn:country_code":"HU",
    "gn:dem":88,
    "gn:feature_class":"P",
    "gn:feature_code":"PPL",
    "gn:name":"Beg\u00e9cspuszta",
    "gn:population":0,
    "gn:timezone":"Europe/Budapest",
    "iso:country":"HU",
    "wof:name":"Begecspuszta",
    "wof:placetype":"locality"
},
  "geometry": {"coordinates":[21.58333,46.91667],"type":"Point"}
}