{
  "type": "Feature",
  "properties": {
    "gn:admin1_code":"24.0",
    "gn:asciiname":"Belezna",
    "gn:country_code":"HU",
    "gn:dem":176,
    "gn:feature_class":"P",
    "gn:feature_code":"PPL",
    "gn:name":"Belezna",
    "gn:population":0,
    "gn:timezone":"Europe/Budapest",
    "iso:country":"HU",
    "name:deu_x_preferred":[
        "Belezna"
    ],
    "name:epo_x_preferred":[
        "Belezna"
    ],
    "name:fas_x_preferred":[
        "\u0628\u0644\u0632\u0646\u0627"
    ],
    "name:fra_x_preferred":[
        "Belezna"
    ],
    "name:hun_x_preferred":[
        "Belezna"
    ],
    "name:ita_x_preferred":[
        "Belezna"
    ],
    "name:msa_x_preferred":[
        "Belezna"
    ],
    "name:nld_x_preferred":[
        "Belezna"
    ],
    "name:ron_x_preferred":[
        "Belezna"
    ],
    "name:slk_x_preferred":[
        "Belezna"
    ],
    "name:slv_x_preferred":[
        "Belezna"
    ],
    "name:vie_x_preferred":[
        "Belezna"
    ],
    "name:zho_x_preferred":[
        "\u62dc\u83b1\u5179\u7459"
    ],
    "wof:name":"Belezna",
    "wof:placetype":"locality"
},
  "geometry": {"coordinates":[16.94,46.32778],"type":"Point"}
}