{
  "type": "Feature",
  "properties": {
    "gn:admin1_code":"4.0",
    "gn:admin2_code":"9644330",
    "gn:asciiname":"Nagykinizs",
    "gn:country_code":"HU",
    "gn:dem":119,
    "gn:feature_class":"P",
    "gn:feature_code":"PPL",
    "gn:name":"Nagykinizs",
    "gn:population":0,
    "gn:timezone":"Europe/Budapest",
    "iso:country":"HU",
    "name:deu_x_preferred":[
        "Nagykinizs"
    ],
    "name:epo_x_preferred":[
        "Nagykinizs"
    ],
    "name:fas_x_preferred":[
        "\u0646\u0627\u06af\u06cc\u06a9\u06cc\u0646\u06cc\u0698"
    ],
    "name:fra_x_preferred":[
        "Nagykinizs"
    ],
    "name:heb_x_preferred":[
        "\u05e0\u05d0\u05d2'\u05e7\u05d9\u05e0\u05d9\u05d6'"
    ],
    "name:hun_x_preferred":[
        "Nagykinizs"
    ],
    "name:ita_x_preferred":[
        "Nagykinizs"
    ],
    "name:msa_x_preferred":[
        "Nagykinizs"
    ],
    "name:nld_x_preferred":[
        "Nagykinizs"
    ],
    "name:pol_x_preferred":[
        "Nagykinizs"
    ],
    "name:ron_x_preferred":[
        "Nagykinizs"
    ],
    "name:slk_x_preferred":[
        "Nagykinizs"
    ],
    "name:slv_x_preferred":[
        "Nagykinizs"
    ],
    "name:vie_x_preferred":[
        "Nagykinizs"
    ],
    "name:zho_x_preferred":[
        "\u5927\u57fa\u5c3c\u65e5"
    ],
    "wof:name":"Nagykinizs",
    "wof:placetype":"locality"
},
  "geometry": {"coordinates":[21.03333,48.23333],"type":"Point"}
}