{
  "type": "Feature",
  "properties": {
    "gn:admin1_code":"8.0",
    "gn:asciiname":"Belsosaripuszta",
    "gn:country_code":"HU",
    "gn:dem":102,
    "gn:feature_class":"P",
    "gn:feature_code":"PPL",
    "gn:name":"Bels\u0151s\u00e1ripuszta",
    "gn:population":0,
    "gn:timezone":"Europe/Budapest",
    "iso:country":"HU",
    "name:und_x_variant":[
        "Bels\u0151s\u00e1ri",
        "Bels\u0151s\u00e1ripuszta"
    ],
    "wof:name":"Belsosaripuszta",
    "wof:placetype":"locality"
},
  "geometry": {"coordinates":[18.33944,46.78923],"type":"Point"}
}