{
  "type": "Feature",
  "properties": {
    "gn:admin1_code":"10.0",
    "gn:asciiname":"Ujiraz",
    "gn:country_code":"HU",
    "gn:dem":84,
    "gn:feature_class":"P",
    "gn:feature_code":"PPL",
    "gn:name":"\u00dajir\u00e1z",
    "gn:population":0,
    "gn:timezone":"Europe/Budapest",
    "iso:country":"HU",
    "name:deu_x_preferred":[
        "\u00dajir\u00e1z"
    ],
    "name:epo_x_preferred":[
        "\u00dajir\u00e1z"
    ],
    "name:fas_x_preferred":[
        "\u0648\u06cc\u06cc\u0631\u0627\u0632"
    ],
    "name:fra_x_preferred":[
        "\u00dajir\u00e1z"
    ],
    "name:hun_x_preferred":[
        "\u00dajir\u00e1z"
    ],
    "name:ita_x_preferred":[
        "\u00dajir\u00e1z"
    ],
    "name:msa_x_preferred":[
        "\u00dajir\u00e1z"
    ],
    "name:nld_x_preferred":[
        "\u00dajir\u00e1z"
    ],
    "name:ron_x_preferred":[
        "\u00dajir\u00e1z"
    ],
    "name:slk_x_preferred":[
        "\u00dajir\u00e1z"
    ],
    "name:slv_x_preferred":[
        "\u00dajir\u00e1z"
    ],
    "name:vie_x_preferred":[
        "\u00dajir\u00e1z"
    ],
    "name:zho_x_preferred":[
        "\u4e4c\u4f0a\u62c9\u5179"
    ],
    "wof:name":"Ujiraz",
    "wof:placetype":"locality"
},
  "geometry": {"coordinates":[21.36667000000001,46.98333],"type":"Point"}
}