{
  "type": "Feature",
  "properties": {
    "gn:admin1_code":"24.0",
    "gn:asciiname":"Csonkahegyhat",
    "gn:country_code":"HU",
    "gn:dem":269,
    "gn:feature_class":"P",
    "gn:feature_code":"PPL",
    "gn:name":"Csonkahegyh\u00e1t",
    "gn:population":0,
    "gn:timezone":"Europe/Budapest",
    "iso:country":"HU",
    "name:und_x_variant":[
        "Csonkahegyh\u00e1t"
    ],
    "wof:name":"Csonkahegyhat",
    "wof:placetype":"locality"
},
  "geometry": {"coordinates":[16.72001,46.80067],"type":"Point"}
}