{
  "type": "Feature",
  "properties": {
    "gn:admin1_code":"24.0",
    "gn:asciiname":"Csonkahegyhat",
    "gn:country_code":"HU",
    "gn:dem":269,
    "gn:feature_class":"P",
    "gn:feature_code":"PPL",
    "gn:name":"Csonkahegyh\u00e1t",
    "gn:population":0,
    "gn:timezone":"Europe/Budapest",
    "iso:country":"HU",
    "name:epo_x_preferred":[
        "Csonkahegyh\u00e1t"
    ],
    "name:fas_x_preferred":[
        "\u0686\u0648\u0646\u06a9\u0627\u0647\u06af\u06cc\u0647\u0627\u062a"
    ],
    "name:fra_x_preferred":[
        "Csonkahegyh\u00e1t"
    ],
    "name:hun_x_preferred":[
        "Csonkahegyh\u00e1t"
    ],
    "name:ita_x_preferred":[
        "Csonkahegyh\u00e1t"
    ],
    "name:msa_x_preferred":[
        "Csonkahegyh\u00e1t"
    ],
    "name:nld_x_preferred":[
        "Csonkahegyh\u00e1t"
    ],
    "name:ron_x_preferred":[
        "Csonkahegyh\u00e1t"
    ],
    "name:slk_x_preferred":[
        "Csonkahegyh\u00e1t"
    ],
    "name:slv_x_preferred":[
        "Csonkahegyh\u00e1t"
    ],
    "name:vie_x_preferred":[
        "Csonkahegyh\u00e1t"
    ],
    "name:zho_x_preferred":[
        "\u743c\u8003\u6d77\u5409\u54c8\u7279"
    ],
    "wof:name":"Csonkahegyhat",
    "wof:placetype":"locality"
},
  "geometry": {"coordinates":[16.72001,46.80067],"type":"Point"}
}