{
  "type": "Feature",
  "properties": {
    "gn:admin1_code":"18.0",
    "gn:asciiname":"Kis Elek-tanya",
    "gn:country_code":"HU",
    "gn:dem":97,
    "gn:feature_class":"P",
    "gn:feature_code":"PPL",
    "gn:name":"Kis Elek-tanya",
    "gn:population":0,
    "gn:timezone":"Europe/Budapest",
    "iso:country":"HU",
    "wof:name":"Kis Elek-tanya",
    "wof:placetype":"locality"
},
  "geometry": {"coordinates":[21.76104,48.13266],"type":"Point"}
}