{
  "type": "Feature",
  "properties": {
    "gn:admin1_code":"2.0",
    "gn:asciiname":"Mariakemend",
    "gn:country_code":"HU",
    "gn:dem":135,
    "gn:feature_class":"P",
    "gn:feature_code":"PPL",
    "gn:name":"M\u00e1riak\u00e9m\u00e9nd",
    "gn:population":0,
    "gn:timezone":"Europe/Budapest",
    "iso:country":"HU",
    "name:und_x_variant":[
        "M\u00e1riak\u00e9m\u00e9nd"
    ],
    "wof:name":"Mariakemend",
    "wof:placetype":"locality"
},
  "geometry": {"coordinates":[18.46183,46.02703],"type":"Point"}
}