{
  "type": "Feature",
  "properties": {
    "gn:admin1_code":"2.0",
    "gn:asciiname":"Mariakemend",
    "gn:country_code":"HU",
    "gn:dem":135,
    "gn:feature_class":"P",
    "gn:feature_code":"PPL",
    "gn:name":"M\u00e1riak\u00e9m\u00e9nd",
    "gn:population":0,
    "gn:timezone":"Europe/Budapest",
    "iso:country":"HU",
    "name:deu_x_preferred":[
        "M\u00e1riak\u00e9m\u00e9nd"
    ],
    "name:epo_x_preferred":[
        "M\u00e1riak\u00e9m\u00e9nd"
    ],
    "name:fas_x_preferred":[
        "\u0645\u0627\u0631\u06cc\u0627\u06a9\u0645\u0646\u062f"
    ],
    "name:fra_x_preferred":[
        "M\u00e1riak\u00e9m\u00e9nd"
    ],
    "name:hrv_x_preferred":[
        "Kemed"
    ],
    "name:hun_x_preferred":[
        "M\u00e1riak\u00e9m\u00e9nd"
    ],
    "name:ita_x_preferred":[
        "M\u00e1riak\u00e9m\u00e9nd"
    ],
    "name:msa_x_preferred":[
        "M\u00e1riak\u00e9m\u00e9nd"
    ],
    "name:nld_x_preferred":[
        "M\u00e1riak\u00e9m\u00e9nd"
    ],
    "name:pol_x_preferred":[
        "M\u00e1riak\u00e9m\u00e9nd"
    ],
    "name:ron_x_preferred":[
        "M\u00e1riak\u00e9m\u00e9nd"
    ],
    "name:slk_x_preferred":[
        "M\u00e1riak\u00e9m\u00e9nd"
    ],
    "name:slv_x_preferred":[
        "M\u00e1riak\u00e9m\u00e9nd"
    ],
    "name:vie_x_preferred":[
        "M\u00e1riak\u00e9m\u00e9nd"
    ],
    "name:zho_x_preferred":[
        "\u9a6c\u91cc\u5965\u51ef\u95e8\u5fb7"
    ],
    "wof:name":"Mariakemend",
    "wof:placetype":"locality"
},
  "geometry": {"coordinates":[18.46183,46.02703],"type":"Point"}
}