{
  "type": "Feature",
  "properties": {
    "gn:admin1_code":"23.0",
    "gn:asciiname":"Varkeszo",
    "gn:country_code":"HU",
    "gn:dem":122,
    "gn:feature_class":"P",
    "gn:feature_code":"PPL",
    "gn:name":"V\u00e1rkesz\u0151",
    "gn:population":0,
    "gn:timezone":"Europe/Budapest",
    "iso:country":"HU",
    "name:und_x_variant":[
        "V\u00e1rkesz\u0151"
    ],
    "wof:name":"Varkeszo",
    "wof:placetype":"locality"
},
  "geometry": {"coordinates":[17.31801,47.43126],"type":"Point"}
}