{
  "type": "Feature",
  "properties": {
    "gn:admin1_code":"23.0",
    "gn:asciiname":"Varkeszo",
    "gn:country_code":"HU",
    "gn:dem":122,
    "gn:feature_class":"P",
    "gn:feature_code":"PPL",
    "gn:name":"V\u00e1rkesz\u0151",
    "gn:population":0,
    "gn:timezone":"Europe/Budapest",
    "iso:country":"HU",
    "name:ces_x_preferred":[
        "V\u00e1rkesz\u0151"
    ],
    "name:epo_x_preferred":[
        "V\u00e1rkesz\u0151"
    ],
    "name:fas_x_preferred":[
        "\u0648\u0627\u0631\u06a9\u0633\u0648"
    ],
    "name:fra_x_preferred":[
        "V\u00e1rkesz\u0151"
    ],
    "name:hun_x_preferred":[
        "V\u00e1rkesz\u0151"
    ],
    "name:ita_x_preferred":[
        "V\u00e1rkesz\u0151"
    ],
    "name:msa_x_preferred":[
        "V\u00e1rkesz\u0151"
    ],
    "name:nld_x_preferred":[
        "V\u00e1rkesz\u0151"
    ],
    "name:ron_x_preferred":[
        "V\u00e1rkesz\u0151"
    ],
    "name:slk_x_preferred":[
        "V\u00e1rkesz\u0151"
    ],
    "name:slv_x_preferred":[
        "V\u00e1rkesz\u0151"
    ],
    "name:vie_x_preferred":[
        "V\u00e1rkesz\u0151"
    ],
    "name:zho_x_preferred":[
        "\u74e6\u5c14\u51ef\u745f"
    ],
    "wof:name":"Varkeszo",
    "wof:placetype":"locality"
},
  "geometry": {"coordinates":[17.31801,47.43126],"type":"Point"}
}