{
  "type": "Feature",
  "properties": {
    "gn:admin1_code":"1.0",
    "gn:asciiname":"Keleshalom",
    "gn:country_code":"HU",
    "gn:dem":137,
    "gn:feature_class":"P",
    "gn:feature_code":"PPL",
    "gn:name":"K\u00e9leshalom",
    "gn:population":0,
    "gn:timezone":"Europe/Budapest",
    "iso:country":"HU",
    "name:ces_x_preferred":[
        "K\u00e9leshalom"
    ],
    "name:epo_x_preferred":[
        "K\u00e9leshalom"
    ],
    "name:fas_x_preferred":[
        "\u06a9\u0644\u0634\u0647\u0627\u0644\u0648\u0645"
    ],
    "name:fra_x_preferred":[
        "K\u00e9leshalom"
    ],
    "name:hrv_x_preferred":[
        "Kila\u0161"
    ],
    "name:hun_x_preferred":[
        "K\u00e9leshalom"
    ],
    "name:ita_x_preferred":[
        "K\u00e9leshalom"
    ],
    "name:msa_x_preferred":[
        "K\u00e9leshalom"
    ],
    "name:nld_x_preferred":[
        "K\u00e9leshalom"
    ],
    "name:pol_x_preferred":[
        "K\u00e9leshalom"
    ],
    "name:ron_x_preferred":[
        "K\u00e9leshalom"
    ],
    "name:slk_x_preferred":[
        "K\u00e9leshalom"
    ],
    "name:slv_x_preferred":[
        "K\u00e9leshalom"
    ],
    "name:srp_x_preferred":[
        "\u041a\u0435\u043b\u0435\u0448\u0445\u0430\u043b\u043e\u043c"
    ],
    "name:vie_x_preferred":[
        "K\u00e9leshalom"
    ],
    "name:zho_x_preferred":[
        "\u51ef\u83b1\u4ec0\u8c6a\u6d1b\u59c6"
    ],
    "wof:name":"Keleshalom",
    "wof:placetype":"locality"
},
  "geometry": {"coordinates":[19.28178,46.36541],"type":"Point"}
}