{
  "type": "Feature",
  "properties": {
    "gn:admin1_code":"23.0",
    "gn:asciiname":"Mogszeg",
    "gn:country_code":"HU",
    "gn:dem":517,
    "gn:feature_class":"P",
    "gn:feature_code":"PPL",
    "gn:name":"M\u00f6gszeg",
    "gn:population":0,
    "gn:timezone":"Europe/Budapest",
    "iso:country":"HU",
    "wof:name":"Mogszeg",
    "wof:placetype":"locality"
},
  "geometry": {"coordinates":[17.7637,47.08695],"type":"Point"}
}