{
  "type": "Feature",
  "properties": {
    "gn:admin1_code":"10.0",
    "gn:asciiname":"Sandormajor",
    "gn:cc2":"HU",
    "gn:country_code":"HU",
    "gn:dem":95,
    "gn:feature_class":"P",
    "gn:feature_code":"PPL",
    "gn:name":"S\u00e1ndormajor",
    "gn:population":0,
    "gn:timezone":"Europe/Budapest",
    "iso:country":"HU",
    "name:und_x_variant":[
        "S\u00e1ndor Puszta",
        "S\u00e1ndormajor"
    ],
    "wof:name":"Sandormajor",
    "wof:placetype":"locality"
},
  "geometry": {"coordinates":[21.71667,47.33333],"type":"Point"}
}