{
  "type": "Feature",
  "properties": {
    "gn:admin1_code":"14.0",
    "gn:asciiname":"Kisuzsapuszta",
    "gn:country_code":"HU",
    "gn:dem":180,
    "gn:feature_class":"P",
    "gn:feature_code":"PPL",
    "gn:name":"Kisuzsapuszta",
    "gn:population":0,
    "gn:timezone":"Europe/Budapest",
    "iso:country":"HU",
    "wof:name":"Kisuzsapuszta",
    "wof:placetype":"locality"
},
  "geometry": {"coordinates":[19.48333,47.78333],"type":"Point"}
}