{
  "type": "Feature",
  "properties": {
    "gn:admin1_code":"20.0",
    "gn:asciiname":"Tapiomajor",
    "gn:country_code":"HU",
    "gn:dem":87,
    "gn:feature_class":"P",
    "gn:feature_code":"PPL",
    "gn:name":"T\u00e1pi\u00f3major",
    "gn:population":0,
    "gn:timezone":"Europe/Budapest",
    "iso:country":"HU",
    "wof:name":"Tapiomajor",
    "wof:placetype":"locality"
},
  "geometry": {"coordinates":[20.03333,47.33333],"type":"Point"}
}