{
  "type": "Feature",
  "properties": {
    "gn:admin1_code":"2.0",
    "gn:asciiname":"Ata",
    "gn:country_code":"HU",
    "gn:dem":139,
    "gn:feature_class":"P",
    "gn:feature_code":"PPL",
    "gn:name":"\u00c1ta",
    "gn:population":0,
    "gn:timezone":"Europe/Budapest",
    "iso:country":"HU",
    "name:und_x_variant":[
        "\u00c1ta"
    ],
    "wof:name":"Ata",
    "wof:placetype":"locality"
},
  "geometry": {"coordinates":[18.29853,45.93896],"type":"Point"}
}