{
  "type": "Feature",
  "properties": {
    "gn:admin1_code":"1.0",
    "gn:asciiname":"Bacsborsodi Tanyak",
    "gn:country_code":"HU",
    "gn:dem":119,
    "gn:feature_class":"P",
    "gn:feature_code":"PPL",
    "gn:name":"B\u00e1csbors\u00f3di Tany\u00e1k",
    "gn:population":0,
    "gn:timezone":"Europe/Budapest",
    "iso:country":"HU",
    "wof:name":"Bacsborsodi Tanyak",
    "wof:placetype":"locality"
},
  "geometry": {"coordinates":[19.23333,46.11667],"type":"Point"}
}