{
  "type": "Feature",
  "properties": {
    "gn:admin1_code":"23.0",
    "gn:asciiname":"Mariapuszta",
    "gn:country_code":"HU",
    "gn:dem":210,
    "gn:feature_class":"P",
    "gn:feature_code":"PPL",
    "gn:name":"M\u00e1riapuszta",
    "gn:population":0,
    "gn:timezone":"Europe/Budapest",
    "iso:country":"HU",
    "wof:name":"Mariapuszta",
    "wof:placetype":"locality"
},
  "geometry": {"coordinates":[17.63332999999999,46.96667],"type":"Point"}
}