{
  "type": "Feature",
  "properties": {
    "gn:admin1_code":"18.0",
    "gn:asciiname":"Vereshaztanya",
    "gn:country_code":"HU",
    "gn:dem":131,
    "gn:feature_class":"P",
    "gn:feature_code":"PPL",
    "gn:name":"Veresh\u00e1ztanya",
    "gn:population":0,
    "gn:timezone":"Europe/Budapest",
    "iso:country":"HU",
    "name:und_x_variant":[
        "Veres H\u00e1z",
        "Veresh\u00e1ztanya"
    ],
    "wof:name":"Vereshaztanya",
    "wof:placetype":"locality"
},
  "geometry": {"coordinates":[22.30164,47.9297],"type":"Point"}
}