{
  "type": "Feature",
  "properties": {
    "gn:admin1_code":"6.0",
    "gn:asciiname":"Kiralyhegyes",
    "gn:country_code":"HU",
    "gn:dem":86,
    "gn:feature_class":"P",
    "gn:feature_code":"PPL",
    "gn:name":"Kir\u00e1lyhegyes",
    "gn:population":0,
    "gn:timezone":"Europe/Budapest",
    "iso:country":"HU",
    "name:epo_x_preferred":[
        "Kir\u00e1lyhegyes"
    ],
    "name:fas_x_preferred":[
        "\u06a9\u06cc\u0631\u0627\u0644\u06cc\u0647\u06af\u06cc\u0634"
    ],
    "name:fra_x_preferred":[
        "Kir\u00e1lyhegyes"
    ],
    "name:hun_x_preferred":[
        "Kir\u00e1lyhegyes"
    ],
    "name:ita_x_preferred":[
        "Kir\u00e1lyhegyes"
    ],
    "name:msa_x_preferred":[
        "Kir\u00e1lyhegyes"
    ],
    "name:nld_x_preferred":[
        "Kir\u00e1lyhegyes"
    ],
    "name:ron_x_preferred":[
        "Kir\u00e1lyhegyes"
    ],
    "name:slk_x_preferred":[
        "Kir\u00e1lyhegyes"
    ],
    "name:slv_x_preferred":[
        "Kir\u00e1lyhegyes"
    ],
    "name:spa_x_preferred":[
        "Kir\u00e1lyhegyes"
    ],
    "name:vie_x_preferred":[
        "Kir\u00e1lyhegyes"
    ],
    "name:zho_x_preferred":[
        "\u57fa\u62c9\u4f0a\u6d77\u6770\u4ec0"
    ],
    "wof:name":"Kiralyhegyes",
    "wof:placetype":"locality"
},
  "geometry": {"coordinates":[20.61667000000001,46.26667],"type":"Point"}
}