{
  "type": "Feature",
  "properties": {
    "gn:admin1_code":"6.0",
    "gn:asciiname":"Kiralyhegyes",
    "gn:country_code":"HU",
    "gn:dem":86,
    "gn:feature_class":"P",
    "gn:feature_code":"PPL",
    "gn:name":"Kir\u00e1lyhegyes",
    "gn:population":0,
    "gn:timezone":"Europe/Budapest",
    "iso:country":"HU",
    "name:und_x_variant":[
        "Kir\u00e1lyhegyes"
    ],
    "wof:name":"Kiralyhegyes",
    "wof:placetype":"locality"
},
  "geometry": {"coordinates":[20.61667000000001,46.26667],"type":"Point"}
}