{
  "type": "Feature",
  "properties": {
    "gn:admin1_code":"24.0",
    "gn:asciiname":"Nagykutas",
    "gn:country_code":"HU",
    "gn:dem":219,
    "gn:feature_class":"P",
    "gn:feature_code":"PPL",
    "gn:name":"Nagykutas",
    "gn:population":0,
    "gn:timezone":"Europe/Budapest",
    "iso:country":"HU",
    "name:epo_x_preferred":[
        "Nagykutas"
    ],
    "name:fas_x_preferred":[
        "\u0646\u0627\u06af\u06cc\u06a9\u0648\u062a\u0627\u0634"
    ],
    "name:fra_x_preferred":[
        "Nagykutas"
    ],
    "name:hun_x_preferred":[
        "Nagykutas"
    ],
    "name:ita_x_preferred":[
        "Nagykutas"
    ],
    "name:msa_x_preferred":[
        "Nagykutas"
    ],
    "name:nld_x_preferred":[
        "Nagykutas"
    ],
    "name:pol_x_preferred":[
        "Nagykutas"
    ],
    "name:ron_x_preferred":[
        "Nagykutas"
    ],
    "name:slk_x_preferred":[
        "Nagykutas"
    ],
    "name:slv_x_preferred":[
        "Nagykutas"
    ],
    "name:szl_x_preferred":[
        "Nagykutas"
    ],
    "name:vie_x_preferred":[
        "Nagykutas"
    ],
    "name:zho_x_preferred":[
        "\u7459\u5409\u5e93\u9676\u4ec0"
    ],
    "wof:name":"Nagykutas",
    "wof:placetype":"locality"
},
  "geometry": {"coordinates":[16.80573,46.9277],"type":"Point"}
}