{
  "type": "Feature",
  "properties": {
    "gn:admin1_code":"10.0",
    "gn:asciiname":"Valeriadulo",
    "gn:country_code":"HU",
    "gn:dem":92,
    "gn:feature_class":"P",
    "gn:feature_code":"PPL",
    "gn:name":"Val\u00e9riad\u0171l\u0151",
    "gn:population":0,
    "gn:timezone":"Europe/Budapest",
    "iso:country":"HU",
    "wof:name":"Valeriadulo",
    "wof:placetype":"locality"
},
  "geometry": {"coordinates":[21.61667000000001,47.15],"type":"Point"}
}