{
  "type": "Feature",
  "properties": {
    "gn:admin1_code":"23.0",
    "gn:asciiname":"Somlovecse",
    "gn:country_code":"HU",
    "gn:dem":152,
    "gn:feature_class":"P",
    "gn:feature_code":"PPL",
    "gn:name":"Soml\u00f3vecse",
    "gn:population":0,
    "gn:timezone":"Europe/Budapest",
    "iso:country":"HU",
    "name:epo_x_preferred":[
        "Soml\u00f3vecse"
    ],
    "name:fra_x_preferred":[
        "Soml\u00f3vecse"
    ],
    "name:hun_x_preferred":[
        "Soml\u00f3vecse"
    ],
    "name:ita_x_preferred":[
        "Soml\u00f3vecse"
    ],
    "name:msa_x_preferred":[
        "Soml\u00f3vecse"
    ],
    "name:nld_x_preferred":[
        "Soml\u00f3vecse"
    ],
    "name:ron_x_preferred":[
        "Soml\u00f3vecse"
    ],
    "name:slk_x_preferred":[
        "Soml\u00f3vecse"
    ],
    "name:slv_x_preferred":[
        "Soml\u00f3vecse"
    ],
    "name:swe_x_preferred":[
        "Soml\u00f3vecse"
    ],
    "name:vie_x_preferred":[
        "Soml\u00f3vecse"
    ],
    "name:zho_x_preferred":[
        "\u7ecd\u59c6\u6d1b\u97e6\u5207"
    ],
    "wof:name":"Somlovecse",
    "wof:placetype":"locality"
},
  "geometry": {"coordinates":[17.35196,47.19487],"type":"Point"}
}