{
  "type": "Feature",
  "properties": {
    "gn:admin1_code":"20.0",
    "gn:asciiname":"Dodaszog",
    "gn:country_code":"HU",
    "gn:dem":89,
    "gn:feature_class":"P",
    "gn:feature_code":"PPL",
    "gn:name":"Dodasz\u00f6g",
    "gn:population":0,
    "gn:timezone":"Europe/Budapest",
    "iso:country":"HU",
    "wof:name":"Dodaszog",
    "wof:placetype":"locality"
},
  "geometry": {"coordinates":[20.45,47.33333],"type":"Point"}
}