{
  "type": "Feature",
  "properties": {
    "gn:admin1_code":"3.0",
    "gn:asciiname":"Balazstanya",
    "gn:country_code":"HU",
    "gn:dem":84,
    "gn:feature_class":"P",
    "gn:feature_code":"PPL",
    "gn:name":"Bal\u00e1zstanya",
    "gn:population":0,
    "gn:timezone":"Europe/Budapest",
    "iso:country":"HU",
    "wof:name":"Balazstanya",
    "wof:placetype":"locality"
},
  "geometry": {"coordinates":[20.81667,46.75],"type":"Point"}
}