{
  "type": "Feature",
  "properties": {
    "gn:admin1_code":"22.0",
    "gn:asciiname":"Bicsakmalom",
    "gn:country_code":"HU",
    "gn:dem":207,
    "gn:feature_class":"P",
    "gn:feature_code":"PPL",
    "gn:name":"Bics\u00e1kmalom",
    "gn:population":0,
    "gn:timezone":"Europe/Budapest",
    "iso:country":"HU",
    "wof:name":"Bicsakmalom",
    "wof:placetype":"locality"
},
  "geometry": {"coordinates":[16.43333,46.96667],"type":"Point"}
}