{
  "type": "Feature",
  "properties": {
    "gn:admin1_code":"9.0",
    "gn:asciiname":"Ujudvar",
    "gn:country_code":"HU",
    "gn:dem":119,
    "gn:feature_class":"P",
    "gn:feature_code":"PPL",
    "gn:name":"\u00dajudvar",
    "gn:population":0,
    "gn:timezone":"Europe/Budapest",
    "iso:country":"HU",
    "name:hun_x_preferred":[
        "Mosonudvar"
    ],
    "name:und_x_variant":[
        "\u00dajudvar"
    ],
    "wof:name":"Ujudvar",
    "wof:placetype":"locality"
},
  "geometry": {"coordinates":[17.22739,47.84393],"type":"Point"}
}