{
  "type": "Feature",
  "properties": {
    "gn:admin1_code":"18.0",
    "gn:asciiname":"Csikoslapostanya",
    "gn:country_code":"HU",
    "gn:dem":133,
    "gn:feature_class":"P",
    "gn:feature_code":"PPL",
    "gn:name":"Csik\u00f3slapostanya",
    "gn:population":0,
    "gn:timezone":"Europe/Budapest",
    "iso:country":"HU",
    "wof:name":"Csikoslapostanya",
    "wof:placetype":"locality"
},
  "geometry": {"coordinates":[21.93333,47.86667],"type":"Point"}
}