{
  "type": "Feature",
  "properties": {
    "gn:country":"HU",
    "gn:fcode":"PPL",
    "gn:population":901,
    "iso:country":"HU",
    "name:ast_x_preferred":[
        "\u00d6tv\u00f6sk\u00f3nyi"
    ],
    "name:ceb_x_preferred":[
        "\u00d6tv\u00f6sk\u00f3nyi"
    ],
    "name:deu_x_preferred":[
        "\u00d6tv\u00f6sk\u00f3nyi"
    ],
    "name:eng_x_preferred":[
        "\u00d6tv\u00f6sk\u00f3nyi"
    ],
    "name:epo_x_preferred":[
        "\u00d6tv\u00f6sk\u00f3nyi"
    ],
    "name:fas_x_preferred":[
        "\u0627\u0648\u062a\u0648\u0648\u0634\u06a9\u0648\u0646\u06cc\u06cc"
    ],
    "name:fra_x_preferred":[
        "\u00d6tv\u00f6sk\u00f3nyi"
    ],
    "name:gle_x_preferred":[
        "\u00d6tv\u00f6sk\u00f3nyi"
    ],
    "name:hun_x_preferred":[
        "\u00d6tv\u00f6sk\u00f3nyi"
    ],
    "name:ita_x_preferred":[
        "\u00d6tv\u00f6sk\u00f3nyi"
    ],
    "name:msa_x_preferred":[
        "\u00d6tv\u00f6sk\u00f3nyi"
    ],
    "name:nld_x_preferred":[
        "\u00d6tv\u00f6sk\u00f3nyi"
    ],
    "name:por_x_preferred":[
        "\u00d6tv\u00f6sk\u00f3nyi"
    ],
    "name:ron_x_preferred":[
        "\u00d6tv\u00f6sk\u00f3nyi"
    ],
    "name:slk_x_preferred":[
        "\u00d6tv\u00f6sk\u00f3nyi"
    ],
    "name:slv_x_preferred":[
        "\u00d6tv\u00f6sk\u00f3nyi"
    ],
    "name:swe_x_preferred":[
        "\u00d6tv\u00f6sk\u00f3nyi"
    ],
    "name:vie_x_preferred":[
        "\u00d6tv\u00f6sk\u00f3nyi"
    ],
    "name:zho_x_preferred":[
        "\u5384\u7279\u6c83\u4ec0\u79d1\u5c3c"
    ],
    "qs_pg:aaroncc":"HU",
    "qs_pg:gn_country":"HU",
    "qs_pg:gn_fcode":"PPL",
    "qs_pg:gn_pop":901,
    "qs_pg:name":"\u00d6tv\u00f6sk\u00f3nyi",
    "qs_pg:photos_9r":0,
    "qs_pg:photos_sr":0,
    "qs_pg:pop_sr":2,
    "qs_pg:qs_pg_placetype":"locality",
    "wof:name":"\u00d6tv\u00f6sk\u00f3nyi",
    "wof:placetype":"locality",
    "wof:population":901
},
  "geometry": {"coordinates":[17.36003,46.28741],"type":"Point"}
}