{
  "type": "Feature",
  "properties": {
    "gn:admin1_code":"10.0",
    "gn:asciiname":"Cirkopuszta",
    "gn:cc2":"HU",
    "gn:country_code":"HU",
    "gn:dem":85,
    "gn:feature_class":"P",
    "gn:feature_code":"PPL",
    "gn:name":"Cirk\u00f3puszta",
    "gn:population":0,
    "gn:timezone":"Europe/Budapest",
    "iso:country":"HU",
    "name:und_x_variant":[
        "Cirk\u00f3",
        "Cirk\u00f3puszta"
    ],
    "wof:name":"Cirkopuszta",
    "wof:placetype":"locality"
},
  "geometry": {"coordinates":[21.33333,47.03333],"type":"Point"}
}