{
  "type": "Feature",
  "properties": {
    "gn:admin1_code":"18.0",
    "gn:asciiname":"Tothtanya",
    "gn:country_code":"HU",
    "gn:dem":95,
    "gn:feature_class":"P",
    "gn:feature_code":"PPL",
    "gn:name":"T\u00f3thtanya",
    "gn:population":0,
    "gn:timezone":"Europe/Budapest",
    "iso:country":"HU",
    "wof:name":"Tothtanya",
    "wof:placetype":"locality"
},
  "geometry": {"coordinates":[21.65,48.16667],"type":"Point"}
}