{
  "type": "Feature",
  "properties": {
    "gn:admin1_code":"2.0",
    "gn:asciiname":"Vorosipuszta",
    "gn:country_code":"HU",
    "gn:dem":101,
    "gn:feature_class":"P",
    "gn:feature_code":"PPL",
    "gn:name":"V\u00f6r\u00f6sipuszta",
    "gn:population":0,
    "gn:timezone":"Europe/Budapest",
    "iso:country":"HU",
    "wof:name":"Vorosipuszta",
    "wof:placetype":"locality"
},
  "geometry": {"coordinates":[17.78204,45.85215],"type":"Point"}
}