{
  "type": "Feature",
  "properties": {
    "gn:admin1_code":"2.0",
    "gn:asciiname":"Borza",
    "gn:country_code":"HU",
    "gn:dem":86,
    "gn:feature_class":"P",
    "gn:feature_code":"PPL",
    "gn:name":"Borza",
    "gn:population":0,
    "gn:timezone":"Europe/Budapest",
    "iso:country":"HU",
    "name:ceb_x_preferred":[
        "Borza"
    ],
    "name:deu_x_preferred":[
        "Borza"
    ],
    "name:epo_x_preferred":[
        "Borza"
    ],
    "name:swe_x_preferred":[
        "Borza"
    ],
    "wof:name":"Borza",
    "wof:placetype":"locality"
},
  "geometry": {"coordinates":[18.65,45.91667],"type":"Point"}
}