{
  "type": "Feature",
  "properties": {
    "gn:admin1_code":"17.0",
    "gn:asciiname":"Poganyszentpeter",
    "gn:country_code":"HU",
    "gn:dem":165,
    "gn:feature_class":"P",
    "gn:feature_code":"PPL",
    "gn:name":"Pog\u00e1nyszentp\u00e9ter",
    "gn:population":0,
    "gn:timezone":"Europe/Budapest",
    "iso:country":"HU",
    "name:und_x_variant":[
        "Pog\u00e1nyszentp\u00e9ter"
    ],
    "wof:name":"Poganyszentpeter",
    "wof:placetype":"locality"
},
  "geometry": {"coordinates":[17.06305,46.38478],"type":"Point"}
}