{
  "type": "Feature",
  "properties": {
    "gn:admin1_code":"17.0",
    "gn:asciiname":"Poganyszentpeter",
    "gn:country_code":"HU",
    "gn:dem":165,
    "gn:feature_class":"P",
    "gn:feature_code":"PPL",
    "gn:name":"Pog\u00e1nyszentp\u00e9ter",
    "gn:population":0,
    "gn:timezone":"Europe/Budapest",
    "iso:country":"HU",
    "name:deu_x_preferred":[
        "Pog\u00e1nyszentp\u00e9ter"
    ],
    "name:epo_x_preferred":[
        "Pog\u00e1nyszentp\u00e9ter"
    ],
    "name:fas_x_preferred":[
        "\u067e\u0648\u06af\u0627\u0646\u06cc\u0633\u0646\u062a\u067e\u062a\u0631"
    ],
    "name:fra_x_preferred":[
        "Pog\u00e1nyszentp\u00e9ter"
    ],
    "name:hrv_x_preferred":[
        "Pog\u00e1nyszentp\u00e9ter"
    ],
    "name:hun_x_preferred":[
        "Pog\u00e1nyszentp\u00e9ter"
    ],
    "name:ita_x_preferred":[
        "Pog\u00e1nyszentp\u00e9ter"
    ],
    "name:msa_x_preferred":[
        "Pog\u00e1nyszentp\u00e9ter"
    ],
    "name:nld_x_preferred":[
        "Pog\u00e1nyszentp\u00e9ter"
    ],
    "name:ron_x_preferred":[
        "Pog\u00e1nyszentp\u00e9ter"
    ],
    "name:slk_x_preferred":[
        "Pog\u00e1nyszentp\u00e9ter"
    ],
    "name:slv_x_preferred":[
        "Pog\u00e1nyszentp\u00e9ter"
    ],
    "name:und_x_variant":[
        "Pog\u00e1nyszentp\u00e9ter"
    ],
    "name:vie_x_preferred":[
        "Pog\u00e1nyszentp\u00e9ter"
    ],
    "name:zho_x_preferred":[
        "\u6ce2\u52a0\u5c3c\u68ee\u7279\u4f69\u6cf0\u5c14"
    ],
    "wof:name":"Poganyszentpeter",
    "wof:placetype":"locality"
},
  "geometry": {"coordinates":[17.06305,46.38478],"type":"Point"}
}