{
  "type": "Feature",
  "properties": {
    "gn:admin1_code":"18.0",
    "gn:asciiname":"Hartsteinmajor",
    "gn:country_code":"HU",
    "gn:dem":115,
    "gn:feature_class":"P",
    "gn:feature_code":"PPL",
    "gn:name":"Hartsteinmajor",
    "gn:population":0,
    "gn:timezone":"Europe/Budapest",
    "iso:country":"HU",
    "wof:name":"Hartsteinmajor",
    "wof:placetype":"locality"
},
  "geometry": {"coordinates":[21.86667000000001,47.93333],"type":"Point"}
}