{
  "type": "Feature",
  "properties": {
    "gn:admin1_code":"10.0",
    "gn:asciiname":"Pusztatarnokhat",
    "gn:country_code":"HU",
    "gn:dem":87,
    "gn:feature_class":"P",
    "gn:feature_code":"PPL",
    "gn:name":"Pusztat\u00e1rnokh\u00e1t",
    "gn:population":0,
    "gn:timezone":"Europe/Budapest",
    "iso:country":"HU",
    "wof:name":"Pusztatarnokhat",
    "wof:placetype":"locality"
},
  "geometry": {"coordinates":[21.16667,47.95],"type":"Point"}
}