{
  "type": "Feature",
  "properties": {
    "gn:admin1_code":"21.0",
    "gn:asciiname":"Ujaladar",
    "gn:country_code":"HU",
    "gn:dem":131,
    "gn:feature_class":"P",
    "gn:feature_code":"PPL",
    "gn:name":"\u00dajalad\u00e1r",
    "gn:population":0,
    "gn:timezone":"Europe/Budapest",
    "iso:country":"HU",
    "wof:name":"Ujaladar",
    "wof:placetype":"locality"
},
  "geometry": {"coordinates":[18.31667,46.78333],"type":"Point"}
}