{
  "type": "Feature",
  "properties": {
    "gn:admin1_code":"17.0",
    "gn:asciiname":"Gadany",
    "gn:country_code":"HU",
    "gn:dem":143,
    "gn:feature_class":"P",
    "gn:feature_code":"PPL",
    "gn:name":"Gad\u00e1ny",
    "gn:population":0,
    "gn:timezone":"Europe/Budapest",
    "iso:country":"HU",
    "name:epo_x_preferred":[
        "Gad\u00e1ny"
    ],
    "name:fas_x_preferred":[
        "\u06af\u0627\u062f\u0627\u0646\u06cc"
    ],
    "name:fra_x_preferred":[
        "Gad\u00e1ny"
    ],
    "name:hun_x_preferred":[
        "Gad\u00e1ny"
    ],
    "name:ita_x_preferred":[
        "Gad\u00e1ny"
    ],
    "name:msa_x_preferred":[
        "Gad\u00e1ny"
    ],
    "name:nld_x_preferred":[
        "Gad\u00e1ny"
    ],
    "name:ron_x_preferred":[
        "Gad\u00e1ny"
    ],
    "name:slk_x_preferred":[
        "Gad\u00e1ny"
    ],
    "name:slv_x_preferred":[
        "Gad\u00e1ny"
    ],
    "name:vie_x_preferred":[
        "Gad\u00e1ny"
    ],
    "name:zho_x_preferred":[
        "\u9ad8\u8fbe\u5c3c"
    ],
    "wof:name":"Gadany",
    "wof:placetype":"locality"
},
  "geometry": {"coordinates":[17.39155,46.51526],"type":"Point"}
}