{
  "type": "Feature",
  "properties": {
    "gn:admin1_code":"17.0",
    "gn:asciiname":"Daranypuszta",
    "gn:country_code":"HU",
    "gn:dem":127,
    "gn:feature_class":"P",
    "gn:feature_code":"PPL",
    "gn:name":"Dar\u00e1nypuszta",
    "gn:population":0,
    "gn:timezone":"Europe/Budapest",
    "iso:country":"HU",
    "wof:name":"Daranypuszta",
    "wof:placetype":"locality"
},
  "geometry": {"coordinates":[18.14513,46.76708],"type":"Point"}
}