{
  "type": "Feature",
  "properties": {
    "gn:admin1_code":"3.0",
    "gn:asciiname":"Zsofiamajor",
    "gn:country_code":"HU",
    "gn:dem":82,
    "gn:feature_class":"P",
    "gn:feature_code":"PPL",
    "gn:name":"Zs\u00f3fiamajor",
    "gn:population":0,
    "gn:timezone":"Europe/Budapest",
    "iso:country":"HU",
    "wof:name":"Zsofiamajor",
    "wof:placetype":"locality"
},
  "geometry": {"coordinates":[20.91667,46.93333],"type":"Point"}
}