{
  "type": "Feature",
  "properties": {
    "gn:admin1_code":"6.0",
    "gn:asciiname":"Borotvastelep",
    "gn:country_code":"HU",
    "gn:dem":84,
    "gn:feature_class":"P",
    "gn:feature_code":"PPL",
    "gn:name":"Borotv\u00e1stelep",
    "gn:population":0,
    "gn:timezone":"Europe/Budapest",
    "iso:country":"HU",
    "wof:name":"Borotvastelep",
    "wof:placetype":"locality"
},
  "geometry": {"coordinates":[20.61667000000001,46.16667],"type":"Point"}
}