{
  "type": "Feature",
  "properties": {
    "gn:admin1_code":"24.0",
    "gn:asciiname":"Dobroce",
    "gn:country_code":"HU",
    "gn:dem":160,
    "gn:feature_class":"P",
    "gn:feature_code":"PPL",
    "gn:name":"D\u00f6br\u00f6ce",
    "gn:population":0,
    "gn:timezone":"Europe/Budapest",
    "iso:country":"HU",
    "name:und_x_variant":[
        "D\u00f6br\u00f6ce"
    ],
    "wof:name":"Dobroce",
    "wof:placetype":"locality"
},
  "geometry": {"coordinates":[17.18779,46.93589],"type":"Point"}
}