{
  "type": "Feature",
  "properties": {
    "gn:admin1_code":"24.0",
    "gn:asciiname":"Dobroce",
    "gn:country_code":"HU",
    "gn:dem":160,
    "gn:feature_class":"P",
    "gn:feature_code":"PPL",
    "gn:name":"D\u00f6br\u00f6ce",
    "gn:population":0,
    "gn:timezone":"Europe/Budapest",
    "iso:country":"HU",
    "name:epo_x_preferred":[
        "D\u00f6br\u00f6ce"
    ],
    "name:fas_x_preferred":[
        "\u062f\u0648\u0628\u0631\u0648\u062a\u0633\u0647"
    ],
    "name:fra_x_preferred":[
        "D\u00f6br\u00f6ce"
    ],
    "name:hun_x_preferred":[
        "D\u00f6br\u00f6ce"
    ],
    "name:ita_x_preferred":[
        "D\u00f6br\u00f6ce"
    ],
    "name:msa_x_preferred":[
        "D\u00f6br\u00f6ce"
    ],
    "name:nld_x_preferred":[
        "D\u00f6br\u00f6ce"
    ],
    "name:ron_x_preferred":[
        "D\u00f6br\u00f6ce"
    ],
    "name:slk_x_preferred":[
        "D\u00f6br\u00f6ce"
    ],
    "name:slv_x_preferred":[
        "D\u00f6br\u00f6ce"
    ],
    "name:und_x_variant":[
        "D\u00f6br\u00f6ce"
    ],
    "name:vie_x_preferred":[
        "D\u00f6br\u00f6ce"
    ],
    "name:zho_x_preferred":[
        "\u5fb7\u5e03\u52d2\u91c7"
    ],
    "wof:name":"Dobroce",
    "wof:placetype":"locality"
},
  "geometry": {"coordinates":[17.18779,46.93589],"type":"Point"}
}