{
  "type": "Feature",
  "properties": {
    "gn:admin1_code":"18.0",
    "gn:asciiname":"Micsurintanya",
    "gn:country_code":"HU",
    "gn:dem":96,
    "gn:feature_class":"P",
    "gn:feature_code":"PPL",
    "gn:name":"Micsurintanya",
    "gn:population":0,
    "gn:timezone":"Europe/Budapest",
    "iso:country":"HU",
    "wof:name":"Micsurintanya",
    "wof:placetype":"locality"
},
  "geometry": {"coordinates":[21.81667,48.11667],"type":"Point"}
}