{
  "type": "Feature",
  "properties": {
    "gn:admin1_code":"1.0",
    "gn:asciiname":"Burkusdulo",
    "gn:country_code":"HU",
    "gn:dem":82,
    "gn:feature_class":"P",
    "gn:feature_code":"PPL",
    "gn:name":"Burkusd\u0171l\u0151",
    "gn:population":0,
    "gn:timezone":"Europe/Budapest",
    "iso:country":"HU",
    "wof:name":"Burkusdulo",
    "wof:placetype":"locality"
},
  "geometry": {"coordinates":[19.95,46.63333],"type":"Point"}
}