{
  "type": "Feature",
  "properties": {
    "gn:admin1_code":"8.0",
    "gn:asciiname":"Fabriciustanya",
    "gn:country_code":"HU",
    "gn:dem":121,
    "gn:feature_class":"P",
    "gn:feature_code":"PPL",
    "gn:name":"Fabriciustanya",
    "gn:population":0,
    "gn:timezone":"Europe/Budapest",
    "iso:country":"HU",
    "wof:name":"Fabriciustanya",
    "wof:placetype":"locality"
},
  "geometry": {"coordinates":[18.68333,47.08333],"type":"Point"}
}