{
  "type": "Feature",
  "properties": {
    "gn:admin1_code":"18.0",
    "gn:asciiname":"Berkesz",
    "gn:country_code":"HU",
    "gn:dem":103,
    "gn:feature_class":"P",
    "gn:feature_code":"PPL",
    "gn:name":"Berkesz",
    "gn:population":0,
    "gn:timezone":"Europe/Budapest",
    "iso:country":"HU",
    "wof:name":"Berkesz",
    "wof:placetype":"locality"
},
  "geometry": {"coordinates":[21.97912,48.09707],"type":"Point"}
}