{
  "type": "Feature",
  "properties": {
    "gn:admin1_code":"17.0",
    "gn:asciiname":"Halasgat",
    "gn:country_code":"HU",
    "gn:dem":165,
    "gn:feature_class":"P",
    "gn:feature_code":"PPL",
    "gn:name":"Halasgat",
    "gn:population":0,
    "gn:timezone":"Europe/Budapest",
    "iso:country":"HU",
    "name:und_x_variant":[
        "Halasg\u00e1tpuszta"
    ],
    "wof:name":"Halasgat",
    "wof:placetype":"locality"
},
  "geometry": {"coordinates":[17.55,46.38333],"type":"Point"}
}