{
  "type": "Feature",
  "properties": {
    "gn:admin1_code":"14.0",
    "gn:asciiname":"Baratonypuszta",
    "gn:country_code":"HU",
    "gn:dem":227,
    "gn:feature_class":"P",
    "gn:feature_code":"PPL",
    "gn:name":"Baratonypuszta",
    "gn:population":0,
    "gn:timezone":"Europe/Budapest",
    "iso:country":"HU",
    "wof:name":"Baratonypuszta",
    "wof:placetype":"locality"
},
  "geometry": {"coordinates":[20.01381,48.14334],"type":"Point"}
}