{
  "type": "Feature",
  "properties": {
    "iso:country":"HU",
    "wof:name":"Gloriett telep",
    "wof:placetype":"neighbourhood"
},
  "geometry": {"coordinates":[19.18693273523476,47.4308741479383],"type":"Point"}
}