{
  "type": "Feature",
  "properties": {
    "gn:admin1_code":"12.0",
    "gn:asciiname":"Surcsatar",
    "gn:country_code":"HU",
    "gn:dem":242,
    "gn:feature_class":"P",
    "gn:feature_code":"PPL",
    "gn:name":"S\u00farcsat\u00e1r",
    "gn:population":0,
    "gn:timezone":"Europe/Budapest",
    "iso:country":"HU",
    "wof:name":"Surcsatar",
    "wof:placetype":"locality"
},
  "geometry": {"coordinates":[17.98151,47.35139],"type":"Point"}
}