{
  "type": "Feature",
  "properties": {
    "gn:admin1_code":"18.0",
    "gn:asciiname":"Gattanya",
    "gn:country_code":"HU",
    "gn:dem":120,
    "gn:feature_class":"P",
    "gn:feature_code":"PPL",
    "gn:name":"G\u00e1ttanya",
    "gn:population":0,
    "gn:timezone":"Europe/Budapest",
    "iso:country":"HU",
    "wof:name":"Gattanya",
    "wof:placetype":"locality"
},
  "geometry": {"coordinates":[21.85,47.86667],"type":"Point"}
}