{
  "type": "Feature",
  "properties": {
    "gn:admin1_code":"11.0",
    "gn:asciiname":"Csokastanya",
    "gn:country_code":"HU",
    "gn:dem":183,
    "gn:feature_class":"P",
    "gn:feature_code":"PPL",
    "gn:name":"Cs\u00f3k\u00e1stanya",
    "gn:population":0,
    "gn:timezone":"Europe/Budapest",
    "iso:country":"HU",
    "name:und_x_variant":[
        "Cs\u00f3k\u00e1spuszta",
        "Cs\u00f3k\u00e1stanya"
    ],
    "wof:name":"Csokastanya",
    "wof:placetype":"locality"
},
  "geometry": {"coordinates":[19.98858,47.75466],"type":"Point"}
}