{
  "type": "Feature",
  "properties": {
    "gn:admin1_code":"24.0",
    "gn:asciiname":"Csacsihegy",
    "gn:country_code":"HU",
    "gn:dem":163,
    "gn:feature_class":"P",
    "gn:feature_code":"PPL",
    "gn:name":"Cs\u00e1csihegy",
    "gn:population":0,
    "gn:timezone":"Europe/Budapest",
    "iso:country":"HU",
    "name:und_x_variant":[
        "Cs\u00e1cs",
        "Cs\u00e1csihegy"
    ],
    "wof:name":"Csacsihegy",
    "wof:placetype":"locality"
},
  "geometry": {"coordinates":[16.88332999999999,46.85],"type":"Point"}
}