{
  "type": "Feature",
  "properties": {
    "gn:admin1_code":"22.0",
    "gn:asciiname":"Dombhatimajor",
    "gn:country_code":"HU",
    "gn:dem":188,
    "gn:feature_class":"P",
    "gn:feature_code":"PPL",
    "gn:name":"Dombh\u00e1timajor",
    "gn:population":0,
    "gn:timezone":"Europe/Budapest",
    "iso:country":"HU",
    "wof:name":"Dombhatimajor",
    "wof:placetype":"locality"
},
  "geometry": {"coordinates":[16.77223,47.22147],"type":"Point"}
}