{
  "type": "Feature",
  "properties": {
    "gn:admin1_code":"17.0",
    "gn:asciiname":"Cserenfa",
    "gn:country_code":"HU",
    "gn:dem":143,
    "gn:feature_class":"P",
    "gn:feature_code":"PPL",
    "gn:name":"Cser\u00e9nfa",
    "gn:population":0,
    "gn:timezone":"Europe/Budapest",
    "iso:country":"HU",
    "name:bar_x_preferred":[
        "Cser\u00e9nfa"
    ],
    "name:deu_x_preferred":[
        "Cser\u00e9nfa"
    ],
    "name:epo_x_preferred":[
        "Cser\u00e9nfa"
    ],
    "name:fas_x_preferred":[
        "\u0686\u0631\u0646\u0641\u0627"
    ],
    "name:fra_x_preferred":[
        "Cser\u00e9nfa"
    ],
    "name:hun_x_preferred":[
        "Cser\u00e9nfa"
    ],
    "name:ita_x_preferred":[
        "Cser\u00e9nfa"
    ],
    "name:msa_x_preferred":[
        "Cser\u00e9nfa"
    ],
    "name:nld_x_preferred":[
        "Cser\u00e9nfa"
    ],
    "name:ron_x_preferred":[
        "Cser\u00e9nfa"
    ],
    "name:slk_x_preferred":[
        "Cser\u00e9nfa"
    ],
    "name:slv_x_preferred":[
        "Cser\u00e9nfa"
    ],
    "name:vie_x_preferred":[
        "Cser\u00e9nfa"
    ],
    "name:zho_x_preferred":[
        "\u5207\u4f26\u798f"
    ],
    "wof:name":"Cserenfa",
    "wof:placetype":"locality"
},
  "geometry": {"coordinates":[17.87882,46.30727],"type":"Point"}
}