{
  "type": "Feature",
  "properties": {
    "gn:admin1_code":"20.0",
    "gn:asciiname":"Erzsebetmajor",
    "gn:country_code":"HU",
    "gn:dem":85,
    "gn:feature_class":"P",
    "gn:feature_code":"PPL",
    "gn:name":"Erzs\u00e9betmajor",
    "gn:population":0,
    "gn:timezone":"Europe/Budapest",
    "iso:country":"HU",
    "wof:name":"Erzsebetmajor",
    "wof:placetype":"locality"
},
  "geometry": {"coordinates":[20.33333,47.08333],"type":"Point"}
}