{
  "type": "Feature",
  "properties": {
    "gn:admin1_code":"17.0",
    "gn:asciiname":"Kisecseny",
    "gn:country_code":"HU",
    "gn:dem":237,
    "gn:feature_class":"P",
    "gn:feature_code":"PPL",
    "gn:name":"Kisecseny",
    "gn:population":0,
    "gn:timezone":"Europe/Budapest",
    "iso:country":"HU",
    "wof:name":"Kisecseny",
    "wof:placetype":"locality"
},
  "geometry": {"coordinates":[18.0269,46.77508],"type":"Point"}
}