{
  "type": "Feature",
  "properties": {
    "gn:admin1_code":"22.0",
    "gn:asciiname":"Annamajor",
    "gn:country_code":"HU",
    "gn:dem":188,
    "gn:feature_class":"P",
    "gn:feature_code":"PPL",
    "gn:name":"Annamajor",
    "gn:population":0,
    "gn:timezone":"Europe/Budapest",
    "iso:country":"HU",
    "wof:name":"Annamajor",
    "wof:placetype":"locality"
},
  "geometry": {"coordinates":[16.71394,47.1659],"type":"Point"}
}