{
  "type": "Feature",
  "properties": {
    "gn:admin1_code":"23.0",
    "gn:asciiname":"Bakonyszentivan",
    "gn:country_code":"HU",
    "gn:dem":170,
    "gn:feature_class":"P",
    "gn:feature_code":"PPL",
    "gn:name":"Bakonyszentiv\u00e1n",
    "gn:population":0,
    "gn:timezone":"Europe/Budapest",
    "iso:country":"HU",
    "name:ces_x_preferred":[
        "Bakonyszentiv\u00e1n"
    ],
    "name:epo_x_preferred":[
        "Bakonyszentiv\u00e1n"
    ],
    "name:fas_x_preferred":[
        "\u0628\u0627\u06a9\u0648\u0646\u06cc\u0633\u0646\u062a\u06cc\u0648\u0627\u0646"
    ],
    "name:fra_x_preferred":[
        "Bakonyszentiv\u00e1n"
    ],
    "name:hun_x_preferred":[
        "Bakonyszentiv\u00e1n"
    ],
    "name:ita_x_preferred":[
        "Bakonyszentiv\u00e1n"
    ],
    "name:msa_x_preferred":[
        "Bakonyszentiv\u00e1n"
    ],
    "name:nld_x_preferred":[
        "Bakonyszentiv\u00e1n"
    ],
    "name:ron_x_preferred":[
        "Bakonyszentiv\u00e1n"
    ],
    "name:slk_x_preferred":[
        "Bakonyszentiv\u00e1n"
    ],
    "name:slv_x_preferred":[
        "Bakonyszentiv\u00e1n"
    ],
    "name:und_x_variant":[
        "Bakonyszentiv\u00e1n"
    ],
    "name:vie_x_preferred":[
        "Bakonyszentiv\u00e1n"
    ],
    "name:zho_x_preferred":[
        "\u9c8d\u79d1\u5c3c\u68ee\u8482\u4e07"
    ],
    "wof:name":"Bakonyszentivan",
    "wof:placetype":"locality"
},
  "geometry": {"coordinates":[17.67059,47.38977],"type":"Point"}
}