{
  "type": "Feature",
  "properties": {
    "gn:admin1_code":"23.0",
    "gn:asciiname":"Bakonyszentivan",
    "gn:country_code":"HU",
    "gn:dem":170,
    "gn:feature_class":"P",
    "gn:feature_code":"PPL",
    "gn:name":"Bakonyszentiv\u00e1n",
    "gn:population":0,
    "gn:timezone":"Europe/Budapest",
    "iso:country":"HU",
    "name:und_x_variant":[
        "Bakonyszentiv\u00e1n"
    ],
    "wof:name":"Bakonyszentivan",
    "wof:placetype":"locality"
},
  "geometry": {"coordinates":[17.67059,47.38977],"type":"Point"}
}