{
  "type": "Feature",
  "properties": {
    "gn:admin1_code":"24.0",
    "gn:asciiname":"Zalamerenye",
    "gn:country_code":"HU",
    "gn:dem":138,
    "gn:feature_class":"P",
    "gn:feature_code":"PPL",
    "gn:name":"Zalamerenye",
    "gn:population":0,
    "gn:timezone":"Europe/Budapest",
    "iso:country":"HU",
    "name:epo_x_preferred":[
        "Zalamerenye"
    ],
    "name:fas_x_preferred":[
        "\u0632\u0627\u0644\u0627\u0645\u0631\u0646\u06cc\u0647"
    ],
    "name:fra_x_preferred":[
        "Zalamerenye"
    ],
    "name:hun_x_preferred":[
        "Zalamerenye"
    ],
    "name:ita_x_preferred":[
        "Zalamerenye"
    ],
    "name:msa_x_preferred":[
        "Zalamerenye"
    ],
    "name:nld_x_preferred":[
        "Zalamerenye"
    ],
    "name:ron_x_preferred":[
        "Zalamerenye"
    ],
    "name:slk_x_preferred":[
        "Zalamerenye"
    ],
    "name:slv_x_preferred":[
        "Zalamerenye"
    ],
    "name:vie_x_preferred":[
        "Zalamerenye"
    ],
    "name:zho_x_preferred":[
        "\u4f50\u6d1b\u8fc8\u8d56\u6d85"
    ],
    "wof:name":"Zalamerenye",
    "wof:placetype":"locality"
},
  "geometry": {"coordinates":[17.0934,46.57128],"type":"Point"}
}