{
  "type": "Feature",
  "properties": {
    "gn:admin1_code":"17.0",
    "gn:asciiname":"Banyaszo",
    "gn:country_code":"HU",
    "gn:dem":158,
    "gn:feature_class":"P",
    "gn:feature_code":"PPL",
    "gn:name":"B\u00e1ny\u00e1sz\u00f3",
    "gn:population":0,
    "gn:timezone":"Europe/Budapest",
    "iso:country":"HU",
    "wof:name":"Banyaszo",
    "wof:placetype":"locality"
},
  "geometry": {"coordinates":[17.68332999999999,46.71667],"type":"Point"}
}