{
  "type": "Feature",
  "properties": {
    "gn:admin1_code":"16.0",
    "gn:asciiname":"Ludvigtanya",
    "gn:country_code":"HU",
    "gn:dem":166,
    "gn:feature_class":"P",
    "gn:feature_code":"PPL",
    "gn:name":"Ludvigtanya",
    "gn:population":0,
    "gn:timezone":"Europe/Budapest",
    "iso:country":"HU",
    "wof:name":"Ludvigtanya",
    "wof:placetype":"locality"
},
  "geometry": {"coordinates":[18.91667,47.43333],"type":"Point"}
}