{
  "type": "Feature",
  "properties": {
    "gn:admin1_code":"2.0",
    "gn:asciiname":"Kistotfalu",
    "gn:country_code":"HU",
    "gn:dem":125,
    "gn:feature_class":"P",
    "gn:feature_code":"PPL",
    "gn:name":"Kist\u00f3tfalu",
    "gn:population":0,
    "gn:timezone":"Europe/Budapest",
    "iso:country":"HU",
    "name:und_x_variant":[
        "Kist\u00f3tfalu"
    ],
    "wof:name":"Kistotfalu",
    "wof:placetype":"locality"
},
  "geometry": {"coordinates":[18.30805,45.90788],"type":"Point"}
}