{
  "type": "Feature",
  "properties": {
    "gn:admin1_code":"2.0",
    "gn:asciiname":"Kistotfalu",
    "gn:country_code":"HU",
    "gn:dem":125,
    "gn:feature_class":"P",
    "gn:feature_code":"PPL",
    "gn:name":"Kist\u00f3tfalu",
    "gn:population":0,
    "gn:timezone":"Europe/Budapest",
    "iso:country":"HU",
    "name:deu_x_preferred":[
        "Kist\u00f3tfalu"
    ],
    "name:epo_x_preferred":[
        "Kist\u00f3tfalu"
    ],
    "name:fas_x_preferred":[
        "\u06a9\u06cc\u0634\u062a\u0648\u062a\u0641\u0627\u0644\u0648"
    ],
    "name:fra_x_preferred":[
        "Kist\u00f3tfalu"
    ],
    "name:hrv_x_preferred":[
        "Tofaluba"
    ],
    "name:hun_x_preferred":[
        "Kist\u00f3tfalu"
    ],
    "name:ita_x_preferred":[
        "Kist\u00f3tfalu"
    ],
    "name:msa_x_preferred":[
        "Kist\u00f3tfalu"
    ],
    "name:nld_x_preferred":[
        "Kist\u00f3tfalu"
    ],
    "name:pol_x_preferred":[
        "Kist\u00f3tfalu"
    ],
    "name:ron_x_preferred":[
        "Kist\u00f3tfalu"
    ],
    "name:slk_x_preferred":[
        "Kist\u00f3tfalu"
    ],
    "name:slv_x_preferred":[
        "Kist\u00f3tfalu"
    ],
    "name:vie_x_preferred":[
        "Kist\u00f3tfalu"
    ],
    "name:zho_x_preferred":[
        "\u57fa\u4ec0\u6258\u7279\u798f\u5362"
    ],
    "wof:name":"Kistotfalu",
    "wof:placetype":"locality"
},
  "geometry": {"coordinates":[18.30805,45.90788],"type":"Point"}
}