{
  "type": "Feature",
  "properties": {
    "gn:admin1_code":"2.0",
    "gn:asciiname":"Ketujfalu",
    "gn:country_code":"HU",
    "gn:dem":106,
    "gn:feature_class":"P",
    "gn:feature_code":"PPL",
    "gn:name":"K\u00e9t\u00fajfalu",
    "gn:population":0,
    "gn:timezone":"Europe/Budapest",
    "iso:country":"HU",
    "name:und_x_variant":[
        "K\u00e9t\u00fajfalu"
    ],
    "wof:name":"Ketujfalu",
    "wof:placetype":"locality"
},
  "geometry": {"coordinates":[17.71209,45.96555],"type":"Point"}
}