{
  "type": "Feature",
  "properties": {
    "gn:admin1_code":"2.0",
    "gn:asciiname":"Cegledpuszta",
    "gn:country_code":"HU",
    "gn:dem":137,
    "gn:feature_class":"P",
    "gn:feature_code":"PPL",
    "gn:name":"Cegl\u00e9dpuszta",
    "gn:population":0,
    "gn:timezone":"Europe/Budapest",
    "iso:country":"HU",
    "wof:name":"Cegledpuszta",
    "wof:placetype":"locality"
},
  "geometry": {"coordinates":[17.68735,46.09601],"type":"Point"}
}