{
  "type": "Feature",
  "properties": {
    "gn:admin1_code":"16.0",
    "gn:asciiname":"Felsojaras",
    "gn:country_code":"HU",
    "gn:dem":137,
    "gn:feature_class":"P",
    "gn:feature_code":"PPLL",
    "gn:name":"Fels\u0151j\u00e1r\u00e1s",
    "gn:population":0,
    "gn:timezone":"Europe/Budapest",
    "iso:country":"HU",
    "wof:name":"Felsojaras",
    "wof:placetype":"locality"
},
  "geometry": {"coordinates":[19.63333,47.08333],"type":"Point"}
}