{
  "type": "Feature",
  "properties": {
    "gn:admin1_code":"12.0",
    "gn:asciiname":"Vertestolna",
    "gn:country_code":"HU",
    "gn:dem":274,
    "gn:feature_class":"P",
    "gn:feature_code":"PPL",
    "gn:name":"V\u00e9rtestolna",
    "gn:population":0,
    "gn:timezone":"Europe/Budapest",
    "iso:country":"HU",
    "name:epo_x_preferred":[
        "V\u00e9rtestolna"
    ],
    "name:fas_x_preferred":[
        "\u0648\u0631\u062a\u0634\u062a\u0648\u0644\u0646\u0627"
    ],
    "name:fra_x_preferred":[
        "V\u00e9rtestolna"
    ],
    "name:hun_x_preferred":[
        "V\u00e9rtestolna"
    ],
    "name:ita_x_preferred":[
        "V\u00e9rtestolna"
    ],
    "name:msa_x_preferred":[
        "V\u00e9rtestolna"
    ],
    "name:nld_x_preferred":[
        "V\u00e9rtestolna"
    ],
    "name:ron_x_preferred":[
        "V\u00e9rtestolna"
    ],
    "name:slk_x_preferred":[
        "V\u00e9rtestolna"
    ],
    "name:slv_x_preferred":[
        "V\u00e9rtestolna"
    ],
    "name:vie_x_preferred":[
        "V\u00e9rtestolna"
    ],
    "name:zho_x_preferred":[
        "\u97e6\u5c14\u6cf0\u4ec0\u6258\u5c14\u7459"
    ],
    "wof:name":"Vertestolna",
    "wof:placetype":"locality"
},
  "geometry": {"coordinates":[18.4546,47.62744],"type":"Point"}
}