{
  "type": "Feature",
  "properties": {
    "gn:admin1_code":"17.0",
    "gn:asciiname":"Somodor",
    "gn:country_code":"HU",
    "gn:dem":139,
    "gn:feature_class":"P",
    "gn:feature_code":"PPL",
    "gn:name":"Somodor",
    "gn:population":0,
    "gn:timezone":"Europe/Budapest",
    "iso:country":"HU",
    "name:epo_x_preferred":[
        "Somodor"
    ],
    "name:fra_x_preferred":[
        "Somodor"
    ],
    "name:hun_x_preferred":[
        "Somodor"
    ],
    "name:ita_x_preferred":[
        "Somodor"
    ],
    "name:msa_x_preferred":[
        "Somodor"
    ],
    "name:nld_x_preferred":[
        "Somodor"
    ],
    "name:ron_x_preferred":[
        "Somodor"
    ],
    "name:slk_x_preferred":[
        "Somodor"
    ],
    "name:slv_x_preferred":[
        "Somodor"
    ],
    "name:vie_x_preferred":[
        "Somodor"
    ],
    "name:zho_x_preferred":[
        "\u7ecd\u83ab\u591a\u5c14"
    ],
    "wof:name":"Somodor",
    "wof:placetype":"locality"
},
  "geometry": {"coordinates":[17.8415,46.47464],"type":"Point"}
}