{
  "type": "Feature",
  "properties": {
    "gn:admin1_code":"4.0",
    "gn:asciiname":"Juliskatanya",
    "gn:country_code":"HU",
    "gn:dem":104,
    "gn:feature_class":"P",
    "gn:feature_code":"PPL",
    "gn:name":"Juliskatanya",
    "gn:population":0,
    "gn:timezone":"Europe/Budapest",
    "iso:country":"HU",
    "wof:name":"Juliskatanya",
    "wof:placetype":"locality"
},
  "geometry": {"coordinates":[20.85,48.05],"type":"Point"}
}