{
  "type": "Feature",
  "properties": {
    "gn:gn_country":"HU",
    "gn:gn_fcode":"PPL",
    "gn:gn_pop":0,
    "iso:country":"HU",
    "name:chi_x_preferred":[
        "\u9c8d\u79d1\u5c3c\u5965"
    ],
    "name:cze_x_preferred":[
        "Bakonya"
    ],
    "name:dut_x_preferred":[
        "Bakonya"
    ],
    "name:eng_x_preferred":[
        "Bakonya"
    ],
    "name:epo_x_preferred":[
        "Bakonya"
    ],
    "name:fre_x_preferred":[
        "Bakonya"
    ],
    "name:hrv_x_preferred":[
        "Bakonya"
    ],
    "name:hun_x_preferred":[
        "Bakonya"
    ],
    "name:ita_x_preferred":[
        "Bakonya"
    ],
    "name:may_x_preferred":[
        "Bakonya"
    ],
    "name:nan_x_preferred":[
        "Bakonya"
    ],
    "name:pol_x_preferred":[
        "Bakonya"
    ],
    "name:rum_x_preferred":[
        "Bakonya"
    ],
    "name:slo_x_preferred":[
        "Bakonya"
    ],
    "name:slv_x_preferred":[
        "Bakonya"
    ],
    "name:vie_x_preferred":[
        "Bakonya"
    ],
    "qs_pg:aaroncc":"HU",
    "qs_pg:gn_country":"HU",
    "qs_pg:gn_fcode":"PPL",
    "qs_pg:gn_pop":0,
    "qs_pg:name":"Bakonya",
    "qs_pg:name_adm0":"Magyarorsz\u00e1g",
    "qs_pg:name_adm1":"Baranya",
    "qs_pg:photos":49,
    "qs_pg:photos_1k":10,
    "qs_pg:photos_9k":1,
    "qs_pg:photos_9r":2,
    "qs_pg:photos_all":49,
    "qs_pg:photos_sr":2,
    "qs_pg:pop_sr":0,
    "qs_pg:qs_pg_placetype":"locality",
    "qs_pg:qs_pg_placetype_gp":"Town",
    "qs_pg:woe_adm0":23424844,
    "woe:adm0_id":23424844,
    "woe:name_adm0":"Magyarorsz\u00e1g",
    "woe:name_adm1":"Baranya",
    "woe:placetype":"Town",
    "wof:name":"Bakonya",
    "wof:placetype":"locality"
},
  "geometry": {"coordinates":[18.08308,46.08523],"type":"Point"}
}