{
  "type": "Feature",
  "properties": {
    "gn:admin1_code":"11.0",
    "gn:asciiname":"Hegedustanya",
    "gn:country_code":"HU",
    "gn:dem":199,
    "gn:feature_class":"P",
    "gn:feature_code":"PPL",
    "gn:name":"Heged\u0171stanya",
    "gn:population":0,
    "gn:timezone":"Europe/Budapest",
    "iso:country":"HU",
    "wof:name":"Hegedustanya",
    "wof:placetype":"locality"
},
  "geometry": {"coordinates":[20.11667000000001,47.96667],"type":"Point"}
}