{
  "type": "Feature",
  "properties": {
    "gn:admin1_code":"18.0",
    "gn:asciiname":"Togyesszog",
    "gn:country_code":"HU",
    "gn:dem":100,
    "gn:feature_class":"P",
    "gn:feature_code":"PPL",
    "gn:name":"T\u0151gyessz\u00f6g",
    "gn:population":0,
    "gn:timezone":"Europe/Budapest",
    "iso:country":"HU",
    "wof:name":"Togyesszog",
    "wof:placetype":"locality"
},
  "geometry": {"coordinates":[22.00816,48.26831],"type":"Point"}
}