{
  "type": "Feature",
  "properties": {
    "gn:admin1_code":"23.0",
    "gn:asciiname":"Bakonytamasi",
    "gn:country_code":"HU",
    "gn:dem":162,
    "gn:feature_class":"P",
    "gn:feature_code":"PPL",
    "gn:name":"Bakonytam\u00e1si",
    "gn:population":0,
    "gn:timezone":"Europe/Budapest",
    "iso:country":"HU",
    "name:aze_x_preferred":[
        "Bakontama\u015fi"
    ],
    "name:ces_x_preferred":[
        "Bakonytam\u00e1si"
    ],
    "name:epo_x_preferred":[
        "Bakonytam\u00e1si"
    ],
    "name:fas_x_preferred":[
        "\u0628\u0627\u06a9\u0648\u0646\u06cc\u062a\u0627\u0645\u0627\u0634\u06cc"
    ],
    "name:fra_x_preferred":[
        "Bakonytam\u00e1si"
    ],
    "name:hun_x_preferred":[
        "Bakonytam\u00e1si"
    ],
    "name:ita_x_preferred":[
        "Bakonytam\u00e1si"
    ],
    "name:msa_x_preferred":[
        "Bakonytam\u00e1si"
    ],
    "name:nld_x_preferred":[
        "Bakonytam\u00e1si"
    ],
    "name:ron_x_preferred":[
        "Bakonytam\u00e1si"
    ],
    "name:slk_x_preferred":[
        "Bakonytam\u00e1si"
    ],
    "name:slv_x_preferred":[
        "Bakonytam\u00e1si"
    ],
    "name:vie_x_preferred":[
        "Bakonytam\u00e1si"
    ],
    "name:zho_x_preferred":[
        "\u9c8d\u79d1\u5c3c\u9676\u9a6c\u5e0c"
    ],
    "wof:name":"Bakonytamasi",
    "wof:placetype":"locality"
},
  "geometry": {"coordinates":[17.73398,47.41238],"type":"Point"}
}