{
  "type": "Feature",
  "properties": {
    "gn:admin1_code":"23.0",
    "gn:asciiname":"Bakonytamasi",
    "gn:country_code":"HU",
    "gn:dem":162,
    "gn:feature_class":"P",
    "gn:feature_code":"PPL",
    "gn:name":"Bakonytam\u00e1si",
    "gn:population":0,
    "gn:timezone":"Europe/Budapest",
    "iso:country":"HU",
    "name:und_x_variant":[
        "Bakonytam\u00e1si"
    ],
    "wof:name":"Bakonytamasi",
    "wof:placetype":"locality"
},
  "geometry": {"coordinates":[17.73398,47.41238],"type":"Point"}
}