{
  "type": "Feature",
  "properties": {
    "gn:admin1_code":"11.0",
    "gn:asciiname":"Darab-kut",
    "gn:cc2":"HU",
    "gn:country_code":"HU",
    "gn:dem":340,
    "gn:feature_class":"P",
    "gn:feature_code":"PPL",
    "gn:name":"Darab-k\u00fat",
    "gn:population":0,
    "gn:timezone":"Europe/Budapest",
    "iso:country":"HU",
    "name:und_x_variant":[
        "Darabk\u00fattanya",
        "Darab-k\u00fat"
    ],
    "wof:name":"Darab-kut",
    "wof:placetype":"locality"
},
  "geometry": {"coordinates":[20.06667,48.08333],"type":"Point"}
}