{
  "type": "Feature",
  "properties": {
    "gn:gn_country":"HU",
    "gn:gn_fcode":"PPLX",
    "gn:gn_pop":0,
    "iso:country":"HU",
    "name:unk_x_variant":[
        "M\u00f6lcnerh\u00e1z"
    ],
    "qs_pg:aaroncc":"HU",
    "qs_pg:gn_country":"HU",
    "qs_pg:gn_fcode":"PPLX",
    "qs_pg:gn_pop":0,
    "qs_pg:name":"M\u00f6lcznertanya",
    "qs_pg:name_adm0":"Magyarorsz\u00e1g",
    "qs_pg:name_adm1":"Gy\u0151r-Moson-Sopron",
    "qs_pg:photos":2,
    "qs_pg:photos_1k":1,
    "qs_pg:photos_9k":1,
    "qs_pg:photos_9r":1,
    "qs_pg:photos_all":2,
    "qs_pg:photos_sr":1,
    "qs_pg:pop_sr":0,
    "qs_pg:qs_pg_placetype":"neighbourhood",
    "qs_pg:qs_pg_placetype_gp":"Suburb",
    "qs_pg:woe_adm0":23424844,
    "woe:adm0_id":23424844,
    "woe:name_adm0":"Magyarorsz\u00e1g",
    "woe:name_adm1":"Gy\u0151r-Moson-Sopron",
    "woe:placetype":"Suburb",
    "wof:name":"M\u00f6lcznertanya",
    "wof:placetype":"neighbourhood"
},
  "geometry": {"coordinates":[17.28333,47.86667],"type":"Point"}
}