{
  "type": "Feature",
  "properties": {
    "gn:admin1_code":"21.0",
    "gn:asciiname":"Jagonak",
    "gn:country_code":"HU",
    "gn:dem":169,
    "gn:feature_class":"P",
    "gn:feature_code":"PPL",
    "gn:name":"J\u00e1g\u00f3nak",
    "gn:population":0,
    "gn:timezone":"Europe/Budapest",
    "iso:country":"HU",
    "name:und_x_variant":[
        "J\u00e1g\u00f3nak"
    ],
    "wof:name":"Jagonak",
    "wof:placetype":"locality"
},
  "geometry": {"coordinates":[18.09241,46.31419],"type":"Point"}
}