{
  "type": "Feature",
  "properties": {
    "gn:admin1_code":"21.0",
    "gn:asciiname":"Jagonak",
    "gn:country_code":"HU",
    "gn:dem":169,
    "gn:feature_class":"P",
    "gn:feature_code":"PPL",
    "gn:name":"J\u00e1g\u00f3nak",
    "gn:population":0,
    "gn:timezone":"Europe/Budapest",
    "iso:country":"HU",
    "name:ces_x_preferred":[
        "J\u00e1g\u00f3nak"
    ],
    "name:epo_x_preferred":[
        "J\u00e1g\u00f3nak"
    ],
    "name:fas_x_preferred":[
        "\u06cc\u0627\u06af\u0648\u0646\u0627\u06a9"
    ],
    "name:fra_x_preferred":[
        "J\u00e1g\u00f3nak"
    ],
    "name:hun_x_preferred":[
        "J\u00e1g\u00f3nak"
    ],
    "name:ita_x_preferred":[
        "J\u00e1g\u00f3nak"
    ],
    "name:msa_x_preferred":[
        "J\u00e1g\u00f3nak"
    ],
    "name:nld_x_preferred":[
        "J\u00e1g\u00f3nak"
    ],
    "name:ron_x_preferred":[
        "J\u00e1g\u00f3nak"
    ],
    "name:slk_x_preferred":[
        "J\u00e1g\u00f3nak"
    ],
    "name:slv_x_preferred":[
        "J\u00e1g\u00f3nak"
    ],
    "name:vie_x_preferred":[
        "J\u00e1g\u00f3nak"
    ],
    "name:zho_x_preferred":[
        "\u4e9a\u6208\u7459\u514b"
    ],
    "wof:name":"Jagonak",
    "wof:placetype":"locality"
},
  "geometry": {"coordinates":[18.09241,46.31419],"type":"Point"}
}