{
  "type": "Feature",
  "properties": {
    "gn:admin1_code":"9.0",
    "gn:asciiname":"Szarfold",
    "gn:country_code":"HU",
    "gn:dem":120,
    "gn:feature_class":"P",
    "gn:feature_code":"PPL",
    "gn:name":"Sz\u00e1rf\u00f6ld",
    "gn:population":0,
    "gn:timezone":"Europe/Budapest",
    "iso:country":"HU",
    "name:deu_x_preferred":[
        "Sz\u00e1rf\u00f6ld"
    ],
    "name:epo_x_preferred":[
        "Sz\u00e1rf\u00f6ld"
    ],
    "name:fas_x_preferred":[
        "\u0633\u0627\u0631\u0641\u0648\u0644\u062f"
    ],
    "name:fra_x_preferred":[
        "Sz\u00e1rf\u00f6ld"
    ],
    "name:heb_x_preferred":[
        "\u05e1\u05d0\u05e8\u05e4\u05dc\u05d3"
    ],
    "name:hun_x_preferred":[
        "Sz\u00e1rf\u00f6ld"
    ],
    "name:ita_x_preferred":[
        "Sz\u00e1rf\u00f6ld"
    ],
    "name:msa_x_preferred":[
        "Sz\u00e1rf\u00f6ld"
    ],
    "name:nld_x_preferred":[
        "Sz\u00e1rf\u00f6ld"
    ],
    "name:pol_x_preferred":[
        "Sz\u00e1rf\u00f6ld"
    ],
    "name:ron_x_preferred":[
        "Sz\u00e1rf\u00f6ld"
    ],
    "name:slk_x_preferred":[
        "Sz\u00e1rf\u00f6ld"
    ],
    "name:slv_x_preferred":[
        "Sz\u00e1rf\u00f6ld"
    ],
    "name:und_x_variant":[
        "Sz\u00e1rf\u00f6ld"
    ],
    "name:vie_x_preferred":[
        "Sz\u00e1rf\u00f6ld"
    ],
    "name:zho_x_preferred":[
        "\u8428\u5c14\u5f17\u5c14\u5fb7"
    ],
    "wof:name":"Szarfold",
    "wof:placetype":"locality"
},
  "geometry": {"coordinates":[17.12227,47.59269000000001],"type":"Point"}
}