{
  "type": "Feature",
  "properties": {
    "gn:admin1_code":"9.0",
    "gn:asciiname":"Szarfold",
    "gn:country_code":"HU",
    "gn:dem":120,
    "gn:feature_class":"P",
    "gn:feature_code":"PPL",
    "gn:name":"Sz\u00e1rf\u00f6ld",
    "gn:population":0,
    "gn:timezone":"Europe/Budapest",
    "iso:country":"HU",
    "name:und_x_variant":[
        "Sz\u00e1rf\u00f6ld"
    ],
    "wof:name":"Szarfold",
    "wof:placetype":"locality"
},
  "geometry": {"coordinates":[17.12227,47.59269000000001],"type":"Point"}
}