{
  "type": "Feature",
  "properties": {
    "gn:admin1_code":"6.0",
    "gn:asciiname":"Eperjes",
    "gn:country_code":"HU",
    "gn:dem":81,
    "gn:feature_class":"P",
    "gn:feature_code":"PPL",
    "gn:name":"Eperjes",
    "gn:population":0,
    "gn:timezone":"Europe/Budapest",
    "iso:country":"HU",
    "wof:name":"Eperjes",
    "wof:placetype":"locality"
},
  "geometry": {"coordinates":[20.56667,46.68333],"type":"Point"}
}