{
  "type": "Feature",
  "properties": {
    "gn:admin1_code":"6.0",
    "gn:asciiname":"Eperjes",
    "gn:country_code":"HU",
    "gn:dem":81,
    "gn:feature_class":"P",
    "gn:feature_code":"PPL",
    "gn:name":"Eperjes",
    "gn:population":0,
    "gn:timezone":"Europe/Budapest",
    "iso:country":"HU",
    "name:epo_x_preferred":[
        "Eperjes"
    ],
    "name:fas_x_preferred":[
        "\u0627\u067e\u0631\u06cc\u0634"
    ],
    "name:fra_x_preferred":[
        "Eperjes"
    ],
    "name:hun_x_preferred":[
        "Eperjes"
    ],
    "name:ita_x_preferred":[
        "Eperjes"
    ],
    "name:msa_x_preferred":[
        "Eperjes"
    ],
    "name:nld_x_preferred":[
        "Eperjes"
    ],
    "name:pol_x_preferred":[
        "Eperjes"
    ],
    "name:ron_x_preferred":[
        "Eperjes"
    ],
    "name:slk_x_preferred":[
        "Eperjes"
    ],
    "name:slv_x_preferred":[
        "Eperjes"
    ],
    "name:vie_x_preferred":[
        "Eperjes"
    ],
    "name:zho_x_preferred":[
        "\u827e\u6d3e\u5c14\u8036\u4ec0"
    ],
    "wof:name":"Eperjes",
    "wof:placetype":"locality"
},
  "geometry": {"coordinates":[20.56667,46.68333],"type":"Point"}
}