{
  "type": "Feature",
  "properties": {
    "gn:admin1_code":"10.0",
    "gn:asciiname":"Kokad",
    "gn:country_code":"HU",
    "gn:dem":117,
    "gn:feature_class":"P",
    "gn:feature_code":"PPL",
    "gn:name":"Kokad",
    "gn:population":0,
    "gn:timezone":"Europe/Budapest",
    "iso:country":"HU",
    "name:deu_x_preferred":[
        "Kokad"
    ],
    "name:epo_x_preferred":[
        "Kokad"
    ],
    "name:fas_x_preferred":[
        "\u06a9\u0648\u06a9\u0627\u062f"
    ],
    "name:fra_x_preferred":[
        "Kokad"
    ],
    "name:hun_x_preferred":[
        "Kokad"
    ],
    "name:ita_x_preferred":[
        "Kokad"
    ],
    "name:msa_x_preferred":[
        "Kokad"
    ],
    "name:nld_x_preferred":[
        "Kokad"
    ],
    "name:ron_x_preferred":[
        "Kokad"
    ],
    "name:slk_x_preferred":[
        "Kokad"
    ],
    "name:slv_x_preferred":[
        "Kokad"
    ],
    "name:vie_x_preferred":[
        "Kokad"
    ],
    "name:zho_x_preferred":[
        "\u79d1\u8003\u5fb7"
    ],
    "wof:name":"Kokad",
    "wof:placetype":"locality"
},
  "geometry": {"coordinates":[21.93452000000001,47.40617],"type":"Point"}
}