{
  "type": "Feature",
  "properties": {
    "gn:admin1_code":"10.0",
    "gn:asciiname":"Kokad",
    "gn:country_code":"HU",
    "gn:dem":117,
    "gn:feature_class":"P",
    "gn:feature_code":"PPL",
    "gn:name":"Kokad",
    "gn:population":0,
    "gn:timezone":"Europe/Budapest",
    "iso:country":"HU",
    "wof:name":"Kokad",
    "wof:placetype":"locality"
},
  "geometry": {"coordinates":[21.93452000000001,47.40617],"type":"Point"}
}