{
  "type": "Feature",
  "properties": {
    "gn:gn_country":"HU",
    "gn:gn_fcode":"PPL",
    "gn:gn_pop":0,
    "iso:country":"HU",
    "name:chi_x_preferred":[
        "\u9c8d\u6d1b\u901a\u6bdb\u7126\u7f57\u5fb7"
    ],
    "name:cze_x_preferred":[
        "Balatonmagyar\u00f3d"
    ],
    "name:dut_x_preferred":[
        "Balatonmagyar\u00f3d"
    ],
    "name:eng_x_preferred":[
        "Balatonmagyar\u00f3d"
    ],
    "name:epo_x_preferred":[
        "Balatonmagyar\u00f3d"
    ],
    "name:fre_x_preferred":[
        "Balatonmagyar\u00f3d"
    ],
    "name:ger_x_preferred":[
        "Balatonmagyar\u00f3d"
    ],
    "name:hun_x_preferred":[
        "Balatonmagyar\u00f3d"
    ],
    "name:ita_x_preferred":[
        "Balatonmagyar\u00f3d"
    ],
    "name:may_x_preferred":[
        "Balatonmagyar\u00f3d"
    ],
    "name:nan_x_preferred":[
        "Balatonmagyar\u00f3d"
    ],
    "name:rum_x_preferred":[
        "Balatonmagyar\u00f3d"
    ],
    "name:slo_x_preferred":[
        "Balatonmagyar\u00f3d"
    ],
    "name:slv_x_preferred":[
        "Balatonmagyar\u00f3d"
    ],
    "name:vie_x_preferred":[
        "Balatonmagyar\u00f3d"
    ],
    "qs_pg:aaroncc":"HU",
    "qs_pg:gn_country":"HU",
    "qs_pg:gn_fcode":"PPL",
    "qs_pg:gn_pop":0,
    "qs_pg:name":"Balatonmagyar\u00f3d",
    "qs_pg:name_adm0":"Magyarorsz\u00e1g",
    "qs_pg:name_adm1":"Zala",
    "qs_pg:photos":284,
    "qs_pg:photos_1k":58,
    "qs_pg:photos_9k":1,
    "qs_pg:photos_9r":4,
    "qs_pg:photos_all":284,
    "qs_pg:photos_sr":5,
    "qs_pg:pop_sr":0,
    "qs_pg:qs_pg_placetype":"locality",
    "qs_pg:qs_pg_placetype_gp":"Town",
    "qs_pg:woe_adm0":23424844,
    "woe:adm0_id":23424844,
    "woe:name_adm0":"Magyarorsz\u00e1g",
    "woe:name_adm1":"Zala",
    "woe:placetype":"Town",
    "wof:name":"Balatonmagyar\u00f3d",
    "wof:placetype":"locality"
},
  "geometry": {"coordinates":[17.17573,46.59593],"type":"Point"}
}