{
  "type": "Feature",
  "properties": {
    "gn:country":"HU",
    "gn:fcode":"PPL",
    "gn:population":0,
    "iso:country":"HU",
    "name:ast_x_preferred":[
        "Balatonmagyar\u00f3d"
    ],
    "name:ces_x_preferred":[
        "Balatonmagyar\u00f3d"
    ],
    "name:deu_x_preferred":[
        "Balatonmagyar\u00f3d"
    ],
    "name:eng_x_preferred":[
        "Balatonmagyar\u00f3d"
    ],
    "name:epo_x_preferred":[
        "Balatonmagyar\u00f3d"
    ],
    "name:fas_x_preferred":[
        "\u0628\u0627\u0644\u0627\u062a\u0648\u0646\u0645\u0627\u06af\u06cc\u0627\u0631\u0648\u062f"
    ],
    "name:fra_x_preferred":[
        "Balatonmagyar\u00f3d"
    ],
    "name:gle_x_preferred":[
        "Balatonmagyar\u00f3d"
    ],
    "name:hun_x_preferred":[
        "Balatonmagyar\u00f3d"
    ],
    "name:ita_x_preferred":[
        "Balatonmagyar\u00f3d"
    ],
    "name:msa_x_preferred":[
        "Balatonmagyar\u00f3d"
    ],
    "name:nan_x_preferred":[
        "Balatonmagyar\u00f3d"
    ],
    "name:nld_x_preferred":[
        "Balatonmagyar\u00f3d"
    ],
    "name:ron_x_preferred":[
        "Balatonmagyar\u00f3d"
    ],
    "name:slk_x_preferred":[
        "Balatonmagyar\u00f3d"
    ],
    "name:slv_x_preferred":[
        "Balatonmagyar\u00f3d"
    ],
    "name:spa_x_preferred":[
        "Balatonmagyar\u00f3d"
    ],
    "name:uzb_x_preferred":[
        "Balatonmagyar\u00f3d"
    ],
    "name:vie_x_preferred":[
        "Balatonmagyar\u00f3d"
    ],
    "name:zho_x_preferred":[
        "\u9c8d\u6d1b\u901a\u6bdb\u7126\u7f57\u5fb7"
    ],
    "qs_pg:aaroncc":"HU",
    "qs_pg:gn_country":"HU",
    "qs_pg:gn_fcode":"PPL",
    "qs_pg:gn_pop":0,
    "qs_pg:name":"Balatonmagyar\u00f3d",
    "qs_pg:name_adm0":"Magyarorsz\u00e1g",
    "qs_pg:name_adm1":"Zala",
    "qs_pg:photos":284,
    "qs_pg:photos_1k":58,
    "qs_pg:photos_9k":1,
    "qs_pg:photos_9r":4,
    "qs_pg:photos_all":284,
    "qs_pg:photos_sr":5,
    "qs_pg:pop_sr":0,
    "qs_pg:qs_pg_placetype":"locality",
    "qs_pg:qs_pg_placetype_gp":"Town",
    "qs_pg:woe_adm0":23424844,
    "woe:adm0_id":23424844,
    "woe:name_adm0":"Magyarorsz\u00e1g",
    "woe:name_adm1":"Zala",
    "woe:placetype":"Town",
    "wof:name":"Balatonmagyar\u00f3d",
    "wof:placetype":"locality"
},
  "geometry": {"coordinates":[17.17573,46.59593],"type":"Point"}
}