{
  "type": "Feature",
  "properties": {
    "gn:gn_country":"HU",
    "gn:gn_fcode":"PPLX",
    "gn:gn_pop":682,
    "gn:population":682,
    "iso:country":"HU",
    "name:ceb_x_preferred":[
        "Kardos"
    ],
    "name:deu_x_preferred":[
        "Kardos"
    ],
    "name:epo_x_preferred":[
        "Kardos"
    ],
    "name:fas_x_preferred":[
        "\u06a9\u0627\u0631\u062f\u0648\u0634"
    ],
    "name:fra_x_preferred":[
        "Kardos"
    ],
    "name:hun_x_preferred":[
        "Kardos"
    ],
    "name:ita_x_preferred":[
        "Kardos"
    ],
    "name:msa_x_preferred":[
        "Kardos"
    ],
    "name:nld_x_preferred":[
        "Kardos"
    ],
    "name:pol_x_preferred":[
        "Kardos"
    ],
    "name:ron_x_preferred":[
        "Kardos"
    ],
    "name:slk_x_preferred":[
        "Kardos"
    ],
    "name:slv_x_preferred":[
        "Kardos"
    ],
    "name:swe_x_preferred":[
        "Kardos"
    ],
    "name:vie_x_preferred":[
        "Kardos"
    ],
    "name:zho_x_preferred":[
        "\u8003\u5c14\u591a\u4ec0"
    ],
    "qs_pg:aaroncc":"HU",
    "qs_pg:gn_country":"HU",
    "qs_pg:gn_fcode":"PPLX",
    "qs_pg:gn_pop":682,
    "qs_pg:name":"Kardos",
    "qs_pg:photos_9r":0,
    "qs_pg:photos_sr":0,
    "qs_pg:pop_sr":2,
    "qs_pg:qs_pg_placetype":"neighbourhood",
    "wof:name":"Kardos",
    "wof:placetype":"neighbourhood",
    "wof:population":682
},
  "geometry": {"coordinates":[20.61667,46.23333],"type":"Point"}
}