{
  "type": "Feature",
  "properties": {
    "gn:admin1_code":"17.0",
    "gn:asciiname":"Nemesvid",
    "gn:country_code":"HU",
    "gn:dem":125,
    "gn:feature_class":"P",
    "gn:feature_code":"PPL",
    "gn:name":"Nemesvid",
    "gn:population":0,
    "gn:timezone":"Europe/Budapest",
    "iso:country":"HU",
    "name:epo_x_preferred":[
        "Nemesvid"
    ],
    "name:fas_x_preferred":[
        "\u0646\u0645\u0634\u0648\u06cc\u062f"
    ],
    "name:fra_x_preferred":[
        "Nemesvid"
    ],
    "name:hun_x_preferred":[
        "Nemesvid"
    ],
    "name:ita_x_preferred":[
        "Nemesvid"
    ],
    "name:msa_x_preferred":[
        "Nemesvid"
    ],
    "name:nld_x_preferred":[
        "Nemesvid"
    ],
    "name:ron_x_preferred":[
        "Nemesvid"
    ],
    "name:slk_x_preferred":[
        "Nemesvid"
    ],
    "name:slv_x_preferred":[
        "Nemesvid"
    ],
    "name:vie_x_preferred":[
        "Nemesvid"
    ],
    "name:zho_x_preferred":[
        "\u5948\u8fc8\u4ec0\u7ef4\u5fb7"
    ],
    "wof:name":"Nemesvid",
    "wof:placetype":"locality"
},
  "geometry": {"coordinates":[17.25652,46.49719],"type":"Point"}
}