{
  "type": "Feature",
  "properties": {
    "gn:admin1_code":"6.0",
    "gn:asciiname":"Ladany",
    "gn:cc2":"HU",
    "gn:country_code":"HU",
    "gn:dem":77,
    "gn:feature_class":"P",
    "gn:feature_code":"PPL",
    "gn:name":"Lad\u00e1ny",
    "gn:population":0,
    "gn:timezone":"Europe/Budapest",
    "iso:country":"HU",
    "name:und_x_variant":[
        "\u00d3lad\u00e1ny",
        "Lad\u00e1ny"
    ],
    "wof:name":"Ladany",
    "wof:placetype":"locality"
},
  "geometry": {"coordinates":[20.46667,46.16667],"type":"Point"}
}