{
  "type": "Feature",
  "properties": {
    "gn:admin1_code":"2.0",
    "gn:asciiname":"Kisherend",
    "gn:country_code":"HU",
    "gn:dem":154,
    "gn:feature_class":"P",
    "gn:feature_code":"PPL",
    "gn:name":"Kisherend",
    "gn:population":0,
    "gn:timezone":"Europe/Budapest",
    "iso:country":"HU",
    "name:epo_x_preferred":[
        "Kisherend"
    ],
    "name:fas_x_preferred":[
        "\u06a9\u06cc\u0634\u0647\u0631\u0646\u062f"
    ],
    "name:fra_x_preferred":[
        "Kisherend"
    ],
    "name:hrv_x_preferred":[
        "Renda"
    ],
    "name:hun_x_preferred":[
        "Kisherend"
    ],
    "name:ita_x_preferred":[
        "Kisherend"
    ],
    "name:msa_x_preferred":[
        "Kisherend"
    ],
    "name:nld_x_preferred":[
        "Kisherend"
    ],
    "name:pol_x_preferred":[
        "Kisherend"
    ],
    "name:ron_x_preferred":[
        "Kisherend"
    ],
    "name:slk_x_preferred":[
        "Kisherend"
    ],
    "name:slv_x_preferred":[
        "Kisherend"
    ],
    "name:vie_x_preferred":[
        "Kisherend"
    ],
    "name:zho_x_preferred":[
        "\u57fa\u4ec0\u6d77\u4f26\u5fb7"
    ],
    "wof:name":"Kisherend",
    "wof:placetype":"locality"
},
  "geometry": {"coordinates":[18.32972,45.96611],"type":"Point"}
}