{
  "type": "Feature",
  "properties": {
    "gn:admin1_code":"24.0",
    "gn:asciiname":"Kalocfa",
    "gn:country_code":"HU",
    "gn:dem":214,
    "gn:feature_class":"P",
    "gn:feature_code":"PPL",
    "gn:name":"K\u00e1l\u00f3cfa",
    "gn:population":0,
    "gn:timezone":"Europe/Budapest",
    "iso:country":"HU",
    "name:epo_x_preferred":[
        "K\u00e1l\u00f3cfa"
    ],
    "name:fas_x_preferred":[
        "\u06a9\u0627\u0644\u0648\u062a\u0633\u0641\u0627"
    ],
    "name:fra_x_preferred":[
        "K\u00e1l\u00f3cfa"
    ],
    "name:hun_x_preferred":[
        "K\u00e1l\u00f3cfa"
    ],
    "name:ita_x_preferred":[
        "K\u00e1l\u00f3cfa"
    ],
    "name:msa_x_preferred":[
        "K\u00e1l\u00f3cfa"
    ],
    "name:nld_x_preferred":[
        "K\u00e1l\u00f3cfa"
    ],
    "name:ron_x_preferred":[
        "K\u00e1l\u00f3cfa"
    ],
    "name:slk_x_preferred":[
        "K\u00e1l\u00f3cfa"
    ],
    "name:slv_x_preferred":[
        "K\u00e1l\u00f3cfa"
    ],
    "name:und_x_variant":[
        "K\u00e1l\u00f3czfa"
    ],
    "name:vie_x_preferred":[
        "K\u00e1l\u00f3cfa"
    ],
    "name:zho_x_preferred":[
        "\u5361\u6d1b\u8328\u798f"
    ],
    "wof:name":"Kalocfa",
    "wof:placetype":"locality"
},
  "geometry": {"coordinates":[16.56431,46.75573],"type":"Point"}
}