{
  "type": "Feature",
  "properties": {
    "gn:admin1_code":"24.0",
    "gn:asciiname":"Kalocfa",
    "gn:country_code":"HU",
    "gn:dem":214,
    "gn:feature_class":"P",
    "gn:feature_code":"PPL",
    "gn:name":"K\u00e1l\u00f3cfa",
    "gn:population":0,
    "gn:timezone":"Europe/Budapest",
    "iso:country":"HU",
    "name:und_x_variant":[
        "K\u00e1l\u00f3czfa",
        "K\u00e1l\u00f3cfa"
    ],
    "wof:name":"Kalocfa",
    "wof:placetype":"locality"
},
  "geometry": {"coordinates":[16.56431,46.75573],"type":"Point"}
}