{
  "type": "Feature",
  "properties": {
    "iso:country":"HU",
    "name:eng_x_preferred":[
        "Palotanegyed"
    ],
    "name:fra_x_preferred":[
        "Palotanegyed"
    ],
    "name:hun_x_preferred":[
        "Palotanegyed"
    ],
    "name:nld_x_preferred":[
        "Palotanegyed"
    ],
    "wof:name":"Palotanegyed",
    "wof:placetype":"neighbourhood"
},
  "geometry": {"coordinates":[19.06611167529826,47.49222997801452],"type":"Point"}
}