{
  "type": "Feature",
  "properties": {
    "gn:admin1_code":"4.0",
    "gn:asciiname":"Cserdulokerulohaz",
    "gn:country_code":"HU",
    "gn:dem":98,
    "gn:feature_class":"P",
    "gn:feature_code":"PPL",
    "gn:name":"Cserd\u00fcl\u0151ker\u00fcl\u0151h\u00e1z",
    "gn:population":0,
    "gn:timezone":"Europe/Budapest",
    "iso:country":"HU",
    "name:hun_x_preferred":[
        "Cserd\u00fcl\u0151ker\u00fcl\u0151h\u00e1z"
    ],
    "name:und_x_variant":[
        "Ker\u00fcl\u0151h\u00e1z"
    ],
    "wof:name":"Cserdulokerulohaz",
    "wof:placetype":"locality"
},
  "geometry": {"coordinates":[22.03333,48.26667],"type":"Point"}
}