{
  "type": "Feature",
  "properties": {
    "gn:admin1_code":"20.0",
    "gn:asciiname":"Nadasdulo",
    "gn:country_code":"HU",
    "gn:dem":86,
    "gn:feature_class":"P",
    "gn:feature_code":"PPL",
    "gn:name":"N\u00e1dasd\u0171l\u0151",
    "gn:population":0,
    "gn:timezone":"Europe/Budapest",
    "iso:country":"HU",
    "wof:name":"Nadasdulo",
    "wof:placetype":"locality"
},
  "geometry": {"coordinates":[20.13333,47.26667],"type":"Point"}
}