{
  "type": "Feature",
  "properties": {
    "gn:admin1_code":"14.0",
    "gn:asciiname":"Alsozsunypuszta",
    "gn:country_code":"HU",
    "gn:dem":270,
    "gn:feature_class":"P",
    "gn:feature_code":"PPL",
    "gn:name":"Als\u00f3zs\u00fanypuszta",
    "gn:population":0,
    "gn:timezone":"Europe/Budapest",
    "iso:country":"HU",
    "wof:name":"Alsozsunypuszta",
    "wof:placetype":"locality"
},
  "geometry": {"coordinates":[19.62086,47.99695],"type":"Point"}
}