{
  "type": "Feature",
  "properties": {
    "gn:admin1_code":"16.0",
    "gn:asciiname":"Vargahegy",
    "gn:country_code":"HU",
    "gn:dem":154,
    "gn:feature_class":"P",
    "gn:feature_code":"PPL",
    "gn:name":"Vargahegy",
    "gn:population":0,
    "gn:timezone":"Europe/Budapest",
    "iso:country":"HU",
    "wof:name":"Vargahegy",
    "wof:placetype":"locality"
},
  "geometry": {"coordinates":[19.61667000000001,47.48333],"type":"Point"}
}