{
  "type": "Feature",
  "properties": {
    "gn:admin1_code":"17.0",
    "gn:asciiname":"Part",
    "gn:country_code":"HU",
    "gn:dem":100,
    "gn:feature_class":"P",
    "gn:feature_code":"PPL",
    "gn:name":"Part",
    "gn:population":0,
    "gn:timezone":"Europe/Budapest",
    "iso:country":"HU",
    "name:ara_x_preferred":[
        "\u062c\u0632\u0621"
    ],
    "name:cat_x_preferred":[
        "Part"
    ],
    "name:ces_x_preferred":[
        "Part"
    ],
    "name:deu_x_preferred":[
        "Part"
    ],
    "name:fas_x_preferred":[
        "\u0628\u062e\u0634"
    ],
    "name:fra_x_preferred":[
        "Part"
    ],
    "name:jpn_x_preferred":[
        "\u30d1\u30fc\u30c8"
    ],
    "name:nor_x_preferred":[
        "Part"
    ],
    "name:swe_x_preferred":[
        "Part"
    ],
    "wof:name":"Part",
    "wof:placetype":"locality"
},
  "geometry": {"coordinates":[17.31667,46.71667],"type":"Point"}
}