{
  "type": "Feature",
  "properties": {
    "gn:admin1_code":"4.0",
    "gn:asciiname":"Tiszaladany",
    "gn:country_code":"HU",
    "gn:dem":91,
    "gn:feature_class":"P",
    "gn:feature_code":"PPL",
    "gn:name":"Tiszalad\u00e1ny",
    "gn:population":0,
    "gn:timezone":"Europe/Budapest",
    "iso:country":"HU",
    "name:deu_x_preferred":[
        "Tiszalad\u00e1ny"
    ],
    "name:epo_x_preferred":[
        "Tiszalad\u00e1ny"
    ],
    "name:fas_x_preferred":[
        "\u062a\u06cc\u0633\u0627\u0644\u0627\u062f\u0627\u0646\u06cc"
    ],
    "name:fra_x_preferred":[
        "Tiszalad\u00e1ny"
    ],
    "name:heb_x_preferred":[
        "\u05d8\u05d9\u05e1\u05dc\u05d3\u05d0\u05df"
    ],
    "name:hun_x_preferred":[
        "Tiszalad\u00e1ny"
    ],
    "name:ita_x_preferred":[
        "Tiszalad\u00e1ny"
    ],
    "name:msa_x_preferred":[
        "Tiszalad\u00e1ny"
    ],
    "name:nld_x_preferred":[
        "Tiszalad\u00e1ny"
    ],
    "name:pol_x_preferred":[
        "Tiszalad\u00e1ny"
    ],
    "name:ron_x_preferred":[
        "Tiszalad\u00e1ny"
    ],
    "name:slk_x_preferred":[
        "Tiszalad\u00e1ny"
    ],
    "name:slv_x_preferred":[
        "Tiszalad\u00e1ny"
    ],
    "name:und_x_variant":[
        "Tiszalad\u00e1ny"
    ],
    "name:vie_x_preferred":[
        "Tiszalad\u00e1ny"
    ],
    "name:zho_x_preferred":[
        "\u8482\u7ecd\u6d1b\u8fbe\u5c3c"
    ],
    "wof:name":"Tiszaladany",
    "wof:placetype":"locality"
},
  "geometry": {"coordinates":[21.41667,48.06667],"type":"Point"}
}