{
  "type": "Feature",
  "properties": {
    "gn:admin1_code":"4.0",
    "gn:asciiname":"Tiszaladany",
    "gn:country_code":"HU",
    "gn:dem":91,
    "gn:feature_class":"P",
    "gn:feature_code":"PPL",
    "gn:name":"Tiszalad\u00e1ny",
    "gn:population":0,
    "gn:timezone":"Europe/Budapest",
    "iso:country":"HU",
    "name:und_x_variant":[
        "Tiszalad\u00e1ny"
    ],
    "wof:name":"Tiszaladany",
    "wof:placetype":"locality"
},
  "geometry": {"coordinates":[21.41667,48.06667],"type":"Point"}
}