{
  "type": "Feature",
  "properties": {
    "gn:admin1_code":"7.0",
    "gn:asciiname":"Kadardulo",
    "gn:country_code":"HU",
    "gn:dem":113,
    "gn:feature_class":"P",
    "gn:feature_code":"PPLL",
    "gn:name":"K\u00e1d\u00e1rd\u0171l\u0151",
    "gn:population":0,
    "gn:timezone":"Europe/Budapest",
    "iso:country":"HU",
    "wof:name":"Kadardulo",
    "wof:placetype":"locality"
},
  "geometry": {"coordinates":[21.46667,47.53333],"type":"Point"}
}