{
  "type": "Feature",
  "properties": {
    "iso:country":"HU",
    "name:hun_x_colloquial":[
        "Korhazdulo"
    ],
    "name:hun_x_preferred":[
        "K\u00f3rh\u00e1zd\u016fl\u0151"
    ],
    "qs:gn_adm0_cc":"HU",
    "qs:gn_fcode":"PPLX",
    "qs:gn_local":715466,
    "qs:gn_nam_loc":"Szarvas, Szarvas, B\u00e9k\u00e9s, HU",
    "qs:gn_namadm1":"03",
    "qs:gn_name":"K\u00f3rh\u00e1zd\u0171l\u0151",
    "qs:local_max":101,
    "qs:local_sum":103,
    "qs:localhoods":2,
    "qs:name":"K\u00f3rh\u00e1zd\u016fl\u0151",
    "qs:name_adm0":"Magyarorsz\u00e1g",
    "qs:name_adm1":"B\u00e9k\u00e9s",
    "qs:name_adm2":"Szarvas",
    "qs:name_local":"Szarvas",
    "qs:photo_max":21,
    "qs:photo_sum":101,
    "qs:placetype":"Suburb",
    "qs:quad_count":16,
    "qs:woe_adm0":23424844,
    "qs:woe_adm1":12577913,
    "qs:woe_adm2":12593737,
    "qs:woe_lau":0,
    "qs:woe_local":815431,
    "qs:woe_ver":"7.10.0",
    "wof:lang":[
        "hun"
    ],
    "wof:name":"K\u00f3rh\u00e1zd\u016fl\u0151",
    "wof:placetype":"neighbourhood"
},
  "geometry": {"coordinates":[20.537168,46.867944],"type":"Point"}
}