{
  "type": "Feature",
  "properties": {
    "gn:admin1_code":"17.0",
    "gn:asciiname":"Erzsebetpuszta",
    "gn:country_code":"HU",
    "gn:dem":134,
    "gn:feature_class":"P",
    "gn:feature_code":"PPL",
    "gn:name":"Erzs\u00e9betpuszta",
    "gn:population":0,
    "gn:timezone":"Europe/Budapest",
    "iso:country":"HU",
    "wof:name":"Erzsebetpuszta",
    "wof:placetype":"locality"
},
  "geometry": {"coordinates":[18.19389,46.84339],"type":"Point"}
}