{
  "type": "Feature",
  "properties": {
    "gn:admin1_code":"9.0",
    "gn:asciiname":"Ujballatag",
    "gn:country_code":"HU",
    "gn:dem":124,
    "gn:feature_class":"P",
    "gn:feature_code":"PPL",
    "gn:name":"\u00dajballatag",
    "gn:population":0,
    "gn:timezone":"Europe/Budapest",
    "iso:country":"HU",
    "wof:name":"Ujballatag",
    "wof:placetype":"locality"
},
  "geometry": {"coordinates":[17.86667000000001,47.65],"type":"Point"}
}