{
  "type": "Feature",
  "properties": {
    "gn:admin1_code":"4.0",
    "gn:asciiname":"Rudolftelep",
    "gn:country_code":"HU",
    "gn:dem":234,
    "gn:feature_class":"P",
    "gn:feature_code":"PPL",
    "gn:name":"Rudolftelep",
    "gn:population":0,
    "gn:timezone":"Europe/Budapest",
    "iso:country":"HU",
    "name:deu_x_preferred":[
        "Rudolftelep"
    ],
    "name:epo_x_preferred":[
        "Rudolftelep"
    ],
    "name:fas_x_preferred":[
        "\u0631\u0648\u062f\u0648\u0644\u0641\u062a\u0644\u067e"
    ],
    "name:fra_x_preferred":[
        "Rudolftelep"
    ],
    "name:heb_x_preferred":[
        "\u05e8\u05d5\u05d3\u05d5\u05dc\u05e4\u05d8\u05dc\u05e4"
    ],
    "name:hun_x_preferred":[
        "Rudolftelep"
    ],
    "name:ita_x_preferred":[
        "Rudolftelep"
    ],
    "name:msa_x_preferred":[
        "Rudolftelep"
    ],
    "name:nld_x_preferred":[
        "Rudolftelep"
    ],
    "name:pol_x_preferred":[
        "Rudolftelep"
    ],
    "name:ron_x_preferred":[
        "Rudolftelep"
    ],
    "name:slk_x_preferred":[
        "Rudolftelep"
    ],
    "name:slv_x_preferred":[
        "Rudolftelep"
    ],
    "name:vie_x_preferred":[
        "Rudolftelep"
    ],
    "name:zho_x_preferred":[
        "\u9c81\u591a\u5c14\u592b\u6cf0\u83b1\u666e"
    ],
    "wof:name":"Rudolftelep",
    "wof:placetype":"locality"
},
  "geometry": {"coordinates":[20.68333,48.31667],"type":"Point"}
}