{
  "type": "Feature",
  "properties": {
    "gn:admin1_code":"21.0",
    "gn:asciiname":"Bonyhadvarasd",
    "gn:country_code":"HU",
    "gn:dem":146,
    "gn:feature_class":"P",
    "gn:feature_code":"PPL",
    "gn:name":"Bonyh\u00e1dvarasd",
    "gn:population":0,
    "gn:timezone":"Europe/Budapest",
    "iso:country":"HU",
    "wof:name":"Bonyhadvarasd",
    "wof:placetype":"locality"
},
  "geometry": {"coordinates":[18.48021,46.36885],"type":"Point"}
}