{
  "type": "Feature",
  "properties": {
    "gn:admin1_code":"21.0",
    "gn:asciiname":"Bonyhadvarasd",
    "gn:country_code":"HU",
    "gn:dem":146,
    "gn:feature_class":"P",
    "gn:feature_code":"PPL",
    "gn:name":"Bonyh\u00e1dvarasd",
    "gn:population":0,
    "gn:timezone":"Europe/Budapest",
    "iso:country":"HU",
    "name:epo_x_preferred":[
        "Bonyh\u00e1dvarasd"
    ],
    "name:fas_x_preferred":[
        "\u0628\u0648\u0646\u06cc\u0647\u0627\u062f\u0648\u0627\u0631\u0627\u0634\u062f"
    ],
    "name:fra_x_preferred":[
        "Bonyh\u00e1dvarasd"
    ],
    "name:hun_x_preferred":[
        "Bonyh\u00e1dvarasd"
    ],
    "name:ita_x_preferred":[
        "Bonyh\u00e1dvarasd"
    ],
    "name:msa_x_preferred":[
        "Bonyh\u00e1dvarasd"
    ],
    "name:nld_x_preferred":[
        "Bonyh\u00e1dvarasd"
    ],
    "name:ron_x_preferred":[
        "Bonyh\u00e1dvarasd"
    ],
    "name:slk_x_preferred":[
        "Bonyh\u00e1dvarasd"
    ],
    "name:slv_x_preferred":[
        "Bonyh\u00e1dvarasd"
    ],
    "name:vie_x_preferred":[
        "Bonyh\u00e1dvarasd"
    ],
    "name:zho_x_preferred":[
        "\u535a\u5c3c\u54c8\u5fb7\u6c83\u52b3\u4ec0\u5fb7"
    ],
    "wof:name":"Bonyhadvarasd",
    "wof:placetype":"locality"
},
  "geometry": {"coordinates":[18.48021,46.36885],"type":"Point"}
}