{
  "type": "Feature",
  "properties": {
    "gn:admin1_code":"1.0",
    "gn:asciiname":"Bagibocsa",
    "gn:country_code":"HU",
    "gn:dem":114,
    "gn:feature_class":"P",
    "gn:feature_code":"PPL",
    "gn:name":"Bagib\u00f3csa",
    "gn:population":0,
    "gn:timezone":"Europe/Budapest",
    "iso:country":"HU",
    "wof:name":"Bagibocsa",
    "wof:placetype":"locality"
},
  "geometry": {"coordinates":[19.55,46.63333],"type":"Point"}
}