{
  "type": "Feature",
  "properties": {
    "gn:admin1_code":"1.0",
    "gn:asciiname":"Imrehegy",
    "gn:country_code":"HU",
    "gn:dem":115,
    "gn:feature_class":"P",
    "gn:feature_code":"PPL",
    "gn:name":"Imrehegy",
    "gn:population":0,
    "gn:timezone":"Europe/Budapest",
    "iso:country":"HU",
    "name:epo_x_preferred":[
        "Imrehegy"
    ],
    "name:fas_x_preferred":[
        "\u0627\u06cc\u0645\u0631\u0647\u06af\u06cc"
    ],
    "name:fra_x_preferred":[
        "Imrehegy"
    ],
    "name:hrv_x_preferred":[
        "Delavnja\u010da"
    ],
    "name:hun_x_preferred":[
        "Imrehegy"
    ],
    "name:ita_x_preferred":[
        "Imrehegy"
    ],
    "name:msa_x_preferred":[
        "Imrehegy"
    ],
    "name:nld_x_preferred":[
        "Imrehegy"
    ],
    "name:pol_x_preferred":[
        "Imrehegy"
    ],
    "name:ron_x_preferred":[
        "Imrehegy"
    ],
    "name:slk_x_preferred":[
        "Imrehegy"
    ],
    "name:slv_x_preferred":[
        "Imrehegy"
    ],
    "name:vie_x_preferred":[
        "Imrehegy"
    ],
    "name:zho_x_preferred":[
        "\u4f0a\u59c6\u8d56\u6d77\u5409"
    ],
    "wof:name":"Imrehegy",
    "wof:placetype":"locality"
},
  "geometry": {"coordinates":[19.31223,46.47744],"type":"Point"}
}