{
  "type": "Feature",
  "properties": {
    "gn:admin1_code":"3.0",
    "gn:asciiname":"Lonovicstanya",
    "gn:cc2":"HU",
    "gn:country_code":"HU",
    "gn:dem":98,
    "gn:feature_class":"P",
    "gn:feature_code":"PPL",
    "gn:name":"Lonovicstanya",
    "gn:population":0,
    "gn:timezone":"Europe/Budapest",
    "iso:country":"HU",
    "name:und_x_variant":[
        "Lonovics Nagy-tanya",
        "Lonovicstanya"
    ],
    "wof:name":"Lonovicstanya",
    "wof:placetype":"locality"
},
  "geometry": {"coordinates":[21.13333,46.36667],"type":"Point"}
}