{
  "type": "Feature",
  "properties": {
    "gn:admin1_code":"14.0",
    "gn:asciiname":"Sandormajor",
    "gn:country_code":"HU",
    "gn:dem":189,
    "gn:feature_class":"P",
    "gn:feature_code":"PPL",
    "gn:name":"S\u00e1ndormajor",
    "gn:population":0,
    "gn:timezone":"Europe/Budapest",
    "iso:country":"HU",
    "wof:name":"Sandormajor",
    "wof:placetype":"locality"
},
  "geometry": {"coordinates":[19.3665,48.01079],"type":"Point"}
}