{
  "type": "Feature",
  "properties": {
    "gn:admin1_code":"17.0",
    "gn:asciiname":"Bodocokpuszta",
    "gn:cc2":"HU",
    "gn:country_code":"HU",
    "gn:dem":154,
    "gn:feature_class":"P",
    "gn:feature_code":"PPL",
    "gn:name":"B\u00f6d\u00f6c\u00f6kpuszta",
    "gn:population":0,
    "gn:timezone":"Europe/Budapest",
    "iso:country":"HU",
    "name:und_x_variant":[
        "B\u00f6d\u00f6c\u00f6k",
        "B\u00f6d\u00f6c\u00f6kpuszta"
    ],
    "wof:name":"Bodocokpuszta",
    "wof:placetype":"locality"
},
  "geometry": {"coordinates":[17.53333,46.41667],"type":"Point"}
}