{
  "type": "Feature",
  "properties": {
    "gn:admin1_code":"20.0",
    "gn:asciiname":"Harkanyidulo",
    "gn:cc2":"HU",
    "gn:country_code":"HU",
    "gn:dem":83,
    "gn:feature_class":"P",
    "gn:feature_code":"PPL",
    "gn:name":"Hark\u00e1nyid\u0171l\u0151",
    "gn:population":0,
    "gn:timezone":"Europe/Budapest",
    "iso:country":"HU",
    "name:und_x_variant":[
        "Hark\u00e1nyi-major"
    ],
    "wof:name":"Harkanyidulo",
    "wof:placetype":"locality"
},
  "geometry": {"coordinates":[20.13333,47.08333],"type":"Point"}
}