{
  "type": "Feature",
  "properties": {
    "gn:admin1_code":"21.0",
    "gn:asciiname":"Kistormas",
    "gn:country_code":"HU",
    "gn:dem":114,
    "gn:feature_class":"P",
    "gn:feature_code":"PPL",
    "gn:name":"Kistorm\u00e1s",
    "gn:population":0,
    "gn:timezone":"Europe/Budapest",
    "iso:country":"HU",
    "name:und_x_variant":[
        "Kistorm\u00e1s"
    ],
    "wof:name":"Kistormas",
    "wof:placetype":"locality"
},
  "geometry": {"coordinates":[18.56289,46.50305],"type":"Point"}
}