{
  "type": "Feature",
  "properties": {
    "gn:admin1_code":"21.0",
    "gn:asciiname":"Kistormas",
    "gn:country_code":"HU",
    "gn:dem":114,
    "gn:feature_class":"P",
    "gn:feature_code":"PPL",
    "gn:name":"Kistorm\u00e1s",
    "gn:population":0,
    "gn:timezone":"Europe/Budapest",
    "iso:country":"HU",
    "name:epo_x_preferred":[
        "Kistorm\u00e1s"
    ],
    "name:fas_x_preferred":[
        "\u06a9\u06cc\u0634\u062a\u0648\u0631\u0645\u0627\u0634"
    ],
    "name:fra_x_preferred":[
        "Kistorm\u00e1s"
    ],
    "name:hun_x_preferred":[
        "Kistorm\u00e1s"
    ],
    "name:ita_x_preferred":[
        "Kistorm\u00e1s"
    ],
    "name:msa_x_preferred":[
        "Kistorm\u00e1s"
    ],
    "name:nld_x_preferred":[
        "Kistorm\u00e1s"
    ],
    "name:ron_x_preferred":[
        "Kistorm\u00e1s"
    ],
    "name:slk_x_preferred":[
        "Kistorm\u00e1s"
    ],
    "name:slv_x_preferred":[
        "Kistorm\u00e1s"
    ],
    "name:und_x_variant":[
        "Kistorm\u00e1s"
    ],
    "name:vie_x_preferred":[
        "Kistorm\u00e1s"
    ],
    "name:zho_x_preferred":[
        "\u57fa\u4ec0\u6258\u5c14\u9a6c\u4ec0"
    ],
    "wof:name":"Kistormas",
    "wof:placetype":"locality"
},
  "geometry": {"coordinates":[18.56289,46.50305],"type":"Point"}
}