{
  "type": "Feature",
  "properties": {
    "gn:admin1_code":"22.0",
    "gn:asciiname":"Chernelhazadamonya",
    "gn:country_code":"HU",
    "gn:dem":161,
    "gn:feature_class":"P",
    "gn:feature_code":"PPL",
    "gn:name":"Chernelh\u00e1zadamonya",
    "gn:population":0,
    "gn:timezone":"Europe/Budapest",
    "iso:country":"HU",
    "name:und_x_variant":[
        "Chernelh\u00e1zadamonya"
    ],
    "wof:name":"Chernelhazadamonya",
    "wof:placetype":"locality"
},
  "geometry": {"coordinates":[16.84313,47.36167],"type":"Point"}
}