{
  "type": "Feature",
  "properties": {
    "gn:admin1_code":"22.0",
    "gn:asciiname":"Chernelhazadamonya",
    "gn:country_code":"HU",
    "gn:dem":161,
    "gn:feature_class":"P",
    "gn:feature_code":"PPL",
    "gn:name":"Chernelh\u00e1zadamonya",
    "gn:population":0,
    "gn:timezone":"Europe/Budapest",
    "iso:country":"HU",
    "name:ces_x_preferred":[
        "Chernelh\u00e1zadamonya"
    ],
    "name:deu_x_preferred":[
        "Chernelh\u00e1zadamonya"
    ],
    "name:epo_x_preferred":[
        "Chernelh\u00e1zadamonya"
    ],
    "name:fas_x_preferred":[
        "\u062a\u0633\u0647\u0631\u0646\u0644\u0647\u0627\u0632\u0627\u062f\u0627\u0645\u0648\u0646\u06cc\u0627"
    ],
    "name:fra_x_preferred":[
        "Chernelh\u00e1zadamonya"
    ],
    "name:hun_x_preferred":[
        "Chernelh\u00e1zadamonya"
    ],
    "name:ita_x_preferred":[
        "Chernelh\u00e1zadamonya"
    ],
    "name:msa_x_preferred":[
        "Chernelh\u00e1zadamonya"
    ],
    "name:nld_x_preferred":[
        "Chernelh\u00e1zadamonya"
    ],
    "name:ron_x_preferred":[
        "Chernelh\u00e1zadamonya"
    ],
    "name:slk_x_preferred":[
        "Chernelh\u00e1zadamonya"
    ],
    "name:slv_x_preferred":[
        "Chernelh\u00e1zadamonya"
    ],
    "name:und_x_variant":[
        "Chernelh\u00e1zadamonya"
    ],
    "name:vie_x_preferred":[
        "Chernelh\u00e1zadamonya"
    ],
    "name:zho_x_preferred":[
        "\u5207\u5c14\u5948\u5c14\u54c8\u4f50\u9053\u83ab\u5c3c\u5965"
    ],
    "wof:name":"Chernelhazadamonya",
    "wof:placetype":"locality"
},
  "geometry": {"coordinates":[16.84313,47.36167],"type":"Point"}
}