{
  "type": "Feature",
  "properties": {
    "gn:admin1_code":"9.0",
    "gn:asciiname":"Csermajor",
    "gn:country_code":"HU",
    "gn:dem":126,
    "gn:feature_class":"P",
    "gn:feature_code":"PPL",
    "gn:name":"Csermajor",
    "gn:population":0,
    "gn:timezone":"Europe/Budapest",
    "iso:country":"HU",
    "wof:name":"Csermajor",
    "wof:placetype":"locality"
},
  "geometry": {"coordinates":[16.98138,47.55804000000001],"type":"Point"}
}