{
  "type": "Feature",
  "properties": {
    "gn:admin1_code":"16.0",
    "gn:asciiname":"Boldogtanya",
    "gn:country_code":"HU",
    "gn:dem":100,
    "gn:feature_class":"P",
    "gn:feature_code":"PPL",
    "gn:name":"Boldogtanya",
    "gn:population":0,
    "gn:timezone":"Europe/Budapest",
    "iso:country":"HU",
    "wof:name":"Boldogtanya",
    "wof:placetype":"locality"
},
  "geometry": {"coordinates":[19.08333,47.66667],"type":"Point"}
}