{
  "type": "Feature",
  "properties": {
    "gn:admin1_code":"9.0",
    "gn:asciiname":"Bakonypeterd",
    "gn:country_code":"HU",
    "gn:dem":181,
    "gn:feature_class":"P",
    "gn:feature_code":"PPL",
    "gn:name":"Bakonyp\u00e9terd",
    "gn:population":0,
    "gn:timezone":"Europe/Budapest",
    "iso:country":"HU",
    "name:und_x_variant":[
        "Bakonyp\u00e9terd"
    ],
    "wof:name":"Bakonypeterd",
    "wof:placetype":"locality"
},
  "geometry": {"coordinates":[17.797,47.46677],"type":"Point"}
}