{
  "type": "Feature",
  "properties": {
    "gn:admin1_code":"9.0",
    "gn:asciiname":"Bakonypeterd",
    "gn:country_code":"HU",
    "gn:dem":181,
    "gn:feature_class":"P",
    "gn:feature_code":"PPL",
    "gn:name":"Bakonyp\u00e9terd",
    "gn:population":0,
    "gn:timezone":"Europe/Budapest",
    "iso:country":"HU",
    "name:ces_x_preferred":[
        "Bakonyp\u00e9terd"
    ],
    "name:epo_x_preferred":[
        "Bakonyp\u00e9terd"
    ],
    "name:fas_x_preferred":[
        "\u0628\u0627\u06a9\u0648\u0646\u06cc\u067e\u062a\u0631\u062f"
    ],
    "name:fra_x_preferred":[
        "Bakonyp\u00e9terd"
    ],
    "name:hun_x_preferred":[
        "Bakonyp\u00e9terd"
    ],
    "name:ita_x_preferred":[
        "Bakonyp\u00e9terd"
    ],
    "name:msa_x_preferred":[
        "Bakonyp\u00e9terd"
    ],
    "name:nld_x_preferred":[
        "Bakonyp\u00e9terd"
    ],
    "name:pol_x_preferred":[
        "Bakonyp\u00e9terd"
    ],
    "name:ron_x_preferred":[
        "Bakonyp\u00e9terd"
    ],
    "name:slk_x_preferred":[
        "Bakonyp\u00e9terd"
    ],
    "name:slv_x_preferred":[
        "Bakonyp\u00e9terd"
    ],
    "name:vie_x_preferred":[
        "Bakonyp\u00e9terd"
    ],
    "name:zho_x_preferred":[
        "\u9c8d\u79d1\u5c3c\u4f69\u6cf0\u5c14\u5fb7"
    ],
    "wof:name":"Bakonypeterd",
    "wof:placetype":"locality"
},
  "geometry": {"coordinates":[17.797,47.46677],"type":"Point"}
}