{
  "type": "Feature",
  "properties": {
    "iso:country":"HU",
    "name:hun_x_preferred":[
        "Kissv\u00e1bhegy"
    ],
    "wof:name":"Kissvabhegy",
    "wof:placetype":"neighbourhood"
},
  "geometry": {"coordinates":[19.01321133435045,47.50249408677615],"type":"Point"}
}