{
  "type": "Feature",
  "properties": {
    "gn:admin1_code":"2.0",
    "gn:asciiname":"Ofalu",
    "gn:country_code":"HU",
    "gn:dem":153,
    "gn:feature_class":"P",
    "gn:feature_code":"PPL",
    "gn:name":"\u00d3falu",
    "gn:population":0,
    "gn:timezone":"Europe/Budapest",
    "iso:country":"HU",
    "name:aze_x_preferred":[
        "Ofalu"
    ],
    "name:deu_x_preferred":[
        "\u00d3falu"
    ],
    "name:epo_x_preferred":[
        "\u00d3falu"
    ],
    "name:fas_x_preferred":[
        "\u0627\u0648\u0641\u0627\u0644\u0648"
    ],
    "name:fra_x_preferred":[
        "\u00d3falu"
    ],
    "name:hrv_x_preferred":[
        "Faluv"
    ],
    "name:hun_x_preferred":[
        "\u00d3falu"
    ],
    "name:ita_x_preferred":[
        "\u00d3falu"
    ],
    "name:msa_x_preferred":[
        "\u00d3falu"
    ],
    "name:nld_x_preferred":[
        "\u00d3falu"
    ],
    "name:pol_x_preferred":[
        "\u00d3falu"
    ],
    "name:ron_x_preferred":[
        "\u00d3falu"
    ],
    "name:slk_x_preferred":[
        "\u00d3falu"
    ],
    "name:slv_x_preferred":[
        "\u00d3falu"
    ],
    "name:vie_x_preferred":[
        "\u00d3falu"
    ],
    "name:zho_x_preferred":[
        "\u6b27\u798f\u5362"
    ],
    "wof:name":"Ofalu",
    "wof:placetype":"locality"
},
  "geometry": {"coordinates":[18.53239,46.22076],"type":"Point"}
}