{
  "type": "Feature",
  "properties": {
    "gn:admin1_code":"18.0",
    "gn:asciiname":"Csajkostanya",
    "gn:country_code":"HU",
    "gn:dem":105,
    "gn:feature_class":"P",
    "gn:feature_code":"PPL",
    "gn:name":"Csajkostanya",
    "gn:population":0,
    "gn:timezone":"Europe/Budapest",
    "iso:country":"HU",
    "name:und_x_variant":[
        "Csajkostag",
        "Csajkostanya"
    ],
    "wof:name":"Csajkostanya",
    "wof:placetype":"locality"
},
  "geometry": {"coordinates":[22.05196,48.11392],"type":"Point"}
}