{
  "type": "Feature",
  "properties": {
    "gn:admin1_code":"17.0",
    "gn:asciiname":"Teleki",
    "gn:country_code":"HU",
    "gn:dem":155,
    "gn:feature_class":"P",
    "gn:feature_code":"PPL",
    "gn:name":"Teleki",
    "gn:population":0,
    "gn:timezone":"Europe/Budapest",
    "iso:country":"HU",
    "name:epo_x_preferred":[
        "Teleki"
    ],
    "name:fas_x_preferred":[
        "\u062a\u0644\u06a9\u06cc"
    ],
    "name:fra_x_preferred":[
        "Teleki"
    ],
    "name:hrv_x_preferred":[
        "Teleki"
    ],
    "name:hun_x_preferred":[
        "Teleki"
    ],
    "name:ita_x_preferred":[
        "Teleki"
    ],
    "name:msa_x_preferred":[
        "Teleki"
    ],
    "name:nld_x_preferred":[
        "Teleki"
    ],
    "name:ron_x_preferred":[
        "Teleki"
    ],
    "name:slk_x_preferred":[
        "Teleki"
    ],
    "name:slv_x_preferred":[
        "Teleki"
    ],
    "name:vie_x_preferred":[
        "Teleki"
    ],
    "name:zho_x_preferred":[
        "\u6cf0\u83b1\u57fa"
    ],
    "wof:name":"Teleki",
    "wof:placetype":"locality"
},
  "geometry": {"coordinates":[17.82521000000001,46.77137000000001],"type":"Point"}
}