{
  "type": "Feature",
  "properties": {
    "gn:admin1_code":"1.0",
    "gn:asciiname":"Nagyszekidulo",
    "gn:country_code":"HU",
    "gn:dem":115,
    "gn:feature_class":"P",
    "gn:feature_code":"PPLL",
    "gn:name":"Nagysz\u00e9kid\u0171l\u0151",
    "gn:population":0,
    "gn:timezone":"Europe/Budapest",
    "iso:country":"HU",
    "wof:name":"Nagyszekidulo",
    "wof:placetype":"locality"
},
  "geometry": {"coordinates":[19.45,47.01667],"type":"Point"}
}