{
  "type": "Feature",
  "properties": {
    "gn:admin1_code":"21.0",
    "gn:asciiname":"Varad",
    "gn:country_code":"HU",
    "gn:dem":88,
    "gn:feature_class":"P",
    "gn:feature_code":"PPL",
    "gn:name":"V\u00e1rad",
    "gn:population":0,
    "gn:timezone":"Europe/Budapest",
    "iso:country":"HU",
    "wof:name":"Varad",
    "wof:placetype":"locality"
},
  "geometry": {"coordinates":[18.85963,46.50095],"type":"Point"}
}