{
  "type": "Feature",
  "properties": {
    "gn:admin1_code":"22.0",
    "gn:asciiname":"Petomihalyfa",
    "gn:country_code":"HU",
    "gn:dem":165,
    "gn:feature_class":"P",
    "gn:feature_code":"PPL",
    "gn:name":"Pet\u0151mih\u00e1lyfa",
    "gn:population":0,
    "gn:timezone":"Europe/Budapest",
    "iso:country":"HU",
    "name:deu_x_preferred":[
        "Pet\u0151mih\u00e1lyfa"
    ],
    "name:epo_x_preferred":[
        "Pet\u0151mih\u00e1lyfa"
    ],
    "name:fas_x_preferred":[
        "\u067e\u062a\u0648\u0645\u06cc\u0647\u0627\u0644\u06cc\u0641\u0627"
    ],
    "name:fra_x_preferred":[
        "Pet\u0151mih\u00e1lyfa"
    ],
    "name:hun_x_preferred":[
        "Pet\u0151mih\u00e1lyfa"
    ],
    "name:ita_x_preferred":[
        "Pet\u0151mih\u00e1lyfa"
    ],
    "name:msa_x_preferred":[
        "Pet\u0151mih\u00e1lyfa"
    ],
    "name:nld_x_preferred":[
        "Pet\u0151mih\u00e1lyfa"
    ],
    "name:ron_x_preferred":[
        "Pet\u0151mih\u00e1lyfa"
    ],
    "name:slk_x_preferred":[
        "Pet\u0151mih\u00e1lyfa"
    ],
    "name:slv_x_preferred":[
        "Pet\u0151mih\u00e1lyfa"
    ],
    "name:und_x_variant":[
        "Pet\u0151mih\u00e1lyfa"
    ],
    "name:vie_x_preferred":[
        "Pet\u0151mih\u00e1lyfa"
    ],
    "name:zho_x_preferred":[
        "\u6d3e\u7279\u7c73\u54c8\u4f0a\u798f"
    ],
    "wof:name":"Petomihalyfa",
    "wof:placetype":"locality"
},
  "geometry": {"coordinates":[16.78661,46.98088],"type":"Point"}
}