{
  "type": "Feature",
  "properties": {
    "gn:admin1_code":"22.0",
    "gn:asciiname":"Petomihalyfa",
    "gn:country_code":"HU",
    "gn:dem":165,
    "gn:feature_class":"P",
    "gn:feature_code":"PPL",
    "gn:name":"Pet\u0151mih\u00e1lyfa",
    "gn:population":0,
    "gn:timezone":"Europe/Budapest",
    "iso:country":"HU",
    "name:und_x_variant":[
        "Pet\u0151mih\u00e1lyfa"
    ],
    "wof:name":"Petomihalyfa",
    "wof:placetype":"locality"
},
  "geometry": {"coordinates":[16.78661,46.98088],"type":"Point"}
}