{
  "type": "Feature",
  "properties": {
    "gn:admin1_code":"9.0",
    "gn:asciiname":"Szentistvanpuszta",
    "gn:country_code":"HU",
    "gn:dem":117,
    "gn:feature_class":"P",
    "gn:feature_code":"PPL",
    "gn:name":"Szentistv\u00e1npuszta",
    "gn:population":0,
    "gn:timezone":"Europe/Budapest",
    "iso:country":"HU",
    "wof:name":"Szentistvanpuszta",
    "wof:placetype":"locality"
},
  "geometry": {"coordinates":[17.28333,47.86667],"type":"Point"}
}