{
  "type": "Feature",
  "properties": {
    "gn:admin1_code":"16.0",
    "gn:asciiname":"Budakeszierdo",
    "gn:country_code":"HU",
    "gn:dem":185,
    "gn:feature_class":"P",
    "gn:feature_code":"PPL",
    "gn:name":"Budakeszierd\u0151",
    "gn:population":0,
    "gn:timezone":"Europe/Budapest",
    "iso:country":"HU",
    "wof:name":"Budakeszierdo",
    "wof:placetype":"locality"
},
  "geometry": {"coordinates":[18.96667,47.46667],"type":"Point"}
}