{
  "type": "Feature",
  "properties": {
    "gn:admin1_code":"4.0",
    "gn:asciiname":"Bekenypuszta",
    "gn:cc2":"HU",
    "gn:country_code":"HU",
    "gn:dem":355,
    "gn:feature_class":"P",
    "gn:feature_code":"PPL",
    "gn:name":"B\u00e9k\u00e9nypuszta",
    "gn:population":0,
    "gn:timezone":"Europe/Budapest",
    "iso:country":"HU",
    "name:und_x_variant":[
        "B\u00e9k\u00e9ny",
        "B\u00e9k\u00e9nypuszta"
    ],
    "wof:name":"Bekenypuszta",
    "wof:placetype":"locality"
},
  "geometry": {"coordinates":[20.65,48.01667],"type":"Point"}
}