{
  "type": "Feature",
  "properties": {
    "gn:admin1_code":"8.0",
    "gn:asciiname":"Kulsokisperkatapuszta",
    "gn:country_code":"HU",
    "gn:dem":113,
    "gn:feature_class":"P",
    "gn:feature_code":"PPL",
    "gn:name":"K\u00fcls\u0151kisperk\u00e1tapuszta",
    "gn:population":0,
    "gn:timezone":"Europe/Budapest",
    "iso:country":"HU",
    "wof:name":"Kulsokisperkatapuszta",
    "wof:placetype":"locality"
},
  "geometry": {"coordinates":[18.76499,47.07356],"type":"Point"}
}