{
  "type": "Feature",
  "properties": {
    "gn:admin1_code":"18.0",
    "gn:asciiname":"Ajaki Tanya",
    "gn:country_code":"HU",
    "gn:dem":101,
    "gn:feature_class":"P",
    "gn:feature_code":"PPL",
    "gn:name":"Ajaki Tanya",
    "gn:population":0,
    "gn:timezone":"Europe/Budapest",
    "iso:country":"HU",
    "wof:name":"Ajaki Tanya",
    "wof:placetype":"locality"
},
  "geometry": {"coordinates":[22.06667,48.18333],"type":"Point"}
}