{
  "type": "Feature",
  "properties": {
    "gn:admin1_code":"17.0",
    "gn:asciiname":"Visz",
    "gn:country_code":"HU",
    "gn:dem":134,
    "gn:feature_class":"P",
    "gn:feature_code":"PPL",
    "gn:name":"Visz",
    "gn:population":0,
    "gn:timezone":"Europe/Budapest",
    "iso:country":"HU",
    "name:deu_x_preferred":[
        "Visz"
    ],
    "name:epo_x_preferred":[
        "Visz"
    ],
    "name:fas_x_preferred":[
        "\u0648\u06cc\u0633"
    ],
    "name:fra_x_preferred":[
        "Visz"
    ],
    "name:hrv_x_preferred":[
        "Visz"
    ],
    "name:hun_x_preferred":[
        "Visz"
    ],
    "name:ita_x_preferred":[
        "Visz"
    ],
    "name:msa_x_preferred":[
        "Visz"
    ],
    "name:nld_x_preferred":[
        "Visz"
    ],
    "name:ron_x_preferred":[
        "Visz"
    ],
    "name:slk_x_preferred":[
        "Visz"
    ],
    "name:slv_x_preferred":[
        "Visz"
    ],
    "name:vie_x_preferred":[
        "Visz"
    ],
    "name:zho_x_preferred":[
        "\u7ef4\u65af"
    ],
    "wof:name":"Visz",
    "wof:placetype":"locality"
},
  "geometry": {"coordinates":[17.78197,46.72607],"type":"Point"}
}