{
  "type": "Feature",
  "properties": {
    "gn:country":"HU",
    "gn:fcode":"PPL",
    "gn:population":0,
    "iso:country":"HU",
    "name:deu_x_preferred":[
        "Gyulakeszi"
    ],
    "name:eng_x_preferred":[
        "Gyulakeszi"
    ],
    "name:epo_x_preferred":[
        "Gyulakeszi"
    ],
    "name:fas_x_preferred":[
        "\u06af\u06cc\u0648\u0644\u0627\u06a9\u0633\u06cc"
    ],
    "name:fra_x_preferred":[
        "Gyulakeszi"
    ],
    "name:hun_x_preferred":[
        "Gyulakeszi"
    ],
    "name:ita_x_preferred":[
        "Gyulakeszi"
    ],
    "name:msa_x_preferred":[
        "Gyulakeszi"
    ],
    "name:nan_x_preferred":[
        "Gyulakeszi"
    ],
    "name:nld_x_preferred":[
        "Gyulakeszi"
    ],
    "name:ron_x_preferred":[
        "Gyulakeszi"
    ],
    "name:slk_x_preferred":[
        "Gyulakeszi"
    ],
    "name:slv_x_preferred":[
        "Gyulakeszi"
    ],
    "name:vie_x_preferred":[
        "Gyulakeszi"
    ],
    "name:zho_x_preferred":[
        "\u4e45\u6d1b\u51ef\u897f"
    ],
    "qs_pg:aaroncc":"HU",
    "qs_pg:gn_country":"HU",
    "qs_pg:gn_fcode":"PPL",
    "qs_pg:gn_pop":0,
    "qs_pg:name":"Gyulakeszi",
    "qs_pg:name_adm0":"Magyarorsz\u00e1g",
    "qs_pg:name_adm1":"Veszpr\u00e9m",
    "qs_pg:photos":210,
    "qs_pg:photos_1k":43,
    "qs_pg:photos_9k":1,
    "qs_pg:photos_9r":4,
    "qs_pg:photos_all":210,
    "qs_pg:photos_sr":4,
    "qs_pg:pop_sr":0,
    "qs_pg:qs_pg_placetype":"locality",
    "qs_pg:qs_pg_placetype_gp":"Town",
    "qs_pg:woe_adm0":23424844,
    "woe:adm0_id":23424844,
    "woe:name_adm0":"Magyarorsz\u00e1g",
    "woe:name_adm1":"Veszpr\u00e9m",
    "woe:placetype":"Town",
    "wof:name":"Gyulakeszi",
    "wof:placetype":"locality"
},
  "geometry": {"coordinates":[17.48082,46.86864],"type":"Point"}
}