{
  "type": "Feature",
  "properties": {
    "gn:admin1_code":"12.0",
    "gn:asciiname":"Oreghegy",
    "gn:country_code":"HU",
    "gn:dem":161,
    "gn:feature_class":"P",
    "gn:feature_code":"PPL",
    "gn:name":"\u00d6reghegy",
    "gn:population":0,
    "gn:timezone":"Europe/Budapest",
    "iso:country":"HU",
    "wof:name":"Oreghegy",
    "wof:placetype":"locality"
},
  "geometry": {"coordinates":[18.18333,47.65],"type":"Point"}
}