{
  "type": "Feature",
  "properties": {
    "gn:admin1_code":"17.0",
    "gn:asciiname":"Tengod",
    "gn:country_code":"HU",
    "gn:dem":182,
    "gn:feature_class":"P",
    "gn:feature_code":"PPL",
    "gn:name":"Teng\u0151d",
    "gn:population":0,
    "gn:timezone":"Europe/Budapest",
    "iso:country":"HU",
    "name:ces_x_preferred":[
        "Teng\u0151d"
    ],
    "name:epo_x_preferred":[
        "Teng\u0151d"
    ],
    "name:fas_x_preferred":[
        "\u062a\u0646\u06af\u0648\u062f"
    ],
    "name:fra_x_preferred":[
        "Teng\u0151d"
    ],
    "name:hun_x_preferred":[
        "Teng\u0151d"
    ],
    "name:ita_x_preferred":[
        "Teng\u0151d"
    ],
    "name:msa_x_preferred":[
        "Teng\u0151d"
    ],
    "name:nld_x_preferred":[
        "Teng\u0151d"
    ],
    "name:ron_x_preferred":[
        "Teng\u0151d"
    ],
    "name:slk_x_preferred":[
        "Teng\u0151d"
    ],
    "name:slv_x_preferred":[
        "Teng\u0151d"
    ],
    "name:und_x_variant":[
        "Teng\u0151d"
    ],
    "name:vie_x_preferred":[
        "Teng\u0151d"
    ],
    "name:zho_x_preferred":[
        "\u6ed5\u683c\u5fb7"
    ],
    "wof:name":"Tengod",
    "wof:placetype":"locality"
},
  "geometry": {"coordinates":[18.09744,46.70272],"type":"Point"}
}