{
  "type": "Feature",
  "properties": {
    "gn:admin1_code":"16.0",
    "gn:asciiname":"Bikahegy",
    "gn:country_code":"HU",
    "gn:dem":122,
    "gn:feature_class":"P",
    "gn:feature_code":"PPL",
    "gn:name":"Bikahegy",
    "gn:population":0,
    "gn:timezone":"Europe/Budapest",
    "iso:country":"HU",
    "wof:name":"Bikahegy",
    "wof:placetype":"locality"
},
  "geometry": {"coordinates":[19.42847,47.1553],"type":"Point"}
}