{
  "type": "Feature",
  "properties": {
    "gn:admin1_code":"24.0",
    "gn:asciiname":"Vindornyalak",
    "gn:country_code":"HU",
    "gn:dem":144,
    "gn:feature_class":"P",
    "gn:feature_code":"PPL",
    "gn:name":"Vindornyalak",
    "gn:population":0,
    "gn:timezone":"Europe/Budapest",
    "iso:country":"HU",
    "name:epo_x_preferred":[
        "Vindornyalak"
    ],
    "name:fas_x_preferred":[
        "\u0648\u06cc\u0646\u062f\u0648\u0631\u0646\u06cc\u0627\u0644\u0627\u06a9"
    ],
    "name:fra_x_preferred":[
        "Vindornyalak"
    ],
    "name:hun_x_preferred":[
        "Vindornyalak"
    ],
    "name:ita_x_preferred":[
        "Vindornyalak"
    ],
    "name:msa_x_preferred":[
        "Vindornyalak"
    ],
    "name:nld_x_preferred":[
        "Vindornyalak"
    ],
    "name:ron_x_preferred":[
        "Vindornyalak"
    ],
    "name:slk_x_preferred":[
        "Vindornyalak"
    ],
    "name:slv_x_preferred":[
        "Vindornyalak"
    ],
    "name:vie_x_preferred":[
        "Vindornyalak"
    ],
    "name:zho_x_preferred":[
        "\u6e29\u591a\u5c14\u5c3c\u5965\u6d1b\u514b"
    ],
    "wof:name":"Vindornyalak",
    "wof:placetype":"locality"
},
  "geometry": {"coordinates":[17.19377,46.88667],"type":"Point"}
}