{
  "type": "Feature",
  "properties": {
    "gn:admin1_code":"2.0",
    "gn:asciiname":"Hassagy",
    "gn:country_code":"HU",
    "gn:dem":132,
    "gn:feature_class":"P",
    "gn:feature_code":"PPL",
    "gn:name":"H\u00e1ss\u00e1gy",
    "gn:population":0,
    "gn:timezone":"Europe/Budapest",
    "iso:country":"HU",
    "name:deu_x_preferred":[
        "H\u00e1ss\u00e1gy"
    ],
    "name:epo_x_preferred":[
        "H\u00e1ss\u00e1gy"
    ],
    "name:fas_x_preferred":[
        "\u0647\u0627\u0634\u0627\u06af\u06cc"
    ],
    "name:fra_x_preferred":[
        "H\u00e1ss\u00e1gy"
    ],
    "name:hrv_x_preferred":[
        "A\u0161a\u0111"
    ],
    "name:hun_x_preferred":[
        "H\u00e1ss\u00e1gy"
    ],
    "name:ita_x_preferred":[
        "H\u00e1ss\u00e1gy"
    ],
    "name:msa_x_preferred":[
        "H\u00e1ss\u00e1gy"
    ],
    "name:nld_x_preferred":[
        "H\u00e1ss\u00e1gy"
    ],
    "name:pol_x_preferred":[
        "H\u00e1ss\u00e1gy"
    ],
    "name:ron_x_preferred":[
        "H\u00e1ss\u00e1gy"
    ],
    "name:slk_x_preferred":[
        "H\u00e1ss\u00e1gy"
    ],
    "name:slv_x_preferred":[
        "H\u00e1ss\u00e1gy"
    ],
    "name:vie_x_preferred":[
        "H\u00e1ss\u00e1gy"
    ],
    "name:zho_x_preferred":[
        "\u54c8\u4ec0\u6c99\u5409"
    ],
    "wof:name":"Hassagy",
    "wof:placetype":"locality"
},
  "geometry": {"coordinates":[18.38724,46.03466],"type":"Point"}
}