{
  "type": "Feature",
  "properties": {
    "gn:admin1_code":"2.0",
    "gn:asciiname":"Hassagy",
    "gn:country_code":"HU",
    "gn:dem":132,
    "gn:feature_class":"P",
    "gn:feature_code":"PPL",
    "gn:name":"H\u00e1ss\u00e1gy",
    "gn:population":0,
    "gn:timezone":"Europe/Budapest",
    "iso:country":"HU",
    "name:und_x_variant":[
        "H\u00e1ss\u00e1gy"
    ],
    "wof:name":"Hassagy",
    "wof:placetype":"locality"
},
  "geometry": {"coordinates":[18.38724,46.03466],"type":"Point"}
}