{
  "type": "Feature",
  "properties": {
    "gn:admin1_code":"18.0",
    "gn:asciiname":"Karkhalom",
    "gn:country_code":"HU",
    "gn:dem":94,
    "gn:feature_class":"P",
    "gn:feature_code":"PPL",
    "gn:name":"Karkhalom",
    "gn:population":0,
    "gn:timezone":"Europe/Budapest",
    "iso:country":"HU",
    "wof:name":"Karkhalom",
    "wof:placetype":"locality"
},
  "geometry": {"coordinates":[21.86365,48.19286],"type":"Point"}
}