{
  "type": "Feature",
  "properties": {
    "gn:admin1_code":"1.0",
    "gn:asciiname":"Mezodulo",
    "gn:country_code":"HU",
    "gn:dem":83,
    "gn:feature_class":"P",
    "gn:feature_code":"PPL",
    "gn:name":"Mez\u0151d\u0171l\u0151",
    "gn:population":0,
    "gn:timezone":"Europe/Budapest",
    "iso:country":"HU",
    "wof:name":"Mezodulo",
    "wof:placetype":"locality"
},
  "geometry": {"coordinates":[18.88333,46.15],"type":"Point"}
}