{
  "type": "Feature",
  "properties": {
    "gn:admin1_code":"17.0",
    "gn:asciiname":"Szokedencs",
    "gn:country_code":"HU",
    "gn:dem":114,
    "gn:feature_class":"P",
    "gn:feature_code":"PPL",
    "gn:name":"Sz\u0151kedencs",
    "gn:population":0,
    "gn:timezone":"Europe/Budapest",
    "iso:country":"HU",
    "name:epo_x_preferred":[
        "Sz\u0151kedencs"
    ],
    "name:fas_x_preferred":[
        "\u0633\u0648\u06a9\u062f\u0646\u0686"
    ],
    "name:fra_x_preferred":[
        "Sz\u0151kedencs"
    ],
    "name:hun_x_preferred":[
        "Sz\u0151kedencs"
    ],
    "name:ita_x_preferred":[
        "Sz\u0151kedencs"
    ],
    "name:msa_x_preferred":[
        "Sz\u0151kedencs"
    ],
    "name:nld_x_preferred":[
        "Sz\u0151kedencs"
    ],
    "name:ron_x_preferred":[
        "Sz\u0151kedencs"
    ],
    "name:slk_x_preferred":[
        "Sz\u0151kedencs"
    ],
    "name:slv_x_preferred":[
        "Sz\u0151kedencs"
    ],
    "name:vie_x_preferred":[
        "Sz\u0151kedencs"
    ],
    "name:zho_x_preferred":[
        "\u745f\u51ef\u767b\u5947"
    ],
    "wof:name":"Szokedencs",
    "wof:placetype":"locality"
},
  "geometry": {"coordinates":[17.24893,46.55932],"type":"Point"}
}