{
  "type": "Feature",
  "properties": {
    "gn:admin1_code":"2.0",
    "gn:asciiname":"Szoreny",
    "gn:country_code":"HU",
    "gn:dem":107,
    "gn:feature_class":"P",
    "gn:feature_code":"PPL",
    "gn:name":"Sz\u00f6r\u00e9ny",
    "gn:population":0,
    "gn:timezone":"Europe/Budapest",
    "iso:country":"HU",
    "name:epo_x_preferred":[
        "Sz\u00f6r\u00e9ny"
    ],
    "name:fas_x_preferred":[
        "\u0633\u0648\u0631\u0646\u06cc"
    ],
    "name:fra_x_preferred":[
        "Sz\u00f6r\u00e9ny"
    ],
    "name:hrv_x_preferred":[
        "Surinj"
    ],
    "name:hun_x_preferred":[
        "Sz\u00f6r\u00e9ny"
    ],
    "name:ita_x_preferred":[
        "Sz\u00f6r\u00e9ny"
    ],
    "name:msa_x_preferred":[
        "Sz\u00f6r\u00e9ny"
    ],
    "name:nld_x_preferred":[
        "Sz\u00f6r\u00e9ny"
    ],
    "name:pol_x_preferred":[
        "Sz\u00f6r\u00e9ny"
    ],
    "name:ron_x_preferred":[
        "Sz\u00f6r\u00e9ny"
    ],
    "name:slk_x_preferred":[
        "Sz\u00f6r\u00e9ny"
    ],
    "name:slv_x_preferred":[
        "Sz\u00f6r\u00e9ny"
    ],
    "name:und_x_variant":[
        "Sz\u00f6r\u00e9ny"
    ],
    "name:vie_x_preferred":[
        "Sz\u00f6r\u00e9ny"
    ],
    "name:zho_x_preferred":[
        "\u745f\u96f7\u5c3c"
    ],
    "wof:name":"Szoreny",
    "wof:placetype":"locality"
},
  "geometry": {"coordinates":[17.68204,45.96753],"type":"Point"}
}