{
  "type": "Feature",
  "properties": {
    "gn:admin1_code":"9.0",
    "gn:asciiname":"Rabaszentandras",
    "gn:country_code":"HU",
    "gn:dem":118,
    "gn:feature_class":"P",
    "gn:feature_code":"PPL",
    "gn:name":"R\u00e1baszentandr\u00e1s",
    "gn:population":0,
    "gn:timezone":"Europe/Budapest",
    "iso:country":"HU",
    "name:und_x_variant":[
        "R\u00e1baszentandr\u00e1s"
    ],
    "wof:name":"Rabaszentandras",
    "wof:placetype":"locality"
},
  "geometry": {"coordinates":[17.32944,47.45914000000001],"type":"Point"}
}