{
  "type": "Feature",
  "properties": {
    "gn:admin1_code":"9.0",
    "gn:asciiname":"Rabaszentandras",
    "gn:country_code":"HU",
    "gn:dem":118,
    "gn:feature_class":"P",
    "gn:feature_code":"PPL",
    "gn:name":"R\u00e1baszentandr\u00e1s",
    "gn:population":0,
    "gn:timezone":"Europe/Budapest",
    "iso:country":"HU",
    "name:epo_x_preferred":[
        "R\u00e1baszentandr\u00e1s"
    ],
    "name:fas_x_preferred":[
        "\u0631\u0627\u0628\u0627\u0633\u0646\u062a\u0627\u0646\u062f\u0631\u0627\u0634"
    ],
    "name:fra_x_preferred":[
        "R\u00e1baszentandr\u00e1s"
    ],
    "name:hun_x_preferred":[
        "R\u00e1baszentandr\u00e1s"
    ],
    "name:ita_x_preferred":[
        "R\u00e1baszentandr\u00e1s"
    ],
    "name:msa_x_preferred":[
        "R\u00e1baszentandr\u00e1s"
    ],
    "name:nld_x_preferred":[
        "R\u00e1baszentandr\u00e1s"
    ],
    "name:pol_x_preferred":[
        "R\u00e1baszentandr\u00e1s"
    ],
    "name:ron_x_preferred":[
        "R\u00e1baszentandr\u00e1s"
    ],
    "name:slk_x_preferred":[
        "R\u00e1baszentandr\u00e1s"
    ],
    "name:slv_x_preferred":[
        "R\u00e1baszentandr\u00e1s"
    ],
    "name:spa_x_preferred":[
        "R\u00e1baszentandr\u00e1s"
    ],
    "name:vie_x_preferred":[
        "R\u00e1baszentandr\u00e1s"
    ],
    "name:zho_x_preferred":[
        "\u62c9\u9c8d\u68ee\u901a\u5fb7\u62c9\u4ec0"
    ],
    "wof:name":"Rabaszentandras",
    "wof:placetype":"locality"
},
  "geometry": {"coordinates":[17.32944,47.45914000000001],"type":"Point"}
}