{
  "type": "Feature",
  "properties": {
    "gn:admin1_code":"24.0",
    "gn:asciiname":"Csalanyos",
    "gn:cc2":"HU",
    "gn:country_code":"HU",
    "gn:dem":172,
    "gn:feature_class":"P",
    "gn:feature_code":"PPL",
    "gn:name":"Csal\u00e1nyos",
    "gn:population":0,
    "gn:timezone":"Europe/Budapest",
    "iso:country":"HU",
    "name:und_x_variant":[
        "Csoll\u00e1nyosi Malom",
        "Csal\u00e1nyos"
    ],
    "wof:name":"Csalanyos",
    "wof:placetype":"locality"
},
  "geometry": {"coordinates":[16.95,46.35],"type":"Point"}
}