{
  "type": "Feature",
  "properties": {
    "gn:admin1_code":"21.0",
    "gn:asciiname":"Zavod",
    "gn:country_code":"HU",
    "gn:dem":156,
    "gn:feature_class":"P",
    "gn:feature_code":"PPL",
    "gn:name":"Z\u00e1vod",
    "gn:population":0,
    "gn:timezone":"Europe/Budapest",
    "iso:country":"HU",
    "name:epo_x_preferred":[
        "Z\u00e1vod"
    ],
    "name:fas_x_preferred":[
        "\u0632\u0627\u0648\u0648\u062f"
    ],
    "name:fra_x_preferred":[
        "Z\u00e1vod"
    ],
    "name:hun_x_preferred":[
        "Z\u00e1vod"
    ],
    "name:ita_x_preferred":[
        "Z\u00e1vod"
    ],
    "name:msa_x_preferred":[
        "Z\u00e1vod"
    ],
    "name:ron_x_preferred":[
        "Z\u00e1vod"
    ],
    "name:slk_x_preferred":[
        "Z\u00e1vod"
    ],
    "name:slv_x_preferred":[
        "Z\u00e1vod"
    ],
    "name:vie_x_preferred":[
        "Z\u00e1vod"
    ],
    "wof:name":"Zavod",
    "wof:placetype":"locality"
},
  "geometry": {"coordinates":[18.41635,46.39454],"type":"Point"}
}