{
  "type": "Feature",
  "properties": {
    "gn:admin1_code":"4.0",
    "gn:asciiname":"Tiszatardos",
    "gn:country_code":"HU",
    "gn:dem":97,
    "gn:feature_class":"P",
    "gn:feature_code":"PPL",
    "gn:name":"Tiszatardos",
    "gn:population":0,
    "gn:timezone":"Europe/Budapest",
    "iso:country":"HU",
    "name:deu_x_preferred":[
        "Tiszatardos"
    ],
    "name:epo_x_preferred":[
        "Tiszatardos"
    ],
    "name:fas_x_preferred":[
        "\u062a\u06cc\u0633\u0627\u062a\u0627\u0631\u062f\u0648\u0634"
    ],
    "name:fra_x_preferred":[
        "Tiszatardos"
    ],
    "name:heb_x_preferred":[
        "\u05d8\u05d9\u05e1\u05d8\u05e8\u05d3\u05d5\u05e9"
    ],
    "name:hun_x_preferred":[
        "Tiszatardos"
    ],
    "name:ita_x_preferred":[
        "Tiszatardos"
    ],
    "name:msa_x_preferred":[
        "Tiszatardos"
    ],
    "name:nld_x_preferred":[
        "Tiszatardos"
    ],
    "name:pol_x_preferred":[
        "Tiszatardos"
    ],
    "name:ron_x_preferred":[
        "Tiszatardos"
    ],
    "name:slk_x_preferred":[
        "Tiszatardos"
    ],
    "name:slv_x_preferred":[
        "Tiszatardos"
    ],
    "name:vie_x_preferred":[
        "Tiszatardos"
    ],
    "name:zho_x_preferred":[
        "\u8482\u7ecd\u9676\u5c14\u591a\u4ec0"
    ],
    "wof:name":"Tiszatardos",
    "wof:placetype":"locality"
},
  "geometry": {"coordinates":[21.38333,48.05],"type":"Point"}
}