{
  "type": "Feature",
  "properties": {
    "gn:admin1_code":"15.0",
    "gn:asciiname":"Fruhweissteto",
    "gn:cc2":"HU",
    "gn:country_code":"HU",
    "gn:dem":171,
    "gn:feature_class":"P",
    "gn:feature_code":"PPL",
    "gn:name":"Fr\u00fchweisstet\u0151",
    "gn:population":0,
    "gn:timezone":"Europe/Budapest",
    "iso:country":"HU",
    "name:und_x_variant":[
        "Fr\u00fchweisz-tet\u0151"
    ],
    "wof:name":"Fruhweissteto",
    "wof:placetype":"locality"
},
  "geometry": {"coordinates":[18.25,46.03333],"type":"Point"}
}