{
  "type": "Feature",
  "properties": {
    "gn:admin1_code":"9.0",
    "gn:asciiname":"Borcs",
    "gn:country_code":"HU",
    "gn:dem":116,
    "gn:feature_class":"P",
    "gn:feature_code":"PPL",
    "gn:name":"B\u00f6rcs",
    "gn:population":0,
    "gn:timezone":"Europe/Budapest",
    "iso:country":"HU",
    "name:epo_x_preferred":[
        "B\u00f6rcs"
    ],
    "name:fas_x_preferred":[
        "\u0628\u0648\u0631\u06a9\u0633"
    ],
    "name:fra_x_preferred":[
        "B\u00f6rcs"
    ],
    "name:hun_x_preferred":[
        "B\u00f6rcs"
    ],
    "name:ita_x_preferred":[
        "B\u00f6rcs"
    ],
    "name:msa_x_preferred":[
        "B\u00f6rcs"
    ],
    "name:nld_x_preferred":[
        "B\u00f6rcs"
    ],
    "name:pol_x_preferred":[
        "B\u00f6rcs"
    ],
    "name:ron_x_preferred":[
        "B\u00f6rcs"
    ],
    "name:slk_x_preferred":[
        "B\u00f6rcs"
    ],
    "name:slv_x_preferred":[
        "B\u00f6rcs"
    ],
    "name:vie_x_preferred":[
        "B\u00f6rcs"
    ],
    "name:zho_x_preferred":[
        "\u4f2f\u5c14\u5947"
    ],
    "wof:name":"Borcs",
    "wof:placetype":"locality"
},
  "geometry": {"coordinates":[17.49991,47.68534],"type":"Point"}
}