{
  "type": "Feature",
  "properties": {
    "gn:admin1_code":"9.0",
    "gn:asciiname":"Borcs",
    "gn:country_code":"HU",
    "gn:dem":116,
    "gn:feature_class":"P",
    "gn:feature_code":"PPL",
    "gn:name":"B\u00f6rcs",
    "gn:population":0,
    "gn:timezone":"Europe/Budapest",
    "iso:country":"HU",
    "name:und_x_variant":[
        "B\u00f6rcs"
    ],
    "wof:name":"Borcs",
    "wof:placetype":"locality"
},
  "geometry": {"coordinates":[17.49991,47.68534],"type":"Point"}
}