{
  "type": "Feature",
  "properties": {
    "gn:admin1_code":"2.0",
    "gn:asciiname":"Durgotanya",
    "gn:cc2":"HU",
    "gn:country_code":"HU",
    "gn:dem":92,
    "gn:feature_class":"P",
    "gn:feature_code":"PPL",
    "gn:name":"Durg\u00f3tanya",
    "gn:population":0,
    "gn:timezone":"Europe/Budapest",
    "iso:country":"HU",
    "name:und_x_variant":[
        "Durk\u00f3tanya",
        "Durg\u00f3tanya"
    ],
    "wof:name":"Durgotanya",
    "wof:placetype":"locality"
},
  "geometry": {"coordinates":[17.98333,45.86667],"type":"Point"}
}