{
  "type": "Feature",
  "properties": {
    "gn:admin1_code":"23.0",
    "gn:asciiname":"Csehbanya",
    "gn:country_code":"HU",
    "gn:dem":367,
    "gn:feature_class":"P",
    "gn:feature_code":"PPL",
    "gn:name":"Csehb\u00e1nya",
    "gn:population":0,
    "gn:timezone":"Europe/Budapest",
    "iso:country":"HU",
    "name:ces_x_preferred":[
        "Csehb\u00e1nya"
    ],
    "name:epo_x_preferred":[
        "Csehb\u00e1nya"
    ],
    "name:fas_x_preferred":[
        "\u0686\u0647\u0628\u0627\u0646\u06cc\u0627"
    ],
    "name:fra_x_preferred":[
        "Csehb\u00e1nya"
    ],
    "name:hun_x_preferred":[
        "Csehb\u00e1nya"
    ],
    "name:ita_x_preferred":[
        "Csehb\u00e1nya"
    ],
    "name:msa_x_preferred":[
        "Csehb\u00e1nya"
    ],
    "name:nld_x_preferred":[
        "Csehb\u00e1nya"
    ],
    "name:ron_x_preferred":[
        "Csehb\u00e1nya"
    ],
    "name:slk_x_preferred":[
        "Csehb\u00e1nya"
    ],
    "name:slv_x_preferred":[
        "Csehb\u00e1nya"
    ],
    "name:swe_x_preferred":[
        "Csehb\u00e1nya"
    ],
    "name:vie_x_preferred":[
        "Csehb\u00e1nya"
    ],
    "name:zho_x_preferred":[
        "\u5207\u8d6b\u5df4\u5c3c\u5965"
    ],
    "wof:name":"Csehbanya",
    "wof:placetype":"locality"
},
  "geometry": {"coordinates":[17.68365,47.18205],"type":"Point"}
}