{
  "type": "Feature",
  "properties": {
    "gn:admin1_code":"6.0",
    "gn:asciiname":"Szektoi Hegy",
    "gn:country_code":"HU",
    "gn:dem":81,
    "gn:feature_class":"P",
    "gn:feature_code":"PPL",
    "gn:name":"Sz\u00e9kt\u00f3i Hegy",
    "gn:population":0,
    "gn:timezone":"Europe/Budapest",
    "iso:country":"HU",
    "wof:name":"Szektoi Hegy",
    "wof:placetype":"locality"
},
  "geometry": {"coordinates":[20.06667,46.28333],"type":"Point"}
}