{
  "type": "Feature",
  "properties": {
    "gn:admin1_code":"23.0",
    "gn:asciiname":"Boba",
    "gn:country_code":"HU",
    "gn:dem":132,
    "gn:feature_class":"P",
    "gn:feature_code":"PPL",
    "gn:name":"Boba",
    "gn:population":0,
    "gn:timezone":"Europe/Budapest",
    "iso:country":"HU",
    "wof:name":"Boba",
    "wof:placetype":"locality"
},
  "geometry": {"coordinates":[17.18737,47.18279],"type":"Point"}
}