{
  "type": "Feature",
  "properties": {
    "gn:admin1_code":"6.0",
    "gn:asciiname":"Barattya",
    "gn:country_code":"HU",
    "gn:dem":77,
    "gn:feature_class":"P",
    "gn:feature_code":"PPL",
    "gn:name":"Barattya",
    "gn:population":0,
    "gn:timezone":"Europe/Budapest",
    "iso:country":"HU",
    "wof:name":"Barattya",
    "wof:placetype":"locality"
},
  "geometry": {"coordinates":[20.28741,46.4872],"type":"Point"}
}