{
  "type": "Feature",
  "properties": {
    "gn:admin1_code":"9.0",
    "gn:asciiname":"Osli",
    "gn:country_code":"HU",
    "gn:dem":114,
    "gn:feature_class":"P",
    "gn:feature_code":"PPL",
    "gn:name":"Osli",
    "gn:population":0,
    "gn:timezone":"Europe/Budapest",
    "iso:country":"HU",
    "name:ces_x_preferred":[
        "Osli"
    ],
    "name:deu_x_preferred":[
        "Osli"
    ],
    "name:epo_x_preferred":[
        "Osli"
    ],
    "name:fas_x_preferred":[
        "\u0627\u0648\u0634\u0644\u06cc"
    ],
    "name:fra_x_preferred":[
        "Osli"
    ],
    "name:heb_x_preferred":[
        "\u05d0\u05d5\u05e9\u05dc\u05d9"
    ],
    "name:hrv_x_preferred":[
        "O\u0161lija"
    ],
    "name:hun_x_preferred":[
        "Osli"
    ],
    "name:ita_x_preferred":[
        "Osli"
    ],
    "name:msa_x_preferred":[
        "Osli"
    ],
    "name:nld_x_preferred":[
        "Osli"
    ],
    "name:pol_x_preferred":[
        "Osli"
    ],
    "name:ron_x_preferred":[
        "Osli"
    ],
    "name:slk_x_preferred":[
        "Osli"
    ],
    "name:slv_x_preferred":[
        "Osli"
    ],
    "name:spa_x_preferred":[
        "Osli"
    ],
    "name:vie_x_preferred":[
        "Osli"
    ],
    "name:zho_x_preferred":[
        "\u6b27\u4ec0\u5229"
    ],
    "wof:name":"Osli",
    "wof:placetype":"locality"
},
  "geometry": {"coordinates":[17.07517,47.63772],"type":"Point"}
}