{
  "type": "Feature",
  "properties": {
    "gn:gn_country":"HU",
    "gn:gn_fcode":"PPL",
    "gn:gn_pop":0,
    "iso:country":"HU",
    "name:chi_x_preferred":[
        "\u8d39\u6d85\u5f17"
    ],
    "name:dut_x_preferred":[
        "Feny\u0151f\u0151"
    ],
    "name:eng_x_preferred":[
        "Feny\u0151f\u0151"
    ],
    "name:epo_x_preferred":[
        "Feny\u0151f\u0151"
    ],
    "name:fre_x_preferred":[
        "Feny\u0151f\u0151"
    ],
    "name:hun_x_preferred":[
        "Feny\u0151f\u0151"
    ],
    "name:ita_x_preferred":[
        "Feny\u0151f\u0151"
    ],
    "name:may_x_preferred":[
        "Feny\u0151f\u0151"
    ],
    "name:nan_x_preferred":[
        "Feny\u0151f\u0151"
    ],
    "name:pol_x_preferred":[
        "Feny\u0151f\u0151"
    ],
    "name:rum_x_preferred":[
        "Feny\u0151f\u0151"
    ],
    "name:slo_x_preferred":[
        "Feny\u0151f\u0151"
    ],
    "name:slv_x_preferred":[
        "Feny\u0151f\u0151"
    ],
    "name:vie_x_preferred":[
        "Feny\u0151f\u0151"
    ],
    "qs_pg:aaroncc":"HU",
    "qs_pg:gn_country":"HU",
    "qs_pg:gn_fcode":"PPL",
    "qs_pg:gn_pop":0,
    "qs_pg:name":"Feny\u0151f\u0151",
    "qs_pg:name_adm0":"Magyarorsz\u00e1g",
    "qs_pg:name_adm1":"Gy\u0151r-Moson-Sopron",
    "qs_pg:photos":29,
    "qs_pg:photos_1k":6,
    "qs_pg:photos_9k":1,
    "qs_pg:photos_9r":2,
    "qs_pg:photos_all":29,
    "qs_pg:photos_sr":2,
    "qs_pg:pop_sr":0,
    "qs_pg:qs_pg_placetype":"locality",
    "qs_pg:qs_pg_placetype_gp":"Town",
    "qs_pg:woe_adm0":23424844,
    "woe:adm0_id":23424844,
    "woe:name_adm0":"Magyarorsz\u00e1g",
    "woe:name_adm1":"Gy\u0151r-Moson-Sopron",
    "woe:placetype":"Town",
    "wof:name":"Feny\u0151f\u0151",
    "wof:placetype":"locality"
},
  "geometry": {"coordinates":[17.76528,47.35032],"type":"Point"}
}