{
  "type": "Feature",
  "properties": {
    "gn:admin1_code":"4.0",
    "gn:asciiname":"Kistanya",
    "gn:cc2":"HU",
    "gn:country_code":"HU",
    "gn:dem":89,
    "gn:feature_class":"P",
    "gn:feature_code":"PPL",
    "gn:name":"Kistanya",
    "gn:population":0,
    "gn:timezone":"Europe/Budapest",
    "iso:country":"HU",
    "name:und_x_variant":[
        "K\u00e1ptalani Kis-tanya",
        "Kaptalani-tanya",
        "Kistanya"
    ],
    "wof:name":"Kistanya",
    "wof:placetype":"locality"
},
  "geometry": {"coordinates":[20.93333,47.73333],"type":"Point"}
}