{
  "type": "Feature",
  "properties": {
    "gn:admin1_code":"23.0",
    "gn:asciiname":"Szedertanya",
    "gn:country_code":"HU",
    "gn:dem":145,
    "gn:feature_class":"P",
    "gn:feature_code":"PPL",
    "gn:name":"Szedertanya",
    "gn:population":0,
    "gn:timezone":"Europe/Budapest",
    "iso:country":"HU",
    "wof:name":"Szedertanya",
    "wof:placetype":"locality"
},
  "geometry": {"coordinates":[17.36667000000001,47.23333],"type":"Point"}
}