{
  "type": "Feature",
  "properties": {
    "gn:gn_country":"HU",
    "gn:gn_fcode":"PPL",
    "gn:gn_pop":0,
    "iso:country":"HU",
    "name:deu_x_preferred":[
        "J\u00e1sz\u00e1g\u00f3"
    ],
    "name:eng_x_preferred":[
        "J\u00e1sz\u00e1g\u00f3"
    ],
    "name:epo_x_preferred":[
        "J\u00e1sz\u00e1g\u00f3"
    ],
    "name:fra_x_preferred":[
        "J\u00e1sz\u00e1g\u00f3"
    ],
    "name:hun_x_preferred":[
        "J\u00e1sz\u00e1g\u00f3"
    ],
    "name:ita_x_preferred":[
        "J\u00e1sz\u00e1g\u00f3"
    ],
    "name:msa_x_preferred":[
        "J\u00e1sz\u00e1g\u00f3"
    ],
    "name:nan_x_preferred":[
        "J\u00e1sz\u00e1g\u00f3"
    ],
    "name:nld_x_preferred":[
        "J\u00e1sz\u00e1g\u00f3"
    ],
    "name:ron_x_preferred":[
        "J\u00e1sz\u00e1g\u00f3"
    ],
    "name:slk_x_preferred":[
        "J\u00e1sz\u00e1g\u00f3"
    ],
    "name:slv_x_preferred":[
        "J\u00e1sz\u00e1g\u00f3"
    ],
    "name:urd_x_preferred":[
        "\u062c\u0627\u0633\u0632\u0627\u06af\u0648"
    ],
    "name:vie_x_preferred":[
        "J\u00e1sz\u00e1g\u00f3"
    ],
    "name:zho_x_preferred":[
        "\u4e9a\u8428\u6208"
    ],
    "qs_pg:aaroncc":"HU",
    "qs_pg:gn_country":"HU",
    "qs_pg:gn_fcode":"PPL",
    "qs_pg:gn_pop":0,
    "qs_pg:name":"J\u00e1sz\u00e1g\u00f3",
    "qs_pg:name_adm0":"Magyarorsz\u00e1g",
    "qs_pg:name_adm1":"J\u00e1sz-Nagykun-Szolnok",
    "qs_pg:photos":31,
    "qs_pg:photos_1k":6,
    "qs_pg:photos_9k":1,
    "qs_pg:photos_9r":2,
    "qs_pg:photos_all":31,
    "qs_pg:photos_sr":2,
    "qs_pg:pop_sr":0,
    "qs_pg:qs_pg_placetype":"locality",
    "qs_pg:qs_pg_placetype_gp":"Town",
    "qs_pg:woe_adm0":23424844,
    "woe:adm0_id":23424844,
    "woe:name_adm0":"Magyarorsz\u00e1g",
    "woe:name_adm1":"J\u00e1sz-Nagykun-Szolnok",
    "woe:placetype":"Town",
    "wof:name":"J\u00e1sz\u00e1g\u00f3",
    "wof:placetype":"locality"
},
  "geometry": {"coordinates":[19.85591,47.59315],"type":"Point"}
}