{
  "type": "Feature",
  "properties": {
    "gn:country":"HU",
    "gn:fcode":"PPL",
    "gn:population":0,
    "iso:country":"HU",
    "name:ast_x_preferred":[
        "Oszk\u00f3"
    ],
    "name:deu_x_preferred":[
        "Oszk\u00f3"
    ],
    "name:eng_x_preferred":[
        "Oszk\u00f3"
    ],
    "name:epo_x_preferred":[
        "Oszk\u00f3"
    ],
    "name:fas_x_preferred":[
        "\u0627\u0648\u0633\u06a9\u0648"
    ],
    "name:fra_x_preferred":[
        "Oszk\u00f3"
    ],
    "name:gle_x_preferred":[
        "Oszk\u00f3"
    ],
    "name:hun_x_preferred":[
        "Oszk\u00f3"
    ],
    "name:ita_x_preferred":[
        "Oszk\u00f3"
    ],
    "name:msa_x_preferred":[
        "Oszk\u00f3"
    ],
    "name:nan_x_preferred":[
        "Oszk\u00f3"
    ],
    "name:nld_x_preferred":[
        "Oszk\u00f3"
    ],
    "name:por_x_preferred":[
        "Oszk\u00f3"
    ],
    "name:ron_x_preferred":[
        "Oszk\u00f3"
    ],
    "name:slk_x_preferred":[
        "Oszk\u00f3"
    ],
    "name:slv_x_preferred":[
        "Oszk\u00f3"
    ],
    "name:vie_x_preferred":[
        "Oszk\u00f3"
    ],
    "name:zho_x_preferred":[
        "\u6b27\u65af\u79d1"
    ],
    "qs_pg:aaroncc":"HU",
    "qs_pg:gn_country":"HU",
    "qs_pg:gn_fcode":"PPL",
    "qs_pg:gn_pop":0,
    "qs_pg:name":"Oszk\u00f3",
    "qs_pg:name_adm0":"Magyarorsz\u00e1g",
    "qs_pg:name_adm1":"Vas",
    "qs_pg:photos":24,
    "qs_pg:photos_1k":5,
    "qs_pg:photos_9k":1,
    "qs_pg:photos_9r":1,
    "qs_pg:photos_all":24,
    "qs_pg:photos_sr":1,
    "qs_pg:pop_sr":0,
    "qs_pg:qs_pg_placetype":"locality",
    "qs_pg:qs_pg_placetype_gp":"Town",
    "qs_pg:woe_adm0":23424844,
    "woe:adm0_id":23424844,
    "woe:name_adm0":"Magyarorsz\u00e1g",
    "woe:name_adm1":"Vas",
    "woe:placetype":"Town",
    "wof:name":"Oszk\u00f3",
    "wof:placetype":"locality"
},
  "geometry": {"coordinates":[16.8769,47.03835],"type":"Point"}
}