{
  "type": "Feature",
  "properties": {
    "gn:admin1_code":"4.0",
    "gn:asciiname":"Solyomvolgydulo",
    "gn:country_code":"HU",
    "gn:dem":139,
    "gn:feature_class":"P",
    "gn:feature_code":"PPL",
    "gn:name":"S\u00f3lyomv\u00f6lgyd\u0171l\u0151",
    "gn:population":0,
    "gn:timezone":"Europe/Budapest",
    "iso:country":"HU",
    "wof:name":"Solyomvolgydulo",
    "wof:placetype":"locality"
},
  "geometry": {"coordinates":[20.58333,48.28333],"type":"Point"}
}