{
  "type": "Feature",
  "properties": {
    "gn:admin1_code":"9.0",
    "gn:asciiname":"Nemesker",
    "gn:country_code":"HU",
    "gn:dem":179,
    "gn:feature_class":"P",
    "gn:feature_code":"PPL",
    "gn:name":"Nemesk\u00e9r",
    "gn:population":0,
    "gn:timezone":"Europe/Budapest",
    "iso:country":"HU",
    "name:ces_x_preferred":[
        "Nemesk\u00e9r"
    ],
    "name:epo_x_preferred":[
        "Nemesk\u00e9r"
    ],
    "name:fas_x_preferred":[
        "\u0646\u0645\u0634\u06a9\u0631"
    ],
    "name:fra_x_preferred":[
        "Nemesk\u00e9r"
    ],
    "name:hrv_x_preferred":[
        "Nami\u0161ir"
    ],
    "name:hun_x_preferred":[
        "Nemesk\u00e9r"
    ],
    "name:ita_x_preferred":[
        "Nemesk\u00e9r"
    ],
    "name:msa_x_preferred":[
        "Nemesk\u00e9r"
    ],
    "name:nld_x_preferred":[
        "Nemesk\u00e9r"
    ],
    "name:pol_x_preferred":[
        "Nemesk\u00e9r"
    ],
    "name:ron_x_preferred":[
        "Nemesk\u00e9r"
    ],
    "name:slk_x_preferred":[
        "Nemesk\u00e9r"
    ],
    "name:slv_x_preferred":[
        "Nemesk\u00e9r"
    ],
    "name:und_x_variant":[
        "Nemesk\u00e9r"
    ],
    "name:vie_x_preferred":[
        "Nemesk\u00e9r"
    ],
    "name:zho_x_preferred":[
        "\u5948\u8fc8\u4ec0\u51ef\u5c14"
    ],
    "wof:name":"Nemesker",
    "wof:placetype":"locality"
},
  "geometry": {"coordinates":[16.80556,47.48333],"type":"Point"}
}