{
  "type": "Feature",
  "properties": {
    "gn:admin1_code":"9.0",
    "gn:asciiname":"Nemesker",
    "gn:country_code":"HU",
    "gn:dem":179,
    "gn:feature_class":"P",
    "gn:feature_code":"PPL",
    "gn:name":"Nemesk\u00e9r",
    "gn:population":0,
    "gn:timezone":"Europe/Budapest",
    "iso:country":"HU",
    "name:hrv_x_preferred":[
        "Nami\u0161ir"
    ],
    "name:und_x_variant":[
        "Nemesk\u00e9r"
    ],
    "wof:name":"Nemesker",
    "wof:placetype":"locality"
},
  "geometry": {"coordinates":[16.80556,47.48333],"type":"Point"}
}