{
  "type": "Feature",
  "properties": {
    "gn:admin1_code":"24.0",
    "gn:asciiname":"Kozmadombja",
    "gn:country_code":"HU",
    "gn:dem":214,
    "gn:feature_class":"P",
    "gn:feature_code":"PPL",
    "gn:name":"Kozmadombja",
    "gn:population":0,
    "gn:timezone":"Europe/Budapest",
    "iso:country":"HU",
    "name:epo_x_preferred":[
        "Kozmadombja"
    ],
    "name:fas_x_preferred":[
        "\u06a9\u0648\u0632\u0645\u0627\u062f\u0648\u0645\u0628\u06cc\u0627"
    ],
    "name:fra_x_preferred":[
        "Kozmadombja"
    ],
    "name:hun_x_preferred":[
        "Kozmadombja"
    ],
    "name:ita_x_preferred":[
        "Kozmadombja"
    ],
    "name:msa_x_preferred":[
        "Kozmadombja"
    ],
    "name:nld_x_preferred":[
        "Kozmadombja"
    ],
    "name:ron_x_preferred":[
        "Kozmadombja"
    ],
    "name:slk_x_preferred":[
        "Kozmadombja"
    ],
    "name:slv_x_preferred":[
        "Kozmadombja"
    ],
    "name:vie_x_preferred":[
        "Kozmadombja"
    ],
    "name:zho_x_preferred":[
        "\u79d1\u5179\u6bdb\u4e1c\u5e03\u5c27"
    ],
    "wof:name":"Kozmadombja",
    "wof:placetype":"locality"
},
  "geometry": {"coordinates":[16.55086,46.76703],"type":"Point"}
}