{
  "type": "Feature",
  "properties": {
    "gn:admin1_code":"4.0",
    "gn:asciiname":"Derenk",
    "gn:country_code":"HU",
    "gn:dem":378,
    "gn:feature_class":"P",
    "gn:feature_code":"PPL",
    "gn:name":"Derenk",
    "gn:population":0,
    "gn:timezone":"Europe/Budapest",
    "iso:country":"HU",
    "name:pol_x_preferred":[
        "Drenka"
    ],
    "wof:name":"Derenk",
    "wof:placetype":"locality"
},
  "geometry": {"coordinates":[20.65,48.55],"type":"Point"}
}