{
  "type": "Feature",
  "properties": {
    "gn:admin1_code":"14.0",
    "gn:asciiname":"Csevicekutpuszta",
    "gn:country_code":"HU",
    "gn:dem":311,
    "gn:feature_class":"P",
    "gn:feature_code":"PPL",
    "gn:name":"Csevicek\u00fatpuszta",
    "gn:population":0,
    "gn:timezone":"Europe/Budapest",
    "iso:country":"HU",
    "name:und_x_variant":[
        "S\u00f3sk\u00fat-puszta",
        "Csevicek\u00fatpuszta"
    ],
    "wof:name":"Csevicekutpuszta",
    "wof:placetype":"locality"
},
  "geometry": {"coordinates":[19.74286,48.2082],"type":"Point"}
}