{
  "type": "Feature",
  "properties": {
    "iso:country":"HU",
    "name:hun_x_preferred":[
        "R\u00e1kosliget"
    ],
    "wof:name":"Rakosliget",
    "wof:placetype":"neighbourhood"
},
  "geometry": {"coordinates":[19.25528260788179,47.49350585214134],"type":"Point"}
}