{
  "type": "Feature",
  "properties": {
    "gn:admin1_code":"2.0",
    "gn:asciiname":"Adorjas",
    "gn:country_code":"HU",
    "gn:dem":97,
    "gn:feature_class":"P",
    "gn:feature_code":"PPL",
    "gn:name":"Adorj\u00e1s",
    "gn:population":0,
    "gn:timezone":"Europe/Budapest",
    "iso:country":"HU",
    "name:ces_x_preferred":[
        "Adorj\u00e1s"
    ],
    "name:deu_x_preferred":[
        "Adorj\u00e1s"
    ],
    "name:epo_x_preferred":[
        "Adorj\u00e1s"
    ],
    "name:fas_x_preferred":[
        "\u0627\u062f\u0648\u0631\u062c\u0627\u0633"
    ],
    "name:fra_x_preferred":[
        "Adorj\u00e1s"
    ],
    "name:hrv_x_preferred":[
        "Adorj\u00e1s"
    ],
    "name:hun_x_preferred":[
        "Adorj\u00e1s"
    ],
    "name:ita_x_preferred":[
        "Adorj\u00e1s"
    ],
    "name:msa_x_preferred":[
        "Adorj\u00e1s"
    ],
    "name:nld_x_preferred":[
        "Adorj\u00e1s"
    ],
    "name:pol_x_preferred":[
        "Adorj\u00e1s"
    ],
    "name:ron_x_preferred":[
        "Adorj\u00e1s"
    ],
    "name:slk_x_preferred":[
        "Adorj\u00e1s"
    ],
    "name:slv_x_preferred":[
        "Adorj\u00e1s"
    ],
    "name:und_x_variant":[
        "Adorj\u00e1s"
    ],
    "name:vie_x_preferred":[
        "Adorj\u00e1s"
    ],
    "name:zho_x_preferred":[
        "\u5965\u591a\u5c14\u4e9a\u4ec0"
    ],
    "wof:name":"Adorjas",
    "wof:placetype":"locality"
},
  "geometry": {"coordinates":[18.06278,45.85056],"type":"Point"}
}