{
  "type": "Feature",
  "properties": {
    "gn:admin1_code":"2.0",
    "gn:asciiname":"Adorjas",
    "gn:country_code":"HU",
    "gn:dem":97,
    "gn:feature_class":"P",
    "gn:feature_code":"PPL",
    "gn:name":"Adorj\u00e1s",
    "gn:population":0,
    "gn:timezone":"Europe/Budapest",
    "iso:country":"HU",
    "name:und_x_variant":[
        "Adorj\u00e1s"
    ],
    "wof:name":"Adorjas",
    "wof:placetype":"locality"
},
  "geometry": {"coordinates":[18.06278,45.85056],"type":"Point"}
}