{
  "type": "Feature",
  "properties": {
    "gn:admin1_code":"2.0",
    "gn:asciiname":"Mekenyesi Tanya",
    "gn:country_code":"HU",
    "gn:dem":194,
    "gn:feature_class":"P",
    "gn:feature_code":"PPL",
    "gn:name":"Mek\u00e9nyesi Tanya",
    "gn:population":0,
    "gn:timezone":"Europe/Budapest",
    "iso:country":"HU",
    "wof:name":"Mekenyesi Tanya",
    "wof:placetype":"locality"
},
  "geometry": {"coordinates":[18.33333,46.38333],"type":"Point"}
}