{
  "type": "Feature",
  "properties": {
    "gn:admin1_code":"11.0",
    "gn:asciiname":"Eskerennatanya",
    "gn:country_code":"HU",
    "gn:dem":349,
    "gn:feature_class":"P",
    "gn:feature_code":"PPL",
    "gn:name":"Eskerennatanya",
    "gn:population":0,
    "gn:timezone":"Europe/Budapest",
    "iso:country":"HU",
    "wof:name":"Eskerennatanya",
    "wof:placetype":"locality"
},
  "geometry": {"coordinates":[20.45,48.13333],"type":"Point"}
}