{
  "type": "Feature",
  "properties": {
    "iso:country":"HU",
    "name:hun_x_colloquial":[
        "Alsovaros",
        "Alsovarosi Feketefoeldek",
        "Alsovarosi Feketefoldek",
        "Alsovarosi Godrok",
        "Alsovarosi Goedroek"
    ],
    "name:hun_x_preferred":[
        "Als\u00f3v\u00e1ros"
    ],
    "name:hun_x_variant":[
        "Als\u00f3v\u00e1rosi Feketef\u00f6ldek",
        "Als\u00f3v\u00e1rosi G\u00f6dr\u00f6k"
    ],
    "qs:gn_adm0_cc":"HU",
    "qs:gn_fcode":"PPLX",
    "qs:gn_local":715429,
    "qs:gn_nam_loc":"Szeged, Szeged, Szeged, HU",
    "qs:gn_namadm1":"19",
    "qs:gn_name":"Als\u00f3v\u00e1ros",
    "qs:local_max":1293,
    "qs:local_sum":3309,
    "qs:localhoods":5,
    "qs:name":"Als\u00f3v\u00e1ros",
    "qs:name_adm0":"Magyarorsz\u00e1g",
    "qs:name_adm1":"Szeged",
    "qs:name_adm2":"Szeged",
    "qs:name_local":"Szeged",
    "qs:photo_max":219,
    "qs:photo_sum":785,
    "qs:placetype":"Suburb",
    "qs:quad_count":41,
    "qs:woe_adm0":23424844,
    "qs:woe_adm1":56043624,
    "qs:woe_adm2":12593409,
    "qs:woe_lau":0,
    "qs:woe_local":815498,
    "qs:woe_ver":"7.10.0",
    "wof:lang":[
        "hun"
    ],
    "wof:name":"Als\u00f3v\u00e1ros",
    "wof:placetype":"neighbourhood"
},
  "geometry": {"coordinates":[20.143048,46.235633],"type":"Point"}
}