{
  "type": "Feature",
  "properties": {
    "gn:admin1_code":"17.0",
    "gn:asciiname":"Antalszallas",
    "gn:country_code":"HU",
    "gn:dem":211,
    "gn:feature_class":"P",
    "gn:feature_code":"PPL",
    "gn:name":"Antalsz\u00e1ll\u00e1s",
    "gn:population":0,
    "gn:timezone":"Europe/Budapest",
    "iso:country":"HU",
    "wof:name":"Antalszallas",
    "wof:placetype":"locality"
},
  "geometry": {"coordinates":[17.83812,46.20511],"type":"Point"}
}