{
  "type": "Feature",
  "properties": {
    "gn:gn_country":"HU",
    "gn:gn_fcode":"PPL",
    "gn:gn_pop":0,
    "iso:country":"HU",
    "name:deu_x_preferred":[
        "Soml\u00f3jen\u0151"
    ],
    "name:eng_x_preferred":[
        "Soml\u00f3jen\u0151"
    ],
    "name:epo_x_preferred":[
        "Soml\u00f3jen\u0151"
    ],
    "name:fra_x_preferred":[
        "Soml\u00f3jen\u0151"
    ],
    "name:hun_x_preferred":[
        "Soml\u00f3jen\u0151"
    ],
    "name:ita_x_preferred":[
        "Soml\u00f3jen\u0151"
    ],
    "name:msa_x_preferred":[
        "Soml\u00f3jen\u0151"
    ],
    "name:nan_x_preferred":[
        "Soml\u00f3jen\u0151"
    ],
    "name:nld_x_preferred":[
        "Soml\u00f3jen\u0151"
    ],
    "name:ron_x_preferred":[
        "Soml\u00f3jen\u0151"
    ],
    "name:slk_x_preferred":[
        "Soml\u00f3jen\u0151"
    ],
    "name:slv_x_preferred":[
        "Soml\u00f3jen\u0151"
    ],
    "name:swe_x_preferred":[
        "Soml\u00f3jen\u0151"
    ],
    "name:vie_x_preferred":[
        "Soml\u00f3jen\u0151"
    ],
    "name:zho_x_preferred":[
        "\u7ecd\u59c6\u6d1b\u8036\u5185"
    ],
    "qs_pg:aaroncc":"HU",
    "qs_pg:gn_country":"HU",
    "qs_pg:gn_fcode":"PPL",
    "qs_pg:gn_pop":0,
    "qs_pg:name":"Soml\u00f3jen\u0151",
    "qs_pg:name_adm0":"Magyarorsz\u00e1g",
    "qs_pg:name_adm1":"Veszpr\u00e9m",
    "qs_pg:photos":116,
    "qs_pg:photos_1k":24,
    "qs_pg:photos_9k":1,
    "qs_pg:photos_9r":3,
    "qs_pg:photos_all":116,
    "qs_pg:photos_sr":3,
    "qs_pg:pop_sr":0,
    "qs_pg:qs_pg_placetype":"locality",
    "qs_pg:qs_pg_placetype_gp":"Town",
    "qs_pg:woe_adm0":23424844,
    "woe:adm0_id":23424844,
    "woe:name_adm0":"Magyarorsz\u00e1g",
    "woe:name_adm1":"Veszpr\u00e9m",
    "woe:placetype":"Town",
    "wof:name":"Soml\u00f3jen\u0151",
    "wof:placetype":"locality"
},
  "geometry": {"coordinates":[17.35448,47.12763],"type":"Point"}
}