{
  "type": "Feature",
  "properties": {
    "gn:country":"HU",
    "gn:fcode":"PPL",
    "gn:population":0,
    "iso:country":"HU",
    "name:eng_x_preferred":[
        "Monoszl\u00f3"
    ],
    "name:epo_x_preferred":[
        "Monoszl\u00f3"
    ],
    "name:fas_x_preferred":[
        "\u0645\u0648\u0646\u0648\u0633\u0644\u0648"
    ],
    "name:fra_x_preferred":[
        "Monoszl\u00f3"
    ],
    "name:hrv_x_preferred":[
        "Moslavina"
    ],
    "name:hun_x_preferred":[
        "Monoszl\u00f3"
    ],
    "name:ita_x_preferred":[
        "Monoszl\u00f3"
    ],
    "name:msa_x_preferred":[
        "Monoszl\u00f3"
    ],
    "name:nan_x_preferred":[
        "Monoszl\u00f3"
    ],
    "name:nld_x_preferred":[
        "Monoszl\u00f3"
    ],
    "name:ron_x_preferred":[
        "Monoszl\u00f3"
    ],
    "name:slk_x_preferred":[
        "Monoszl\u00f3"
    ],
    "name:slv_x_preferred":[
        "Monoszl\u00f3"
    ],
    "name:slv_x_variant":[
        "Moslavina"
    ],
    "name:swe_x_preferred":[
        "Monoszl\u00f3"
    ],
    "name:vie_x_preferred":[
        "Monoszl\u00f3"
    ],
    "name:zho_x_preferred":[
        "\u83ab\u8bfa\u65af\u6d1b"
    ],
    "qs_pg:aaroncc":"HU",
    "qs_pg:gn_country":"HU",
    "qs_pg:gn_fcode":"PPL",
    "qs_pg:gn_pop":0,
    "qs_pg:name":"Monoszl\u00f3",
    "qs_pg:name_adm0":"Magyarorsz\u00e1g",
    "qs_pg:name_adm1":"Veszpr\u00e9m",
    "qs_pg:photos":135,
    "qs_pg:photos_1k":27,
    "qs_pg:photos_9k":1,
    "qs_pg:photos_9r":3,
    "qs_pg:photos_all":135,
    "qs_pg:photos_sr":3,
    "qs_pg:pop_sr":0,
    "qs_pg:qs_pg_placetype":"locality",
    "qs_pg:qs_pg_placetype_gp":"Town",
    "qs_pg:woe_adm0":23424844,
    "woe:adm0_id":23424844,
    "woe:name_adm0":"Magyarorsz\u00e1g",
    "woe:name_adm1":"Veszpr\u00e9m",
    "woe:placetype":"Town",
    "wof:name":"Monoszl\u00f3",
    "wof:placetype":"locality"
},
  "geometry": {"coordinates":[17.63941,46.90278],"type":"Point"}
}