{
  "type": "Feature",
  "properties": {
    "gn:admin1_code":"4.0",
    "gn:asciiname":"Horvathtanya",
    "gn:country_code":"HU",
    "gn:dem":96,
    "gn:feature_class":"P",
    "gn:feature_code":"PPL",
    "gn:name":"Horv\u00e1thtanya",
    "gn:population":0,
    "gn:timezone":"Europe/Budapest",
    "iso:country":"HU",
    "wof:name":"Horvathtanya",
    "wof:placetype":"locality"
},
  "geometry": {"coordinates":[20.61667000000001,47.75],"type":"Point"}
}