{
  "type": "Feature",
  "properties": {
    "gn:admin1_code":"18.0",
    "gn:asciiname":"Marokpapi Tanya",
    "gn:country_code":"HU",
    "gn:dem":107,
    "gn:feature_class":"P",
    "gn:feature_code":"PPL",
    "gn:name":"M\u00e1rokpapi Tanya",
    "gn:population":0,
    "gn:timezone":"Europe/Budapest",
    "iso:country":"HU",
    "wof:name":"Marokpapi Tanya",
    "wof:placetype":"locality"
},
  "geometry": {"coordinates":[22.51667,48.15],"type":"Point"}
}