{
  "type": "Feature",
  "properties": {
    "gn:admin1_code":"24.0",
    "gn:asciiname":"Baconakhegy",
    "gn:country_code":"HU",
    "gn:dem":164,
    "gn:feature_class":"P",
    "gn:feature_code":"PPL",
    "gn:name":"Bac\u00f3nakhegy",
    "gn:population":0,
    "gn:timezone":"Europe/Budapest",
    "iso:country":"HU",
    "wof:name":"Baconakhegy",
    "wof:placetype":"locality"
},
  "geometry": {"coordinates":[17.05,46.48333],"type":"Point"}
}