{
  "type": "Feature",
  "properties": {
    "gn:admin1_code":"22.0",
    "gn:asciiname":"Lajerhazidulo",
    "gn:country_code":"HU",
    "gn:dem":214,
    "gn:feature_class":"P",
    "gn:feature_code":"PPL",
    "gn:name":"Lajerh\u00e1zid\u0171l\u0151",
    "gn:population":0,
    "gn:timezone":"Europe/Budapest",
    "iso:country":"HU",
    "wof:name":"Lajerhazidulo",
    "wof:placetype":"locality"
},
  "geometry": {"coordinates":[16.91667,47.11667],"type":"Point"}
}