{
  "type": "Feature",
  "properties": {
    "gn:admin1_code":"18.0",
    "gn:asciiname":"Magosliget",
    "gn:country_code":"HU",
    "gn:dem":119,
    "gn:feature_class":"P",
    "gn:feature_code":"PPL",
    "gn:name":"Magosliget",
    "gn:population":0,
    "gn:timezone":"Europe/Budapest",
    "iso:country":"HU",
    "name:epo_x_preferred":[
        "Magosliget"
    ],
    "name:fas_x_preferred":[
        "\u0645\u0627\u06af\u0648\u0634\u0644\u06cc\u06af\u062a"
    ],
    "name:fra_x_preferred":[
        "Magosliget"
    ],
    "name:hun_x_preferred":[
        "Magosliget"
    ],
    "name:ita_x_preferred":[
        "Magosliget"
    ],
    "name:msa_x_preferred":[
        "Magosliget"
    ],
    "name:nld_x_preferred":[
        "Magosliget"
    ],
    "name:ron_x_preferred":[
        "Magosliget"
    ],
    "name:slk_x_preferred":[
        "Magosliget"
    ],
    "name:slv_x_preferred":[
        "Magosliget"
    ],
    "name:vie_x_preferred":[
        "Magosliget"
    ],
    "name:zho_x_preferred":[
        "\u6bdb\u6208\u4ec0\u5229\u76d6\u7279"
    ],
    "wof:name":"Magosliget",
    "wof:placetype":"locality"
},
  "geometry": {"coordinates":[22.86342,48.05477],"type":"Point"}
}