{
  "type": "Feature",
  "properties": {
    "gn:admin1_code":"24.0",
    "gn:asciiname":"Miksamajor",
    "gn:country_code":"HU",
    "gn:dem":107,
    "gn:feature_class":"P",
    "gn:feature_code":"PPL",
    "gn:name":"Miksamajor",
    "gn:population":0,
    "gn:timezone":"Europe/Budapest",
    "iso:country":"HU",
    "wof:name":"Miksamajor",
    "wof:placetype":"locality"
},
  "geometry": {"coordinates":[17.1227,46.69897],"type":"Point"}
}