{
  "type": "Feature",
  "properties": {
    "gn:admin1_code":"20.0",
    "gn:asciiname":"Cukrosdulo",
    "gn:cc2":"HU",
    "gn:country_code":"HU",
    "gn:dem":86,
    "gn:feature_class":"P",
    "gn:feature_code":"PPL",
    "gn:name":"Cukrosd\u0171l\u0151",
    "gn:population":0,
    "gn:timezone":"Europe/Budapest",
    "iso:country":"HU",
    "name:und_x_variant":[
        "Cukrossz\u0151ll\u0151"
    ],
    "wof:name":"Cukrosdulo",
    "wof:placetype":"locality"
},
  "geometry": {"coordinates":[20.18333,46.86667],"type":"Point"}
}