{
  "type": "Feature",
  "properties": {
    "gn:admin1_code":"24.0",
    "gn:asciiname":"Tuskospuszta",
    "gn:country_code":"HU",
    "gn:dem":205,
    "gn:feature_class":"P",
    "gn:feature_code":"PPL",
    "gn:name":"Tusk\u00f3spuszta",
    "gn:population":0,
    "gn:timezone":"Europe/Budapest",
    "iso:country":"HU",
    "wof:name":"Tuskospuszta",
    "wof:placetype":"locality"
},
  "geometry": {"coordinates":[16.81667,46.46667],"type":"Point"}
}