{
  "type": "Feature",
  "properties": {
    "gn:admin1_code":"14.0",
    "gn:asciiname":"Matramindszent",
    "gn:country_code":"HU",
    "gn:dem":247,
    "gn:feature_class":"P",
    "gn:feature_code":"PPL",
    "gn:name":"M\u00e1tramindszent",
    "gn:population":0,
    "gn:timezone":"Europe/Budapest",
    "iso:country":"HU",
    "name:und_x_variant":[
        "M\u00e1tramindszent"
    ],
    "wof:name":"Matramindszent",
    "wof:placetype":"locality"
},
  "geometry": {"coordinates":[19.94024,47.98563],"type":"Point"}
}