{
  "type": "Feature",
  "properties": {
    "iso:country":"HU",
    "name:hun_x_preferred":[
        "Lip\u00f3tmez\u0151"
    ],
    "wof:name":"Lipotmezo",
    "wof:placetype":"neighbourhood"
},
  "geometry": {"coordinates":[18.97866446485641,47.5324485859355],"type":"Point"}
}