{
  "type": "Feature",
  "properties": {
    "gn:admin1_code":"18.0",
    "gn:asciiname":"Langtanya",
    "gn:country_code":"HU",
    "gn:dem":108,
    "gn:feature_class":"P",
    "gn:feature_code":"PPL",
    "gn:name":"L\u00e1ngtanya",
    "gn:population":0,
    "gn:timezone":"Europe/Budapest",
    "iso:country":"HU",
    "wof:name":"Langtanya",
    "wof:placetype":"locality"
},
  "geometry": {"coordinates":[22.43333,47.88333],"type":"Point"}
}