{
  "type": "Feature",
  "properties": {
    "gn:admin1_code":"20.0",
    "gn:asciiname":"Nagyallasdulo",
    "gn:country_code":"HU",
    "gn:dem":95,
    "gn:feature_class":"P",
    "gn:feature_code":"PPL",
    "gn:name":"Nagy\u00e1ll\u00e1sd\u0171l\u0151",
    "gn:population":0,
    "gn:timezone":"Europe/Budapest",
    "iso:country":"HU",
    "wof:name":"Nagyallasdulo",
    "wof:placetype":"locality"
},
  "geometry": {"coordinates":[20.18333,47.56667],"type":"Point"}
}