{
  "type": "Feature",
  "properties": {
    "gn:admin1_code":"4.0",
    "gn:asciiname":"Sajoivanka",
    "gn:country_code":"HU",
    "gn:dem":133,
    "gn:feature_class":"P",
    "gn:feature_code":"PPL",
    "gn:name":"Saj\u00f3iv\u00e1nka",
    "gn:population":0,
    "gn:timezone":"Europe/Budapest",
    "iso:country":"HU",
    "name:deu_x_preferred":[
        "Saj\u00f3iv\u00e1nka"
    ],
    "name:epo_x_preferred":[
        "Saj\u00f3iv\u00e1nka"
    ],
    "name:fas_x_preferred":[
        "\u0634\u0627\u06cc\u0648\u06cc\u0648\u0627\u0646\u06a9\u0627"
    ],
    "name:fra_x_preferred":[
        "Saj\u00f3iv\u00e1nka"
    ],
    "name:heb_x_preferred":[
        "\u05e9\u05d0\u05d9\u05d5\u05d0\u05d9\u05d5\u05d5\u05d0\u05e0\u05e7\u05d4"
    ],
    "name:hun_x_preferred":[
        "Saj\u00f3iv\u00e1nka"
    ],
    "name:ita_x_preferred":[
        "Saj\u00f3iv\u00e1nka"
    ],
    "name:msa_x_preferred":[
        "Saj\u00f3iv\u00e1nka"
    ],
    "name:nld_x_preferred":[
        "Saj\u00f3iv\u00e1nka"
    ],
    "name:pol_x_preferred":[
        "Saj\u00f3iv\u00e1nka"
    ],
    "name:ron_x_preferred":[
        "Saj\u00f3iv\u00e1nka"
    ],
    "name:slk_x_preferred":[
        "Saj\u00f3iv\u00e1nka"
    ],
    "name:slv_x_preferred":[
        "Saj\u00f3iv\u00e1nka"
    ],
    "name:und_x_variant":[
        "Saj\u00f3iv\u00e1nka"
    ],
    "name:vie_x_preferred":[
        "Saj\u00f3iv\u00e1nka"
    ],
    "name:zho_x_preferred":[
        "\u7ecd\u7ea6\u4f0a\u4e07\u8003"
    ],
    "wof:name":"Sajoivanka",
    "wof:placetype":"locality"
},
  "geometry": {"coordinates":[20.58333,48.26667],"type":"Point"}
}