{
  "type": "Feature",
  "properties": {
    "gn:admin1_code":"23.0",
    "gn:asciiname":"Bogot",
    "gn:country_code":"HU",
    "gn:dem":169,
    "gn:feature_class":"P",
    "gn:feature_code":"PPL",
    "gn:name":"B\u00f6g\u00f6t",
    "gn:population":0,
    "gn:timezone":"Europe/Budapest",
    "iso:country":"HU",
    "name:epo_x_preferred":[
        "B\u00f6g\u00f6t"
    ],
    "name:fas_x_preferred":[
        "\u0628\u0648\u06af\u0648\u062a"
    ],
    "name:fra_x_preferred":[
        "B\u00f6g\u00f6t"
    ],
    "name:hun_x_preferred":[
        "B\u00f6g\u00f6t"
    ],
    "name:ita_x_preferred":[
        "B\u00f6g\u00f6t"
    ],
    "name:msa_x_preferred":[
        "B\u00f6g\u00f6t"
    ],
    "name:nld_x_preferred":[
        "B\u00f6g\u00f6t"
    ],
    "name:ron_x_preferred":[
        "B\u00f6g\u00f6t"
    ],
    "name:slk_x_preferred":[
        "B\u00f6g\u00f6t"
    ],
    "name:slv_x_preferred":[
        "B\u00f6g\u00f6t"
    ],
    "name:und_x_variant":[
        "B\u00f6g\u00f6t"
    ],
    "name:vie_x_preferred":[
        "B\u00f6g\u00f6t"
    ],
    "name:zho_x_preferred":[
        "\u4f2f\u683c\u7279"
    ],
    "wof:name":"Bogot",
    "wof:placetype":"locality"
},
  "geometry": {"coordinates":[16.82886,47.25273],"type":"Point"}
}