{
  "type": "Feature",
  "properties": {
    "gn:admin1_code":"18.0",
    "gn:asciiname":"Vilmatanya",
    "gn:country_code":"HU",
    "gn:dem":144,
    "gn:feature_class":"P",
    "gn:feature_code":"PPL",
    "gn:name":"Vilmatanya",
    "gn:population":0,
    "gn:timezone":"Europe/Budapest",
    "iso:country":"HU",
    "wof:name":"Vilmatanya",
    "wof:placetype":"locality"
},
  "geometry": {"coordinates":[22.23729,47.98131],"type":"Point"}
}