{
  "type": "Feature",
  "properties": {
    "gn:admin1_code":"6.0",
    "gn:asciiname":"Berek",
    "gn:country_code":"HU",
    "gn:dem":81,
    "gn:feature_class":"P",
    "gn:feature_code":"PPL",
    "gn:name":"Berek",
    "gn:population":0,
    "gn:timezone":"Europe/Budapest",
    "iso:country":"HU",
    "name:bos_x_preferred":[
        "Berek"
    ],
    "name:ceb_x_preferred":[
        "Berek"
    ],
    "name:deu_x_preferred":[
        "Berek"
    ],
    "name:fra_x_preferred":[
        "Berek"
    ],
    "name:hrv_x_preferred":[
        "Berek"
    ],
    "name:hun_x_preferred":[
        "Berek"
    ],
    "name:slv_x_preferred":[
        "Berek"
    ],
    "name:srp_x_preferred":[
        "\u0411\u0435\u0440\u0435\u043a"
    ],
    "name:swe_x_preferred":[
        "Berek"
    ],
    "wof:name":"Berek",
    "wof:placetype":"locality"
},
  "geometry": {"coordinates":[20.22348,46.60853],"type":"Point"}
}