{
  "type": "Feature",
  "properties": {
    "gn:admin1_code":"4.0",
    "gn:asciiname":"Vamosujfalu",
    "gn:country_code":"HU",
    "gn:dem":119,
    "gn:feature_class":"P",
    "gn:feature_code":"PPL",
    "gn:name":"V\u00e1mos\u00fajfalu",
    "gn:population":0,
    "gn:timezone":"Europe/Budapest",
    "iso:country":"HU",
    "name:deu_x_preferred":[
        "V\u00e1mos\u00fajfalu"
    ],
    "name:epo_x_preferred":[
        "V\u00e1mos\u00fajfalu"
    ],
    "name:fas_x_preferred":[
        "\u0648\u0627\u0645\u0648\u0634\u0648\u06cc\u0641\u0627\u0644\u0648"
    ],
    "name:fra_x_preferred":[
        "V\u00e1mos\u00fajfalu"
    ],
    "name:heb_x_preferred":[
        "\u05d5\u05d0\u05de\u05d5\u05e9\u05d0\u05d5\u05d9\u05e4\u05dc\u05d5"
    ],
    "name:hun_x_preferred":[
        "V\u00e1mos\u00fajfalu"
    ],
    "name:ita_x_preferred":[
        "V\u00e1mos\u00fajfalu"
    ],
    "name:msa_x_preferred":[
        "V\u00e1mos\u00fajfalu"
    ],
    "name:nld_x_preferred":[
        "V\u00e1mos\u00fajfalu"
    ],
    "name:pol_x_preferred":[
        "V\u00e1mos\u00fajfalu"
    ],
    "name:ron_x_preferred":[
        "V\u00e1mos\u00fajfalu"
    ],
    "name:slk_x_preferred":[
        "V\u00e1mos\u00fajfalu"
    ],
    "name:slv_x_preferred":[
        "V\u00e1mos\u00fajfalu"
    ],
    "name:und_x_variant":[
        "V\u00e1mos\u00fajfalu"
    ],
    "name:vie_x_preferred":[
        "V\u00e1mos\u00fajfalu"
    ],
    "name:zho_x_preferred":[
        "\u74e6\u83ab\u8212\u4f0a\u798f\u5362"
    ],
    "wof:name":"Vamosujfalu",
    "wof:placetype":"locality"
},
  "geometry": {"coordinates":[21.46667,48.26667],"type":"Point"}
}