{
  "type": "Feature",
  "properties": {
    "gn:admin1_code":"4.0",
    "gn:asciiname":"Vamosujfalu",
    "gn:country_code":"HU",
    "gn:dem":119,
    "gn:feature_class":"P",
    "gn:feature_code":"PPL",
    "gn:name":"V\u00e1mos\u00fajfalu",
    "gn:population":0,
    "gn:timezone":"Europe/Budapest",
    "iso:country":"HU",
    "name:und_x_variant":[
        "V\u00e1mos\u00fajfalu"
    ],
    "wof:name":"Vamosujfalu",
    "wof:placetype":"locality"
},
  "geometry": {"coordinates":[21.46667,48.26667],"type":"Point"}
}