{
  "type": "Feature",
  "properties": {
    "iso:country":"HU",
    "name:deu_x_preferred":[
        "Szigetszentm\u00e1rton"
    ],
    "name:eng_x_preferred":[
        "Szigetszentm\u00e1rton"
    ],
    "name:epo_x_preferred":[
        "Szigetszentm\u00e1rton"
    ],
    "name:fra_x_preferred":[
        "Szigetszentm\u00e1rton"
    ],
    "name:hrv_x_preferred":[
        "Smartin"
    ],
    "name:hun_x_colloquial":[
        "Szigetszentmarton"
    ],
    "name:hun_x_preferred":[
        "Szigetszentm\u00e1rton"
    ],
    "name:ita_x_preferred":[
        "Szigetszentm\u00e1rton"
    ],
    "name:msa_x_preferred":[
        "Szigetszentm\u00e1rton"
    ],
    "name:nan_x_preferred":[
        "Szigetszentm\u00e1rton"
    ],
    "name:nld_x_preferred":[
        "Szigetszentm\u00e1rton"
    ],
    "name:pol_x_preferred":[
        "Szigetszentm\u00e1rton"
    ],
    "name:ron_x_preferred":[
        "Szigetszentm\u00e1rton"
    ],
    "name:slk_x_preferred":[
        "Szigetszentm\u00e1rton"
    ],
    "name:slv_x_preferred":[
        "Szigetszentm\u00e1rton"
    ],
    "name:vie_x_preferred":[
        "Szigetszentm\u00e1rton"
    ],
    "name:zho_x_preferred":[
        "\u897f\u76d6\u7279\u68ee\u7279\u9a6c\u5c14\u901a"
    ],
    "qs:a0":"Magyarorsz\u00e1g",
    "qs:a1":"*Pest",
    "qs:a1r":"0K\u00f6z\u00e9p-Magyarorsz\u00e1g",
    "qs:adm0":"Magyarorsz\u00e1g",
    "qs:la_lc":"*",
    "qs:level":"locality",
    "qs:loc":"Szigetszentm\u00e1rton",
    "qs:loc_alt":"Szigetszentmarton",
    "qs:pop":0,
    "qs:type":"buffered point",
    "wd:wordcount":52,
    "wof:lang":[
        "hun"
    ],
    "wof:name":"Szigetszentm\u00e1rton",
    "wof:placetype":"locality"
},
  "geometry": {"coordinates":[18.954859,47.218263],"type":"Point"}
}