{
  "type": "Feature",
  "properties": {
    "gn:admin1_code":"24.0",
    "gn:asciiname":"Alsotollosmajor",
    "gn:cc2":"HU",
    "gn:country_code":"HU",
    "gn:dem":148,
    "gn:feature_class":"P",
    "gn:feature_code":"PPL",
    "gn:name":"Als\u00f3t\u00f6ll\u00f6smajor",
    "gn:population":0,
    "gn:timezone":"Europe/Budapest",
    "iso:country":"HU",
    "name:und_x_variant":[
        "Szunyogv\u00e1r",
        "Als\u00f3t\u00f6ll\u00f6smajor"
    ],
    "wof:name":"Alsotollosmajor",
    "wof:placetype":"locality"
},
  "geometry": {"coordinates":[16.96667,46.63333],"type":"Point"}
}