{
  "type": "Feature",
  "properties": {
    "gn:admin1_code":"2.0",
    "gn:asciiname":"Szentimre Alsopuszta",
    "gn:country_code":"HU",
    "gn:dem":120,
    "gn:feature_class":"P",
    "gn:feature_code":"PPL",
    "gn:name":"Szentimre Als\u00f3puszta",
    "gn:population":0,
    "gn:timezone":"Europe/Budapest",
    "iso:country":"HU",
    "wof:name":"Szentimre Alsopuszta",
    "wof:placetype":"locality"
},
  "geometry": {"coordinates":[18.73333,46.11667],"type":"Point"}
}