{
  "type": "Feature",
  "properties": {
    "gn:admin1_code":"24.0",
    "gn:asciiname":"Nagygorbo",
    "gn:country_code":"HU",
    "gn:dem":185,
    "gn:feature_class":"P",
    "gn:feature_code":"PPL",
    "gn:name":"Nagyg\u00f6rb\u0151",
    "gn:population":0,
    "gn:timezone":"Europe/Budapest",
    "iso:country":"HU",
    "name:epo_x_preferred":[
        "Nagyg\u00f6rb\u0151"
    ],
    "name:fas_x_preferred":[
        "\u0646\u0627\u06af\u06cc\u06af\u0648\u0631\u0628\u0648"
    ],
    "name:fra_x_preferred":[
        "Nagyg\u00f6rb\u0151"
    ],
    "name:hun_x_preferred":[
        "Nagyg\u00f6rb\u0151"
    ],
    "name:ita_x_preferred":[
        "Nagyg\u00f6rb\u0151"
    ],
    "name:msa_x_preferred":[
        "Nagyg\u00f6rb\u0151"
    ],
    "name:nld_x_preferred":[
        "Nagyg\u00f6rb\u0151"
    ],
    "name:ron_x_preferred":[
        "Nagyg\u00f6rb\u0151"
    ],
    "name:slk_x_preferred":[
        "Nagyg\u00f6rb\u0151"
    ],
    "name:slv_x_preferred":[
        "Nagyg\u00f6rb\u0151"
    ],
    "name:vie_x_preferred":[
        "Nagyg\u00f6rb\u0151"
    ],
    "name:zho_x_preferred":[
        "\u7459\u5409\u683c\u5c14\u4f2f"
    ],
    "wof:name":"Nagygorbo",
    "wof:placetype":"locality"
},
  "geometry": {"coordinates":[17.1788,46.93119],"type":"Point"}
}