{
  "type": "Feature",
  "properties": {
    "gn:admin1_code":"24.0",
    "gn:asciiname":"Nagygorbo",
    "gn:country_code":"HU",
    "gn:dem":185,
    "gn:feature_class":"P",
    "gn:feature_code":"PPL",
    "gn:name":"Nagyg\u00f6rb\u0151",
    "gn:population":0,
    "gn:timezone":"Europe/Budapest",
    "iso:country":"HU",
    "name:und_x_variant":[
        "Nagyg\u00f6rb\u0151"
    ],
    "wof:name":"Nagygorbo",
    "wof:placetype":"locality"
},
  "geometry": {"coordinates":[17.1788,46.93119],"type":"Point"}
}