{
  "type": "Feature",
  "properties": {
    "gn:admin1_code":"24.0",
    "gn:asciiname":"Poloske",
    "gn:country_code":"HU",
    "gn:dem":150,
    "gn:feature_class":"P",
    "gn:feature_code":"PPL",
    "gn:name":"P\u00f6l\u00f6ske",
    "gn:population":0,
    "gn:timezone":"Europe/Budapest",
    "iso:country":"HU",
    "name:epo_x_preferred":[
        "P\u00f6l\u00f6ske"
    ],
    "name:fas_x_preferred":[
        "\u067e\u0648\u0644\u0648\u0634\u06a9\u0647"
    ],
    "name:fra_x_preferred":[
        "P\u00f6l\u00f6ske"
    ],
    "name:hun_x_preferred":[
        "P\u00f6l\u00f6ske"
    ],
    "name:ita_x_preferred":[
        "P\u00f6l\u00f6ske"
    ],
    "name:msa_x_preferred":[
        "P\u00f6l\u00f6ske"
    ],
    "name:nld_x_preferred":[
        "P\u00f6l\u00f6ske"
    ],
    "name:ron_x_preferred":[
        "P\u00f6l\u00f6ske"
    ],
    "name:slk_x_preferred":[
        "P\u00f6l\u00f6ske"
    ],
    "name:slv_x_preferred":[
        "P\u00f6l\u00f6ske"
    ],
    "name:vie_x_preferred":[
        "P\u00f6l\u00f6ske"
    ],
    "name:zho_x_preferred":[
        "\u73c0\u52d2\u4ec0\u51ef"
    ],
    "wof:name":"Poloske",
    "wof:placetype":"locality"
},
  "geometry": {"coordinates":[16.92405,46.75528],"type":"Point"}
}