{
  "type": "Feature",
  "properties": {
    "iso:country":"HU",
    "name:hun_x_preferred":[
        "Istv\u00e1ntelek"
    ],
    "wof:name":"Istvantelek",
    "wof:placetype":"neighbourhood"
},
  "geometry": {"coordinates":[19.10662378064282,47.55648772467353],"type":"Point"}
}