{
  "type": "Feature",
  "properties": {
    "iso:country":"HU",
    "name:hun_x_preferred":[
        "Felh\u00e9viz"
    ],
    "wof:name":"Felheviz",
    "wof:placetype":"neighbourhood"
},
  "geometry": {"coordinates":[19.03791627994723,47.51726334278909],"type":"Point"}
}