{
  "type": "Feature",
  "properties": {
    "gn:admin1_code":"17.0",
    "gn:asciiname":"Paisspuszta",
    "gn:country_code":"HU",
    "gn:dem":128,
    "gn:feature_class":"P",
    "gn:feature_code":"PPL",
    "gn:name":"Paisspuszta",
    "gn:population":0,
    "gn:timezone":"Europe/Budapest",
    "iso:country":"HU",
    "name:und_x_variant":[
        "Paizs-puszta",
        "Paisspuszta"
    ],
    "wof:name":"Paisspuszta",
    "wof:placetype":"locality"
},
  "geometry": {"coordinates":[17.27302,46.5137],"type":"Point"}
}