{
  "type": "Feature",
  "properties": {
    "gn:admin1_code":"4.0",
    "gn:asciiname":"Pusztaradvany",
    "gn:country_code":"HU",
    "gn:dem":224,
    "gn:feature_class":"P",
    "gn:feature_code":"PPL",
    "gn:name":"Pusztaradv\u00e1ny",
    "gn:population":0,
    "gn:timezone":"Europe/Budapest",
    "iso:country":"HU",
    "name:deu_x_preferred":[
        "Pusztaradv\u00e1ny"
    ],
    "name:epo_x_preferred":[
        "Pusztaradv\u00e1ny"
    ],
    "name:fas_x_preferred":[
        "\u067e\u0648\u0633\u062a\u0627\u0631\u0627\u062f\u0648\u0627\u0646\u06cc"
    ],
    "name:fra_x_preferred":[
        "Pusztaradv\u00e1ny"
    ],
    "name:heb_x_preferred":[
        "\u05e4\u05d5\u05e1\u05d8\u05e8\u05d3\u05d5\u05d5\u05d0\u05df"
    ],
    "name:hun_x_preferred":[
        "Pusztaradv\u00e1ny"
    ],
    "name:ita_x_preferred":[
        "Pusztaradv\u00e1ny"
    ],
    "name:msa_x_preferred":[
        "Pusztaradv\u00e1ny"
    ],
    "name:nld_x_preferred":[
        "Pusztaradv\u00e1ny"
    ],
    "name:pol_x_preferred":[
        "Pusztaradv\u00e1ny"
    ],
    "name:ron_x_preferred":[
        "Pusztaradv\u00e1ny"
    ],
    "name:slk_x_preferred":[
        "Pusztaradv\u00e1ny"
    ],
    "name:slv_x_preferred":[
        "Pusztaradv\u00e1ny"
    ],
    "name:vie_x_preferred":[
        "Pusztaradv\u00e1ny"
    ],
    "name:zho_x_preferred":[
        "\u666e\u65af\u9676\u52b3\u5fb7\u74e6\u5c3c"
    ],
    "wof:name":"Pusztaradvany",
    "wof:placetype":"locality"
},
  "geometry": {"coordinates":[21.13333,48.46667],"type":"Point"}
}