{
  "type": "Feature",
  "properties": {
    "gn:admin1_code":"4.0",
    "gn:asciiname":"Pusztaradvany",
    "gn:country_code":"HU",
    "gn:dem":224,
    "gn:feature_class":"P",
    "gn:feature_code":"PPL",
    "gn:name":"Pusztaradv\u00e1ny",
    "gn:population":0,
    "gn:timezone":"Europe/Budapest",
    "iso:country":"HU",
    "name:und_x_variant":[
        "Pusztaradv\u00e1ny"
    ],
    "wof:name":"Pusztaradvany",
    "wof:placetype":"locality"
},
  "geometry": {"coordinates":[21.13333,48.46667],"type":"Point"}
}