{
  "type": "Feature",
  "properties": {
    "gn:admin1_code":"24.0",
    "gn:asciiname":"Totszentmarton",
    "gn:country_code":"HU",
    "gn:dem":150,
    "gn:feature_class":"P",
    "gn:feature_code":"PPL",
    "gn:name":"T\u00f3tszentm\u00e1rton",
    "gn:population":0,
    "gn:timezone":"Europe/Budapest",
    "iso:country":"HU",
    "name:epo_x_preferred":[
        "T\u00f3tszentm\u00e1rton"
    ],
    "name:fas_x_preferred":[
        "\u062a\u0648\u062a\u0632\u0646\u062a \u0645\u0627\u0631\u062a\u0646"
    ],
    "name:fra_x_preferred":[
        "T\u00f3tszentm\u00e1rton"
    ],
    "name:hun_x_preferred":[
        "T\u00f3tszentm\u00e1rton"
    ],
    "name:ita_x_preferred":[
        "T\u00f3tszentm\u00e1rton"
    ],
    "name:msa_x_preferred":[
        "T\u00f3tszentm\u00e1rton"
    ],
    "name:nld_x_preferred":[
        "T\u00f3tszentm\u00e1rton"
    ],
    "name:ron_x_preferred":[
        "T\u00f3tszentm\u00e1rton"
    ],
    "name:slk_x_preferred":[
        "T\u00f3tszentm\u00e1rton"
    ],
    "name:slv_x_preferred":[
        "T\u00f3tszentm\u00e1rton"
    ],
    "name:und_x_variant":[
        "T\u00f3tszentm\u00e1rton"
    ],
    "name:vie_x_preferred":[
        "T\u00f3tszentm\u00e1rton"
    ],
    "name:zho_x_preferred":[
        "\u6258\u7279\u68ee\u7279\u9a6c\u5c14\u901a"
    ],
    "wof:name":"Totszentmarton",
    "wof:placetype":"locality"
},
  "geometry": {"coordinates":[16.80555,46.4219],"type":"Point"}
}