{
  "type": "Feature",
  "properties": {
    "gn:admin1_code":"24.0",
    "gn:asciiname":"Totszentmarton",
    "gn:country_code":"HU",
    "gn:dem":150,
    "gn:feature_class":"P",
    "gn:feature_code":"PPL",
    "gn:name":"T\u00f3tszentm\u00e1rton",
    "gn:population":0,
    "gn:timezone":"Europe/Budapest",
    "iso:country":"HU",
    "name:und_x_variant":[
        "T\u00f3tszentm\u00e1rton"
    ],
    "wof:name":"Totszentmarton",
    "wof:placetype":"locality"
},
  "geometry": {"coordinates":[16.80555,46.4219],"type":"Point"}
}