{
  "type": "Feature",
  "properties": {
    "gn:admin1_code":"17.0",
    "gn:asciiname":"Magyarodpuszta",
    "gn:cc2":"HU",
    "gn:country_code":"HU",
    "gn:dem":164,
    "gn:feature_class":"P",
    "gn:feature_code":"PPL",
    "gn:name":"Magyar\u00f3dpuszta",
    "gn:population":0,
    "gn:timezone":"Europe/Budapest",
    "iso:country":"HU",
    "name:und_x_variant":[
        "Magyar\u00e1d-puszta",
        "Magyar\u00f3dpuszta"
    ],
    "wof:name":"Magyarodpuszta",
    "wof:placetype":"locality"
},
  "geometry": {"coordinates":[18.01667,46.53333],"type":"Point"}
}