{
  "type": "Feature",
  "properties": {
    "gn:admin1_code":"2.0",
    "gn:asciiname":"Dravasztara",
    "gn:country_code":"HU",
    "gn:dem":98,
    "gn:feature_class":"P",
    "gn:feature_code":"PPL",
    "gn:name":"Dr\u00e1vaszt\u00e1ra",
    "gn:population":0,
    "gn:timezone":"Europe/Budapest",
    "iso:country":"HU",
    "name:deu_x_preferred":[
        "Dr\u00e1vaszt\u00e1ra"
    ],
    "name:epo_x_preferred":[
        "Dr\u00e1vaszt\u00e1ra"
    ],
    "name:fas_x_preferred":[
        "\u062f\u0631\u0627\u0648\u0627\u0633\u062a\u0627\u0631\u0627"
    ],
    "name:fra_x_preferred":[
        "Dr\u00e1vaszt\u00e1ra"
    ],
    "name:hrv_x_preferred":[
        "Starin"
    ],
    "name:hun_x_preferred":[
        "Dr\u00e1vaszt\u00e1ra"
    ],
    "name:ita_x_preferred":[
        "Dr\u00e1vaszt\u00e1ra"
    ],
    "name:msa_x_preferred":[
        "Dr\u00e1vaszt\u00e1ra"
    ],
    "name:nld_x_preferred":[
        "Dr\u00e1vaszt\u00e1ra"
    ],
    "name:pol_x_preferred":[
        "Dr\u00e1vaszt\u00e1ra"
    ],
    "name:ron_x_preferred":[
        "Dr\u00e1vaszt\u00e1ra"
    ],
    "name:slk_x_preferred":[
        "Dr\u00e1vaszt\u00e1ra"
    ],
    "name:slv_x_preferred":[
        "Dr\u00e1vaszt\u00e1ra"
    ],
    "name:vie_x_preferred":[
        "Dr\u00e1vaszt\u00e1ra"
    ],
    "name:zho_x_preferred":[
        "\u5fb7\u62c9\u6c83\u65af\u5854\u52b3"
    ],
    "wof:name":"Dravasztara",
    "wof:placetype":"locality"
},
  "geometry": {"coordinates":[17.82064,45.82751],"type":"Point"}
}