{
  "type": "Feature",
  "properties": {
    "gn:admin1_code":"16.0",
    "gn:asciiname":"Aporkaitanya",
    "gn:country_code":"HU",
    "gn:dem":100,
    "gn:feature_class":"P",
    "gn:feature_code":"PPL",
    "gn:name":"\u00c1porkaitanya",
    "gn:population":0,
    "gn:timezone":"Europe/Budapest",
    "iso:country":"HU",
    "name:und_x_variant":[
        "\u00c1porkai \u0170rb\u0151-tanya",
        "\u00c1porkaitanya"
    ],
    "wof:name":"Aporkaitanya",
    "wof:placetype":"locality"
},
  "geometry": {"coordinates":[19.17675,47.13122],"type":"Point"}
}