{
  "type": "Feature",
  "properties": {
    "gn:admin1_code":"24.0",
    "gn:asciiname":"Dioskal",
    "gn:country_code":"HU",
    "gn:dem":141,
    "gn:feature_class":"P",
    "gn:feature_code":"PPL",
    "gn:name":"Di\u00f3sk\u00e1l",
    "gn:population":0,
    "gn:timezone":"Europe/Budapest",
    "iso:country":"HU",
    "name:aze_x_preferred":[
        "Dioskal"
    ],
    "name:epo_x_preferred":[
        "Di\u00f3sk\u00e1l"
    ],
    "name:fas_x_preferred":[
        "\u062f\u06cc\u0648\u0634\u06a9\u0627\u0644"
    ],
    "name:fra_x_preferred":[
        "Di\u00f3sk\u00e1l"
    ],
    "name:hun_x_preferred":[
        "Di\u00f3sk\u00e1l"
    ],
    "name:ita_x_preferred":[
        "Di\u00f3sk\u00e1l"
    ],
    "name:msa_x_preferred":[
        "Di\u00f3sk\u00e1l"
    ],
    "name:nld_x_preferred":[
        "Di\u00f3sk\u00e1l"
    ],
    "name:ron_x_preferred":[
        "Di\u00f3sk\u00e1l"
    ],
    "name:slk_x_preferred":[
        "Di\u00f3sk\u00e1l"
    ],
    "name:slv_x_preferred":[
        "Di\u00f3sk\u00e1l"
    ],
    "name:und_x_variant":[
        "Di\u00f3sk\u00e1l"
    ],
    "name:vie_x_preferred":[
        "Di\u00f3sk\u00e1l"
    ],
    "name:zho_x_preferred":[
        "\u8fea\u6b27\u4ec0\u5361\u5c14"
    ],
    "wof:name":"Dioskal",
    "wof:placetype":"locality"
},
  "geometry": {"coordinates":[17.05572,46.67365],"type":"Point"}
}