{
  "type": "Feature",
  "properties": {
    "gn:admin1_code":"24.0",
    "gn:asciiname":"Dioskal",
    "gn:country_code":"HU",
    "gn:dem":141,
    "gn:feature_class":"P",
    "gn:feature_code":"PPL",
    "gn:name":"Di\u00f3sk\u00e1l",
    "gn:population":0,
    "gn:timezone":"Europe/Budapest",
    "iso:country":"HU",
    "name:und_x_variant":[
        "Di\u00f3sk\u00e1l"
    ],
    "wof:name":"Dioskal",
    "wof:placetype":"locality"
},
  "geometry": {"coordinates":[17.05572,46.67365],"type":"Point"}
}