{
  "type": "Feature",
  "properties": {
    "gn:admin1_code":"4.0",
    "gn:asciiname":"Martonyi",
    "gn:country_code":"HU",
    "gn:dem":168,
    "gn:feature_class":"P",
    "gn:feature_code":"PPL",
    "gn:name":"Martonyi",
    "gn:population":0,
    "gn:timezone":"Europe/Budapest",
    "iso:country":"HU",
    "name:deu_x_preferred":[
        "Martonyi"
    ],
    "name:epo_x_preferred":[
        "Martonyi"
    ],
    "name:fas_x_preferred":[
        "\u0645\u0627\u0631\u062a\u0648\u0646\u06cc\u06cc"
    ],
    "name:fra_x_preferred":[
        "Martonyi"
    ],
    "name:heb_x_preferred":[
        "\u05de\u05e8\u05d8\u05d5\u05e0\u05d9"
    ],
    "name:hun_x_preferred":[
        "Martonyi"
    ],
    "name:ita_x_preferred":[
        "Martonyi"
    ],
    "name:msa_x_preferred":[
        "Martonyi"
    ],
    "name:nld_x_preferred":[
        "Martonyi"
    ],
    "name:pol_x_preferred":[
        "Martonyi"
    ],
    "name:ron_x_preferred":[
        "Martonyi"
    ],
    "name:slk_x_preferred":[
        "Martonyi"
    ],
    "name:vie_x_preferred":[
        "Martonyi"
    ],
    "name:zho_x_preferred":[
        "\u6bdb\u5c14\u6258\u5c3c"
    ],
    "wof:name":"Martonyi",
    "wof:placetype":"locality"
},
  "geometry": {"coordinates":[20.76667,48.46667],"type":"Point"}
}