{
  "type": "Feature",
  "properties": {
    "gn:admin1_code":"14.0",
    "gn:asciiname":"Ujzsunypuszta",
    "gn:country_code":"HU",
    "gn:dem":302,
    "gn:feature_class":"P",
    "gn:feature_code":"PPL",
    "gn:name":"\u00dajzs\u00fanypuszta",
    "gn:population":0,
    "gn:timezone":"Europe/Budapest",
    "iso:country":"HU",
    "wof:name":"Ujzsunypuszta",
    "wof:placetype":"locality"
},
  "geometry": {"coordinates":[19.59648,48.01162],"type":"Point"}
}