{
  "type": "Feature",
  "properties": {
    "gn:admin1_code":"21.0",
    "gn:asciiname":"Voroskeresztdulo",
    "gn:country_code":"HU",
    "gn:dem":126,
    "gn:feature_class":"P",
    "gn:feature_code":"PPL",
    "gn:name":"V\u00f6r\u00f6skeresztd\u0171l\u0151",
    "gn:population":0,
    "gn:timezone":"Europe/Budapest",
    "iso:country":"HU",
    "wof:name":"Voroskeresztdulo",
    "wof:placetype":"locality"
},
  "geometry": {"coordinates":[18.28333,46.63333],"type":"Point"}
}