{
  "type": "Feature",
  "properties": {
    "gn:admin1_code":"6.0",
    "gn:asciiname":"Balatan",
    "gn:country_code":"HU",
    "gn:dem":85,
    "gn:feature_class":"P",
    "gn:feature_code":"PPL",
    "gn:name":"Balat\u00e1n",
    "gn:population":0,
    "gn:timezone":"Europe/Budapest",
    "iso:country":"HU",
    "wof:name":"Balatan",
    "wof:placetype":"locality"
},
  "geometry": {"coordinates":[20.71667,46.16667],"type":"Point"}
}