{
  "type": "Feature",
  "properties": {
    "gn:admin1_code":"24.0",
    "gn:asciiname":"Poloskefo",
    "gn:country_code":"HU",
    "gn:dem":155,
    "gn:feature_class":"P",
    "gn:feature_code":"PPL",
    "gn:name":"P\u00f6l\u00f6skef\u0151",
    "gn:population":0,
    "gn:timezone":"Europe/Budapest",
    "iso:country":"HU",
    "name:deu_x_preferred":[
        "P\u00f6l\u00f6skef\u0151"
    ],
    "name:epo_x_preferred":[
        "P\u00f6l\u00f6skef\u0151"
    ],
    "name:fas_x_preferred":[
        "\u067e\u0648\u0644\u0648\u0634\u06a9\u0641\u0648"
    ],
    "name:fra_x_preferred":[
        "P\u00f6l\u00f6skef\u0151"
    ],
    "name:hun_x_preferred":[
        "P\u00f6l\u00f6skef\u0151"
    ],
    "name:ita_x_preferred":[
        "P\u00f6l\u00f6skef\u0151"
    ],
    "name:msa_x_preferred":[
        "P\u00f6l\u00f6skef\u0151"
    ],
    "name:nld_x_preferred":[
        "P\u00f6l\u00f6skef\u0151"
    ],
    "name:ron_x_preferred":[
        "P\u00f6l\u00f6skef\u0151"
    ],
    "name:slk_x_preferred":[
        "P\u00f6l\u00f6skef\u0151"
    ],
    "name:slv_x_preferred":[
        "P\u00f6l\u00f6skef\u0151"
    ],
    "name:und_x_variant":[
        "P\u00f6l\u00f6skef\u0151"
    ],
    "name:vie_x_preferred":[
        "P\u00f6l\u00f6skef\u0151"
    ],
    "name:zho_x_preferred":[
        "\u73c0\u52d2\u4ec0\u51ef\u5f17"
    ],
    "wof:name":"Poloskefo",
    "wof:placetype":"locality"
},
  "geometry": {"coordinates":[16.94646,46.60393],"type":"Point"}
}