{
  "type": "Feature",
  "properties": {
    "gn:admin1_code":"24.0",
    "gn:asciiname":"Poloskefo",
    "gn:country_code":"HU",
    "gn:dem":155,
    "gn:feature_class":"P",
    "gn:feature_code":"PPL",
    "gn:name":"P\u00f6l\u00f6skef\u0151",
    "gn:population":0,
    "gn:timezone":"Europe/Budapest",
    "iso:country":"HU",
    "name:und_x_variant":[
        "P\u00f6l\u00f6skef\u0151"
    ],
    "wof:name":"Poloskefo",
    "wof:placetype":"locality"
},
  "geometry": {"coordinates":[16.94646,46.60393],"type":"Point"}
}