{
  "type": "Feature",
  "properties": {
    "gn:admin1_code":"8.0",
    "gn:asciiname":"Laszlopuszta",
    "gn:cc2":"HU",
    "gn:country_code":"HU",
    "gn:dem":140,
    "gn:feature_class":"P",
    "gn:feature_code":"PPL",
    "gn:name":"L\u00e1szl\u00f3puszta",
    "gn:population":0,
    "gn:timezone":"Europe/Budapest",
    "iso:country":"HU",
    "name:und_x_variant":[
        "L\u00e1zl\u00f3puszta",
        "L\u00e1szl\u00f3puszta"
    ],
    "wof:name":"Laszlopuszta",
    "wof:placetype":"locality"
},
  "geometry": {"coordinates":[18.31667,46.96667],"type":"Point"}
}