{
  "type": "Feature",
  "properties": {
    "gn:admin1_code":"9.0",
    "gn:asciiname":"Ballatag",
    "gn:country_code":"HU",
    "gn:dem":126,
    "gn:feature_class":"P",
    "gn:feature_code":"PPL",
    "gn:name":"Ballatag",
    "gn:population":0,
    "gn:timezone":"Europe/Budapest",
    "iso:country":"HU",
    "name:und_x_variant":[
        "Balla-major",
        "Ballatag"
    ],
    "wof:name":"Ballatag",
    "wof:placetype":"locality"
},
  "geometry": {"coordinates":[17.85,47.63333],"type":"Point"}
}