{
  "type": "Feature",
  "properties": {
    "gn:admin1_code":"10.0",
    "gn:asciiname":"Balazskert",
    "gn:country_code":"HU",
    "gn:dem":135,
    "gn:feature_class":"P",
    "gn:feature_code":"PPL",
    "gn:name":"Bal\u00e1zskert",
    "gn:population":0,
    "gn:timezone":"Europe/Budapest",
    "iso:country":"HU",
    "wof:name":"Balazskert",
    "wof:placetype":"locality"
},
  "geometry": {"coordinates":[21.68333,47.71667],"type":"Point"}
}