{
  "type": "Feature",
  "properties": {
    "gn:admin1_code":"23.0",
    "gn:asciiname":"Nyarad",
    "gn:country_code":"HU",
    "gn:dem":139,
    "gn:feature_class":"P",
    "gn:feature_code":"PPL",
    "gn:name":"Ny\u00e1r\u00e1d",
    "gn:population":0,
    "gn:timezone":"Europe/Budapest",
    "iso:country":"HU",
    "name:und_x_variant":[
        "Ny\u00e1r\u00e1d"
    ],
    "wof:name":"Nyarad",
    "wof:placetype":"locality"
},
  "geometry": {"coordinates":[17.36447,47.28708],"type":"Point"}
}