{
  "type": "Feature",
  "properties": {
    "gn:admin1_code":"18.0",
    "gn:asciiname":"Lonya",
    "gn:country_code":"HU",
    "gn:dem":104,
    "gn:feature_class":"P",
    "gn:feature_code":"PPL",
    "gn:name":"L\u00f3nya",
    "gn:population":0,
    "gn:timezone":"Europe/Budapest",
    "iso:country":"HU",
    "name:deu_x_preferred":[
        "L\u00f3nya"
    ],
    "name:epo_x_preferred":[
        "L\u00f3nya"
    ],
    "name:fas_x_preferred":[
        "\u0644\u0648\u0646\u06cc\u0627"
    ],
    "name:fra_x_preferred":[
        "L\u00f3nya"
    ],
    "name:hun_x_preferred":[
        "L\u00f3nya"
    ],
    "name:ita_x_preferred":[
        "L\u00f3nya"
    ],
    "name:msa_x_preferred":[
        "L\u00f3nya"
    ],
    "name:nld_x_preferred":[
        "L\u00f3nya"
    ],
    "name:ron_x_preferred":[
        "L\u00f3nya"
    ],
    "name:slk_x_preferred":[
        "L\u00f3nya"
    ],
    "name:slv_x_preferred":[
        "L\u00f3nya"
    ],
    "name:und_x_variant":[
        "Nagyl\u00f3nya",
        "Kisl\u00f3nya"
    ],
    "name:vie_x_preferred":[
        "L\u00f3nya"
    ],
    "name:zho_x_preferred":[
        "\u6d1b\u5c3c\u5965"
    ],
    "wof:name":"Lonya",
    "wof:placetype":"locality"
},
  "geometry": {"coordinates":[22.26526,48.33115],"type":"Point"}
}