{
  "type": "Feature",
  "properties": {
    "gn:admin1_code":"18.0",
    "gn:asciiname":"Lonya",
    "gn:country_code":"HU",
    "gn:dem":104,
    "gn:feature_class":"P",
    "gn:feature_code":"PPL",
    "gn:name":"L\u00f3nya",
    "gn:population":0,
    "gn:timezone":"Europe/Budapest",
    "iso:country":"HU",
    "name:und_x_variant":[
        "Nagyl\u00f3nya",
        "Kisl\u00f3nya",
        "L\u00f3nya"
    ],
    "wof:name":"Lonya",
    "wof:placetype":"locality"
},
  "geometry": {"coordinates":[22.26526,48.33115],"type":"Point"}
}