{
  "type": "Feature",
  "properties": {
    "gn:admin1_code":"17.0",
    "gn:asciiname":"Kiskorpad",
    "gn:country_code":"HU",
    "gn:dem":165,
    "gn:feature_class":"P",
    "gn:feature_code":"PPL",
    "gn:name":"Kiskorp\u00e1d",
    "gn:population":0,
    "gn:timezone":"Europe/Budapest",
    "iso:country":"HU",
    "name:und_x_variant":[
        "Kiskorp\u00e1d"
    ],
    "wof:name":"Kiskorpad",
    "wof:placetype":"locality"
},
  "geometry": {"coordinates":[17.61257999999999,46.34895],"type":"Point"}
}