{
  "type": "Feature",
  "properties": {
    "gn:admin1_code":"17.0",
    "gn:asciiname":"Kiskorpad",
    "gn:country_code":"HU",
    "gn:dem":165,
    "gn:feature_class":"P",
    "gn:feature_code":"PPL",
    "gn:name":"Kiskorp\u00e1d",
    "gn:population":0,
    "gn:timezone":"Europe/Budapest",
    "iso:country":"HU",
    "name:deu_x_preferred":[
        "Kiskorp\u00e1d"
    ],
    "name:epo_x_preferred":[
        "Kiskorp\u00e1d"
    ],
    "name:fas_x_preferred":[
        "\u06a9\u06cc\u0634\u06a9\u0648\u0631\u067e\u0627\u062f"
    ],
    "name:fra_x_preferred":[
        "Kiskorp\u00e1d"
    ],
    "name:hun_x_preferred":[
        "Kiskorp\u00e1d"
    ],
    "name:ita_x_preferred":[
        "Kiskorp\u00e1d"
    ],
    "name:msa_x_preferred":[
        "Kiskorp\u00e1d"
    ],
    "name:nld_x_preferred":[
        "Kiskorp\u00e1d"
    ],
    "name:ron_x_preferred":[
        "Kiskorp\u00e1d"
    ],
    "name:slk_x_preferred":[
        "Kiskorp\u00e1d"
    ],
    "name:slv_x_preferred":[
        "Kiskorp\u00e1d"
    ],
    "name:und_x_variant":[
        "Kiskorp\u00e1d"
    ],
    "name:vie_x_preferred":[
        "Kiskorp\u00e1d"
    ],
    "name:zho_x_preferred":[
        "\u57fa\u4ec0\u79d1\u5c14\u5e15\u5fb7"
    ],
    "wof:name":"Kiskorpad",
    "wof:placetype":"locality"
},
  "geometry": {"coordinates":[17.61257999999999,46.34895],"type":"Point"}
}