{
  "type": "Feature",
  "properties": {
    "gn:admin1_code":"2.0",
    "gn:asciiname":"Ipacsfa",
    "gn:country_code":"HU",
    "gn:dem":91,
    "gn:feature_class":"P",
    "gn:feature_code":"PPL",
    "gn:name":"Ipacsfa",
    "gn:population":0,
    "gn:timezone":"Europe/Budapest",
    "iso:country":"HU",
    "name:deu_x_preferred":[
        "Ipacsfa"
    ],
    "name:epo_x_preferred":[
        "Ipacsfa"
    ],
    "name:fas_x_preferred":[
        "\u0627\u06cc\u067e\u0627\u0686\u0641\u0627"
    ],
    "name:fra_x_preferred":[
        "Ipacsfa"
    ],
    "name:hrv_x_preferred":[
        "Pa\u010dva"
    ],
    "name:hun_x_preferred":[
        "Ipacsfa"
    ],
    "name:ita_x_preferred":[
        "Ipacsfa"
    ],
    "name:msa_x_preferred":[
        "Ipacsfa"
    ],
    "name:nld_x_preferred":[
        "Ipacsfa"
    ],
    "name:pol_x_preferred":[
        "Ipacsfa"
    ],
    "name:ron_x_preferred":[
        "Ipacsfa"
    ],
    "name:slk_x_preferred":[
        "Ipacsfa"
    ],
    "name:slv_x_preferred":[
        "Ipacsfa"
    ],
    "name:vie_x_preferred":[
        "Ipacsfa"
    ],
    "name:zho_x_preferred":[
        "\u4f0a\u4fdd\u5947\u798f"
    ],
    "wof:name":"Ipacsfa",
    "wof:placetype":"locality"
},
  "geometry": {"coordinates":[18.20551,45.8345],"type":"Point"}
}