{
  "type": "Feature",
  "properties": {
    "gn:admin1_code":"2.0",
    "gn:asciiname":"Ipacsfa",
    "gn:country_code":"HU",
    "gn:dem":91,
    "gn:feature_class":"P",
    "gn:feature_code":"PPL",
    "gn:name":"Ipacsfa",
    "gn:population":0,
    "gn:timezone":"Europe/Budapest",
    "iso:country":"HU",
    "wof:name":"Ipacsfa",
    "wof:placetype":"locality"
},
  "geometry": {"coordinates":[18.20551,45.8345],"type":"Point"}
}