{
  "type": "Feature",
  "properties": {
    "gn:admin1_code":"12.0",
    "gn:asciiname":"Kerekteleki",
    "gn:country_code":"HU",
    "gn:dem":181,
    "gn:feature_class":"P",
    "gn:feature_code":"PPL",
    "gn:name":"Ker\u00e9kteleki",
    "gn:population":0,
    "gn:timezone":"Europe/Budapest",
    "iso:country":"HU",
    "name:epo_x_preferred":[
        "Ker\u00e9kteleki"
    ],
    "name:fas_x_preferred":[
        "\u06a9\u0631\u06a9\u062a\u0644\u06a9\u06cc"
    ],
    "name:fra_x_preferred":[
        "Ker\u00e9kteleki"
    ],
    "name:hun_x_preferred":[
        "Ker\u00e9kteleki"
    ],
    "name:ita_x_preferred":[
        "Ker\u00e9kteleki"
    ],
    "name:msa_x_preferred":[
        "Ker\u00e9kteleki"
    ],
    "name:nld_x_preferred":[
        "Ker\u00e9kteleki"
    ],
    "name:pol_x_preferred":[
        "Ker\u00e9kteleki"
    ],
    "name:ron_x_preferred":[
        "Ker\u00e9kteleki"
    ],
    "name:slk_x_preferred":[
        "Ker\u00e9kteleki"
    ],
    "name:slv_x_preferred":[
        "Ker\u00e9kteleki"
    ],
    "name:und_x_variant":[
        "Ker\u00e9kteleki"
    ],
    "name:vie_x_preferred":[
        "Ker\u00e9kteleki"
    ],
    "name:zho_x_preferred":[
        "\u51ef\u96f7\u514b\u6cf0\u83b1\u57fa"
    ],
    "wof:name":"Kerekteleki",
    "wof:placetype":"locality"
},
  "geometry": {"coordinates":[17.93676,47.51292],"type":"Point"}
}