{
  "type": "Feature",
  "properties": {
    "gn:admin1_code":"18.0",
    "gn:asciiname":"Barathtanya",
    "gn:country_code":"HU",
    "gn:dem":110,
    "gn:feature_class":"P",
    "gn:feature_code":"PPL",
    "gn:name":"Bar\u00e1thtanya",
    "gn:population":0,
    "gn:timezone":"Europe/Budapest",
    "iso:country":"HU",
    "wof:name":"Barathtanya",
    "wof:placetype":"locality"
},
  "geometry": {"coordinates":[22.11667000000001,48.13333],"type":"Point"}
}