{
  "type": "Feature",
  "properties": {
    "iso:country":"HU",
    "name:hun_x_preferred":[
        "Erd\u0151skert"
    ],
    "wof:name":"Erdoskert",
    "wof:placetype":"neighbourhood"
},
  "geometry": {"coordinates":[19.20467108644495,47.39889123773907],"type":"Point"}
}