{
  "type": "Feature",
  "properties": {
    "gn:admin1_code":"11.0",
    "gn:asciiname":"Bagolyvar",
    "gn:country_code":"HU",
    "gn:dem":338,
    "gn:feature_class":"P",
    "gn:feature_code":"PPL",
    "gn:name":"Bagolyv\u00e1r",
    "gn:population":0,
    "gn:timezone":"Europe/Budapest",
    "iso:country":"HU",
    "wof:name":"Bagolyvar",
    "wof:placetype":"locality"
},
  "geometry": {"coordinates":[19.89239,47.84772],"type":"Point"}
}