{
  "type": "Feature",
  "properties": {
    "gn:admin1_code":"17.0",
    "gn:asciiname":"Santos",
    "gn:country_code":"HU",
    "gn:dem":142,
    "gn:feature_class":"P",
    "gn:feature_code":"PPL",
    "gn:name":"S\u00e1ntos",
    "gn:population":0,
    "gn:timezone":"Europe/Budapest",
    "iso:country":"HU",
    "name:deu_x_preferred":[
        "S\u00e1ntos"
    ],
    "name:epo_x_preferred":[
        "S\u00e1ntos"
    ],
    "name:fas_x_preferred":[
        "\u0634\u0627\u0646\u062a\u0648\u0634"
    ],
    "name:fra_x_preferred":[
        "S\u00e1ntos"
    ],
    "name:hun_x_preferred":[
        "S\u00e1ntos"
    ],
    "name:ita_x_preferred":[
        "S\u00e1ntos"
    ],
    "name:msa_x_preferred":[
        "S\u00e1ntos"
    ],
    "name:nld_x_preferred":[
        "S\u00e1ntos"
    ],
    "name:ron_x_preferred":[
        "S\u00e1ntos"
    ],
    "name:slk_x_preferred":[
        "S\u00e1ntos"
    ],
    "name:slv_x_preferred":[
        "S\u00e1ntos"
    ],
    "name:spa_x_preferred":[
        "S\u00e1ntos"
    ],
    "name:und_x_variant":[
        "S\u00e1ntos"
    ],
    "name:vie_x_preferred":[
        "S\u00e1ntos"
    ],
    "name:zho_x_preferred":[
        "\u5c1a\u6258\u4ec0"
    ],
    "wof:name":"Santos",
    "wof:placetype":"locality"
},
  "geometry": {"coordinates":[17.87867,46.34241],"type":"Point"}
}