{
  "type": "Feature",
  "properties": {
    "gn:admin1_code":"14.0",
    "gn:asciiname":"Ciframajor",
    "gn:country_code":"HU",
    "gn:dem":234,
    "gn:feature_class":"P",
    "gn:feature_code":"PPL",
    "gn:name":"Ciframajor",
    "gn:population":0,
    "gn:timezone":"Europe/Budapest",
    "iso:country":"HU",
    "wof:name":"Ciframajor",
    "wof:placetype":"locality"
},
  "geometry": {"coordinates":[19.51486,47.80905],"type":"Point"}
}