{
  "type": "Feature",
  "properties": {
    "gn:admin1_code":"16.0",
    "gn:asciiname":"Lakihegy",
    "gn:country_code":"HU",
    "gn:dem":103,
    "gn:feature_class":"P",
    "gn:feature_code":"PPL",
    "gn:name":"Lakihegy",
    "gn:population":0,
    "gn:timezone":"Europe/Budapest",
    "iso:country":"HU",
    "name:ces_x_preferred":[
        "Lakihegyi ad\u00f3torony"
    ],
    "name:deu_x_preferred":[
        "Sender Lakihegy"
    ],
    "name:hun_x_preferred":[
        "Lakihegyi ad\u00f3torony"
    ],
    "name:ind_x_preferred":[
        "Menara Lakihegy"
    ],
    "name:slk_x_preferred":[
        "Lakihegyi ad\u00f3torony"
    ],
    "wof:name":"Lakihegy",
    "wof:placetype":"locality"
},
  "geometry": {"coordinates":[19.01034,47.37765],"type":"Point"}
}