{
  "type": "Feature",
  "properties": {
    "gn:admin1_code":"4.0",
    "gn:asciiname":"Leh",
    "gn:country_code":"HU",
    "gn:dem":135,
    "gn:feature_class":"P",
    "gn:feature_code":"PPL",
    "gn:name":"L\u00e9h",
    "gn:population":0,
    "gn:timezone":"Europe/Budapest",
    "iso:country":"HU",
    "name:bar_x_preferred":[
        "L\u00e9h"
    ],
    "name:deu_x_preferred":[
        "L\u00e9h"
    ],
    "name:epo_x_preferred":[
        "L\u00e9h"
    ],
    "name:fas_x_preferred":[
        "\u0644\u0647"
    ],
    "name:fra_x_preferred":[
        "L\u00e9h"
    ],
    "name:heb_x_preferred":[
        "\u05dc\u05d4"
    ],
    "name:hun_x_preferred":[
        "L\u00e9h"
    ],
    "name:ita_x_preferred":[
        "L\u00e9h"
    ],
    "name:msa_x_preferred":[
        "L\u00e9h"
    ],
    "name:nld_x_preferred":[
        "L\u00e9h"
    ],
    "name:pol_x_preferred":[
        "L\u00e9h"
    ],
    "name:ron_x_preferred":[
        "L\u00e9h"
    ],
    "name:slk_x_preferred":[
        "L\u00e9h"
    ],
    "name:slv_x_preferred":[
        "L\u00e9h"
    ],
    "name:und_x_variant":[
        "L\u00e9h"
    ],
    "name:vie_x_preferred":[
        "L\u00e9h"
    ],
    "wof:name":"Leh",
    "wof:placetype":"locality"
},
  "geometry": {"coordinates":[20.98333,48.28333],"type":"Point"}
}