{
  "type": "Feature",
  "properties": {
    "gn:admin1_code":"22.0",
    "gn:asciiname":"Molnaszecsod",
    "gn:country_code":"HU",
    "gn:dem":183,
    "gn:feature_class":"P",
    "gn:feature_code":"PPL",
    "gn:name":"Molnaszecs\u0151d",
    "gn:population":0,
    "gn:timezone":"Europe/Budapest",
    "iso:country":"HU",
    "name:epo_x_preferred":[
        "Molnaszecs\u0151d"
    ],
    "name:fas_x_preferred":[
        "\u0645\u0648\u0644\u0646\u0627\u0633\u0686\u0648\u062f"
    ],
    "name:fra_x_preferred":[
        "Molnaszecs\u0151d"
    ],
    "name:hun_x_preferred":[
        "Molnaszecs\u0151d"
    ],
    "name:ita_x_preferred":[
        "Molnaszecs\u0151d"
    ],
    "name:msa_x_preferred":[
        "Molnaszecs\u0151d"
    ],
    "name:nld_x_preferred":[
        "Molnaszecs\u0151d"
    ],
    "name:ron_x_preferred":[
        "Molnaszecs\u0151d"
    ],
    "name:slk_x_preferred":[
        "Molnaszecs\u0151d"
    ],
    "name:slv_x_preferred":[
        "Molnaszecs\u0151d"
    ],
    "name:und_x_variant":[
        "Molnaszecs\u0151d"
    ],
    "name:vie_x_preferred":[
        "Molnaszecs\u0151d"
    ],
    "name:zho_x_preferred":[
        "\u83ab\u5c14\u7459\u585e\u5f7b\u5fb7"
    ],
    "wof:name":"Molnaszecsod",
    "wof:placetype":"locality"
},
  "geometry": {"coordinates":[16.67482,47.04531],"type":"Point"}
}